Workbook

Sheet Matriz Trazabilidad
A1: WALVY | M1 – Matriz de trazabilidad para validación con Cliente / Product Owner
A2: Cadena de trazabilidad: Historia de Usuario → Criterio de Aceptación → Regla de Negocio → Variante → Caso de Prueba → Evidencia QA. Las reglas derivadas de Figma/QA se mantienen identificadas como pendientes de aprobación cuando corresponda.
A4: ID Variante | B4: Flujo / Subflujo | C4: Variante / Escenario | D4: Condición / Disparador | E4: Comportamiento esperado | F4: HU asociada | G4: CA asociado | H4: Regla de negocio asociada | I4: Origen / Estado RN | J4: Código fuente RN | K4: Descripción fuente RN | L4: Caso de Prueba | M4: Evidencia QA | N4: Estado evidencia | O4: Nodo Figma | P4: URL Figma | Q4: Clasificación de soporte | R4: Validación Cliente | S4: Decisión PO / Comentarios | T4: ID Pendiente Cliente | U4: Regla Walvy validada
A5: M1-V01 | B5: Acceso / Login | C5: Usuario sin sesión guardada | D5: Inicio de app sin usuario recordado/biometría activa | E5: Mostrar login con correo y contraseña. | F5: M1-HU-001 | G5: CA1-CA3 | H5: M1-RN-ACC-001 / M1-RN-ACC-003 / M1-RN-ACC-005 | I5: Evidencia QA | J5: F-01, F-03 | F-03 | K5: F-01 – Login Exitoso – Passed – iOS / Android: Acceso con correo y contraseña; llegada a Home. F-03 – Validar links de la pantalla de login 01/02 – iOS / Android: Links Crear mi cuenta y ¿Olvidaste tu contraseña?; elementos visibles. | L5: CP-M1-ACC-001 | M5: Validar links de la pantalla de login 01/02 – Android/iOS | N5: Passed | O5: 3470:6974 | P5: https://www.figma.com/design/v45c4HTKnPnU0XABMa5vjY/Walvi-APP---Edificate-Inteligente?node-id=3470-6974 | Q5: Figma + QA / regla funcional pendiente | R5: Aprobado | U5: M01-RGL-001
A6: M1-V02 | B6: Acceso / Login | C6: Credenciales válidas | D6: Correo/usuario y contraseña válidos | E6: Permitir ingreso y dirigir a Home. | F6: M1-HU-003 | G6: CA1-CA3 | H6: M1-RN-ACC-004 | I6: Evidencia QA | J6: F-01 | K6: F-01 – Login Exitoso – Passed – iOS / Android: Acceso con correo y contraseña; llegada a Home. | L6: CP-M1-ACC-003 | M6: Login Exitoso – Android/iOS | N6: Passed | O6: 3361:2744 | P6: https://www.figma.com/design/v45c4HTKnPnU0XABMa5vjY/Walvi-APP---Edificate-Inteligente?node-id=3361-2744 | Q6: Figma + QA / regla funcional pendiente | R6: Ajustar | S6: Las credenciales válidas no bastan para V02. Solo aplica si la cuenta está activa/verificada y no restringida. Si está pending_verification, derivar a V13; si está restricted, aplicar el tratamiento de acceso restringido (BC-005). Con cuenta habilitada, el destino sigue dependiendo del estado: onboarding pendiente → iniciar/retomar; si corresponde → Home. | U6: M01-RGL-001
A7: M1-V03 | B7: Acceso / Login | C7: Credenciales inválidas / error de validación | D7: Usuario intenta ingresar con datos inválidos | E7: No permitir ingreso; mantener usuario en login y mostrar tratamiento de error definido. | F7: M1-HU-030 | G7: CA1-CA3 | H7: M1-RN-ACC-031 | I7: Figma / pendiente PO-Seguridad | J7: Figma 3677:2837 | K7: Figma – referencia visual en nodo(s): 3677:2837 | L7: CP-M1-ACC-018 | M7: Evidencia específica de credenciales inválidas por enlazar | N7: Pendiente | O7: 3677:2837 | P7: https://www.figma.com/design/v45c4HTKnPnU0XABMa5vjY/Walvi-APP---Edificate-Inteligente?node-id=3677-2837 | Q7: Figma solamente / validar regla | R7: Ajustar | S7: En Figma existe un estado con el mensaje “Correo no registrado”, que permite inferir si una cuenta existe. El comportamiento esperado debe utilizar una respuesta genérica, por ejemplo “Correo o contraseña incorrectos”, mantener al usuario en Login y permitir reintentar o recuperar acceso sin revelar si el correo está registrado. | T7: PD-M1-01 | U7: M01-RGL-001
A8: M1-V04 | B8: Acceso / Login | C8: Usuario previamente guardado | D8: Existe usuario persistido en dispositivo | E8: Mostrar correo/usuario persistido y solicitar credencial según diseño. | F8: M1-HU-013 | G8: CA1-CA3 | H8: M1-RN-ACC-025 | I8: Evidencia QA | J8: F-10, F-11 | K8: F-10 – Login biométrico exitoso/fallido – iOS: Acceso biométrico y fallback tras tres intentos fallidos. F-11 – Reingreso con usuario guardado – Android: Persistencia del usuario y reingreso. | L8: CP-M1-ACC-013 | M8: Reingreso con usuario guardado – Android | N8: Passed | O8: 3470:7098 | P8: https://www.figma.com/design/v45c4HTKnPnU0XABMa5vjY/Walvi-APP---Edificate-Inteligente?node-id=3470-7098 | Q8: Figma + QA / regla funcional pendiente | R8: Aprobado | U8: M01-RGL-001
A9: M1-V05 | B9: Biometría | C9: Biometría disponible y activa | D9: Usuario guardado tiene biometría habilitada | E9: Ofrecer autenticación biométrica. | F9: M1-HU-014 | G9: CA1-CA3 | H9: M1-RN-ACC-026 | I9: Evidencia QA | J9: F-10 | K9: F-10 – Login biométrico exitoso/fallido – iOS: Acceso biométrico y fallback tras tres intentos fallidos. | L9: CP-M1-ACC-014 | M9: Login biométrico – disponibilidad/éxito iOS | N9: Passed parcial | O9: 3470:7080 | P9: https://www.figma.com/design/v45c4HTKnPnU0XABMa5vjY/Walvi-APP---Edificate-Inteligente?node-id=3470-7080 | Q9: Figma + QA / regla funcional pendiente | R9: Aprobado | U9: M01-RGL-004
A10: M1-V06 | B10: Biometría | C10: Biometría exitosa | D10: Autenticación biométrica aprobada | E10: Ingresar a Home. | F10: M1-HU-014 | G10: CA2 | H10: M1-RN-ACC-026 | I10: Evidencia QA | J10: F-10 | K10: F-10 – Login biométrico exitoso/fallido – iOS: Acceso biométrico y fallback tras tres intentos fallidos. | L10: CP-M1-ACC-014 | M10: Login exitoso con usuario biométrico guardado – iOS | N10: Passed | O10: 3470:7138 | P10: https://www.figma.com/design/v45c4HTKnPnU0XABMa5vjY/Walvi-APP---Edificate-Inteligente?node-id=3470-7138 | Q10: Confirmado por Figma + QA | R10: Ajustar | S10: Ajustar el destino posterior a la autenticación biométrica. Una autenticación exitosa permite iniciar sesión, pero no debe fijarse universalmente el destino como Home; la continuidad depende del estado funcional del usuario. | U10: M01-RGL-004
A11: M1-V07 | B11: Biometría | C11: Biometría fallida / fallback | D11: Tres intentos biométricos fallidos según evidencia QA | E11: Volver a login con credenciales. | F11: M1-HU-015 | G11: CA1-CA3 | H11: M1-RN-ACC-027 | I11: Evidencia QA | J11: F-10 | K11: F-10 – Login biométrico exitoso/fallido – iOS: Acceso biométrico y fallback tras tres intentos fallidos. | L11: CP-M1-ACC-015 | M11: Login fallido biométrico / 3 intentos / fallback – iOS | N11: Passed | O11: 3361:2744 | P11: https://www.figma.com/design/v45c4HTKnPnU0XABMa5vjY/Walvi-APP---Edificate-Inteligente?node-id=3361-2744 | Q11: Confirmado por QA; formalizar regla | R11: Aprobado | S11: No se identificó una definición Walvy que establezca tres intentos como umbral funcional. Para esta matriz se acoge el comportamiento referenciado por Kabeli, sustentado en QA + Figma, como criterio observado del flujo; el número de intentos no se eleva a regla transversal de Walvy. | U11: M01-RGL-004
A12: M1-V08 | B12: Registro | C12: Acceso a crear cuenta | D12: Usuario selecciona “Crear mi cuenta” | E12: Abrir formulario de creación de cuenta. | F12: M1-HU-004 | G12: CA1-CA3 | H12: M1-RN-ACC-005 | I12: Evidencia QA | J12: F-03 | K12: F-03 – Validar links de la pantalla de login 01/02 – iOS / Android: Links Crear mi cuenta y ¿Olvidaste tu contraseña?; elementos visibles. | L12: CP-M1-ACC-004 | M12: Links Login / Crear mi cuenta – Android/iOS | N12: Passed | O12: 3470:7249 | P12: https://www.figma.com/design/v45c4HTKnPnU0XABMa5vjY/Walvi-APP---Edificate-Inteligente?node-id=3470-7249 | Q12: Figma + QA / regla funcional pendiente | R12: Aprobado | U12: M01-RGL-002
A13: M1-V09 | B13: Registro | C13: Datos de registro válidos | D13: Correo, confirmación, RUT y contraseña cumplen validación | E13: Permitir continuar si además están aceptados T&C y Privacidad. | F13: M1-HU-005 | G13: CA1-CA3 | H13: M1-RN-ACC-006 / M1-RN-ACC-007 / M1-RN-ACC-008 / M1-RN-ACC-009 / M1-RN-ACC-010 | I13: Evidencia QA | Derivada del flujo | Evidencia visual | J13: F-04 | F-04, F-05 | K13: F-04 – Creación de cuenta / Creación de cuenta exitosa – iOS / Android: Formulario, campos y envío a verificación. F-05 – Creación de cuenta – validación Términos y Condiciones – iOS / Android: Aceptación y acceso a documentos legales. | L13: CP-M1-ACC-005 | M13: Creación de cuenta / validaciones – Android/iOS | N13: Passed | O13: 3604:3521 | P13: https://www.figma.com/design/v45c4HTKnPnU0XABMa5vjY/Walvi-APP---Edificate-Inteligente?node-id=3604-3521 | Q13: Figma + QA / regla funcional pendiente | R13: Ajustar | S13: Completar la condición de aceptación de Términos y Política de Privacidad. Cada documento debe abrirse y su aceptación registrarse desde el propio documento después de alcanzar su final. Solo con el formulario válido y ambas aceptaciones registradas se habilita la creación de la cuenta. | U13: M01-RGL-002
A14: M1-V10 | B14: Registro | C14: Campos incompletos o inválidos | D14: Uno o más campos no cumplen validación | E14: Mantener CTA de creación deshabilitado o impedir avance. | F14: M1-HU-005 | G14: CA1-CA3 | H14: M1-RN-ACC-006 / M1-RN-ACC-007 / M1-RN-ACC-008 / M1-RN-ACC-009 / M1-RN-ACC-010 | I14: Evidencia QA | Derivada del flujo | Evidencia visual | J14: F-04 | F-04, F-05 | K14: F-04 – Creación de cuenta / Creación de cuenta exitosa – iOS / Android: Formulario, campos y envío a verificación. F-05 – Creación de cuenta – validación Términos y Condiciones – iOS / Android: Aceptación y acceso a documentos legales. | L14: CP-M1-ACC-005 | M14: Creación de cuenta / validaciones – Android/iOS | N14: Passed | O14: 3604:3621 | P14: https://www.figma.com/design/v45c4HTKnPnU0XABMa5vjY/Walvi-APP---Edificate-Inteligente?node-id=3604-3621 | Q14: Figma + QA / regla funcional pendiente | R14: Aprobado | U14: M01-RGL-002
A15: M1-V11 | B15: Registro | C15: Términos y Condiciones no aceptados | D15: Campos válidos, T&C sin aceptar | E15: No habilitar creación de cuenta. | F15: M1-HU-006 | G15: CA1-CA3 | H15: M1-RN-ACC-010 / M1-RN-ACC-011 | I15: Evidencia QA | J15: F-04, F-05 | F-05 | K15: F-04 – Creación de cuenta / Creación de cuenta exitosa – iOS / Android: Formulario, campos y envío a verificación. F-05 – Creación de cuenta – validación Términos y Condiciones – iOS / Android: Aceptación y acceso a documentos legales. | L15: CP-M1-ACC-006 | M15: Validación Términos y Condiciones / Privacidad – Android/iOS | N15: Passed | O15: 3604:3925 | P15: https://www.figma.com/design/v45c4HTKnPnU0XABMa5vjY/Walvi-APP---Edificate-Inteligente?node-id=3604-3925 | Q15: Figma + QA | R15: Aprobado | U15: M01-RGL-002
A16: M1-V12 | B16: Registro | C16: Política de Privacidad no aceptada | D16: Campos válidos, Privacidad sin aceptar | E16: No habilitar creación de cuenta. | F16: M1-HU-006 | G16: CA1-CA3 | H16: M1-RN-ACC-010 / M1-RN-ACC-011 | I16: Evidencia QA | J16: F-04, F-05 | F-05 | K16: F-04 – Creación de cuenta / Creación de cuenta exitosa – iOS / Android: Formulario, campos y envío a verificación. F-05 – Creación de cuenta – validación Términos y Condiciones – iOS / Android: Aceptación y acceso a documentos legales. | L16: CP-M1-ACC-006 | M16: Validación Términos y Condiciones / Privacidad – Android/iOS | N16: Passed | O16: 3361:2744 | P16: https://www.figma.com/design/v45c4HTKnPnU0XABMa5vjY/Walvi-APP---Edificate-Inteligente?node-id=3361-2744 | Q16: Figma + QA | R16: Aprobado | U16: M01-RGL-002
A17: M1-V13 | B17: Verificación de cuenta | C17: Código en estado inicial | D17: Cuenta creada; aún no se completa código | E17: Mostrar ingreso/verificación de código; CTA según completitud. | F17: M1-HU-007 | G17: CA1 | H17: M1-RN-ACC-012 / M1-RN-ACC-013 / M1-RN-ACC-032 | I17: Evidencia QA | Figma / pendiente PO | J17: F-04 | F-07 | Figma 3470:7580 | K17: F-04 – Creación de cuenta / Creación de cuenta exitosa – iOS / Android: Formulario, campos y envío a verificación. F-07 – Ingreso primera vez – Completar datos / Omitir y continuar – iOS / Android: Flujo posterior a la activación de cuenta. Figma – referencia visual en nodo(s): 3470:7580 | L17: CP-M1-ACC-007 | M17: Creación de cuenta – verificación – Android/iOS | N17: Passed | O17: 3470:7580 | P17: https://www.figma.com/design/v45c4HTKnPnU0XABMa5vjY/Walvi-APP---Edificate-Inteligente?node-id=3470-7580 | Q17: Figma + QA / ciclo de código pendiente | R17: Ajustar | S17: Ampliar la condición de entrada: V13 aplica tanto inmediatamente después del registro como cuando una cuenta existente en pending_verification intenta iniciar sesión. No crear sesión completa; mostrar/reabrir Verificación de cuenta y permitir completar o reenviar OTP según M01-RGL-002 / M1-DP-010. No requiere nueva variante ni pantalla. | T17: PD-M1-02 | U17: M01-RGL-001 / M01-RGL-002 / M1-DP-010
A18: M1-V14 | B18: Verificación de cuenta | C18: Código incorrecto | D18: Usuario ingresa código inválido | E18: No activar cuenta; informar error y permitir corrección según regla. | F18: M1-HU-007 | G18: CA3 | H18: M1-RN-ACC-015 | I18: Evidencia QA | J18: F-06 | K18: F-06 – Creación de cuenta – verificación código incorrecto – iOS / Android: Tratamiento de código inválido. | L18: CP-M1-ACC-007 | M18: Verificación código incorrecto – Android/iOS | N18: Passed | O18: 3470:7723 | P18: https://www.figma.com/design/v45c4HTKnPnU0XABMa5vjY/Walvi-APP---Edificate-Inteligente?node-id=3470-7723 | Q18: Confirmado por Figma + QA | R18: Aprobado | U18: M01-RGL-002
A19: M1-V15 | B19: Verificación de cuenta | C19: Código correcto | D19: Usuario ingresa código válido | E19: Confirmar cuenta y avanzar a primer ingreso. | F19: M1-HU-007 | G19: CA2 | H19: M1-RN-ACC-014 | I19: Evidencia QA | J19: F-07 | K19: F-07 – Ingreso primera vez – Completar datos / Omitir y continuar – iOS / Android: Flujo posterior a la activación de cuenta. | L19: CP-M1-ACC-007 | M19: Verificación código correcto – Android/iOS | N19: Passed | O19: 3470:7774 | P19: https://www.figma.com/design/v45c4HTKnPnU0XABMa5vjY/Walvi-APP---Edificate-Inteligente?node-id=3470-7774 | Q19: Confirmado por Figma + QA | R19: Aprobado | U19: M01-RGL-002
A20: M1-V16 | B20: Verificación de cuenta | C20: Código vencido / reenvío | D20: Temporizador finaliza o el código requiere reenvío | E20: Habilitar tratamiento de reenvío/vencimiento conforme regla de Producto. | F20: M1-HU-031 | G20: CA1-CA3 | H20: M1-RN-ACC-033 | I20: Figma / pendiente PO-Seguridad | J20: Figma 3470:7626 | K20: Figma – referencia visual en nodo(s): 3470:7626 | L20: CP-M1-ACC-019 | M20: Evidencia QA de vencimiento/reenvío por enlazar | N20: Pendiente | O20: 3470:7626 | P20: https://www.figma.com/design/v45c4HTKnPnU0XABMa5vjY/Walvi-APP---Edificate-Inteligente?node-id=3470-7626 | Q20: Figma solamente / decisión Producto | R20: Ajustar | S20: Decisión de Producto cerrada. Ver M1-DP-010 y AX-M1-001. Separar vigencia del OTP y temporizador de reenvío: el contador visible solo habilita solicitar un nuevo código; la expiración depende del TTL configurado. Baseline Walvy aceptado por Producto: OTP de 6 dígitos, TTL 10 min, reenvío a 60 s, máximo 5 intentos fallidos acumulados sin reinicio por reenvío, máximo 5 reenvíos en 15 min y cooldown de 15 min al superar el límite. Un nuevo código invalida el anterior; un código incorrecto, vencido, reutilizado o reemplazado no activa la cuenta. Kabeli debe ajustar D/E de V16 y M1-RN-ACC-032/033, mantener los parámetros configurables/versionados y confirmar los valores efectivos o justificar desviaciones. Aplicar rate limiting al menos por cuenta/correo, complementado por IP y, cuando sea viable, sesión/dispositivo; registrar eventos sin registrar el OTP. | T20: PD-M1-02 | U20: M01-RGL-002
A21: M1-V17 | B21: Recuperación de acceso | C21: Usuario inicia recuperación | D21: Selecciona “¿Olvidaste tu contraseña?” | E21: Abrir Recupera tu acceso. | F21: M1-HU-010 | G21: CA1 | H21: M1-RN-ACC-019 | I21: Evidencia QA | J21: F-08 | K21: F-08 – Confirmar cuenta con correo – código válido/no válido – iOS: Recuperación de acceso y validación de código. | L21: CP-M1-ACC-010 | M21: Confirmar cuenta con correo electrónico – iOS | N21: Passed | O21: 3470:7010 | P21: https://www.figma.com/design/v45c4HTKnPnU0XABMa5vjY/Walvi-APP---Edificate-Inteligente?node-id=3470-7010 | Q21: Figma + QA / regla funcional pendiente | R21: Aprobado | U21: M01-RGL-003
A22: M1-V18 | B22: Recuperación de acceso | C22: Usuario tiene acceso al correo | D22: Ingresa correo válido | E22: Permitir envío de código. | F22: M1-HU-010 | G22: CA2-CA3 | H22: M1-RN-ACC-020 | I22: Evidencia QA | J22: F-08 | K22: F-08 – Confirmar cuenta con correo – código válido/no válido – iOS: Recuperación de acceso y validación de código. | L22: CP-M1-ACC-010 | M22: Recuperación – envío de código – iOS | N22: Passed | O22: 3470:7010 | P22: https://www.figma.com/design/v45c4HTKnPnU0XABMa5vjY/Walvi-APP---Edificate-Inteligente?node-id=3470-7010 | Q22: Figma + QA | R22: Ajustar | S22: Precisar la condición y el comportamiento. El OTP se envía cuando el correo corresponde a una cuenta registrada; la respuesta visible del flujo de recuperación no debe confirmar si una cuenta existe o no. Este criterio se complementa con el control M01-SEC-003 de prevención de enumeración. | U22: M01-RGL-003
A23: M1-V19 | B23: Recuperación de acceso | C23: Usuario no tiene acceso al correo | D23: Usuario indica/no puede utilizar correo registrado | E23: Derivar al mecanismo de soporte mostrado en diseño; operación debe confirmarse. | F23: M1-HU-032 | G23: CA1-CA3 | H23: M1-RN-ACC-034 | I23: Figma / pendiente PO-Seguridad | J23: Figma 3470:7029 | K23: Figma – referencia visual en nodo(s): 3470:7029 | L23: CP-M1-ACC-020 | M23: Evidencia QA alternativa sin acceso al correo por enlazar | N23: Pendiente | O23: 3470:7029 | P23: https://www.figma.com/design/v45c4HTKnPnU0XABMa5vjY/Walvi-APP---Edificate-Inteligente?node-id=3470-7029 | Q23: Figma solamente / validar operación | R23: Aprobado | S23: Decisión de Producto cerrada. Ver M1-DP-011. Si el usuario no puede acceder al correo registrado, Walvy lo deriva al canal de soporte definido en Figma (soporte@walvy.cl); el contacto con soporte no acredita identidad ni permite por sí solo cambiar correo, contraseña o acceso. Solo una verificación de identidad satisfactoria conforme al procedimiento de Seguridad/Operaciones habilita la recuperación. Si continúa sin acceso al correo actual, el correo sustituto debe ser distinto y verificarse antes de reemplazar al anterior; si recupera acceso al correo original, debe volver al flujo estándar. Al completar la recuperación deben renovarse credenciales, invalidarse sesiones previas y registrarse/notificarse el evento. | T23: PD-M1-03 | U23: M01-RGL-003
A24: M1-V20 | B24: Recuperación de acceso | C24: Código válido | D24: Código de recuperación correcto | E24: Permitir crear nueva contraseña. | F24: M1-HU-011 | G24: CA1 | H24: M1-RN-ACC-021 | I24: Evidencia QA | J24: F-08, F-09 | K24: F-08 – Confirmar cuenta con correo – código válido/no válido – iOS: Recuperación de acceso y validación de código. F-09 – Nueva contraseña: modal, coincidente y no coincidente – iOS / Android: Reglas para guardar nueva contraseña. | L24: CP-M1-ACC-011 | M24: Código válido recuperación – iOS | N24: Passed | O24: 3361:2744 | P24: https://www.figma.com/design/v45c4HTKnPnU0XABMa5vjY/Walvi-APP---Edificate-Inteligente?node-id=3361-2744 | Q24: Confirmado por Figma + QA | R24: Aprobado | U24: M01-RGL-003
A25: M1-V21 | B25: Recuperación de acceso | C25: Código inválido | D25: Código de recuperación incorrecto | E25: Bloquear avance y permitir corregir/reintentar conforme regla. | F25: M1-HU-011 | G25: CA2-CA3 | H25: M1-RN-ACC-021 | I25: Evidencia QA | J25: F-08, F-09 | K25: F-08 – Confirmar cuenta con correo – código válido/no válido – iOS: Recuperación de acceso y validación de código. F-09 – Nueva contraseña: modal, coincidente y no coincidente – iOS / Android: Reglas para guardar nueva contraseña. | L25: CP-M1-ACC-011 | M25: Código no válido recuperación – iOS | N25: Passed | O25: 3361:2744 | P25: https://www.figma.com/design/v45c4HTKnPnU0XABMa5vjY/Walvi-APP---Edificate-Inteligente?node-id=3361-2744 | Q25: Confirmado por QA; ciclo pendiente | R25: Aprobado | U25: M01-RGL-003
A26: M1-V22 | B26: Recuperación de acceso | C26: Nueva contraseña coincide | D26: Nueva contraseña y confirmación son iguales | E26: Habilitar guardado y retorno a Login. | F26: M1-HU-012 | G26: CA1-CA3 | H26: M1-RN-ACC-022 / M1-RN-ACC-024 | I26: Evidencia QA | J26: F-09 | K26: F-09 – Nueva contraseña: modal, coincidente y no coincidente – iOS / Android: Reglas para guardar nueva contraseña. | L26: CP-M1-ACC-012 | M26: Nueva contraseña coincidente – Android/iOS | N26: Passed | O26: 3655:2970 | P26: https://www.figma.com/design/v45c4HTKnPnU0XABMa5vjY/Walvi-APP---Edificate-Inteligente?node-id=3655-2970 | Q26: Confirmado por Figma + QA | R26: Ajustar | S26: La coincidencia entre nueva contraseña y confirmación no es condición suficiente. La nueva contraseña debe además cumplir la política vigente antes de habilitar el guardado y retorno a Login. | U26: M01-RGL-003
A27: M1-V23 | B27: Recuperación de acceso | C27: Nueva contraseña no coincide | D27: Nueva contraseña y confirmación son distintas | E27: Mostrar error y mantener guardado deshabilitado. | F27: M1-HU-012 | G27: CA2 | H27: M1-RN-ACC-023 | I27: Evidencia QA | J27: F-09 | K27: F-09 – Nueva contraseña: modal, coincidente y no coincidente – iOS / Android: Reglas para guardar nueva contraseña. | L27: CP-M1-ACC-012 | M27: Nueva contraseña no coincidente – Android/iOS | N27: Passed | O27: 3655:3058 | P27: https://www.figma.com/design/v45c4HTKnPnU0XABMa5vjY/Walvi-APP---Edificate-Inteligente?node-id=3655-3058 | Q27: Confirmado por Figma + QA | R27: Aprobado | U27: M01-RGL-003
A28: M1-V24 | B28: Primer ingreso | C28: Completar datos | D28: Cuenta verificada en primer acceso | E28: Permitir completar nombre/apellido/alias según diseño y continuar. | F28: M1-HU-008 | G28: CA1-CA3 | H28: M1-RN-ACC-016 / M1-RN-ACC-017 / M1-RN-ACC-018 | I28: Evidencia QA | J28: F-07 | K28: F-07 – Ingreso primera vez – Completar datos / Omitir y continuar – iOS / Android: Flujo posterior a la activación de cuenta. | L28: CP-M1-ACC-008 | M28: Primer ingreso – Completar datos – Android/iOS | N28: Passed | O28: 3470:7207 | P28: https://www.figma.com/design/v45c4HTKnPnU0XABMa5vjY/Walvi-APP---Edificate-Inteligente?node-id=3470-7207 | Q28: Figma + QA / regla funcional pendiente | R28: Aprobado
A29: M1-V25 | B29: Primer ingreso | C29: Omitir datos | D29: Usuario decide omitir paso permitido | E29: Continuar sin completar esos datos, conservando el estado correspondiente. | F29: M1-HU-009 | G29: CA1-CA3 | H29: M1-RN-ACC-016 | I29: Evidencia QA | J29: F-07 | K29: F-07 – Ingreso primera vez – Completar datos / Omitir y continuar – iOS / Android: Flujo posterior a la activación de cuenta. | L29: CP-M1-ACC-009 | M29: Primer ingreso – Omitir y continuar – Android/iOS | N29: Passed | O29: 3470:7228 | P29: https://www.figma.com/design/v45c4HTKnPnU0XABMa5vjY/Walvi-APP---Edificate-Inteligente?node-id=3470-7228 | Q29: Figma + QA | R29: Ajustar | S29: Ajustar al comportamiento cerrado en Figma. La acción disponible es “Guardar y salir”: conserva la información ingresada y sale del flujo. No corresponde describirla como una omisión que continúa directamente al siguiente paso. | U29: M01-RGL-007
A30: M1-V26 | B30: Primer ingreso | C30: Ofrecer biometría | D30: Primer ingreso posterior a activación | E30: Mostrar opción de activar biometría conforme disponibilidad del dispositivo. | F30: M1-HU-033 | G30: CA1-CA3 | H30: M1-RN-ACC-035 | I30: Figma / pendiente PO-Seguridad | J30: Figma 4911:5511 | K30: Figma – referencia visual en nodo(s): 4911:5511 | L30: CP-M1-ACC-021 | M30: Evidencia de enrolamiento biométrico por enlazar | N30: Pendiente | O30: 4911:5511 | P30: https://www.figma.com/design/v45c4HTKnPnU0XABMa5vjY/Walvi-APP---Edificate-Inteligente?node-id=4911-5511 | Q30: Figma solamente / validar regla | R30: Aprobado | T30: PD-M1-04 | U30: M01-RGL-004
A31: M1-V27 | B31: Onboarding | C31: Bienvenida / activación | D31: Usuario entra al onboarding | E31: Explicar valor y ofrecer CTA dominante “Comenzar”. | F31: M1-HU-018 | G31: CA1-CA3 | H31: M1-RN-ACC-029 / M1-RN-ACC-030 / M1-RN-ONB-001 / M1-RN-ONB-012 | I31: Consolidación funcional | Funcional | MVP | J31: F-07, F-13 | S1/S4 | S1/S2/S4 | K31: S1 – Walvy_Especificacion_UX_Onboarding_App: Secuencia, pantallas, carga documental, postergación y reactivación. S4 – Walvy_Rector_Producto_y_Funcionalidades_MVP_v1.0_OLD_20260516: Responsabilidad del onboarding y límites transversales. S2 – Walvy_Onboarding_Diagnostico_Fase3_Reglas_Contextuales_Suficiencia_Semaforo_CTA_v1_0: Suficiencia, diagnóstico parcial, semáforo, presión principal y CTA. F-07 – Ingreso primera vez – Completar datos / Omitir y continuar – iOS / Android: Flujo posterior a la activación de cuenta. F-13 – Walvy_Especificacion_UX_Onboarding_App: Continuidad post autenticación hacia onboarding y primera acción útil. | L31: CP-M1-ONB-001 | M31: Evidencia QA onboarding por enlazar | N31: Pendiente | O31: 6670:13197 | P31: https://www.figma.com/design/v45c4HTKnPnU0XABMa5vjY/Walvi-APP---Edificate-Inteligente?node-id=6670-13197 | Q31: Confirmado Doc + Figma | R31: Aprobado | U31: M01-RGL-005
A32: M1-V28 | B32: Foco del Mes | C32: Foco declarado | D32: Usuario selecciona un objetivo | E32: Registrar foco como declarado y usarlo como contexto; no debe superar señales críticas. | F32: M1-HU-019 | G32: CA1-CA3 | H32: M1-RN-ONB-019 / M1-RN-ONB-011 / M1-RN-ONB-012 | I32: Documental / validación Producto | MVP | J32: HU M1-HU-019; Fase 3 | S2/S3 | S1/S2/S4 | K32: S2 – Walvy_Onboarding_Diagnostico_Fase3_Reglas_Contextuales_Suficiencia_Semaforo_CTA_v1_0: Suficiencia, diagnóstico parcial, semáforo, presión principal y CTA. S3 – Walvy_Onboarding_Diagnostico_Fase3_Anexo_BDD_Reglas_Productivas_v1_0: Datos, enums, eventos, versionamiento, retoma y trazabilidad. S1 – Walvy_Especificacion_UX_Onboarding_App: Secuencia, pantallas, carga documental, postergación y reactivación. S4 – Walvy_Rector_Producto_y_Funcionalidades_MVP_v1.0_OLD_20260516: Responsabilidad del onboarding y límites transversales. M1-HU-019 – Historia de Usuario del onboarding utilizada como respaldo funcional. Fase 3 – Reglas contextuales de suficiencia, semáforo, presión principal y CTA. | L32: CP-M1-ONB-002 | M32: Evidencia QA Foco del Mes por enlazar | N32: Pendiente | O32: 6670:13227 | P32: https://www.figma.com/design/v45c4HTKnPnU0XABMa5vjY/Walvi-APP---Edificate-Inteligente?node-id=6670-13227 | Q32: Confirmado Doc + Figma | R32: Aprobado | T32: PD-M1-05 | U32: M01-RGL-006 / RB-FM-001 / RB-FM-002 / RB-FM-003
A33: M1-V29 | B33: Foco del Mes | C33: Foco no declarado | D33: Usuario continúa sin seleccionar foco | E33: Permitir continuar; registrar no declarado y no bloquear carga documental. | F33: M1-HU-019 | G33: CA1-CA3 | H33: M1-RN-ONB-019 / M1-RN-ONB-011 / M1-RN-ONB-012 | I33: Documental / validación Producto | MVP | J33: HU M1-HU-019; Fase 3 | S2/S3 | S1/S2/S4 | K33: S2 – Walvy_Onboarding_Diagnostico_Fase3_Reglas_Contextuales_Suficiencia_Semaforo_CTA_v1_0: Suficiencia, diagnóstico parcial, semáforo, presión principal y CTA. S3 – Walvy_Onboarding_Diagnostico_Fase3_Anexo_BDD_Reglas_Productivas_v1_0: Datos, enums, eventos, versionamiento, retoma y trazabilidad. S1 – Walvy_Especificacion_UX_Onboarding_App: Secuencia, pantallas, carga documental, postergación y reactivación. S4 – Walvy_Rector_Producto_y_Funcionalidades_MVP_v1.0_OLD_20260516: Responsabilidad del onboarding y límites transversales. M1-HU-019 – Historia de Usuario del onboarding utilizada como respaldo funcional. Fase 3 – Reglas contextuales de suficiencia, semáforo, presión principal y CTA. | L33: CP-M1-ONB-002 | M33: Evidencia QA Foco del Mes por enlazar | N33: Pendiente | O33: 6670:13290 | P33: https://www.figma.com/design/v45c4HTKnPnU0XABMa5vjY/Walvi-APP---Edificate-Inteligente?node-id=6670-13290 | Q33: Documentado; representación UI a confirmar | R33: Ajustar | S33: Ajustar la continuidad. Si el usuario posterga la selección de foco, debe conservarse el estado pendiente y aplicarse la salida de postergación; no corresponde describir esta acción como avance directo a carga documental. | T33: PD-M1-05 | U33: M01-RGL-007
A34: M1-V30 | B34: Foco del Mes | C34: Foco inferido/sugerido | D34: No existe foco declarado y hay señales de comportamiento | E34: Puede registrarse como inferido/sugerido; comunicarlo como aproximación y sujeto a regla de Producto. | F34: M1-HU-019 | G34: CA1-CA3 | H34: M1-RN-ONB-019 / M1-RN-ONB-011 / M1-RN-ONB-012 | I34: Documental / validación Producto | MVP | J34: HU M1-HU-019; Fase 3 | S2/S3 | S1/S2/S4 | K34: S2 – Walvy_Onboarding_Diagnostico_Fase3_Reglas_Contextuales_Suficiencia_Semaforo_CTA_v1_0: Suficiencia, diagnóstico parcial, semáforo, presión principal y CTA. S3 – Walvy_Onboarding_Diagnostico_Fase3_Anexo_BDD_Reglas_Productivas_v1_0: Datos, enums, eventos, versionamiento, retoma y trazabilidad. S1 – Walvy_Especificacion_UX_Onboarding_App: Secuencia, pantallas, carga documental, postergación y reactivación. S4 – Walvy_Rector_Producto_y_Funcionalidades_MVP_v1.0_OLD_20260516: Responsabilidad del onboarding y límites transversales. M1-HU-019 – Historia de Usuario del onboarding utilizada como respaldo funcional. Fase 3 – Reglas contextuales de suficiencia, semáforo, presión principal y CTA. | L34: CP-M1-ONB-002 | M34: Evidencia QA Foco del Mes por enlazar | N34: Pendiente | O34: 3361:2744 | P34: https://www.figma.com/design/v45c4HTKnPnU0XABMa5vjY/Walvi-APP---Edificate-Inteligente?node-id=3361-2744 | Q34: Documento solamente / UI a validar | R34: Ajustar | S34: Decisión de Producto cerrada. Ver M1-DP-002 y AX-M1-002. Cuando no exista Foco del Mes activo y haya una versión válida del Diagnóstico, Walvy puede sugerir un foco usando la lectura consolidada de M04, M06 y M05 con prioridad M04 → M06 → M05. M04 deriva a Bajar deuda; M06 a Evitar atrasos cuando exista riesgo temporal de pago/vencimiento y, en caso contrario, a Ordenar compromisos; M05 a Aumentar margen, Ahorrar un monto o Cumplir presupuesto según la señal dominante y las condiciones ya documentadas. La sugerencia se presenta con CTA primario “Usar este foco”, que la guarda directamente como foco activo, y secundario “Revisar foco”, que lleva a Mi Perfil → Mi foco del mes con la opción sugerida premarcada. Si no se acepta, el foco permanece no declarado y puede recalcularse con una nueva versión válida del Diagnóstico. Una vez aceptado, no se reemplaza automáticamente. Ajuste requerido a Kabeli: actualizar D/E de V30 y complementar M1-RN-ONB-019; usar únicamente el estado “sugerido”. | T34: PD-M1-05 | U34: RB-FM-004 / RB-FM-006 / M1-DP-002
A35: M1-V31 | B35: Foco del Mes | C35: Bajar deuda | D35: Usuario selecciona Bajar deuda | E35: Guardar objetivo y usarlo como contexto de experiencia sin ocultar señal crítica. | F35: M1-HU-019 | G35: CA1-CA3 | H35: M1-RN-ONB-020 / M1-RN-ONB-012 | I35: Figma + reglas de foco / validar vigencia | MVP | J35: Figma 6670:13227 | S1/S2/S4 | K35: S1 – Walvy_Especificacion_UX_Onboarding_App: Secuencia, pantallas, carga documental, postergación y reactivación. S2 – Walvy_Onboarding_Diagnostico_Fase3_Reglas_Contextuales_Suficiencia_Semaforo_CTA_v1_0: Suficiencia, diagnóstico parcial, semáforo, presión principal y CTA. S4 – Walvy_Rector_Producto_y_Funcionalidades_MVP_v1.0_OLD_20260516: Responsabilidad del onboarding y límites transversales. Figma – referencia visual en nodo(s): 6670:13227 | L35: CP-M1-ONB-002 | M35: Evidencia QA catálogo Foco del Mes por enlazar | N35: Pendiente | O35: 6670:13227 | P35: https://www.figma.com/design/v45c4HTKnPnU0XABMa5vjY/Walvi-APP---Edificate-Inteligente?node-id=6670-13227 | Q35: Confirmado Doc + Figma | R35: Aprobado | T35: PD-M1-06 | U35: M01-RGL-006 / RB-FM-001
A36: M1-V32 | B36: Foco del Mes | C36: Ahorrar un monto | D36: Usuario selecciona Ahorrar un monto | E36: Guardar objetivo y usarlo como contexto. | F36: M1-HU-019 | G36: CA1-CA3 | H36: M1-RN-ONB-020 / M1-RN-ONB-012 | I36: Figma + reglas de foco / validar vigencia | MVP | J36: Figma 6670:13227 | S1/S2/S4 | K36: S1 – Walvy_Especificacion_UX_Onboarding_App: Secuencia, pantallas, carga documental, postergación y reactivación. S2 – Walvy_Onboarding_Diagnostico_Fase3_Reglas_Contextuales_Suficiencia_Semaforo_CTA_v1_0: Suficiencia, diagnóstico parcial, semáforo, presión principal y CTA. S4 – Walvy_Rector_Producto_y_Funcionalidades_MVP_v1.0_OLD_20260516: Responsabilidad del onboarding y límites transversales. Figma – referencia visual en nodo(s): 6670:13227 | L36: CP-M1-ONB-002 | M36: Evidencia QA catálogo Foco del Mes por enlazar | N36: Pendiente | O36: 6670:13227 | P36: https://www.figma.com/design/v45c4HTKnPnU0XABMa5vjY/Walvi-APP---Edificate-Inteligente?node-id=6670-13227 | Q36: Confirmado Doc + Figma | R36: Aprobado | T36: PD-M1-06 | U36: M01-RGL-006 / RB-FM-001
A37: M1-V33 | B37: Foco del Mes | C37: Aumentar margen | D37: Usuario selecciona Aumentar margen | E37: Guardar objetivo y usarlo como contexto. | F37: M1-HU-019 | G37: CA1-CA3 | H37: M1-RN-ONB-020 / M1-RN-ONB-012 | I37: Figma + reglas de foco / validar vigencia | MVP | J37: Figma 6670:13227 | S1/S2/S4 | K37: S1 – Walvy_Especificacion_UX_Onboarding_App: Secuencia, pantallas, carga documental, postergación y reactivación. S2 – Walvy_Onboarding_Diagnostico_Fase3_Reglas_Contextuales_Suficiencia_Semaforo_CTA_v1_0: Suficiencia, diagnóstico parcial, semáforo, presión principal y CTA. S4 – Walvy_Rector_Producto_y_Funcionalidades_MVP_v1.0_OLD_20260516: Responsabilidad del onboarding y límites transversales. Figma – referencia visual en nodo(s): 6670:13227 | L37: CP-M1-ONB-002 | M37: Evidencia QA catálogo Foco del Mes por enlazar | N37: Pendiente | O37: 6670:13227 | P37: https://www.figma.com/design/v45c4HTKnPnU0XABMa5vjY/Walvi-APP---Edificate-Inteligente?node-id=6670-13227 | Q37: Confirmado Doc + Figma | R37: Aprobado | T37: PD-M1-06 | U37: M01-RGL-006 / RB-FM-001
A38: M1-V34 | B38: Foco del Mes | C38: Evitar atrasos | D38: Usuario selecciona Evitar atrasos | E38: Guardar objetivo y usarlo como contexto. | F38: M1-HU-019 | G38: CA1-CA3 | H38: M1-RN-ONB-020 / M1-RN-ONB-012 | I38: Figma + reglas de foco / validar vigencia | MVP | J38: Figma 6670:13227 | S1/S2/S4 | K38: S1 – Walvy_Especificacion_UX_Onboarding_App: Secuencia, pantallas, carga documental, postergación y reactivación. S2 – Walvy_Onboarding_Diagnostico_Fase3_Reglas_Contextuales_Suficiencia_Semaforo_CTA_v1_0: Suficiencia, diagnóstico parcial, semáforo, presión principal y CTA. S4 – Walvy_Rector_Producto_y_Funcionalidades_MVP_v1.0_OLD_20260516: Responsabilidad del onboarding y límites transversales. Figma – referencia visual en nodo(s): 6670:13227 | L38: CP-M1-ONB-002 | M38: Evidencia QA catálogo Foco del Mes por enlazar | N38: Pendiente | O38: 6670:13227 | P38: https://www.figma.com/design/v45c4HTKnPnU0XABMa5vjY/Walvi-APP---Edificate-Inteligente?node-id=6670-13227 | Q38: Confirmado Doc + Figma | R38: Aprobado | T38: PD-M1-06 | U38: M01-RGL-006 / RB-FM-001
A39: M1-V35 | B39: Foco del Mes | C39: Cumplir presupuesto | D39: Usuario selecciona Cumplir presupuesto | E39: Guardar objetivo y usarlo como contexto. | F39: M1-HU-019 | G39: CA1-CA3 | H39: M1-RN-ONB-020 / M1-RN-ONB-012 | I39: Figma + reglas de foco / validar vigencia | MVP | J39: Figma 6670:13227 | S1/S2/S4 | K39: S1 – Walvy_Especificacion_UX_Onboarding_App: Secuencia, pantallas, carga documental, postergación y reactivación. S2 – Walvy_Onboarding_Diagnostico_Fase3_Reglas_Contextuales_Suficiencia_Semaforo_CTA_v1_0: Suficiencia, diagnóstico parcial, semáforo, presión principal y CTA. S4 – Walvy_Rector_Producto_y_Funcionalidades_MVP_v1.0_OLD_20260516: Responsabilidad del onboarding y límites transversales. Figma – referencia visual en nodo(s): 6670:13227 | L39: CP-M1-ONB-002 | M39: Evidencia QA catálogo Foco del Mes por enlazar | N39: Pendiente | O39: 6670:13227 | P39: https://www.figma.com/design/v45c4HTKnPnU0XABMa5vjY/Walvi-APP---Edificate-Inteligente?node-id=6670-13227 | Q39: Confirmado Doc + Figma | R39: Aprobado | T39: PD-M1-06 | U39: M01-RGL-006 / RB-FM-001
A40: M1-V36 | B40: Foco del Mes | C40: Ordenar compromisos | D40: Usuario selecciona Ordenar compromisos | E40: Guardar objetivo y usarlo como contexto. | F40: M1-HU-019 | G40: CA1-CA3 | H40: M1-RN-ONB-020 / M1-RN-ONB-012 | I40: Figma + reglas de foco / validar vigencia | MVP | J40: Figma 6670:13227 | S1/S2/S4 | K40: S1 – Walvy_Especificacion_UX_Onboarding_App: Secuencia, pantallas, carga documental, postergación y reactivación. S2 – Walvy_Onboarding_Diagnostico_Fase3_Reglas_Contextuales_Suficiencia_Semaforo_CTA_v1_0: Suficiencia, diagnóstico parcial, semáforo, presión principal y CTA. S4 – Walvy_Rector_Producto_y_Funcionalidades_MVP_v1.0_OLD_20260516: Responsabilidad del onboarding y límites transversales. Figma – referencia visual en nodo(s): 6670:13227 | L40: CP-M1-ONB-002 | M40: Evidencia QA catálogo Foco del Mes por enlazar | N40: Pendiente | O40: 6670:13227 | P40: https://www.figma.com/design/v45c4HTKnPnU0XABMa5vjY/Walvi-APP---Edificate-Inteligente?node-id=6670-13227 | Q40: Confirmado Doc + Figma | R40: Aprobado | T40: PD-M1-06 | U40: M01-RGL-006 / RB-FM-001
A41: M1-V37 | B41: Carga documental | C41: Sin documento cargado | D41: No existe archivo seleccionado | E41: Mostrar estado listo para cargar; CTA cargar cartola/documento. | F41: M1-HU-020 | G41: CA1-CA3 | H41: M1-RN-ONB-002 / M1-RN-ONB-006 / M1-RN-ONB-021 | I41: MVP | Figma / pendiente validación técnica | J41: S1/S2/S3 | S2/S3 | Figma 6670:13168 | K41: S1 – Walvy_Especificacion_UX_Onboarding_App: Secuencia, pantallas, carga documental, postergación y reactivación. S2 – Walvy_Onboarding_Diagnostico_Fase3_Reglas_Contextuales_Suficiencia_Semaforo_CTA_v1_0: Suficiencia, diagnóstico parcial, semáforo, presión principal y CTA. S3 – Walvy_Onboarding_Diagnostico_Fase3_Anexo_BDD_Reglas_Productivas_v1_0: Datos, enums, eventos, versionamiento, retoma y trazabilidad. Figma – referencia visual en nodo(s): 6670:13168 | L41: CP-M1-ONB-003 | M41: Evidencia QA carga documental por enlazar | N41: Pendiente | O41: 6670:13168 | P41: https://www.figma.com/design/v45c4HTKnPnU0XABMa5vjY/Walvi-APP---Edificate-Inteligente?node-id=6670-13168 | Q41: Confirmado Doc + Figma | R41: Aprobado | T41: PD-M1-07 | U41: M01-RGL-009
A42: M1-V38 | B42: Carga documental | C42: Documento seleccionado / subiendo | D42: Usuario selecciona archivo | E42: Mostrar progreso de carga y mantener continuidad. | F42: M1-HU-020 | G42: CA1-CA3 | H42: M1-RN-ONB-002 / M1-RN-ONB-021 | I42: MVP | Figma / pendiente validación técnica | J42: S1/S2/S3 | Figma 6670:13168 | K42: S1 – Walvy_Especificacion_UX_Onboarding_App: Secuencia, pantallas, carga documental, postergación y reactivación. S2 – Walvy_Onboarding_Diagnostico_Fase3_Reglas_Contextuales_Suficiencia_Semaforo_CTA_v1_0: Suficiencia, diagnóstico parcial, semáforo, presión principal y CTA. S3 – Walvy_Onboarding_Diagnostico_Fase3_Anexo_BDD_Reglas_Productivas_v1_0: Datos, enums, eventos, versionamiento, retoma y trazabilidad. Figma – referencia visual en nodo(s): 6670:13168 | L42: CP-M1-ONB-003 | M42: Evidencia QA carga documental por enlazar | N42: Pendiente | O42: 6459:8023 | P42: https://www.figma.com/design/v45c4HTKnPnU0XABMa5vjY/Walvi-APP---Edificate-Inteligente?node-id=6459-8023 | Q42: Confirmado Doc + Figma | R42: Aprobado | T42: PD-M1-07 | U42: M01-RGL-009
A43: M1-V39 | B43: Carga documental | C43: Documento usable | D43: Archivo permite extraer información relevante | E43: Continuar a revisión/suficiencia. | F43: M1-HU-025 | G43: CA1 | H43: M1-RN-ONB-004 / M1-RN-ONB-008 | I43: MVP | J43: S2/S3 | K43: S2 – Walvy_Onboarding_Diagnostico_Fase3_Reglas_Contextuales_Suficiencia_Semaforo_CTA_v1_0: Suficiencia, diagnóstico parcial, semáforo, presión principal y CTA. S3 – Walvy_Onboarding_Diagnostico_Fase3_Anexo_BDD_Reglas_Productivas_v1_0: Datos, enums, eventos, versionamiento, retoma y trazabilidad. | L43: CP-M1-ONB-011 | M43: Evidencia QA documento usable/base suficiente por enlazar | N43: Pendiente | O43: 6672:8252 | P43: https://www.figma.com/design/v45c4HTKnPnU0XABMa5vjY/Walvi-APP---Edificate-Inteligente?node-id=6672-8252 | Q43: Confirmado Doc + Figma | R43: Aprobado | U43: M01-RGL-009 / M01-RGL-012
A44: M1-V40 | B44: Carga documental | C44: Documento no usable/no procesable | D44: Archivo no permite extracción relevante o no corresponde | E44: No habilitar diagnóstico; pedir subir otro/revisar archivo. | F44: M1-HU-022 | G44: CA1-CA3 | H44: M1-RN-ONB-006 / M1-RN-ONB-007 | I44: MVP | J44: S2/S3 | S1/S2 | K44: S2 – Walvy_Onboarding_Diagnostico_Fase3_Reglas_Contextuales_Suficiencia_Semaforo_CTA_v1_0: Suficiencia, diagnóstico parcial, semáforo, presión principal y CTA. S3 – Walvy_Onboarding_Diagnostico_Fase3_Anexo_BDD_Reglas_Productivas_v1_0: Datos, enums, eventos, versionamiento, retoma y trazabilidad. S1 – Walvy_Especificacion_UX_Onboarding_App: Secuencia, pantallas, carga documental, postergación y reactivación. | L44: CP-M1-ONB-007 | M44: Evidencia QA documento no procesable por enlazar | N44: Pendiente | O44: 3361:2744 | P44: https://www.figma.com/design/v45c4HTKnPnU0XABMa5vjY/Walvi-APP---Edificate-Inteligente?node-id=3361-2744 | Q44: Documentado; pantalla exacta a validar | R44: Aprobado | U44: M01-RGL-010
A45: M1-V41 | B45: Carga documental | C45: Documento con contraseña | D45: Archivo protegido requiere tratamiento | E45: Solicitar contraseña o tratamiento definido en diseño; regla técnica/seguridad debe formalizarse. | F45: M1-HU-034 | G45: CA1-CA3 | H45: M1-RN-ONB-022 | I45: Figma / pendiente PO-Técnica | J45: Figma 6672:7841; 6672:7945; 6672:8098 | K45: Figma – referencia visual en nodo(s): 6672:7841, 6672:7945, 6672:8098 | L45: CP-M1-ONB-021 | M45: Evidencia QA documento protegido por enlazar | N45: Pendiente | O45: 6672:7841 | P45: https://www.figma.com/design/v45c4HTKnPnU0XABMa5vjY/Walvi-APP---Edificate-Inteligente?node-id=6672-7841 | Q45: Figma solamente / formalizar regla | R45: Aprobado | S45: Decisión de Producto cerrada. Ver M1-DP-003. Baseline Walvy: para un documento protegido asociado al RUT, intentar como máximo tres variantes automáticas, una vez cada una y detenerse al abrir: (1) RUT numérico completo sin dígito verificador, (2) últimos 4 dígitos sin DV y (3) primeros 4 dígitos sin DV. Si ninguna funciona, solicitar contraseña manual. Una contraseña manual incorrecta permite corregir/reintentar o cargar otro documento, sin bloquear la cuenta ni crear un contador propio de Producto para el MVP. Ninguna contraseña automática o manual debe persistirse ni registrarse en logs, analytics, eventos o checkpoints. Kabeli/Seguridad debe validar catálogo, orden, manejo temporal seguro, ausencia de persistencia y comportamiento de error, e informar cualquier restricción que exija modificar este baseline. | T45: PD-M1-08 | U45: M1-DP-003 (baseline funcional/técnico PO; validación Kabeli/Seguridad pendiente)
A46: M1-V42 | B46: Carga documental | C46: Documento desactualizado | D46: Dato existe pero no corresponde al período/vigencia | E46: Reducir confianza o pedir corrección; no tratar como base suficiente sin regla. | F46: M1-HU-034 | G46: CA1-CA3 | H46: M1-RN-ONB-023 / M1-RN-ONB-008 | I46: Anexo BDD / UI por validar | MVP | J46: D2-S3 | S2/S3 | K46: D2-S3 – Walvy_Onboarding_Diagnostico_Fase3_Anexo_BDD_Reglas_Productivas_v1_0: Datos, enums, eventos, versionamiento, retoma y trazabilidad. S2 – Walvy_Onboarding_Diagnostico_Fase3_Reglas_Contextuales_Suficiencia_Semaforo_CTA_v1_0: Suficiencia, diagnóstico parcial, semáforo, presión principal y CTA. S3 – Walvy_Onboarding_Diagnostico_Fase3_Anexo_BDD_Reglas_Productivas_v1_0: Datos, enums, eventos, versionamiento, retoma y trazabilidad. | L46: CP-M1-ONB-022 | M46: Evidencia QA documento desactualizado por enlazar | N46: Pendiente | O46: 3361:2744 | P46: https://www.figma.com/design/v45c4HTKnPnU0XABMa5vjY/Walvi-APP---Edificate-Inteligente?node-id=3361-2744 | Q46: Documento solamente / UI a validar | R46: Aprobado | T46: PD-M1-09 | U46: M01-RGL-010
A47: M1-V43 | B47: Carga documental | C47: Documento duplicado | D47: Documento ya fue cargado/detectado como duplicado | E47: Aplicar tratamiento productivo definido; evitar duplicar información. | F47: M1-HU-034 | G47: CA1-CA3 | H47: M1-RN-ONB-024 / M1-RN-ONB-008 | I47: Anexo BDD / UI por validar | MVP | J47: D2-S3 | S2/S3 | K47: D2-S3 – Walvy_Onboarding_Diagnostico_Fase3_Anexo_BDD_Reglas_Productivas_v1_0: Datos, enums, eventos, versionamiento, retoma y trazabilidad. S2 – Walvy_Onboarding_Diagnostico_Fase3_Reglas_Contextuales_Suficiencia_Semaforo_CTA_v1_0: Suficiencia, diagnóstico parcial, semáforo, presión principal y CTA. S3 – Walvy_Onboarding_Diagnostico_Fase3_Anexo_BDD_Reglas_Productivas_v1_0: Datos, enums, eventos, versionamiento, retoma y trazabilidad. | L47: CP-M1-ONB-023 | M47: Evidencia QA duplicado por enlazar | N47: Pendiente | O47: 3361:2744 | P47: https://www.figma.com/design/v45c4HTKnPnU0XABMa5vjY/Walvi-APP---Edificate-Inteligente?node-id=3361-2744 | Q47: Documento / validación técnica-producto | R47: Ajustar | S47: Decisión de Producto cerrada. Ver M1-DP-004. La deduplicación debe operar por cuenta/usuario mediante una huella de contenido (hash o token equivalente) sin requerir almacenamiento permanente del archivo. Si la misma huella corresponde a un documento procesado correctamente y permanece vigente, no admitir una nueva carga ni reprocesarla; informar que el archivo ya fue cargado y evitar duplicar datos/suficiencia. Si el procesamiento anterior falló por una causa técnica transitoria, permitir retry/reprocesamiento sin tratarlo como duplicado. Si el documento fue determinísticamente no procesable, puede conservarse temporalmente la huella junto con motivo y versión del procesador para evitar reprocesamientos idénticos hasta su expiración o cambio de procesador. Kabeli debe ajustar D/E y M1-RN-ONB-024, manteniendo el archivo como insumo temporal y la metadata mínima necesaria para deduplicación. | T47: PD-M1-09 | U47: M1-DP-004
A48: M1-V44 | B48: Procesamiento | C48: Procesamiento normal | D48: Documento cargado y análisis en curso | E48: Mostrar progreso guiado. | F48: M1-HU-021 | G48: CA1 | H48: M1-RN-ONB-002 / M1-RN-ONB-008 | I48: MVP | J48: S1/S2/S3 | S2/S3 | K48: S1 – Walvy_Especificacion_UX_Onboarding_App: Secuencia, pantallas, carga documental, postergación y reactivación. S2 – Walvy_Onboarding_Diagnostico_Fase3_Reglas_Contextuales_Suficiencia_Semaforo_CTA_v1_0: Suficiencia, diagnóstico parcial, semáforo, presión principal y CTA. S3 – Walvy_Onboarding_Diagnostico_Fase3_Anexo_BDD_Reglas_Productivas_v1_0: Datos, enums, eventos, versionamiento, retoma y trazabilidad. | L48: CP-M1-ONB-004 | M48: Evidencia QA procesamiento por enlazar | N48: Pendiente | O48: 6459:8394 | P48: https://www.figma.com/design/v45c4HTKnPnU0XABMa5vjY/Walvi-APP---Edificate-Inteligente?node-id=6459-8394 | Q48: Confirmado Doc + Figma | R48: Ajustar | S48: Completar el comportamiento esperado. Durante el procesamiento debe mostrarse el progreso y permitirse continuar más tarde o salir sin perder los documentos ni el avance, conservando el estado necesario para retomar cuando corresponda. | U48: M01-RGL-014 / M01-RGL-008
A49: M1-V45 | B49: Procesamiento | C49: Demora suave | D49: Análisis supera umbral configurable inicial | E49: Mostrar que tarda más de lo esperado y permitir esperar o salir sin perder avance. | F49: M1-HU-021 | G49: CA1-CA3 | H49: M1-RN-ONB-013 / M1-RN-ONB-014 / M1-RN-ONB-018 | I49: Requiere validación técnica | MVP | J49: S2/S3 | S1/S2/S3 | S3 | K49: S2 – Walvy_Onboarding_Diagnostico_Fase3_Reglas_Contextuales_Suficiencia_Semaforo_CTA_v1_0: Suficiencia, diagnóstico parcial, semáforo, presión principal y CTA. S3 – Walvy_Onboarding_Diagnostico_Fase3_Anexo_BDD_Reglas_Productivas_v1_0: Datos, enums, eventos, versionamiento, retoma y trazabilidad. S1 – Walvy_Especificacion_UX_Onboarding_App: Secuencia, pantallas, carga documental, postergación y reactivación. | L49: CP-M1-ONB-006 | M49: Evidencia QA demora por enlazar | N49: Pendiente | O49: 6670:13533 | P49: https://www.figma.com/design/v45c4HTKnPnU0XABMa5vjY/Walvi-APP---Edificate-Inteligente?node-id=6670-13533 | Q49: Doc + Figma / parámetro por validar | R49: Aprobado | T49: PD-M1-10 | U49: M01-RGL-014 / M01-RGL-008
A50: M1-V46 | B50: Procesamiento | C50: Demora extendida | D50: Análisis supera segundo umbral configurable | E50: Ofrecer salida segura: avisarme/volver después/seguir esperando según implementación. | F50: M1-HU-021 | G50: CA1-CA3 | H50: M1-RN-ONB-013 / M1-RN-ONB-014 / M1-RN-ONB-018 | I50: Requiere validación técnica | MVP | J50: S2/S3 | S1/S2/S3 | S3 | K50: S2 – Walvy_Onboarding_Diagnostico_Fase3_Reglas_Contextuales_Suficiencia_Semaforo_CTA_v1_0: Suficiencia, diagnóstico parcial, semáforo, presión principal y CTA. S3 – Walvy_Onboarding_Diagnostico_Fase3_Anexo_BDD_Reglas_Productivas_v1_0: Datos, enums, eventos, versionamiento, retoma y trazabilidad. S1 – Walvy_Especificacion_UX_Onboarding_App: Secuencia, pantallas, carga documental, postergación y reactivación. | L50: CP-M1-ONB-006 | M50: Evidencia QA demora por enlazar | N50: Pendiente | O50: 3361:2744 | P50: https://www.figma.com/design/v45c4HTKnPnU0XABMa5vjY/Walvi-APP---Edificate-Inteligente?node-id=3361-2744 | Q50: Documento solamente / UI a validar | R50: Aprobado | T50: PD-M1-10 | U50: M01-RGL-014 / M01-RGL-008
A51: M1-V47 | B51: Procesamiento | C51: Procesamiento fallido | D51: No se puede procesar documento o dato crítico | E51: Pedir nueva carga o completar información clave; registrar fallback/error. | F51: M1-HU-021 / M1-HU-022 | G51: CA1-CA3 | H51: M1-RN-ONB-025 / M1-RN-ONB-006 | I51: Documental + Figma / validar copy | MVP | J51: D2-S1/D2-S2 | S2/S3 | K51: D2-S1 – Walvy_Especificacion_UX_Onboarding_App: Secuencia, pantallas, carga documental, postergación y reactivación. D2-S2 – Walvy_Onboarding_Diagnostico_Fase3_Reglas_Contextuales_Suficiencia_Semaforo_CTA_v1_0: Suficiencia, diagnóstico parcial, semáforo, presión principal y CTA. S2 – Walvy_Onboarding_Diagnostico_Fase3_Reglas_Contextuales_Suficiencia_Semaforo_CTA_v1_0: Suficiencia, diagnóstico parcial, semáforo, presión principal y CTA. S3 – Walvy_Onboarding_Diagnostico_Fase3_Anexo_BDD_Reglas_Productivas_v1_0: Datos, enums, eventos, versionamiento, retoma y trazabilidad. | L51: CP-M1-ONB-007 | M51: Evidencia QA fallo de procesamiento por enlazar | N51: Pendiente | O51: 3361:2744 | P51: https://www.figma.com/design/v45c4HTKnPnU0XABMa5vjY/Walvi-APP---Edificate-Inteligente?node-id=3361-2744 | Q51: Documento solamente / UI a validar | R51: Ajustar | S51: Decisión de Producto cerrada. Ver M1-DP-005. V47 corresponde exclusivamente a un fallo técnico recuperable/transitorio ocurrido después de admitir el documento y durante el procesamiento/análisis. No debe mezclarse con documento no procesable (V40) ni con insuficiencia de datos (V50/V51). Ante V47 no se genera Diagnóstico; se conservan documentos, selección y checkpoint. CTA primario: Reintentar. CTA secundario: Volver a revisión, desde donde el usuario puede reemplazar o agregar documentación; Continuar más tarde puede mantenerse si la capacidad de retoma está disponible. El nuevo intento debe quedar trazado al job original y no duplicar documentos ni datos. Kabeli debe ajustar D/E y precisar M1-RN-ONB-025 sin crear una nueva RN. Además, en la próxima versión Kabeli debe corregir la asociación documental: V47 debe quedar en M1-HU-021 + M1-RN-ONB-025; M1-HU-022 / M1-RN-ONB-006 corresponden a documento no procesable/insuficiencia y no deben permanecer mezclados. | T51: PD-M1-11 | U51: M01-RGL-014 / M1-DP-005
A52: M1-V48 | B52: Suficiencia | C52: Base suficiente | D52: Documento usable + ingreso y movimientos detectados/confirmados + compromisos o recurrentes + confianza suficiente | E52: Permitir diagnóstico completo; CTA Comenzar diagnóstico. | F52: M1-HU-025 | G52: CA1-CA3 | H52: M1-RN-ONB-004 / M1-RN-ONB-009 / M1-RN-ONB-011 / M1-RN-ONB-012 / M1-RN-ONB-016 | I52: MVP | J52: S2/S3 | S1/S2/S4 | S1/S2 | K52: S2 – Walvy_Onboarding_Diagnostico_Fase3_Reglas_Contextuales_Suficiencia_Semaforo_CTA_v1_0: Suficiencia, diagnóstico parcial, semáforo, presión principal y CTA. S3 – Walvy_Onboarding_Diagnostico_Fase3_Anexo_BDD_Reglas_Productivas_v1_0: Datos, enums, eventos, versionamiento, retoma y trazabilidad. S1 – Walvy_Especificacion_UX_Onboarding_App: Secuencia, pantallas, carga documental, postergación y reactivación. S4 – Walvy_Rector_Producto_y_Funcionalidades_MVP_v1.0_OLD_20260516: Responsabilidad del onboarding y límites transversales. | L52: CP-M1-ONB-011 | M52: Evidencia QA diagnóstico completo por enlazar | N52: Pendiente | O52: 6670:13387 | P52: https://www.figma.com/design/v45c4HTKnPnU0XABMa5vjY/Walvi-APP---Edificate-Inteligente?node-id=6670-13387 | Q52: Confirmado Doc + Figma | R52: Aprobado | S52: Corrección de trazabilidad: V48 representa revisión/suficiencia previa al Diagnóstico, no cierre del onboarding. En la próxima versión Kabeli debe retirar de V48 las asociaciones de diagnóstico/cierre (HU-025; RN-ONB-009/011/012/016 según corresponda) y alinearla con revisión/suficiencia (HU-024; M01-RGL-011/012/013). D/E se mantienen. | U52: M01-RGL-011 / M01-RGL-012 / M01-RGL-013 / M1-DP-009
A53: M1-V49 | B53: Suficiencia | C53: Datos por confirmar no bloqueantes | D53: Base documental usable y faltantes puntuales que no cambian lectura central | E53: Permitir diagnóstico parcial con advertencia; CTA principal completar y secundario comenzar con esta base cuando corresponda. | F53: M1-HU-026 | G53: CA1-CA3 | H53: M1-RN-ONB-005 / M1-RN-ONB-008 | I53: MVP condicionado | MVP | J53: S2/S3 | K53: S2 – Walvy_Onboarding_Diagnostico_Fase3_Reglas_Contextuales_Suficiencia_Semaforo_CTA_v1_0: Suficiencia, diagnóstico parcial, semáforo, presión principal y CTA. S3 – Walvy_Onboarding_Diagnostico_Fase3_Anexo_BDD_Reglas_Productivas_v1_0: Datos, enums, eventos, versionamiento, retoma y trazabilidad. | L53: CP-M1-ONB-012 | M53: Evidencia QA diagnóstico parcial por enlazar | N53: Pendiente | O53: 6459:8169 | P53: https://www.figma.com/design/v45c4HTKnPnU0XABMa5vjY/Walvi-APP---Edificate-Inteligente?node-id=6459-8169 | Q53: Confirmado Doc + Figma | R53: Aprobado | U53: M01-RGL-011 / M01-RGL-012 / M01-RGL-013 / M1-DP-009
A54: M1-V50 | B54: Suficiencia | C54: Datos por confirmar críticos | D54: Dato pendiente puede cambiar diagnóstico central | E54: Bloquear diagnóstico parcial hasta confirmar/completar. | F54: M1-HU-027 / M1-HU-023 | G54: CA1-CA3 | H54: M1-RN-ONB-006 / M1-RN-ONB-007 / M1-RN-ONB-010 | I54: MVP | J54: S2/S3 | S1/S2 | K54: S2 – Walvy_Onboarding_Diagnostico_Fase3_Reglas_Contextuales_Suficiencia_Semaforo_CTA_v1_0: Suficiencia, diagnóstico parcial, semáforo, presión principal y CTA. S3 – Walvy_Onboarding_Diagnostico_Fase3_Anexo_BDD_Reglas_Productivas_v1_0: Datos, enums, eventos, versionamiento, retoma y trazabilidad. S1 – Walvy_Especificacion_UX_Onboarding_App: Secuencia, pantallas, carga documental, postergación y reactivación. | L54: CP-M1-ONB-014 | M54: Evidencia QA bloqueo/suficiencia por enlazar | N54: Pendiente | O54: 3361:2744 | P54: https://www.figma.com/design/v45c4HTKnPnU0XABMa5vjY/Walvi-APP---Edificate-Inteligente?node-id=3361-2744 | Q54: Documento solamente / UI a validar | R54: Ajustar | S54: Decisión de Producto cerrada. Ver M1-DP-008 y AX-M1-003. M01-RGL-012 permanece como único gate de suficiencia. Cada indicador conserva detection_status, data_origin, confidence y evidence, pero debe normalizarse primero a sufficient, pending o missing; el gate evalúa luego disponibilidad mínima y criticidad funcional. Falta elemento mínimo obligatorio → blocked; base mínima + pendiente crítico → partial bloqueado; base mínima + solo pendientes no críticos → partial permitido; sin pendientes relevantes → complete. Fronteras documentadas: movimientos recientes pendientes bloquean; pagos recurrentes pendientes pueden permitir parcial cuando ingreso, movimientos y compromisos están suficientemente establecidos; ausencia de instrumentos de pago no bloquea por sí sola. No extrapolar combinaciones no cubiertas por reglas/fixtures. Kabeli debe sustituir la condición subjetiva actual y hacer que E responda al output determinista del gate. | T54: PD-M1-13 | U54: M01-RGL-011 / M01-RGL-012 / M01-RGL-013 / M1-DP-008 / M1-DP-009
A55: M1-V51 | B55: Suficiencia | C55: Datos clave insuficientes | D55: Falta documento usable, ingreso, movimientos o base mínima de compromisos/pagos | E55: Bloquear diagnóstico; solicitar completar/cargar más información. | F55: M1-HU-027 / M1-HU-023 | G55: CA1-CA3 | H55: M1-RN-ONB-006 / M1-RN-ONB-007 / M1-RN-ONB-010 | I55: MVP | J55: S2/S3 | S1/S2 | K55: S2 – Walvy_Onboarding_Diagnostico_Fase3_Reglas_Contextuales_Suficiencia_Semaforo_CTA_v1_0: Suficiencia, diagnóstico parcial, semáforo, presión principal y CTA. S3 – Walvy_Onboarding_Diagnostico_Fase3_Anexo_BDD_Reglas_Productivas_v1_0: Datos, enums, eventos, versionamiento, retoma y trazabilidad. S1 – Walvy_Especificacion_UX_Onboarding_App: Secuencia, pantallas, carga documental, postergación y reactivación. | L55: CP-M1-ONB-014 | M55: Evidencia QA bloqueo/suficiencia por enlazar | N55: Pendiente | O55: 6459:8282 | P55: https://www.figma.com/design/v45c4HTKnPnU0XABMa5vjY/Walvi-APP---Edificate-Inteligente?node-id=6459-8282 | Q55: Confirmado Doc + Figma | R55: Aprobado | U55: M01-RGL-011 / M01-RGL-012 / M01-RGL-013 / M1-DP-009
A56: M1-V52 | B56: Suficiencia | C56: Sin base documental | D56: No hay documentos o se intenta omitir carga inicial | E56: No habilitar diagnóstico ni ruta manual sustitutiva; CTA cargar documentos. | F56: M1-HU-027 / M1-HU-023 | G56: CA1-CA3 | H56: M1-RN-ONB-006 / M1-RN-ONB-007 / M1-RN-ONB-010 | I56: MVP | J56: S2/S3 | S1/S2 | K56: S2 – Walvy_Onboarding_Diagnostico_Fase3_Reglas_Contextuales_Suficiencia_Semaforo_CTA_v1_0: Suficiencia, diagnóstico parcial, semáforo, presión principal y CTA. S3 – Walvy_Onboarding_Diagnostico_Fase3_Anexo_BDD_Reglas_Productivas_v1_0: Datos, enums, eventos, versionamiento, retoma y trazabilidad. S1 – Walvy_Especificacion_UX_Onboarding_App: Secuencia, pantallas, carga documental, postergación y reactivación. | L56: CP-M1-ONB-014 | M56: Evidencia QA bloqueo/suficiencia por enlazar | N56: Pendiente | O56: 3361:2744 | P56: https://www.figma.com/design/v45c4HTKnPnU0XABMa5vjY/Walvi-APP---Edificate-Inteligente?node-id=3361-2744 | Q56: Documentado / UI a validar | R56: Aprobado | S56: Reutilizar el mismo patrón visual rojo/bloqueante de suficiencia para Sin base documental. Copy: título “Falta información para tu diagnóstico”; bajada “Carga tus documentos para completar la información de tu mes.”; CTA “Cargar documentos”. No habilitar diagnóstico mientras no exista base documental usable. | U56: M01-RGL-012 / M1-DP-009
A57: M1-V53 | B57: Diagnóstico | C57: En control | D57: Base suficiente, sin presión principal crítica | E57: Mostrar lectura favorable y una acción dominante. | F57: M1-HU-025 | G57: CA2-CA3 | H57: M1-RN-ONB-009 / M1-RN-ONB-011 / M1-RN-ONB-012 | I57: MVP | J57: S2/S3 | S1/S2/S4 | K57: S2 – Walvy_Onboarding_Diagnostico_Fase3_Reglas_Contextuales_Suficiencia_Semaforo_CTA_v1_0: Suficiencia, diagnóstico parcial, semáforo, presión principal y CTA. S3 – Walvy_Onboarding_Diagnostico_Fase3_Anexo_BDD_Reglas_Productivas_v1_0: Datos, enums, eventos, versionamiento, retoma y trazabilidad. S1 – Walvy_Especificacion_UX_Onboarding_App: Secuencia, pantallas, carga documental, postergación y reactivación. S4 – Walvy_Rector_Producto_y_Funcionalidades_MVP_v1.0_OLD_20260516: Responsabilidad del onboarding y límites transversales. | L57: CP-M1-ONB-011 | M57: Evidencia QA semáforo En control por enlazar | N57: Pendiente | O57: 6670:13628 | P57: https://www.figma.com/design/v45c4HTKnPnU0XABMa5vjY/Walvi-APP---Edificate-Inteligente?node-id=6670-13628 | Q57: Confirmado Doc + Figma | R57: Ajustar | S57: Decisión de Producto cerrada. Ver M1-DP-006 y AX-M1-004. V53 aplica cuando M01-RGL-012 habilita Diagnóstico, no existe mora_confirmada y el ratio canónico del snapshot mensual (egreso mensual proyectado / ingreso mensual reconocido) es < 0,90. Mostrar En control; la presión y CTA se seleccionan posteriormente mediante M01-RGL-015 y no cambian el color por sí solas. Kabeli debe ajustar D/E y M1-RN-ONB-009 para reflejar la regla canónica y su versionamiento. | T57: PD-M1-12 | U57: M01-RGL-012 / M01-RGL-015 / M01-RGL-016 / M1-DP-006
A58: M1-V54 | B58: Diagnóstico | C58: Atención | D58: Base usable con datos por confirmar, movimientos pendientes, fugas/recurrentes o margen ajustado | E58: Mostrar atención con presión principal y CTA dominante adecuado. | F58: M1-HU-025 / M1-HU-028 | G58: CA1-CA3 | H58: M1-RN-ONB-009 / M1-RN-ONB-011 / M1-RN-ONB-012 | I58: MVP | J58: S2/S3 | S1/S2/S4 | K58: S2 – Walvy_Onboarding_Diagnostico_Fase3_Reglas_Contextuales_Suficiencia_Semaforo_CTA_v1_0: Suficiencia, diagnóstico parcial, semáforo, presión principal y CTA. S3 – Walvy_Onboarding_Diagnostico_Fase3_Anexo_BDD_Reglas_Productivas_v1_0: Datos, enums, eventos, versionamiento, retoma y trazabilidad. S1 – Walvy_Especificacion_UX_Onboarding_App: Secuencia, pantallas, carga documental, postergación y reactivación. S4 – Walvy_Rector_Producto_y_Funcionalidades_MVP_v1.0_OLD_20260516: Responsabilidad del onboarding y límites transversales. | L58: CP-M1-ONB-015 | M58: Evidencia QA semáforo/presión por enlazar | N58: Pendiente | O58: 6670:13717 | P58: https://www.figma.com/design/v45c4HTKnPnU0XABMa5vjY/Walvi-APP---Edificate-Inteligente?node-id=6670-13717 | Q58: Confirmado Doc + Figma | R58: Ajustar | S58: Decisión de Producto cerrada. Ver M1-DP-006 y AX-M1-004. V54 aplica cuando M01-RGL-012 habilita Diagnóstico, no existe mora_confirmada y 0,90 <= ratio canónico del snapshot mensual < 1,00. Datos por confirmar, movimientos pendientes, fugas o compromisos no generan Atención por sí solos: la calidad/completitud pertenece al gate de suficiencia y las señales económicas explican presión/CTA después de determinar el estado. Un diagnóstico parcial permitido puede, por ejemplo, seguir mostrando En control si el ratio está bajo el umbral. Kabeli debe ajustar D/E, M1-RN-ONB-009 y los fixtures que hoy coloreen Atención directamente desde señales. | T58: PD-M1-12 | U58: M01-RGL-012 / M01-RGL-015 / M01-RGL-016 / M1-DP-006
A59: M1-V55 | B59: Diagnóstico | C59: Riesgo | D59: Base usable con señales fuertes de sobrecarga/compromisos que presionan | E59: Mostrar riesgo con acción prioritaria serena y trazable. | F59: M1-HU-025 / M1-HU-028 | G59: CA1-CA3 | H59: M1-RN-ONB-009 / M1-RN-ONB-011 / M1-RN-ONB-012 | I59: MVP | J59: S2/S3 | S1/S2/S4 | K59: S2 – Walvy_Onboarding_Diagnostico_Fase3_Reglas_Contextuales_Suficiencia_Semaforo_CTA_v1_0: Suficiencia, diagnóstico parcial, semáforo, presión principal y CTA. S3 – Walvy_Onboarding_Diagnostico_Fase3_Anexo_BDD_Reglas_Productivas_v1_0: Datos, enums, eventos, versionamiento, retoma y trazabilidad. S1 – Walvy_Especificacion_UX_Onboarding_App: Secuencia, pantallas, carga documental, postergación y reactivación. S4 – Walvy_Rector_Producto_y_Funcionalidades_MVP_v1.0_OLD_20260516: Responsabilidad del onboarding y límites transversales. | L59: CP-M1-ONB-015 | M59: Evidencia QA semáforo/presión por enlazar | N59: Pendiente | O59: 6670:13805 | P59: https://www.figma.com/design/v45c4HTKnPnU0XABMa5vjY/Walvi-APP---Edificate-Inteligente?node-id=6670-13805 | Q59: Confirmado Doc + Figma | R59: Ajustar | S59: Decisión de Producto cerrada. Ver M1-DP-006 y AX-M1-004. V55 aplica cuando M01-RGL-012 habilita Diagnóstico y el ratio canónico del snapshot mensual es >= 1,00, o cuando existe el único override determinista de Riesgo aprobado para el MVP: mora_confirmada = obligación vencida + saldo pendiente + evidencia suficiente. Otras señales no cambian directamente el color; alimentan ratio, presión o CTA. Riesgo no activa automáticamente M04: Ruta Despeje mantiene sus propios criterios de deuda confirmada, suficiencia y presión. Kabeli debe ajustar D/E, M1-RN-ONB-009 y alinear M01-RGL-015 para que opere después del estado. | T59: PD-M1-12 | U59: M01-RGL-012 / M01-RGL-015 / M01-RGL-016 / M1-DP-006
A60: M1-V56 | B60: Diagnóstico | C60: Sin diagnóstico | D60: No existe base suficiente para lectura confiable | E60: No usar rojo por falta de información; mostrar bloqueo/completitud. | F60: M1-HU-027 | G60: CA1-CA3 | H60: M1-RN-ONB-009 / M1-RN-ONB-010 | I60: MVP | J60: S2/S3 | K60: S2 – Walvy_Onboarding_Diagnostico_Fase3_Reglas_Contextuales_Suficiencia_Semaforo_CTA_v1_0: Suficiencia, diagnóstico parcial, semáforo, presión principal y CTA. S3 – Walvy_Onboarding_Diagnostico_Fase3_Anexo_BDD_Reglas_Productivas_v1_0: Datos, enums, eventos, versionamiento, retoma y trazabilidad. | L60: CP-M1-ONB-014 | M60: Evidencia QA Sin diagnóstico por enlazar | N60: Pendiente | O60: 3361:2744 | P60: https://www.figma.com/design/v45c4HTKnPnU0XABMa5vjY/Walvi-APP---Edificate-Inteligente?node-id=3361-2744 | Q60: Documento solamente / UI a validar | R60: Aprobado | S60: Sin diagnóstico se resuelve mediante los gates de suficiencia previos al diagnóstico y no requiere una cuarta tarjeta equivalente a En control / Atención / Riesgo. Cuando no existe información suficiente para una lectura confiable, Walvy bloquea el diagnóstico, explica qué información falta y permite completar la base necesaria. No usar Riesgo/rojo como sustituto de falta de información. | U60: M01-RGL-012 / M01-RGL-015 / M1-DP-007
A61: M1-V57 | B61: Diagnóstico | C61: Una presión principal / un CTA dominante | D61: Evaluación detecta múltiples señales | E61: Seleccionar una presión principal única y una acción dominante; el resto queda secundario. | F61: M1-HU-028 | G61: CA1-CA3 | H61: M1-RN-ONB-011 / M1-RN-ONB-012 | I61: MVP | J61: S2/S3 | S1/S2/S4 | K61: S2 – Walvy_Onboarding_Diagnostico_Fase3_Reglas_Contextuales_Suficiencia_Semaforo_CTA_v1_0: Suficiencia, diagnóstico parcial, semáforo, presión principal y CTA. S3 – Walvy_Onboarding_Diagnostico_Fase3_Anexo_BDD_Reglas_Productivas_v1_0: Datos, enums, eventos, versionamiento, retoma y trazabilidad. S1 – Walvy_Especificacion_UX_Onboarding_App: Secuencia, pantallas, carga documental, postergación y reactivación. S4 – Walvy_Rector_Producto_y_Funcionalidades_MVP_v1.0_OLD_20260516: Responsabilidad del onboarding y límites transversales. | L61: CP-M1-ONB-015 | M61: Evidencia QA múltiples señales por enlazar | N61: Pendiente | O61: 3361:2744 | P61: https://www.figma.com/design/v45c4HTKnPnU0XABMa5vjY/Walvi-APP---Edificate-Inteligente?node-id=3361-2744 | Q61: Regla documental transversal | R61: Aprobado | S61: Mantener una única presión principal y un CTA dominante; las demás señales quedan como información secundaria. La presión y el CTA explican y orientan la acción sobre el estado financiero, pero no reemplazan la regla canónica que determina En control / Atención / Riesgo. | U61: M01-RGL-015 / M01-RGL-016
A62: M1-V58 | B62: Retoma | C62: Pausa antes de carga | D62: Usuario posterga en bienvenida/foco | E62: Conservar estado aplicable y retomar desde punto de mayor valor pendiente. | F62: M1-HU-029 | G62: CA1-CA2 | H62: M1-RN-ONB-014 | I62: MVP | J62: S1/S2/S3 | K62: S1 – Walvy_Especificacion_UX_Onboarding_App: Secuencia, pantallas, carga documental, postergación y reactivación. S2 – Walvy_Onboarding_Diagnostico_Fase3_Reglas_Contextuales_Suficiencia_Semaforo_CTA_v1_0: Suficiencia, diagnóstico parcial, semáforo, presión principal y CTA. S3 – Walvy_Onboarding_Diagnostico_Fase3_Anexo_BDD_Reglas_Productivas_v1_0: Datos, enums, eventos, versionamiento, retoma y trazabilidad. | L62: CP-M1-ONB-016 | M62: Evidencia QA pausa/retoma por enlazar | N62: Pendiente | O62: 3361:2744 | P62: https://www.figma.com/design/v45c4HTKnPnU0XABMa5vjY/Walvi-APP---Edificate-Inteligente?node-id=3361-2744 | Q62: Documentado / UI parcial | R62: Aprobado | S62: Permitir postergar antes de la carga conservando el checkpoint alcanzado y retomar desde el punto de mayor valor pendiente, sin generar una primera lectura concluyente mientras no se complete la base requerida. | U62: M01-RGL-007 / M01-RGL-008 / M1-DP-009
A63: M1-V59 | B63: Retoma | C63: Pausa después de carga parcial | D63: Usuario sale con carga procesada o parcial | E63: Conservar evidencia ya cargada; no reiniciar desde cero. | F63: M1-HU-029 | G63: CA1-CA2 | H63: M1-RN-ONB-014 | I63: MVP | J63: S1/S2/S3 | K63: S1 – Walvy_Especificacion_UX_Onboarding_App: Secuencia, pantallas, carga documental, postergación y reactivación. S2 – Walvy_Onboarding_Diagnostico_Fase3_Reglas_Contextuales_Suficiencia_Semaforo_CTA_v1_0: Suficiencia, diagnóstico parcial, semáforo, presión principal y CTA. S3 – Walvy_Onboarding_Diagnostico_Fase3_Anexo_BDD_Reglas_Productivas_v1_0: Datos, enums, eventos, versionamiento, retoma y trazabilidad. | L63: CP-M1-ONB-016 | M63: Evidencia QA pausa/retoma por enlazar | N63: Pendiente | O63: 3361:2744 | P63: https://www.figma.com/design/v45c4HTKnPnU0XABMa5vjY/Walvi-APP---Edificate-Inteligente?node-id=3361-2744 | Q63: Documentado | R63: Aprobado | S63: Conservar documentos/evidencia y avance ya obtenido al salir después de una carga parcial o procesada. La retoma debe continuar desde el checkpoint correspondiente sin reiniciar el onboarding ni duplicar documentos o jobs. | U63: M01-RGL-008 / M01-RGL-014 / M1-DP-009
A64: M1-V60 | B64: Retoma | C64: Salida durante análisis | D64: Usuario sale mientras procesamiento continúa | E64: Permitir salir sin perder avance y retomar análisis o resultado. | F64: M1-HU-021 / M1-HU-029 | G64: CA2 / CA1-CA2 | H64: M1-RN-ONB-013 / M1-RN-ONB-014 | I64: Requiere validación técnica | MVP | J64: S2/S3 | S1/S2/S3 | K64: S2 – Walvy_Onboarding_Diagnostico_Fase3_Reglas_Contextuales_Suficiencia_Semaforo_CTA_v1_0: Suficiencia, diagnóstico parcial, semáforo, presión principal y CTA. S3 – Walvy_Onboarding_Diagnostico_Fase3_Anexo_BDD_Reglas_Productivas_v1_0: Datos, enums, eventos, versionamiento, retoma y trazabilidad. S1 – Walvy_Especificacion_UX_Onboarding_App: Secuencia, pantallas, carga documental, postergación y reactivación. | L64: CP-M1-ONB-005 / CP-M1-ONB-016 | M64: Evidencia QA salida durante análisis por enlazar | N64: Pendiente | O64: 6670:13533 | P64: https://www.figma.com/design/v45c4HTKnPnU0XABMa5vjY/Walvi-APP---Edificate-Inteligente?node-id=6670-13533 | Q64: Confirmado regla; UI parcial | R64: Aprobado | S64: Permitir salir durante el análisis sin perder documentos, job ni progreso. Al retomar, recuperar el análisis en curso o el resultado disponible según el estado alcanzado, evitando reprocesamiento o duplicación. | T64: PD-M1-10 | U64: M01-RGL-008 / M01-RGL-014 / M1-DP-009

Sheet Historias y CA
A1: WALVY | M1 – Historias de Usuario y Criterios de Aceptación
A3: ID | B3: Historia | C3: Redacción | D3: Criterios de aceptación
A4: M1-HU-001 | B4: Visualizar la pantalla de acceso | C4: Como usuario, quiero visualizar la pantalla de Login para conocer las opciones disponibles de acceso. | D4: CA1. La pantalla de Login muestra logo, mensaje de bienvenida, correo electrónico, contraseña, control para mostrar u ocultar la contraseña y botón Entrar. CA2. Desde Login se visualizan las opciones Crear mi cuenta y ¿Olvidaste tu contraseña?. CA3. Los elementos y enlaces visibles permiten navegar a los flujos definidos.
A5: M1-HU-002 | B5: Controlar habilitación de Entrar | C5: Como usuario, quiero que el botón Entrar se habilite solo cuando complete los datos necesarios. | D5: CA1. Con correo o contraseña vacíos, el botón Entrar permanece deshabilitado. CA2. Al completar los datos requeridos, el usuario puede ejecutar el intento de acceso. CA3. La habilitación del botón no reemplaza la validación posterior de credenciales.
A6: M1-HU-003 | B6: Iniciar sesión | C6: Como usuario registrado, quiero ingresar con correo y contraseña para acceder a Walvy. | D6: CA1. Dadas credenciales válidas, al seleccionar Entrar el sistema autentica al usuario. CA2. El resultado esperado de un login exitoso es el acceso al Home. CA3. La contraseña puede mantenerse oculta o mostrarse mediante el control disponible.
A7: M1-HU-004 | B7: Navegar a registro o recuperación | C7: Como usuario, quiero acceder desde Login a crear una cuenta o recuperar mi contraseña. | D7: CA1. Crear mi cuenta abre la vista de registro. CA2. ¿Olvidaste tu contraseña? abre el flujo Recupera tu acceso. CA3. Las pantallas asociadas permiten retornar al Login cuando corresponde.
A8: M1-HU-005 | B8: Crear cuenta | C8: Como usuario nuevo, quiero registrar mis datos para crear una cuenta Walvy. | D8: CA1. El formulario solicita correo, confirmación de correo, RUT y contraseña. CA2. Los correos deben coincidir, el RUT debe ser válido según la regla técnica y la contraseña debe cumplir los requisitos visibles. CA3. Con datos válidos y las aceptaciones requeridas, el flujo permite enviar la creación de cuenta y avanzar a verificación.
A9: M1-HU-006 | B9: Aceptar documentos legales | C9: Como usuario nuevo, quiero revisar y aceptar Términos y Condiciones y Política de Privacidad antes de crear mi cuenta. | D9: CA1. Se muestran Términos y Condiciones y Política de Privacidad con sus controles de aceptación. CA2. Los textos legales están disponibles mediante enlaces. CA3. La creación de cuenta permanece condicionada a las aceptaciones obligatorias.
A10: M1-HU-007 | B10: Verificar la cuenta | C10: Como usuario nuevo, quiero ingresar el código recibido para activar mi cuenta. | D10: CA1. Después de crear la cuenta se presenta una vista de ingreso de código con campos inicialmente vacíos. CA2. Un código válido permite verificar la cuenta y continuar al primer ingreso. CA3. Un código incorrecto no confirma la cuenta y mantiene al usuario en el flujo de verificación.
A11: M1-HU-008 | B11: Completar datos del primer ingreso | C11: Como usuario recién verificado, quiero completar nombre, apellido y alias para continuar. | D11: CA1. El primer ingreso permite completar nombre, apellido y alias. CA2. Al completar datos válidos se habilita Guardar y continuar. CA3. El resultado esperado es la continuidad hacia Onboarding Welcome.
A12: M1-HU-009 | B12: Omitir información de primer ingreso | C12: Como usuario recién verificado, quiero omitir la completitud inicial y continuar sin perder el avance. | D12: CA1. El primer ingreso presenta la opción Omitir y continuar. CA2. Al utilizarla, el usuario avanza a la siguiente vista definida por el flujo. CA3. La omisión no debe borrar el estado ya alcanzado en la activación de la cuenta.
A13: M1-HU-010 | B13: Solicitar recuperación de acceso | C13: Como usuario que olvidó su contraseña, quiero solicitar un código usando mi correo. | D13: CA1. La recuperación se inicia desde ¿Olvidaste tu contraseña? y solicita correo electrónico. CA2. Al ingresar el correo se habilita Enviar código. CA3. Después del envío se presenta la vista para ingresar y validar el código.
A14: M1-HU-011 | B14: Validar código de recuperación | C14: Como usuario, quiero validar el código recibido para poder crear una nueva contraseña. | D14: CA1. Un código válido muestra confirmación y habilita Crear nueva contraseña. CA2. Un código inválido no permite avanzar al cambio de contraseña. CA3. El usuario permanece dentro del flujo de recuperación hasta validar correctamente o volver al Login.
... A37: M1-HU-034 | B37: Gestionar documentos con restricciones o duplicidad | C37: Como usuario que carga documentación, quiero recibir un tratamiento claro cuando un archivo tenga contraseña, esté desactualizado o sea duplicado, para saber cómo corregirlo sin perder el avance. | D37: CA1. Un documento protegido requiere el tratamiento de desbloqueo definido antes de considerarse usable. CA2. Un documento desactualizado o duplicado no debe mejorar artificialmente la suficiencia de datos. CA3. El usuario recibe una acción concreta para corregir, reemplazar o continuar según el estado del archivo.

Sheet Reglas de Negocio
A1: WALVY | M1 – Matriz completa de Reglas de Negocio
A3: ID | B3: Nombre / Grupo | C3: Regla | D3: Estado / Origen | E3: Código fuente RN | F3: Descripción fuente RN
A4: M1-RN-ACC-001 | B4: Acceso | C4: La pantalla de Login debe mostrar correo electrónico y contraseña como datos de acceso. | D4: Evidencia QA | E4: F-01, F-03 | F4: F-01 – Login Exitoso – Passed – iOS / Android: Acceso con correo y contraseña; llegada a Home. F-03 – Validar links de la pantalla de login 01/02 – iOS / Android: Links Crear mi cuenta y ¿Olvidaste tu contraseña?; elementos visibles.
A5: M1-RN-ACC-002 | B5: Acceso | C5: El botón Entrar debe permanecer deshabilitado cuando falte el correo o la contraseña. | D5: Evidencia QA | E5: F-02 | F5: F-02 – Validar botón Entrar deshabilitado – iOS / Android: Botón deshabilitado cuando correo o contraseña están vacíos.
A6: M1-RN-ACC-003 | B6: Acceso | C6: El campo contraseña debe contar con control para mostrar u ocultar su contenido. | D6: Evidencia QA | E6: F-03 | F6: F-03 – Validar links de la pantalla de login 01/02 – iOS / Android: Links Crear mi cuenta y ¿Olvidaste tu contraseña?; elementos visibles.
A7: M1-RN-ACC-004 | B7: Acceso | C7: Con credenciales válidas, el resultado esperado es acceso al Home. | D7: Evidencia QA | E7: F-01 | F7: F-01 – Login Exitoso – Passed – iOS / Android: Acceso con correo y contraseña; llegada a Home.
A8: M1-RN-ACC-005 | B8: Navegación | C8: Desde Login deben estar disponibles Crear mi cuenta y ¿Olvidaste tu contraseña?. | D8: Evidencia QA | E8: F-03 | F8: F-03 – Validar links de la pantalla de login 01/02 – iOS / Android: Links Crear mi cuenta y ¿Olvidaste tu contraseña?; elementos visibles.
A9: M1-RN-ACC-006 | B9: Registro | C9: La creación de cuenta requiere correo, confirmación de correo, RUT y contraseña. | D9: Evidencia QA | E9: F-04 | F9: F-04 – Creación de cuenta / Creación de cuenta exitosa – iOS / Android: Formulario, campos y envío a verificación.
A10: M1-RN-ACC-007 | B10: Registro | C10: Los correos ingresados en registro deben coincidir para continuar. | D10: Derivada del flujo | E10: F-04 | F10: F-04 – Creación de cuenta / Creación de cuenta exitosa – iOS / Android: Formulario, campos y envío a verificación.
A11: M1-RN-ACC-008 | B11: Registro | C11: La ruta aceptada utiliza un RUT válido. La regla completa de validación debe confirmarse técnicamente. | D11: Derivada del flujo | E11: F-04 | F11: F-04 – Creación de cuenta / Creación de cuenta exitosa – iOS / Android: Formulario, campos y envío a verificación.
A12: M1-RN-ACC-009 | B12: Registro | C12: La interfaz debe mostrar requisitos de contraseña. En la evidencia se observan al menos ocho caracteres, una mayúscula y un número. | D12: Evidencia visual | E12: F-04 | F12: F-04 – Creación de cuenta / Creación de cuenta exitosa – iOS / Android: Formulario, campos y envío a verificación.
A13: M1-RN-ACC-010 | B13: Registro | C13: Términos y Condiciones y Política de Privacidad deben aceptarse antes de habilitar Crear mi cuenta. | D13: Evidencia QA | E13: F-04, F-05 | F13: F-04 – Creación de cuenta / Creación de cuenta exitosa – iOS / Android: Formulario, campos y envío a verificación. F-05 – Creación de cuenta – validación Términos y Condiciones – iOS / Android: Aceptación y acceso a documentos legales.
A14: M1-RN-ACC-011 | B14: Registro | C14: Los textos de Términos y Condiciones y Política de Privacidad deben estar disponibles mediante links. | D14: Evidencia QA | E14: F-05 | F14: F-05 – Creación de cuenta – validación Términos y Condiciones – iOS / Android: Aceptación y acceso a documentos legales.
... A63: M1-RN-ONB-025 | B63: Procesamiento fallido | C63: Si el procesamiento falla, la evidencia fallida no habilita diagnóstico; el usuario debe recibir una acción de reintento, reemplazo o completitud definida. | D63: Documental + Figma / validar copy | E63: D2-S1/D2-S2 | F63: D2-S1 – Walvy_Especificacion_UX_Onboarding_App: Secuencia, pantallas, carga documental, postergación y reactivación. D2-S2 – Walvy_Onboarding_Diagnostico_Fase3_Reglas_Contextuales_Suficiencia_Semaforo_CTA_v1_0: Suficiencia, diagnóstico parcial, semáforo, presión principal y CTA.

Sheet Fuentes
A1: WALVY | M1 – Fuentes documentales, QA y Figma
A3: Código | B3: Fuente | C3: Tipo | D3: Uso / cobertura | E3: Equivalencia / referencia
A4: M1-DOC | B4: Walvy_M1_Documentacion_Formal_Consolidada_Completa_v3.0 | C4: Documento formal | D4: HU, CA, reglas de acceso/onboarding y trazabilidad base | E4: Documento consolidado base
A5: M1-FIG | B5: Walvi APP – Módulo 1 | C5: Figma | D5: Acceso, registro, recuperación, primer ingreso, onboarding y diagnóstico | E5: Nodo raíz 3361:2744
A6: D1 | B6: Walvy_M1_Documentacion_Formal_Acceso_Registro_Recuperacion_Primer_Ingreso_v2.0.docx | C6: Documento formal | D6: Acceso, login, registro, verificación, recuperación, biometría, usuario guardado y primer ingreso | E6: Fuente consolidada en M1 v3.0
A7: D2 | B7: Walvy_M1_Documentacion_Formal_Onboarding_Diagnostico_v1.0.docx | C7: Documento formal | D7: Onboarding, carga documental, suficiencia, diagnóstico, semáforo, presión, CTA y retoma | E7: Fuente consolidada en M1 v3.0
A8: F-01 | B8: Login Exitoso – Passed – iOS / Android | C8: Evidencia QA / fuente funcional | D8: Acceso con correo y contraseña; llegada a Home. | E8: Equivale a D1-F-01
A9: F-02 | B9: Validar botón Entrar deshabilitado – iOS / Android | C9: Evidencia QA / fuente funcional | D9: Botón deshabilitado cuando correo o contraseña están vacíos. | E9: Equivale a D1-F-02
A10: F-03 | B10: Validar links de la pantalla de login 01/02 – iOS / Android | C10: Evidencia QA / fuente funcional | D10: Links Crear mi cuenta y ¿Olvidaste tu contraseña?; elementos visibles. | E10: Equivale a D1-F-03
A11: F-04 | B11: Creación de cuenta / Creación de cuenta exitosa – iOS / Android | C11: Evidencia QA / fuente funcional | D11: Formulario, campos y envío a verificación. | E11: Equivale a D1-F-04
A12: F-05 | B12: Creación de cuenta – validación Términos y Condiciones – iOS / Android | C12: Evidencia QA / fuente funcional | D12: Aceptación y acceso a documentos legales. | E12: Equivale a D1-F-05
A13: F-06 | B13: Creación de cuenta – verificación código incorrecto – iOS / Android | C13: Evidencia QA / fuente funcional | D13: Tratamiento de código inválido. | E13: Equivale a D1-F-06
A14: F-07 | B14: Ingreso primera vez – Completar datos / Omitir y continuar – iOS / Android | C14: Evidencia QA / fuente funcional | D14: Flujo posterior a la activación de cuenta. | E14: Equivale a D1-F-07
... A24: S4 | B24: Walvy_Rector_Producto_y_Funcionalidades_MVP_v1.0_OLD_20260516 | C24: Documento funcional / reglas | D24: Responsabilidad del onboarding y límites transversales. | E24: Equivale a D2-S4

Sheet Pendientes Cliente
A1: WALVY | M1 – Decisiones funcionales pendientes del Cliente / Product Owner
A2: Esta pestaña NO replica las variantes pendientes de aprobación. Incluye únicamente definiciones, parámetros o comportamientos que aún requieren una decisión explícita. La aprobación de cada variante se registra en la columna “Validación Cliente” de la Matriz Trazabilidad.
A4: ID Pendiente | B4: Tipo de decisión | C4: Variantes / RN afectadas | D4: Tema a definir | E4: Motivo / Fuente | F4: Nodo(s) Figma | G4: Estado decisión | H4: Decisión PO / Comentarios | I4: Observación Producto relacionada | J4: Estado Observación Producto
A5: PD-M1-01 | B5: Producto / Seguridad | C5: M1-V03 | M1-RN-ACC-031 | D5: Definir el tratamiento de credenciales inválidas. | E5: Figma representa el estado de error, pero la política funcional/seguridad asociada no está formalizada en la documentación de Producto. | F5: 3677:2837 | G5: Resuelto | H5: Resuelto desde Producto. V03 debe usar respuesta genérica ante credenciales inválidas, mantener al usuario en Login y permitir reintento/recuperación sin revelar existencia de cuenta. La política de intentos, rate limiting, cooldown, logging y controles antiabuso queda como parametrización/validación de Seguridad/Kabeli y no mantiene abierto el análisis de Producto.
A6: PD-M1-02 | B6: Producto / Seguridad | C6: M1-V13, M1-V16 | M1-RN-ACC-032, M1-RN-ACC-033 | D6: Definir ciclo de vida del código de verificación: vigencia, vencimiento, reenvío y condiciones de reintento. | E6: El flujo está representado en Figma y parcialmente respaldado por QA, pero estos parámetros no están formalizados. | F6: 3470:7580 / 3470:7626 | G6: Resuelto | H6: Resuelto por Producto mediante M1-DP-010 / AX-M1-001. Se separa la vigencia del OTP del temporizador de reenvío y se adopta un baseline parametrizable para TTL, reenvío, intentos, límites, invalidación, rate limiting y logging. Kabeli/Seguridad debe confirmar los valores efectivos implementados o justificar desviaciones y propagarlos a M1-V13/M1-V16, M1-RN-ACC-032/033 y casos de prueba. V16 pasa a Ajustar. Tras la revisión de trazabilidad, V13 también pasa a Ajustar únicamente para ampliar su condición de entrada a cuentas pending_verification que intentan Login; no se reabre el baseline OTP ni esta decisión de Producto. | I6: M1-DP-010 | J6: Resuelto
A7: PD-M1-03 | B7: Producto / Operación | C7: M1-V19 | M1-RN-ACC-034 | D7: Definir qué debe ocurrir cuando el usuario no tiene acceso al correo registrado. | E7: Figma muestra una alternativa de soporte, pero la operación y resolución del caso requieren confirmación. | F7: 3470:7029 | G7: Resuelto | H7: Resuelto por Producto mediante M1-DP-011. Para el MVP, sin acceso al correo registrado → soporte@walvy.cl → verificación de identidad conforme a procedimiento Seguridad/Operaciones → nuevo correo distinto y verificado antes de sustituir el anterior. Si el usuario recupera acceso al correo original, vuelve al recovery estándar. El contacto con soporte por sí solo no habilita cambio de correo, contraseña ni acceso. El procedimiento/evidencia concreta queda pendiente de formalización Seguridad/Operaciones. | I7: M1-DP-011 | J7: Resuelto
A8: PD-M1-04 | B8: Producto / Seguridad | C8: M1-V26 | M1-RN-ACC-035 | D8: Confirmar cuándo se ofrece activar biometría en el primer ingreso y el comportamiento esperado según disponibilidad del dispositivo. | E8: La opción está representada en Figma; la regla formal y su alcance entre plataformas requieren ratificación. | F8: 4911:5511 | G8: Resuelto | H8: Resuelto desde Producto. La biometría es opcional, se ofrece según disponibilidad del dispositivo, puede omitirse/activarse posteriormente y mantiene contraseña como fallback. La autenticación biométrica se delega al sistema operativo; plataforma, permisos, desactivación y evidencia de no persistencia/transmisión de plantillas corresponden a validación Técnica/Seguridad.
A9: PD-M1-05 | B9: Producto | C9: M1-V28, M1-V29, M1-V30 | M1-RN-ONB-019 | D9: Ratificar los estados del Foco del Mes: declarado, no declarado e inferido/sugerido, y cómo se comunica un foco inferido. | E9: La documentación funcional define el concepto, pero la aplicación exacta del foco inferido/sugerido queda sujeta a validación de Producto. | F9: 6670:13227 / 3361:2744 | G9: Resuelto | H9: Resuelto por Producto mediante M1-DP-002 / AX-M1-002. Cuando no exista foco activo y haya Diagnóstico válido, Walvy puede sugerir un foco con prioridad M04 → M06 → M05. Se usa únicamente el estado “sugerido”. CTA primario Usar este foco guarda directamente; CTA secundario Revisar foco lleva a Mi Perfil → Mi foco del mes con la sugerencia premarcada. Sin aceptación permanece no declarado y puede recalcularse; una vez aceptado no cambia automáticamente. Kabeli debe ajustar V30 y M1-RN-ONB-019. | I9: M1-DP-002 | J9: Resuelto
A10: PD-M1-06 | B10: Producto | C10: M1-V31 a M1-V36 | M1-RN-ONB-020 | D10: Confirmar el catálogo vigente de seis opciones de Foco del Mes y sus denominaciones. | E10: El catálogo está representado en Figma y alineado con reglas de foco, pero debe ratificarse su vigencia como catálogo oficial. | F10: 6670:13227 | G10: Resuelto | H10: Catálogo vigente confirmado: Bajar deuda, Ahorrar un monto, Aumentar margen, Evitar atrasos, Cumplir presupuesto y Ordenar compromisos. No queda decisión funcional abierta sobre las seis denominaciones.
A11: PD-M1-07 | B11: Producto / Técnica | C11: M1-V37, M1-V38 | M1-RN-ONB-021 | D11: Formalizar los parámetros técnicos de carga documental asociados a los estados sin documento y documento subiendo. | E11: La matriz define el comportamiento funcional y Figma muestra los estados; los parámetros técnicos de carga aún requieren validación. | F11: 6670:13168 / 6459:8023 | G11: Resuelto | H11: Resuelto desde Producto. M01-RGL-009 ya formaliza el baseline MVP de admisión documental: PDF/XLSX/CSV, archivo <30 MB y máximo 15 documentos, con rechazo controlado cuando no se cumplen las condiciones. Lo pendiente es validación técnica/parametrización efectiva en Kabeli y evidencia backend/QA; no una decisión funcional adicional de Producto.
A12: PD-M1-08 | B12: Producto / Técnica / Seguridad | C12: M1-V41 | M1-RN-ONB-022 | D12: Definir el tratamiento de documentos protegidos con contraseña. | E12: Figma contempla este escenario, pero la regla técnica/seguridad no está formalizada. | F12: 6672:7841 | G12: Resuelto | H12: Resuelto desde Producto mediante M1-DP-003. Baseline a validar por Kabeli/Seguridad: máximo tres variantes automáticas del RUT sin DV, en orden RUT completo → últimos 4 → primeros 4, un intento por variante y detención al abrir; si ninguna funciona, contraseña manual. Error manual permite corregir/reintentar o cargar otro documento. No persistir ni registrar contraseñas. Queda pendiente únicamente validación técnica/seguridad del baseline y evidencia. | I12: M1-DP-003 | J12: Resuelto
A13: PD-M1-09 | B13: Producto / UX | C13: M1-V42, M1-V43 | M1-RN-ONB-023, M1-RN-ONB-024 | D13: Confirmar el tratamiento visible para documento desactualizado y documento duplicado. | E13: El Anexo BDD respalda los estados productivos, pero la representación y acción exacta en UI requieren validación. | F13: 3361:2744 | G13: Resuelto | H13: Resuelto por Producto mediante M1-DP-004. Dedupe por cuenta/usuario mediante huella de contenido sin almacenamiento permanente del archivo. Procesado OK → bloquear duplicado; fallo transitorio → permitir retry; no procesable → conservar temporalmente huella/motivo/versión para bloquear reprocesamiento idéntico hasta expiración o cambio de procesador. Kabeli debe ajustar V43 y M1-RN-ONB-024. | I13: M1-DP-004 | J13: Resuelto
A14: PD-M1-10 | B14: Producto / Técnica | C14: M1-V45, M1-V46, M1-V60 | M1-RN-ONB-013, M1-RN-ONB-014, M1-RN-ONB-018 | D14: Validar umbrales de demora y comportamiento al salir durante el análisis. | E14: La documentación propone manejo de demora y retoma, pero los umbrales y el comportamiento técnico definitivo requieren confirmación. | F14: 6670:13533 / 3361:2744 | G14: Resuelto | H14: Resuelto desde Producto. Los recorridos de demora/salida/retoma ya están definidos por M01-RGL-014 y M01-RGL-008. Los umbrales 45/90 s deben tratarse como parámetros internos versionados, no copy UX fijo. Kabeli debe validar valores efectivos, persistencia de job/estado, retoma del análisis o resultado y ausencia de reprocesamiento/duplicación.
A15: PD-M1-11 | B15: Producto / UX | C15: M1-V47 | M1-RN-ONB-025, M1-RN-ONB-006 | D15: Confirmar mensaje y acción de recuperación ante procesamiento fallido. | E15: El escenario está documentado y representado en Figma, pero el copy/acción final debe ser validado. | F15: 3361:2744 | G15: Resuelto | H15: Resuelto por Producto mediante M1-DP-005. V47 queda acotado a fallo técnico recuperable/transitorio después de admitir el documento. Conservar documentos/checkpoint, no generar Diagnóstico, CTA primario Reintentar y secundario Volver a revisión; el retry debe mantener correlación con el job original y no duplicar datos. Documento no procesable e insuficiencia se tratan en sus estados propios. | I15: M1-DP-005 | J15: Resuelto
A16: PD-M1-12 | B16: Producto / Reglas / Arquitectura | C16: M1-V53, M1-V54, M1-V55 | M1-RN-ONB-009, M1-RN-ONB-011, M1-RN-ONB-012 | D16: Completar regla canónica del Estado Financiero del Mes y contrato intermodular. | E16: M1-DP-006. Las variantes existen, pero las condiciones actuales de la trazabilidad no incorporan la política inicial de Producto ni separan completamente calidad de dato de estado financiero. | F16: 6670:13628 / 6670:13717 / 6670:13805 | G16: Resuelto | H16: Resuelto por Producto mediante M1-DP-006 / AX-M1-004. M01-RGL-012 gobierna suficiencia; una regla canónica única por snapshot gobierna En control/Atención/Riesgo mediante ratio y override; M01-RGL-015 opera después para presión/CTA. Umbrales: <90% / 90%-<100% / >=100%. Único override MVP: mora_confirmada = obligación vencida + saldo pendiente + evidencia suficiente. Kabeli debe ajustar V53–V55, M1-RN-ONB-009 y fixtures/reglas que mezclen señales con color. | I16: M1-DP-006 | J16: Resuelto
A17: PD-M1-13 | B17: Producto / Desarrollo | C17: M1-V50 | M1-RN-ONB-006, M1-RN-ONB-007, M1-RN-ONB-010 | D17: Completar parametrización productiva de la regla de suficiencia. | E17: M1-DP-008. La política funcional identifica indicadores críticos y reglas generales de avance/bloqueo, pero falta una combinación determinista implementable. | F17: 3361:2744 | G17: Resuelto | H17: Resuelto por Producto mediante M1-DP-008 / AX-M1-003. M01-RGL-012 se mantiene como gate único. Normalizar cada indicador a sufficient/pending/missing y aplicar criticidad: falta mínimo obligatorio → blocked; pendiente crítico → partial bloqueado; solo pendientes no críticos → partial permitido; sin pendientes relevantes → complete. Los reasons explican el output; no crear ramas de código por cada combinación técnica ni extrapolar combinaciones no cubiertas. | I17: M1-DP-008 | J17: Resuelto

Sheet Resumen
A1: WALVY | M1 – Resumen de trazabilidad
A3: Indicador | B3: Valor | E3: Cómo revisar con el cliente
A4: Variantes | B4: =COUNTA('Matriz Trazabilidad'!$A$5:$A$64) -> 60 | E4: 1 | F4: Revisar HU/CA | G4: Confirmar que la intención y criterios representan el comportamiento esperado.
A5: Historias de Usuario | B5: 34 | E5: 2 | F5: Revisar RN | G5: Ratificar las reglas y especialmente las marcadas como Figma/pendiente.
A6: Reglas de Negocio | B6: 60 | E6: 3 | F6: Revisar variante | G6: Aprobar, ajustar o excluir cada escenario.
A7: Variantes con evidencia Passed | B7: =COUNTIF('Matriz Trazabilidad'!$N$5:$N$64,"Passed") -> 21 | E7: 4 | F7: Revisar CP/QA | G7: Confirmar que exista un caso de prueba y que luego se vincule evidencia real.
A8: Variantes con evidencia pendiente | B8: =COUNTIF('Matriz Trazabilidad'!$N$5:$N$64,"Pendiente") -> 38
A9: Puntos de decisión/validación Cliente | B9: =COUNTA('Pendientes Cliente'!$A$5:$A$17) -> 13
A10: Nota Fuente RN | B10: El código identifica el artefacto de origen; la descripción explica su nombre y cobertura para revisión del Cliente.
A12: Métrica de revisión del Cliente | E12: Decisiones funcionales pendientes
A13: Estado de validación | B13: Cantidad | C13: % del total | E13: Estado decisión | F13: Cantidad | G13: % del total
A14: Aprobado | B14: =COUNTIF('Matriz Trazabilidad'!$R$5:$R$64,"Aprobado") -> 42 | C14: =IF($B$4=0,0,B14/$B$4) -> 0.7 | E14: Pendiente | F14: =COUNTIF('Pendientes Cliente'!$G$5:$G$17,"Pendiente") -> 0 | G14: =IF($B$9=0,0,F14/$B$9) -> 0
A15: Pendiente | B15: =COUNTIF('Matriz Trazabilidad'!$R$5:$R$64,"Pendiente") -> 0 | C15: =IF($B$4=0,0,B15/$B$4) -> 0 | E15: Resuelto | F15: =COUNTIF('Pendientes Cliente'!$G$5:$G$17,"Resuelto") -> 13 | G15: =IF($B$9=0,0,F15/$B$9) -> 1
A16: Ajustar | B16: =COUNTIF('Matriz Trazabilidad'!$R$5:$R$64,"Ajustar") -> 18 | C16: =IF($B$4=0,0,B16/$B$4) -> 0.3 | E16: Requiere análisis | F16: =COUNTIF('Pendientes Cliente'!$G$5:$G$17,"Requiere análisis") -> 0 | G16: =IF($B$9=0,0,F16/$B$9) -> 0
A17: Fuera de alcance | B17: =COUNTIF('Matriz Trazabilidad'!$R$5:$R$64,"Fuera de alcance") -> 0 | C17: =IF($B$4=0,0,B17/$B$4) -> 0 | E17: Fuera de alcance | F17: =COUNTIF('Pendientes Cliente'!$G$5:$G$17,"Fuera de alcance") -> 0 | G17: =IF($B$9=0,0,F17/$B$9) -> 0
A18: Requiere análisis | B18: =COUNTIF('Matriz Trazabilidad'!$R$5:$R$64,"Requiere análisis") -> 0 | C18: =IF($B$4=0,0,B18/$B$4) -> 0
A20: Variantes revisadas | B20: =SUM(B14,B16:B18) -> 60
A21: Avance de revisión | B21: =IF($B$4=0,0,B20/$B$4) -> 1
A22: Aprobación sobre revisadas | B22: =IF(B20=0,0,B14/B20) -> 0.7

Sheet Reglas Walvy
A1: M1 – Reglas Walvy y trazabilidad documental
A2: Las reglas de esta hoja provienen del assessment M01 existente; no se crean en esta revisión. Se conserva su redacción, resultado esperado y fuentes para transparentar cómo se construyó cada regla. “Uso en revisión Kabeli” indica si ya fue aplicada al validar la matriz de variantes.
A4: Regla ID | B4: Subárea | C4: Tipo de control | D4: Regla / criterio a verificar | E4: Resultado esperado | F4: Fuente principal (IDs) | G4: Ubicación fuente | H4: Estado documental | I4: Prioridad | J4: Bloqueante si falla | K4: Validador principal | L4: Evidencia requerida | M4: Caso de prueba | N4: Observaciones | O4: Uso en revisión Kabeli | P4: Variantes Kabeli asociadas | Q4: Origen
A5: M01-RGL-001 | B5: Acceso | C5: Flujo funcional | D5: Autenticar a una cuenta activa y verificada con correo y contraseña; rechazar credenciales inválidas sin revelar si la cuenta existe; y bloquear de forma recuperable el acceso de una cuenta restringida. | E5: Credenciales válidas de una cuenta habilitada crean sesión y abren el destino correspondiente. Credenciales inválidas mantienen Login con respuesta genérica. Una cuenta restringida no crea sesión, muestra “Acceso restringido”, permite contactar a soporte y volver a Login sin exponer el motivo interno. | F5: SRC-02 / SRC-25 / SRC-30 | G5: Alcance MVP fila 2 + build/endpoints de autenticación de SRC-25 + capturas congeladas de acceso restringido en SRC-30 | H5: Cerrado | I5: Alta | J5: Sí | K5: Andrea | L5: Video de acceso válido, inválido y restringido + build/plataforma + respuesta observable + identificación de usuarios sintéticos | M5: TC-M01-001 / TC-M01-002 | N5: Absorbe M01-ACC-002. TC-M01-001 y TC-M01-002 permanecen separados; TC-M01-002 contiene credenciales inválidas y cuenta restringida como subescenarios con no creación de sesión. | O5: Aplicada en V01–V23 | P5: M1-V01, M1-V02, M1-V03, M1-V04, M1-V13 | Q5: Walvy_Assessment_Validacion_M01_v1.1 (diferido_onboarding) · hoja 02_Reglas_M01
A6: M01-RGL-002 | B6: Registro | C6: Flujo funcional / validaciones | D6: Registrar una cuenta con correo, confirmación de correo, RUT, contraseña y las aceptaciones obligatorias visibles. Términos y Política de privacidad no pueden aceptarse directamente desde el formulario de Registro: cada documento debe abrirse y su acción «Aceptar» solo se habilita después de que el usuario alcance el final del contenido. Cerrar o volver antes de aceptar conserva el documento pendiente. Verificar el correo mediante un código de 6 dígitos antes del primer acceso. | E6: Correos coinciden; RUT válido; Términos y Política permanecen pendientes hasta abrir cada documento, alcanzar el final y seleccionar «Aceptar» dentro de este. Cerrar o volver antes no registra la aceptación. «Crear mi cuenta» solo se habilita con el formulario válido y ambas aceptaciones registradas. El OTP válido activa la cuenta. | F6: SRC-02 / SRC-27 / SRC-29 | G6: Alcance MVP fila 4 + ManifestLegalM01/MatrizAceptacionesM01 + referencia visual congelada de Registro M01 | H6: Cerrado | I6: Must | J6: Sí | K6: Andrea | L6: Video del registro y verificación + video de apertura, scroll y aceptación de cada documento + capturas de los estados bloqueados y habilitados + correo OTP + payload de registro/aceptaciones + manifest legal + build/plataforma | M6: TC-M01-003 / TC-M01-004 | N6: Absorbe M01-ACC-004. Campos obligatorios: correo, confirmación de correo, RUT, contraseña, Términos y Política de privacidad. No exigir nombre dentro del formulario de Registro. Decisión funcional Walvy: las aceptaciones legales solo se registran desde el documento correspondiente después de alcanzar el final; no se permite aceptarlas directamente desde Registro. | O6: Aplicada en V01–V23 | P6: M1-V08 a M1-V16 | Q6: Walvy_Assessment_Validacion_M01_v1.1 (diferido_onboarding) · hoja 02_Reglas_M01
A7: M01-RGL-003 | B7: Recuperación | C7: Flujo funcional | D7: Restablecer la contraseña mediante OTP enviado al correo registrado, aplicando la política de contraseña y la confirmación coincidente antes de habilitar el cambio. | E7: OTP válido y contraseña aceptada/coincidente cambian la clave una sola vez; OTP inválido, expirado o reutilizado, contraseña fuera de política o confirmación distinta no habilitan el cambio. | F7: SRC-02 / SRC-25 / SRC-27 / SRC-30 | G7: Alcance MVP + Release Note QA + ParametrosSeguridadM01 + estados visuales de nueva contraseña en SRC-30 | H7: Cerrado | I7: Must | J7: Sí | K7: Andrea | L7: Correo con OTP + video de validaciones y éxito + respuestas API controladas + acceso con nueva contraseña | M7: TC-M01-005 | N7: El único mecanismo aprobado es OTP por correo. TC-M01-005 incluye política, confirmación y CTA; seguridad del OTP permanece en M01-SEC-002. | O7: Aplicada en V01–V23 | P7: M1-V17 a M1-V23 | Q7: Walvy_Assessment_Validacion_M01_v1.1 (diferido_onboarding) · hoja 02_Reglas_M01
A8: M01-RGL-004 | B8: Biometría | C8: Capacidad opcional | D8: Permitir activar, usar y desactivar biometría local, manteniendo la contraseña como alternativa. | E8: Éxito, cancelación y fallo conservan el fallback; desactivar elimina la solicitud biométrica. | F8: SRC-02 / SRC-27 | G8: Alcance MVP fila 3 + contrato biométrico local | H8: Cerrado | I8: Media | J8: Condicional | K8: Andrea | L8: Video en dispositivo compatible: activación, uso, cancelación, fallo, fallback y desactivación | M8: TC-M01-006 | N8: Condicional a dispositivo/plataforma compatible. M01-BIO-001 mantiene la evidencia técnica separada. | O8: Aplicada en V01–V36 | P8: M1-V05, M1-V06, M1-V07, M1-V26 | Q8: Walvy_Assessment_Validacion_M01_v1.1 (diferido_onboarding) · hoja 02_Reglas_M01
A9: M01-RGL-005 | B9: Onboarding | C9: Flujo integral | D9: Completar Bienvenida → Concientización → Foco → Carga/Revisión → Suficiencia → Primera lectura, preservando el avance y habilitando el diagnóstico solo con datos requeridos completos. | E9: Secuencia y CTA aprobados; foco y documentos persisten; faltantes requeridos se corrigen, ingresan o categorizan; la base suficiente habilita el diagnóstico. | F9: SRC-06 / SRC-21 / SRC-22 / SRC-23 / SRC-26 | G9: Secuencia UX congelada + fixtures ONB/DOC/SUF/DIA y matrices de completitud | H9: Cerrado | I9: Must | J9: Sí | K9: Jose | L9: Video E2E + checkpoints + manifest de fixtures + payload de suficiencia/diagnóstico + build/plataforma | M9: TC-M01-007 | N9: Absorbe M01-ONB-002, M01-ONB-003 y la navegación inicial de M01-ONB-005. La completitud dirigida se valida en M01-RGL-011/TC-M01-031. | O9: Aplicada en V24–V36 y brecha M1-BC-001 | P9: M1-V27; M1-BC-001 | Q9: Walvy_Assessment_Validacion_M01_v1.1 (diferido_onboarding) · hoja 02_Reglas_M01
A10: M01-RGL-006 | B10: Foco del mes | C10: Regla de negocio / persistencia | D10: Persistir el foco y usarlo solo para personalización contextual, sin alterar la conclusión financiera central. | E10: Con la misma evidencia financiera, el estado y la conclusión central permanecen; el foco persiste. | F10: SRC-08 / SRC-22 / SRC-26 | G10: Flujo funcional + DATA-M01-FOCO-01 + matriz de empate contextual | H10: Cerrado | I10: Alta | J10: Sí | K10: Jose | L10: Dos ejecuciones con el mismo fixture financiero + persistencia del foco + comparación de resultado | M10: TC-M01-008 | N10: No permite que el foco sustituya evidencia financiera ni modifique el estado central. | O10: Aplicada en V24–V36 | P10: M1-V28, M1-V31 a M1-V36 | Q10: Walvy_Assessment_Validacion_M01_v1.1 (diferido_onboarding) · hoja 02_Reglas_M01
A11: M01-RGL-007 | B11: Omisión/postergación | C11: Continuidad explícita | D11: Permitir salir desde un checkpoint no concluido, guardar el avance y retornar a Inicio sin generar una primera lectura concluyente. | E11: CTA y modal coinciden con la referencia; el checkpoint persiste; Inicio refleja estado pendiente y la retoma continúa desde el punto guardado. | F11: SRC-21 / SRC-22 / SRC-26 | G11: Figma modal 6670:13499 + DATA-M01-PARTIAL-01 + MatrizContinuidadM01 | H11: Cerrado | I11: Must | J11: Sí | K11: Jose | L11: Video de dos puntos de salida + capturas de CTA/modal/Home + checkpoint persistido | M11: TC-M01-009 | N11: Absorbe M01-CON-001 y la mitad pendiente de M01-CON-004. El detalle de copy/nodos queda en fuentes/caso, no en la regla. | O11: Aplicada en V24–V36 y V58 | P11: M1-V25, M1-V29, M1-V58 | Q11: Walvy_Assessment_Validacion_M01_v1.1 (diferido_onboarding) · hoja 02_Reglas_M01
A12: M01-RGL-008 | B12: Retoma | C12: Continuidad transversal | D12: Recuperar el mismo checkpoint, selección documental, job o resultado después de cerrar la app o cerrar sesión. | E12: No se repiten pasos completados ni se duplican documentos/jobs; cada checkpoint reabre en el destino y estado correctos. | F12: SRC-08 / SRC-23 / SRC-26 | G12: MatrizContinuidadM01 + fixtures de carga/análisis/retoma | H12: Cerrado | I12: Must | J12: Sí | K12: Jose | L12: Videos de retoma + document_ids/job_id/checkpoint + ausencia de duplicados | M12: TC-M01-010 / TC-M01-014 / TC-M01-022 | N12: Absorbe M01-DOC-007 y M01-ANA-004. M01-CON-002/TC-M01-049 se elimina como meta-caso. | O12: Aplicada en V37–V60 | P12: M1-V44, M1-V45, M1-V46, M1-V58, M1-V59, M1-V60 | Q12: Walvy_Assessment_Validacion_M01_v1.1 (diferido_onboarding) · hoja 02_Reglas_M01
A13: M01-RGL-009 | B13: Carga documental | C13: Flujo funcional | D13: Seleccionar, cargar, quitar y reintentar documentos admitidos dentro de los formatos y límites vigentes antes de iniciar el análisis. | E13: La selección es editable; admisión, progreso, cancelación y reintento coinciden con la matriz; no se procesa un archivo cancelado. | F13: SRC-21 / SRC-23 / SRC-24 | G13: Figma 6670:13168 + MatrizAdmisionDS + fixtures MULTI/UPLOAD | H13: Cerrado | I13: Must | J13: Sí | K13: Andrea | L13: Video + archivos/manifest + estados de selección/carga/cancelación/reintento | M13: TC-M01-011 / TC-M01-012 | N13: Absorbe M01-DOC-002 y M01-DOC-003. Los estados dejan de tener una regla separada y se validan en los casos que los producen. | O13: Aplicada en V37–V52 | P13: M1-V37, M1-V38 | Q13: Walvy_Assessment_Validacion_M01_v1.1 (diferido_onboarding) · hoja 02_Reglas_M01
A14: M01-RGL-010 | B14: Carga documental | C14: Ruta negativa | D14: Cuando un documento no pueda utilizarse para construir el diagnóstico por incumplir las condiciones de admisión, no contener datos procesables o estar desactualizado, informar la causa y permitir reemplazarlo o cargar otra evidencia. | E14: El documento queda identificado como Rechazado, No procesable o Desactualizado; se muestra una acción siguiente adecuada y el diagnóstico permanece bloqueado hasta contar con información suficiente. | F14: SRC-23 / SRC-24 / SRC-27 | G14: MatrizAdmisionDS + fixtures REJECT/NONPROC + control DOCSEC-001 | H14: Cerrado | I14: Alta | J14: Sí | K14: Jose | L14: Video/capturas + payload/código de estado + parámetro de vigencia + manifest | M14: TC-M01-013 | N14: Una regla con tres subescenarios en el mismo caso porque comparten el oráculo de negocio: explicar, recuperar y no habilitar el diagnóstico. DOCSEC-001 conserva la validación técnica de admisión segura. | O14: Aplicada en V37–V52 | P14: M1-V40, M1-V42 | Q14: Walvy_Assessment_Validacion_M01_v1.1 (diferido_onboarding) · hoja 02_Reglas_M01
A15: M01-RGL-011 | B15: Revisión documental | C15: Regla de negocio / completitud dirigida | D15: Antes del diagnóstico, permitir confirmar, corregir, ingresar o categorizar únicamente los datos requeridos que la extracción no resolvió. | E15: Los datos clave quedan completos o confirmados; un documento usable parcial se conserva; no se habilita diagnóstico con faltantes bloqueantes. | F15: SRC-23 / SRC-24 | G15: 07_Fixtures_DS: MatrizCompletitudDS + MatrizIndicadoresDS | H15: Cerrado | I15: Must | J15: Sí | K15: Jose | L15: Video + payload antes/después + fixture de corrección/ingreso/categorización | M15: TC-M01-030 / TC-M01-031 | N15: Absorbe M01-DOC-005 y M01-DOC-009. Permite intervención puntual; no crea una ruta manual integral paralela. En M01, “Completar información clave” orquesta capacidades ya definidas en módulos dueños: M05 para ingreso/movimientos/categorización; M06 para compromisos/pagos/recurrencias; M04 para deuda/atraso/mora cuando exista señal. Debe abrir el contexto mínimo necesario, devolver el dato confirmado/corregido y recalcular M01-RGL-012. No crear formularios paralelos en M01 ni exigir M04 como condición universal del Diagnóstico. | O15: Aplicada en V37–V52 | P15: M1-V48, M1-V49, M1-V50, M1-V51 | Q15: Walvy_Assessment_Validacion_M01_v1.1 (diferido_onboarding) · hoja 02_Reglas_M01
... A20: M01-RGL-016 | B20: Cierre del onboarding | C20: Persistencia / destino | D20: Persistir la primera lectura, cerrar el onboarding y aterrizar en Home/Inicio de M01. | E20: El resultado persiste; el onboarding no se repite; Inicio refleja el estado completado. | F20: SRC-21 / SRC-26 | G20: Primera lectura 6670:13628 + definición Home/Inicio + MatrizContinuidadM01 | H20: Cerrado | I20: Must | J20: Sí | K20: Jose | L20: Video E2E + estado API/BDD + captura Home/Inicio + reingreso | M20: TC-M01-026 | N20: Absorbe la mitad completada de M01-CON-004. Mi Perfil Financiero permanece como dependencia M02. | O20: Aplicada al cierre del Diagnóstico | P20: M1-V53, M1-V54, M1-V55, M1-V57 | Q20: Walvy_Assessment_Validacion_M01_v1.1 (diferido_onboarding) · hoja 02_Reglas_M01
A21: M01-RGL-017 | B21: Datos y eventos | C21: Control técnico | D21: Registrar eventos mínimos de carga, análisis, diagnóstico, CTA, pausa/retoma y cierre sin datos sensibles. | E21: Los payloads cumplen campos obligatorios, null controlado y correlación técnica; no contienen PII ni contenido financiero. | F21: SRC-26 / SRC-27 / SRC-28 | G21: ContratoEventosM01 + DiccionarioEvidenciaM01 | H21: Cerrado | I21: Alta | J21: Sí | K21: Erick | L21: Export de eventos + matriz campo/fixture + logs redaccionados + correlación | M21: TC-M01-027 | N21: Absorbe M01-ANA-003/TC-M01-036. No duplicar con M01-LOG-001: DAT-001 valida contrato; LOG-001 valida no exposición. | O21: Control transversal de QA; no requiere variante visual específica M01. | Q21: Walvy_Assessment_Validacion_M01_v1.1 (diferido_onboarding) · hoja 02_Reglas_M01
A22: M01-RGL-018 | B22: Versionamiento | C22: Control técnico / readiness | D22: Asociar resultados y parámetros efectivos a versiones, fuente y vigencia verificables. | E22: rule_version, config_version, parameter_source, effective_from y evaluated_at permiten reproducir el diagnóstico. | F22: SRC-26 / SRC-27 / SRC-28 | G22: Manifest técnico + registry de regla/configuración + parámetros efectivos | H22: Cerrado | I22: Alta | J22: Condicional | K22: Erick | L22: Registros versionados + configuración/pipeline + payloads comparados | M22: TC-M01-028 | N22: Absorbe M01-DOC-008/TC-M01-025 como parámetro versionado. Gate de cumplimiento: Preproducción. | O22: Control transversal de readiness/versionamiento; no requiere variante visual específica M01. | Q22: Walvy_Assessment_Validacion_M01_v1.1 (diferido_onboarding) · hoja 02_Reglas_M01
A23: M01-RGL-019 | B23: Errores globales | C23: Recuperación / navegación | D23: Mostrar una salida recuperable ante una ruta inexistente o una indisponibilidad temporal, evitando cierres inesperados, ciclos de reintento y pérdida del estado seguro previo. | E23: Una ruta inexistente muestra “No encontramos esta página” y «Volver» retorna a la pantalla anterior. Una falla temporal muestra “No pudimos cargar la información”; «Reintentar» recupera la carga cuando el servicio vuelve, sin duplicar acciones ni perder el estado seguro de sesión. | F23: SRC-30 | G23: Capturas congeladas: página no encontrada y falla temporal de servidor; harness técnico para provocar ambas condiciones | H23: Cerrado | I23: Alta | J23: Sí | K23: Andrea | L23: Video de ambos subescenarios + ruta/request y código de respuesta + estado antes/después + evidencia de no duplicación | M23: TC-M01-049 | N23: Regla transversal para errores globales. No sustituye los errores específicos de autenticación, documentos o análisis; reutiliza el mismo caso con dos subescenarios porque comparten el oráculo de recuperación y preservación de estado. | O23: Control transversal de navegación/recuperación; no requiere variante visual específica M01. | Q23: Walvy_Assessment_Validacion_M01_v1.1 (diferido_onboarding) · hoja 02_Reglas_M01
A24: RB-FM-001 | B24: Foco del mes | C24: Regla de negocio / priorización CTA | D24: Si el usuario tiene un Objetivo Foco del Mes activo, Walvy debe priorizar los CTAs asociados a ese foco en Home, Perfil Financiero, Mi Foco del Mes, recomendaciones y pantallas relacionadas, salvo que exista una señal financiera crítica de mayor prioridad. | E24: La experiencia prioriza el foco activo cuando no exista una señal financiera crítica de mayor prioridad. | F24: Walvy_Regla_Priorizacion_CTA_por_Foco_Mes_v1_0.docx | G24: Sección 6 · Regla de negocio principal | H24: Oficial entregado a Kabeli | K24: PO | N24: Se conserva el identificador y contenido de la regla oficial; cualquier pendiente de implementación se registra por separado. Ajuste editorial PO aprobado: hacer explícito que el foco activo puede orientar CTAs, recomendaciones, alertas/notificaciones in-app y próximos pasos cuando no exista una señal funcional superior; opera como orientación/desempate y no como override. | O24: Aplicada en V28 y V31–V36 | P24: M1-V28, M1-V31 a M1-V36 | Q24: Walvy_Regla_Priorizacion_CTA_por_Foco_Mes_v1_0.docx · documento oficial entregado a Kabeli
A25: RB-FM-002 | B25: Foco del mes | C25: Regla de negocio / prioridad | D25: Una señal crítica de salud financiera siempre prevalece sobre el foco declarado. | E25: Las señales críticas no pueden quedar ocultas o subordinadas por el foco elegido. | F25: Walvy_Regla_Priorizacion_CTA_por_Foco_Mes_v1_0.docx | G25: Sección 9 · Reglas complementarias | H25: Oficial entregado a Kabeli | K25: PO | N25: Se conserva el identificador y contenido de la regla oficial; cualquier pendiente de implementación se registra por separado. Ajuste editorial PO aprobado: para sugerencia/priorización contextual sin foco activo, hacer visible la prioridad funcional M04 → M06 → M05. Las señales críticas/superiores siguen prevaleciendo sobre cualquier foco. | O25: Aplicada en V28 | P25: M1-V28 | Q25: Walvy_Regla_Priorizacion_CTA_por_Foco_Mes_v1_0.docx · documento oficial entregado a Kabeli
A26: RB-FM-003 | B26: Foco del mes | C26: Regla de negocio / CTA | D26: Si no hay señales críticas, el CTA dominante debe alinearse con el Foco del Mes activo. | E26: El CTA dominante refleja el foco activo cuando no existe una señal crítica superior. | F26: Walvy_Regla_Priorizacion_CTA_por_Foco_Mes_v1_0.docx | G26: Sección 9 · Reglas complementarias | H26: Oficial entregado a Kabeli | K26: PO | N26: Se conserva el identificador y contenido de la regla oficial; cualquier pendiente de implementación se registra por separado. | O26: Aplicada en V28 | P26: M1-V28 | Q26: Walvy_Regla_Priorizacion_CTA_por_Foco_Mes_v1_0.docx · documento oficial entregado a Kabeli
A27: RB-FM-004 | B27: Foco del mes | C27: Regla de negocio / sugerencia de foco | D27: Si el usuario no tiene foco activo, Walvy puede sugerir uno según Perfil Financiero. | E27: La capacidad de sugerencia existe cuando no hay foco activo; la selección específica del foco requiere una lógica determinista de Producto todavía pendiente. | F27: Walvy_Regla_Priorizacion_CTA_por_Foco_Mes_v1_0.docx | G27: Sección 9 · Reglas complementarias | H27: Oficial entregado a Kabeli | K27: PO | N27: Se conserva el identificador y contenido de la regla oficial; cualquier pendiente de implementación se registra por separado. Ajuste editorial PO aprobado: cuando no exista foco activo, la sugerencia consume una versión válida del Diagnóstico y aplica prioridad M04 → M06 → M05 usando las condiciones ya documentadas por foco, sin crear umbrales nuevos en M01. Ver M1-DP-002 / AX-M1-002. | O27: Aplicada en V30 | P27: M1-V30 | Q27: Walvy_Regla_Priorizacion_CTA_por_Foco_Mes_v1_0.docx · documento oficial entregado a Kabeli
A28: RB-FM-005 | B28: Foco del mes | C28: Guardrail funcional | D28: El foco elegido no debe ocultar deuda presionada, mora, atrasos, vencimientos críticos o disponible insuficiente. | E28: Una señal crítica visible mantiene prioridad aunque exista un foco activo. | F28: Walvy_Regla_Priorizacion_CTA_por_Foco_Mes_v1_0.docx | G28: Sección 9 · Reglas complementarias | H28: Oficial entregado a Kabeli | K28: PO | N28: Se conserva el identificador y contenido de la regla oficial; cualquier pendiente de implementación se registra por separado. | O28: Disponible para validación posterior | Q28: Walvy_Regla_Priorizacion_CTA_por_Foco_Mes_v1_0.docx · documento oficial entregado a Kabeli
A29: RB-FM-006 | B29: Foco del mes | C29: Trazabilidad indicador → foco | D29: Cada foco debe estar trazado a uno o más indicadores del Perfil Financiero. | E29: Toda sugerencia de foco debe poder justificarse por indicadores del Perfil Financiero; la matriz determinista indicador→foco queda pendiente de definición PO. | F29: Walvy_Regla_Priorizacion_CTA_por_Foco_Mes_v1_0.docx | G29: Sección 9 · Reglas complementarias | H29: Oficial entregado a Kabeli | K29: PO | N29: Se conserva el identificador y contenido de la regla oficial; cualquier pendiente de implementación se registra por separado. | O29: Aplicada en V30 | P29: M1-V30 | Q29: Walvy_Regla_Priorizacion_CTA_por_Foco_Mes_v1_0.docx · documento oficial entregado a Kabeli
A30: RB-FM-007 | B30: Foco del mes | C30: Jerarquía CTA | D30: No deben mostrarse dos CTAs con el mismo peso visual. Debe existir una acción dominante y accesos secundarios si corresponde. | E30: La pantalla presenta una acción dominante y subordina las secundarias. | F30: Walvy_Regla_Priorizacion_CTA_por_Foco_Mes_v1_0.docx | G30: Sección 9 · Reglas complementarias | H30: Oficial entregado a Kabeli | K30: PO | N30: Se conserva el identificador y contenido de la regla oficial; cualquier pendiente de implementación se registra por separado. Ajuste editorial PO aprobado: cuando se presenta un foco sugerido puede existir CTA primario “Usar este foco” para aceptación directa y CTA secundario “Revisar foco” hacia Mi Perfil → Mi foco del mes, manteniendo una única acción dominante. | O30: Disponible para validación posterior | Q30: Walvy_Regla_Priorizacion_CTA_por_Foco_Mes_v1_0.docx · documento oficial entregado a Kabeli
A31: RB-FM-008 | B31: Foco del mes | C31: Calidad de dato | D31: Si la calidad del dato es insuficiente para sostener el foco, debe priorizarse completar o confirmar información. | E31: Walvy no sostiene una personalización de foco con datos insuficientes; prioriza completar o confirmar información. | F31: Walvy_Regla_Priorizacion_CTA_por_Foco_Mes_v1_0.docx | G31: Sección 9 · Reglas complementarias | H31: Oficial entregado a Kabeli | K31: PO | N31: Se conserva el identificador y contenido de la regla oficial; cualquier pendiente de implementación se registra por separado. | O31: Disponible para validación posterior | Q31: Walvy_Regla_Priorizacion_CTA_por_Foco_Mes_v1_0.docx · documento oficial entregado a Kabeli
A32: RB-FM-009 | B32: Foco del mes | C32: Persistencia / superficies | D32: El foco activo puede influir en recomendaciones, Home, Perfil Financiero y Mi Foco del Mes. | E32: El foco activo puede personalizar las superficies definidas sin reemplazar señales críticas. | F32: Walvy_Regla_Priorizacion_CTA_por_Foco_Mes_v1_0.docx | G32: Sección 9 · Reglas complementarias | H32: Oficial entregado a Kabeli | K32: PO | N32: Se conserva el identificador y contenido de la regla oficial; cualquier pendiente de implementación se registra por separado. Ajuste editorial PO aprobado: incluir explícitamente alertas/notificaciones in-app y próximos pasos entre las superficies influenciables por el foco, sin reemplazar señales superiores. | O32: Disponible para validación posterior | Q32: Walvy_Regla_Priorizacion_CTA_por_Foco_Mes_v1_0.docx · documento oficial entregado a Kabeli
A33: RB-FM-010 | B33: Foco del mes | C33: Gestión del foco | D33: El usuario debe poder cambiar su foco, pero Walvy debe advertir si existe una señal crítica más prioritaria. | E33: El cambio de foco no oculta ni desplaza una señal crítica superior. | F33: Walvy_Regla_Priorizacion_CTA_por_Foco_Mes_v1_0.docx | G33: Sección 9 · Reglas complementarias | H33: Oficial entregado a Kabeli | K33: PO | N33: Se conserva el identificador y contenido de la regla oficial; cualquier pendiente de implementación se registra por separado. | O33: Disponible para validación posterior | Q33: Walvy_Regla_Priorizacion_CTA_por_Foco_Mes_v1_0.docx · documento oficial entregado a Kabeli
A34: RB-FM-011 | B34: Foco del mes | C34: Trazabilidad catálogo / UI | D34: Si la UI muestra menos focos que el catálogo funcional, la selección visible debe justificarse por contexto, espacio o personalización; no debe eliminar la trazabilidad funcional. | E34: El catálogo funcional completo conserva trazabilidad aunque una superficie muestre una selección contextual. | F34: Walvy_Regla_Priorizacion_CTA_por_Foco_Mes_v1_0.docx | G34: Sección 9 · Reglas complementarias | H34: Oficial entregado a Kabeli | K34: PO | N34: Se conserva el identificador y contenido de la regla oficial; cualquier pendiente de implementación se registra por separado. | O34: Disponible para validación posterior | Q34: Walvy_Regla_Priorizacion_CTA_por_Foco_Mes_v1_0.docx · documento oficial entregado a Kabeli
A36: Catálogo de fuentes citadas por las reglas
A38: Fuente ID | B38: Documento / fuente | C38: Nivel | D38: Estado | E38: Uso en assessment M01 | F38: Ubicación / referencia
A39: SRC-02 | B39: MVP_CheckApp_VF_10032026_alineado_estrategia.xlsx | C39: N1 alcance | D39: Vigente | E39: Alcance funcional y criterios de aceptación del MVP. | F39: Alcance MVP, filas 2 a 7
A40: SRC-06 | B40: Walvy_Especificacion_UX_Onboarding_App.docx | C40: N2 UX | D40: Vigente | E40: Principios, pantallas, estados y salida del onboarding. | F40: Secciones 1 a 6
A41: SRC-08 | B41: Walvy_Onboarding_Diagnostico_Fase1_Flujo_Funcional_v1_0.docx | C41: N2 funcional | D41: Cerrado | E41: Flujo punta a punta, suficiencia, retoma y criterios QA. | F41: Tablas 6 a 26
A42: SRC-10 | B42: Walvy_Onboarding_Diagnostico_Fase3_Reglas_Contextuales_Suficiencia_Semaforo_CTA_v1_0.docx | C42: N2 reglas | D42: Cerrado con candidatos | E42: Reglas de suficiencia, semáforo, presión y CTA dominante. | F42: Tablas 5 a 28
A43: SRC-12 | B43: 00 Matriz_Estados_Visibles_Walvy_v1_0_cards_M01_M02_banco_documental.docx | C43: N3 QA visual | D43: Vigente | E43: Estados visibles y textos exactos aprobados para M01. | F43: Tablas 0, 4, 5 y 6
A44: SRC-13 | B44: 00 Walvy_Catalogo_Maestro_CTA_Contextuales_Walvy_v1_0.docx | C44: N3 CTA | D44: Vigente con dependencias | E44: CTA contextuales y dependencias futuras entre M01 y los módulos dueños. | F44: Tablas 3, 4 y 19
A45: SRC-21 | B45: Figma M01 congelado para QA · Acceso, Onboarding y estados disponibles | C45: N2 UX ejecutable | D45: Vigente · congelado 24-07-2026 | E45: Referencia visual exacta únicamente para los node IDs enumerados. Registro se valida contra SRC-29 mientras no exista node exacto congelado. Los estados sin frame se validan por comportamiento, copy y jerarquía contra las fuentes funcionales declaradas. | F45: https://www.figma.com/design/v45c4HTKnPnU0XABMa5vjY?node-id=3361-2744 Archivo v45c4HTKnPnU0XABMa5vjY · sección 3361:2744. Nodos: bienvenida inicial “Tu mes, en claro” 6670:13197; bienvenida/concientización 6670:13103, 6670:13126 y 6670:13145; foco 6670:13227; carga documental 6670:13168; revisión/base suficiente 6459:7869; modal de salida 6670:13499; anotación de transición a Home 6670:13526 (no corresponde a un frame de pantalla); primera lectura 6670:13628; verificación de cuenta 3470:7580, 3470:7774 y 3470:7862. Los demás estados DOC/SUF usan la fuente funcional alternativa declarada en SRC-24 hasta incorporar sus node IDs.
A46: SRC-22 | B46: Catálogo de usuarios y fixtures sintéticos QA M01 · especificación 1.3 | C46: N3 QA ejecutable | D46: Vigente · especificación v1.3; manifest obligatorio antes de ejecutar | E46: USUARIOS QA-ACC-NEW-01: nuevo/no registrado. QA-ACC-ACT-01: activo/verificado, onboarding pendiente. QA-ACC-BIO-01: activo/verificado, biometría configurada. QA-ACC-REC-01: activo/verificado, buzón de prueba. QA-ACC-REST-01: activo/verificado, access_state=restricted, credenciales válidas, motivo interno no expuesto y canal de soporte configurado. DATA-M01-DOC-01 | SPEC-1.2 Alias de DATA-M01-SUF-FULL-01 definido en SRC-23. Usuario QA-ACC-ACT-01; foco “Bajar deuda”; inicio en Selección de foco, sin documentos ni diagnóstico. Los archivos se materializan dentro de la ventana de vigencia efectiva del build. Esperado: documentos visibles, análisis iniciado, cinco indicadores núcleo visibles, estado “Base suficiente para empezar” y CTA dominante “Comenzar diagnóstico”; secundarias “Cargar más documentos” y “Continuar más tarde”. DATA-M01-ONB-01 | SPEC-1.2 QA-ACC-ACT-01; foco “Bajar deuda”; cuenta activa/verificada; onboarding pendiente; sin documentos ni primera lectura. Insumo DOC-01. Resultado intermedio: “Base suficiente para empezar”. Resultado final: “Tu primera lectura está lista” / “En control”; Margen Saludable, Compromisos Bajo control y Movimientos Sin alertas. Los destinos M06/M02 visibles no se ejecutan para cerrar M01. DATA-M01-REG-VALID-01 | SPEC-1.0 QA-ACC-NEW-01; correo qa.m01.registro+001@walvy.test y confirmación idéntica; RUT sintético válido 11.111.111-1; contraseña válida; Términos=true; Política=true. Esperado: CTA habilitado, cuenta pending_verification, OTP válido activa la cuenta. DATA-M01-REG-ERROR-01 | SPEC-1.0 A: correos distintos. B: RUT 12.345.678-9 inválido. C: Términos=false. D: Política=false. Cada subcaso muestra error específico y mantiene CTA deshabilitado hasta corregirse. | F46: DATA-M01-FOCO-01 | SPEC-1.2 Dos ejecuciones de ONB-01 con focos “Bajar deuda” y “Ahorrar un monto”. Esperado: mismo semáforo y señales; solo varía priorización o copy contextual permitido. DATA-M01-PARTIAL-01 | SPEC-1.2 Alias de DATA-M01-SUF-PARTIAL-BLOCK-01 definido en SRC-23. Usuario QA-ACC-ACT-01; checkpoint Revisión documental. Esperado: “Faltan datos por confirmar”, partial_diagnostic_allowed=false, sin primera lectura concluyente y acciones “Completar información clave” / “Continuar más tarde”. MANIFEST OBLIGATORIO Para cada fixture: ID y versión, nombre exacto, ruta/URI, formato, tipo documental, período, tamaño real, SHA-256, fecha de generación, responsable, build/plataforma, parámetro de vigencia efectivo y resultado de admisión. Mientras falte un campo, el caso permanece “No iniciado”. Registro: SRC-29 + TC-M01-003/004. No utilizar datos personales reales.
A47: SRC-23 | B47: Especificación QA Documentos y Suficiencia M01 · fixtures y matriz de admisión v1.2 | C47: N3 QA ejecutable | D47: Vigente para assessment · especificación v1.2; materialización pendiente | E47: Matriz ejecutable de admisión, catálogo de fixtures, matriz determinista por indicador y MatrizCompletitudDS. Owners activos: M01-RGL-009/004, M01-RGL-011 y M01-RGL-012/007. | F47: Hoja 07_Fixtures_DS: MatrizAdmisionDS, CatalogoFixturesDS, MatrizIndicadoresDS y MatrizCompletitudDS. Cero fixture eliminado.
A48: SRC-24 | B48: Decisiones QA Documentos y Suficiencia M01 · versión 1.0 | C48: N2 decisión funcional/QA | D48: Vigente para ejecución del assessment M01 | E48: Decisiones DS-001 a DS-006 remapeadas: completitud dirigida→M01-RGL-011/TC-M01-031; gates→M01-RGL-012; trazabilidad→M01-RGL-013. No constituye contrato técnico. | F48: Detalle histórico en 06_Iteracion_B_DS; datos ejecutables en 07_Fixtures_DS; owners activos en 02/03.
A49: SRC-25 | B49: Walvy_M01_Release_Note_QA.pdf | C49: N1 entrega técnica | D49: Vigente · entrega 21-07-2026 | E49: Congela build y contratos técnicos entregados: recuperación por OTP, endpoints de autenticación, rotación/replay de refresh tokens, logout local/global, rate limit y ausencia de backoffice admin. | F49: Backend v1.0.0 c2e9460; Frontend v1.0.0 94199ee; Sandbox/QA. Secciones 1, 2, 4 y 5.
... A55: SRC-FM-01 | B55: Walvy_Regla_Priorizacion_CTA_por_Foco_Mes_v1_0.docx | C55: N2 reglas de Producto | D55: Oficial entregado a Kabeli | E55: Catálogo de seis focos, priorización de CTA, jerarquía entre señales críticas/foco declarado/foco sugerido y reglas RB-FM-001 a RB-FM-011. | F55: Secciones 3, 6, 7, 9 y 11

Sheet Brechas de Cobertura
A1: M1 – Brechas de cobertura detectadas en la matriz Kabeli
A2: Registra únicamente variantes, condiciones o reglas que debían estar cubiertas por las fuentes vigentes y que no fueron levantadas por Kabeli. No se incluyen mejoras nuevas de Producto ni hallazgos de ejecución QA.
A4: ID Brecha | B4: Bloque | C4: Variante / condición faltante | D4: Fuente que la exige | E4: Regla Walvy | F4: Tratamiento propuesto | G4: Estado | H4: Observación
A5: M1-BC-001 | B5: Onboarding | C5: Secuencia de concientización posterior a la bienvenida | D5: Walvy_Onboarding_Diagnostico_Fase1_Flujo_Funcional_v1_0.docx + Walvy_Onboarding_Diagnostico_Fase2_Matriz_Pantallas_Estados_Acciones_v1_0.docx + Figma cerrado | E5: M01-RGL-005 | F5: Incorporar cobertura explícita de la secuencia breve de concientización antes de Foco del Mes. | G5: Confirmada | H5: Kabeli pasa de M1-V27 Bienvenida / activación a M1-V28 Foco declarado y no representa la secuencia intermedia documentada y construida en Figma.
A6: M1-BC-003 | B6: Carga documental | C6: Error de carga/subida del archivo | D6: Walvy_Especificacion_UX_Onboarding_App.docx · 4.2 Estados operativos | E6: M01-RGL-009 | F6: Si el archivo no completa correctamente su carga, informar que no pudo cargarse y permitir reintentar o seleccionar nuevamente. No comunicar que quedó disponible para análisis. | G6: Confirmada | H6: Ocurre antes de conocer la usabilidad del archivo. Debe diferenciarse de M1-V40, donde el archivo ya llegó a evaluación pero no resulta usable/no procesable.
A7: M1-BC-004 | B7: Carga documental | C7: Archivo rechazado por condiciones de admisión | D7: Figma cerrado + Walvy_Onboarding_Diagnostico_Fase3_Anexo_BDD_Reglas_Productivas_v1_0.docx | E7: M01-RGL-010 | F7: Si el archivo incumple una condición de admisión aplicable —formato, tamaño, límite u otra validación definida—, no incorporarlo al conjunto a analizar, informar la causa y permitir reemplazarlo. | G7: Confirmada | H7: Diferente de M1-V40: el rechazo ocurre en la admisión; M1-V40 corresponde a un archivo admitido que posteriormente no produce información útil/procesable.
A8: M1-BC-005 | B8: Acceso / Login | C8: Cuenta restringida con credenciales válidas | D8: M01-RGL-001 + Walvy_Assessment_Validacion_M01_v1.1 (diferido_onboarding) · TC-M01-002 / SRC-30 | E8: M01-RGL-001 | F8: Incorporar cobertura explícita del caso: credenciales válidas + cuenta restricted → no crear sesión; mostrar “Acceso restringido”; permitir contactar a soporte y volver a Login; no exponer motivo interno. | G8: Confirmada | H8: No corresponde a V03: allí las credenciales son inválidas. Aquí la autenticación es válida, pero el estado de cuenta bloquea el acceso. No requiere una decisión adicional de Producto.

Sheet Observaciones Producto
A1: M1 – Decisiones y observaciones de Producto surgidas durante la revisión
A2: Estas observaciones no se atribuyen a Kabeli como brechas de cobertura. Se registran separadamente para no contaminar la validación de la matriz entregada. La columna “Pendiente Cliente relacionado” vincula la observación con el backlog de Kabeli cuando corresponde; una observación resuelta puede no tener pendiente asociado.
A4: ID | B4: Bloque | C4: Observación | D4: Tipo | E4: Relación con matriz Kabeli | F4: Estado | G4: Pendiente Cliente relacionado
A5: M1-DP-001 | B5: Registro | C5: El Registro utiliza un único campo de contraseña y el Figma cerrado incorpora el control mostrar/ocultar contraseña, permitiendo al usuario revisar el valor digitado sin requerir un segundo campo de confirmación. | D5: Observación de Producto cerrada | E5: No constituye brecha de cobertura de Kabeli; resuelto por el diseño cerrado. | F5: Resuelto
A6: M1-DP-002 | B6: Foco del Mes | C6: Definición funcional cerrada. Cuando el usuario no tenga un Foco del Mes activo y exista información suficiente para generar una versión válida del Diagnóstico, Walvy puede sugerir un foco usando la lectura consolidada de M04, M06 y M05 con prioridad M04 → M06 → M05. La sugerencia se presenta con CTA primario Usar este foco y secundario Revisar foco; si no se acepta, permanece no declarado y puede recalcularse; una vez aceptado, se mantiene activo y no cambia automáticamente. El foco orienta CTAs, recomendaciones, alertas y próximos pasos cuando no existe una señal superior. Ver AX-M1-002 para lógica completa, derivaciones, persistencia y ajustes editoriales. | D6: Definición funcional cerrada / ajuste documental Kabeli | E6: M1-V30 · M1-RN-ONB-019 · RB-FM-001/002/004/006/007/009 · Ver AX-M1-002 | F6: Resuelto | G6: PD-M1-05
A7: M1-DP-003 | B7: Carga documental | C7: Definición funcional cerrada. Para documentos protegidos asociados al RUT del usuario, Walvy debe intentar automáticamente un catálogo cerrado de tres contraseñas derivadas del RUT, excluyendo siempre el dígito verificador, en este orden: (1) RUT numérico completo sin DV, (2) últimos 4 dígitos y (3) primeros 4 dígitos. Máximo un intento por variante y detenerse al abrir. Si ninguna funciona, solicitar contraseña manual. Una contraseña manual incorrecta permite corregir/reintentar o cargar otro documento, sin bloqueo propio del MVP. Las contraseñas solo pueden utilizarse temporalmente durante apertura/procesamiento y no deben persistirse ni registrarse en logs, analytics, eventos o checkpoints. Kabeli/Seguridad debe validar el baseline e informar cualquier restricción técnica que exija modificarlo. | D7: Definición funcional cerrada / baseline funcional-técnico propuesto | E7: M1-V41 · M1-RN-ONB-022 · M01-DOCSEC-003 | F7: Resuelto | G7: PD-M1-08
A8: M1-DP-004 | B8: Carga documental | C8: Definición funcional cerrada. La duplicidad debe detectarse por cuenta/usuario mediante una huella de contenido (hash o token equivalente), sin almacenar permanentemente el archivo. Procesado OK: bloquear una nueva carga del mismo contenido e informar que ya fue cargado, sin duplicar datos ni suficiencia. Fallo técnico transitorio: permitir retry/reprocesamiento y no tratarlo como duplicado. Documento determinísticamente no procesable: conservar temporalmente la huella junto con motivo y versión del procesador para evitar reprocesamientos idénticos hasta expiración o cambio de procesador. La retención exacta de huellas es parámetro técnico/privacidad; el comportamiento funcional queda cerrado. | D8: Definición funcional cerrada / ajuste documental y técnico Kabeli | E8: M1-V43 · M1-RN-ONB-024 | F8: Resuelto | G8: PD-M1-09
A9: M1-DP-005 | B9: Procesamiento | C9: Definición funcional cerrada. V47 corresponde exclusivamente a un fallo técnico recuperable/transitorio ocurrido después de admitir el documento y durante el procesamiento/análisis. No se genera Diagnóstico y se conservan documentos, selección y checkpoint. CTA primario Reintentar; CTA secundario Volver a revisión, desde donde se puede reemplazar o agregar documentación; Continuar más tarde puede mantenerse cuando exista retoma. Cada retry debe mantener trazabilidad con el job original y no duplicar documentos ni datos. Documento no procesable (V40) e insuficiencia de datos (V50/V51) se tratan en sus reglas específicas. | D9: Definición funcional cerrada / ajuste documental Kabeli | E9: M1-V47 · M1-RN-ONB-025 · M01-RGL-014 | F9: Resuelto | G9: PD-M1-11
A10: M1-DP-006 | B10: Diagnóstico / Estado Financiero del Mes | C10: Definición funcional cerrada. M01-RGL-012 gobierna si existe base suficiente para diagnosticar. Una regla canónica única por snapshot mensual gobierna En control/Atención/Riesgo mediante ratio = egreso mensual proyectado / ingreso mensual reconocido, con umbrales parametrizables <90%, 90%-<100% y >=100%. El ratio mide flujo/liquidez mensual: ahorro, inversiones o patrimonio no compensan déficit. Único override determinista de Riesgo MVP: mora_confirmada = obligación vencida + saldo pendiente + evidencia suficiente. M01-RGL-015 opera después para presión/CTA. M05/M06 aportan inputs normalizados y conciliados; M04 no es input del cálculo y mantiene sus propios criterios. Ver AX-M1-004. | D10: Definición funcional cerrada / contrato intermodular y ajuste documental Kabeli | E10: M1-V53 a M1-V55 · M1-RN-ONB-009/011/012 · M01-RGL-012/015 · Ver AX-M1-004 | F10: Resuelto | G10: PD-M1-12
A11: M1-DP-007 | B11: Suficiencia / Diagnóstico | C11: Sin diagnóstico se representa mediante los gates de suficiencia previos a la primera lectura y no mediante una cuarta tarjeta equivalente a En control / Atención / Riesgo. Cuando la base es insuficiente, Walvy bloquea el diagnóstico, explica qué falta y ofrece la acción de recuperación correspondiente. | D11: Decisión funcional cerrada | E11: M1-V56 y relación con M1-V50 a M1-V52 · no constituye brecha de cobertura de Kabeli. | F11: Resuelto
A12: M1-DP-008 | B12: Suficiencia | C12: Definición funcional cerrada. M01-RGL-012 permanece como único gate de suficiencia. Cada indicador conserva estado de detección, origen, confianza y evidencia, pero debe normalizarse previamente a sufficient, pending o missing; el gate aplica después disponibilidad mínima y criticidad funcional. Falta elemento obligatorio → blocked; base mínima + pendiente crítico → partial bloqueado; base mínima + solo pendientes no críticos → partial permitido; sin pendientes relevantes → complete. Movimientos pendientes bloquean; pagos recurrentes pendientes pueden permitir parcial bajo la combinación documentada; instrumentos de pago no bloquean por sí solos. Reasons explican el resultado y no son reglas independientes. Ver AX-M1-003. | D12: Definición funcional cerrada / simplificación implementable | E12: M1-V50 · M01-RGL-012/013 · Ver AX-M1-003 | F12: Resuelto | G12: PD-M1-13
A13: M1-DP-009 | B13: Retoma de onboarding | C13: Definición funcional cerrada. Si el usuario abandona el onboarding sin cargar datos en otros módulos, al volver debe retomarlo desde el checkpoint/punto útil abandonado. Si después de salir incorpora datos desde Home u otro módulo, Walvy debe reevaluar la suficiencia global con M01-RGL-012: si aún falta información, deriva al punto de onboarding correspondiente; si ya existe información suficiente para generar el Diagnóstico, no devuelve al onboarding y habilita el Diagnóstico desde Home. El onboarding se considera cumplido cuando puede mostrarse el diagnóstico inicial con información suficiente y la próxima acción correspondiente. | D13: Definición funcional cerrada / continuidad transversal | E13: M1-V48 a M1-V52 · M1-V58 a M1-V60 · M1-RN-ONB-014/016 · M01-RGL-012 | F13: Resuelto
A14: M1-DP-010 | B14: Registro / Verificación de correo | C14: Definición funcional cerrada. La verificación de correo separa la vigencia del código del temporizador de reenvío: el contador visible solo habilita solicitar un nuevo código y no implica su expiración. El OTP es temporal y de un solo uso; una validación exitosa o un nuevo envío invalida el código anterior, y un código incorrecto, vencido, reutilizado o reemplazado no habilita la cuenta. Producto adopta un baseline de seguridad parametrizable documentado en AX-M1-001 · Ciclo de vida y parametrización OTP, que contiene parámetros, fundamentos NIST/OWASP, guardrails, referencias y controles QA. Kabeli/Seguridad debe confirmar los valores efectivos implementados o justificar cualquier desviación. | D14: Definición funcional cerrada / baseline de seguridad aceptado por Producto | E14: M1-V13 y M1-V16 · M1-RN-ACC-032 / M1-RN-ACC-033 · Ver AX-M1-001 | F14: Resuelto | G14: PD-M1-02
A15: M1-DP-011 | B15: Recuperación excepcional sin acceso al correo registrado | C15: Definición funcional cerrada. Cuando el usuario no pueda acceder al correo registrado, Walvy no ofrecerá recuperación automática alternativa en el MVP y lo derivará a soporte@walvy.cl. El contacto con soporte no acredita identidad ni habilita por sí solo cambio de correo, contraseña o acceso. Solo una verificación satisfactoria conforme al procedimiento aprobado por Seguridad/Operaciones permite iniciar la recuperación. Si continúa sin acceso al correo actual, debe proporcionar un correo diferente bajo su control, que se verifica antes de sustituir al anterior; si recupera acceso al correo original, vuelve al flujo estándar. Al completar la recuperación deben renovarse credenciales, invalidarse sesiones previas y registrarse/notificarse el evento. Sin evidencia suficiente, no se modifica la cuenta. | D15: Definición funcional cerrada / procedimiento Seguridad-Operaciones pendiente | E15: M1-V19 · M1-RN-ACC-034 · M01-RGL-003 | F15: Resuelto | G15: PD-M1-03

Sheet Anexos Producto
A1: M1 – Anexos Producto
A2: Hoja complementaria de Producto. Amplía decisiones que requieren estructura, parámetros o fundamento técnico sin modificar las hojas originales de Kabeli. Cada anexo debe ser referenciado desde Observaciones Producto y mantener trazabilidad con DP, PD y variantes.
A4: ID Anexo | B4: Título | C4: DP relacionado | D4: PD relacionado | E4: Variantes | F4: Estado
A5: AX-M1-001 | B5: Ciclo de vida y parametrización OTP | C5: M1-DP-010 | D5: PD-M1-02 | E5: M1-V13 / M1-V16 | F5: Aceptado Producto · pendiente confirmación Kabeli/Seguridad
A7: Decisión funcional
A8: La vigencia del OTP y el temporizador de reenvío son controles distintos. El contador visible solo habilita solicitar un nuevo código. El OTP debe ser temporal, de un solo uso, generado de forma criptográficamente segura y asociado a la cuenta/proceso. Una validación exitosa o un nuevo envío invalida el código anterior; un código incorrecto, vencido, reutilizado o reemplazado no habilita la cuenta. Los parámetros de esta hoja constituyen el baseline Walvy aceptado por Producto; deben quedar configurables/versionados y Kabeli/Seguridad debe confirmar los valores efectivos del build o justificar cualquier desviación.
A10: Parámetros y controles de referencia
A11: Control / parámetro | B11: Baseline Walvy | C11: Fundamento | D11: Naturaleza | E11: Fuentes | F11: QA / validación esperada
A12: Longitud OTP | B12: 6 dígitos | C12: Mantiene el comportamiento observado. NIST usa al menos seis dígitos para secretos temporales comparables; OWASP recomienda considerar 8 o más cuando la usabilidad lo permita. No se reabre V13 por este punto. | D12: Definición existente + benchmark | E12: REF-01 / REF-02 | F12: Generación con CSPRNG; aceptar exactamente el formato configurado.
A13: verification_otp_ttl | B13: 10 min | C13: TTL corto para limitar exposición. NIST exige completar autenticación OOB dentro de 10 min; Walvy lo usa solo como benchmark conservador porque NIST indica que email no debe usarse como canal OOB de autenticación. | D13: Baseline Producto | E13: REF-01 | F13: Código vencido no activa cuenta; expiración independiente del temporizador de reenvío.
A14: verification_resend_cooldown | B14: 60 s | C14: Baseline Walvy para reducir reenvíos repetitivos, flooding y consumo innecesario manteniendo una recuperación razonable. OWASP exige rate limiting/monitorización, pero no prescribe 60 s. | D14: Baseline Producto | E14: REF-03 / REF-04 | F14: Reenvío no disponible antes del cooldown; el contador visible representa este control.
A15: verification_max_attempts | B15: 5 fallidos acumulados | C15: Limita guessing sobre un secreto corto. NIST exige rate limiting por cuenta para secretos cortos y especifica que generar un nuevo secreto no reinicia el contador de fallos; OWASP exige límites estrictos de intentos. | D15: Baseline Producto | E15: REF-01 / REF-02 | F15: El reenvío no reinicia intentos fallidos; validar límite y recuperación segura.
A16: verification_resend_limit / window | B16: 5 reenvíos / 15 min | C16: Baseline Walvy para contener automatización, flooding del correo y abuso del endpoint. OWASP recomienda limitar solicitudes excesivas y monitorear la función de verificación. | D16: Baseline Producto | E16: REF-03 / REF-04 / REF-05 | F16: Contabilizar como mínimo por cuenta/correo; probar ráfagas y múltiples IP.
A17: verification_resend_block_cooldown | B17: 15 min | C17: Cooldown temporal al superar el límite, evitando un bloqueo permanente provocado únicamente por abuso del mecanismo de reenvío. | D17: Baseline Producto | E17: REF-03 / REF-05 | F17: Bloquear nuevos envíos durante el cooldown y permitir recuperación posterior.
A18: Nuevo código invalida anterior | B18: Sí | C18: Evita múltiples secretos válidos simultáneamente. OWASP recomienda que el reenvío genere un OTP nuevo y sobrescriba/invalide el anterior. | D18: Guardrail | E18: REF-02 | F18: Después de reenviar, el código anterior debe fallar siempre.
A19: Rate limiting | B19: Cuenta/correo como mínimo + IP y, cuando sea viable, sesión/dispositivo/señales de riesgo | C19: El control por cuenta protege ante ataques distribuidos desde múltiples IP; los controles complementarios reducen abuso horizontal y automatización. No depender exclusivamente de una IP. | D19: Guardrail técnico | E19: REF-01 / REF-04 / REF-05 | F19: Probar mismo usuario desde varias IP y una IP contra varias cuentas; registrar activación de límites.
A20: Logging / monitoreo | B20: Registrar eventos; nunca el valor del OTP | C20: Los fallos, reenvíos, límites y activación deben ser observables para seguridad, sin exponer el secreto en logs. | D20: Guardrail técnico | E20: REF-02 / REF-06 | F20: Verificar ausencia de OTP en logs y presencia de eventos de seguridad necesarios.
A22: Guardrails adicionales
A23: • La expiración del OTP no debe deducirse del contador visible de reenvío: son parámetros independientes.
A24: • Un OTP válido solo puede utilizarse una vez; validación exitosa, expiración o reemplazo lo invalidan.
A25: • Solicitar un nuevo código no reinicia el contador acumulado de intentos fallidos.
A26: • Los parámetros deben mantenerse configurables y versionados; Kabeli/Seguridad debe confirmar los valores efectivos del build o justificar cualquier desviación.
A27: • La referencia NIST se utiliza como benchmark de seguridad para secretos temporales. NIST indica expresamente que email no debe utilizarse como canal out-of-band de autenticación, por lo que no se presenta como requisito de cumplimiento directo para la verificación de correo de Walvy.
A29: Impacto esperado en documentación Kabeli
A30: Elemento | B30: Ajuste requerido
A31: M1-V13 | B31: Mantener la variante; confirmar formalmente longitud/configuración y controles aplicables sin reabrir el diseño visual.
A32: M1-V16 · D | B32: Separar disparador de reenvío (fin de cooldown) de vencimiento del OTP (fin de TTL).
A33: M1-V16 · E | B33: Definir reenvío, invalidación del código anterior, rechazo de código vencido/reutilizado/reemplazado y recuperación ante límites.
A34: M1-RN-ACC-032 / 033 | B34: Incorporar ciclo de vida, single-use, reenvío, intentos, límites y parametrización versionada.
A35: Casos de prueba / evidencia | B35: Cubrir válido, incorrecto, vencido, reutilizado, reemplazado, máximo de intentos, límites de reenvío, rate limiting y ausencia de OTP en logs.
A37: Referencias
A38: ID | B38: Fuente / uso | C38: URL
A39: REF-01 | B39: NIST SP 800-63B · benchmark para vigencia, single-use y rate limiting de secretos temporales; incluye advertencia de que email no debe utilizarse para autenticación OOB. | C39: https://pages.nist.gov/800-63-4/sp800-63b.html
A40: REF-02 | B40: OWASP Multifactor Authentication Cheat Sheet · manejo de OTP: TTL corto, single-use, límites, CSPRNG, no logging y reemplazo al reenviar. | C40: https://cheatsheetseries.owasp.org/cheatsheets/Multifactor_Authentication_Cheat_Sheet.html
A41: REF-03 | B41: OWASP Forgot Password Cheat Sheet · protección frente a brute force y solicitudes excesivas. | C41: https://cheatsheetseries.owasp.org/cheatsheets/Forgot_Password_Cheat_Sheet.html
A42: REF-04 | B42: OWASP Email Validation and Verification Cheat Sheet · expiración, invalidación, rate limiting y monitorización en verificación de correo. | C42: https://cheatsheetseries.owasp.org/cheatsheets/Email_Validation_and_Verification_Cheat_Sheet.html
A43: REF-05 | B43: OWASP Bot Management and Anti-Automation Cheat Sheet · rate limiting, cuotas y mitigación de automatización. | C43: https://cheatsheetseries.owasp.org/cheatsheets/Bot_Management_and_Anti-Automation_Cheat_Sheet.html
A44: REF-06 | B44: OWASP Logging Cheat Sheet · eventos de seguridad y monitoreo. | C44: https://cheatsheetseries.owasp.org/cheatsheets/Logging_Cheat_Sheet.html
A46: ID Anexo | B46: Título | C46: DP relacionado | D46: PD relacionado | E46: Variantes | F46: Estado
A47: AX-M1-002 | B47: Foco del Mes sugerido y priorización contextual | C47: M1-DP-002 | D47: PD-M1-05 | E47: M1-V30 | F47: Aceptado Producto · pendiente incorporación Kabeli
A49: Decisión funcional
A50: Cuando no exista un Foco del Mes activo y exista una versión válida del Diagnóstico, Walvy puede presentar un foco sugerido. La sugerencia utiliza la lectura consolidada de M04, M06 y M05 con prioridad funcional M04 → M06 → M05. El estado previo a aceptación se denomina únicamente “sugerido”. El foco sugerido no bloquea carga ni Diagnóstico, no reemplaza señales superiores y no se convierte en foco activo hasta aceptación del usuario.
A52: Derivación y prioridad por dominio
A53: Dominio prioritario | B53: Condición funcional | C53: Foco sugerido | D53: Naturaleza | E53: Guardrail | F53: Salida
A54: M04 | B54: Existe señal elegible de deuda/presión conforme al diagnóstico y reglas del dominio | C54: Bajar deuda | D54: Prioridad 1 | E54: No activar M04 solo por tener deuda; respetar elegibilidad propia | F54: Sugerencia de foco
A55: M06 | B55: Existe riesgo temporal de pago/vencimiento | C55: Evitar atrasos | D55: Prioridad 2 | E55: Aplica si no prevalece M04 | F55: Sugerencia de foco
A56: M06 | B56: Necesidad estructural de ordenar pagos/compromisos sin riesgo temporal dominante | C56: Ordenar compromisos | D56: Prioridad 2 | E56: Aplica si no prevalece M04 | F56: Sugerencia de foco
A57: M05 | B57: Señal dominante de flujo/margen/ahorro/presupuesto según condiciones ya documentadas | C57: Aumentar margen / Ahorrar un monto / Cumplir presupuesto | D57: Prioridad 3 | E57: No crear nuevos umbrales en M01 | F57: Sugerencia de foco
A59: Presentación, aceptación y persistencia
A60: La recomendación/alerta in-app debe ofrecer dos rutas: CTA primario “Usar este foco”, que acepta la sugerencia y la guarda directamente como foco activo sin navegar a configuración; y CTA secundario “Revisar foco”, que lleva a Mi Perfil → Mi foco del mes con la alternativa sugerida premarcada para confirmar con “Guardar mi foco” o elegir otra. Si no se acepta, el foco permanece no declarado y puede recalcularse con una nueva versión válida del Diagnóstico. Una vez aceptado, el foco persiste y no se reemplaza automáticamente por cambios posteriores del Diagnóstico.
A62: Prioridad contextual y superficies
A63: El foco puede orientar CTAs, recomendaciones, alertas/notificaciones in-app y próximos pasos cuando no exista una señal funcional de mayor prioridad. Señales críticas/superiores prevalecen. El foco es especialmente útil como orientación o desempate en estados estables. El desarrollo detallado del catálogo de alertas por módulo permanece fuera de este anexo; cada catálogo debe mantener trigger → mensaje/severidad → CTA → destino y someterse a la priorización transversal.
A65: Impacto esperado en documentación Kabeli
A66: Elemento | B66: Ajuste requerido
A67: M1-V30 · D | B67: Sustituir condición genérica por: sin foco activo + Diagnóstico válido/suficiente + aplicación de prioridad M04→M06→M05.
A68: M1-V30 · E | B68: Representar sugerencia, aceptación directa, revisión en Mi Perfil, persistencia y recálculo si no se acepta.
A69: M1-RN-ONB-019 | B69: Mantener estados declarado / no declarado / sugerido e incorporar la lógica de sugerencia/aceptación; no usar “inferido/sugerido”.
A70: Reglas Walvy | B70: Aplicar ajustes editoriales en Observaciones de RB-FM-001/002/004/007/009 sin alterar el texto oficial hasta su incorporación formal.
A72: ID Anexo | B72: Título | C72: DP relacionado | D72: PD relacionado | E72: Variantes | F72: Estado
A73: AX-M1-003 | B73: Regla determinista de suficiencia y normalización de indicadores | C73: M1-DP-008 | D73: PD-M1-13 | E73: M1-V50 | F73: Aceptado Producto · pendiente incorporación Kabeli
A75: Modelo funcional canónico
A76: M01-RGL-012 es el único gate de suficiencia. La riqueza de datos (detection_status, data_origin, confidence, evidence) se conserva para trazabilidad, pero no debe traducirse 1:1 a ramas de negocio. Cada indicador se normaliza primero a sufficient, pending o missing. Luego el gate combina disponibilidad mínima y criticidad funcional para producir sufficiency_status, diagnostic_mode, partial_diagnostic_allowed y reason.
A78: Salida del gate
A79: Estado funcional | B79: Condición normalizada | C79: sufficiency_status | D79: diagnostic_mode | E79: partial_diagnostic_allowed | F79: Comportamiento
A80: Base suficiente | B80: Base mínima suficiente y sin pendientes relevantes | C80: base_suficiente | D80: complete | E80: — | F80: Habilitar Diagnóstico completo
A81: Datos por confirmar · parcial permitido | B81: Base mínima suficiente + solo pendientes no críticos | C81: datos_por_confirmar | D81: partial | E81: true | F81: Advertir y permitir completar; puede avanzar con la base disponible
A82: Datos por confirmar · parcial bloqueado | B82: Base mínima suficiente + indicador crítico pending | C82: datos_por_confirmar | D82: blocked | E82: false | F82: Completar/confirmar; sin CTA de Diagnóstico
A83: Aún faltan datos clave | B83: Falta mínimo obligatorio o calidad/confianza insuficiente | C83: aun_faltan_datos_clave | D83: blocked | E83: false | F83: Explicar faltante y ofrecer recuperación correspondiente
A85: Fronteras explícitamente documentadas
A86: Caso / indicador | B86: Estado de referencia | C86: Criticidad / interpretación | D86: Resultado | E86: Reason / ejemplo | F86: Regla de no extrapolación
A87: Movimientos recientes por confirmar | B87: pending | C87: Crítico | D87: Partial bloqueado | E87: recent_movements_pending | F87: No generalizar a todas las combinaciones no documentadas
A88: Pagos recurrentes por confirmar con ingreso, movimientos y compromisos sufficient | B88: pending | C88: No bloqueante bajo la combinación documentada | D88: Partial permitido | E88: payments_pending_noncritical | F88: Usar como fixture de la regla común, no como if especial
A89: Ingreso ausente | B89: missing | C89: Obligatorio | D89: Blocked | E89: income_missing | F89: Salida explicativa del gate
A90: Movimientos recientes ausentes | B90: missing | C90: Obligatorio | D90: Blocked | E90: recent_movements_missing | F90: Salida explicativa del gate
A91: Compromisos y pagos ausentes | B91: missing | C91: Base mínima insuficiente | D91: Blocked | E91: commitments_or_payments_missing | F91: No inferir comportamiento de combinaciones parciales no cubiertas
A92: Confianza global insuficiente | B92: insufficient | C92: Bloqueante | D92: Blocked | E92: global_confidence_insufficient | F92: La normalización absorbe detalle técnico
A93: Instrumentos de pago ausentes | B93: missing | C93: Complementario | D93: No bloquea por sí solo | E93: NO-INSTRUMENTS | F93: Mantener frontera explícita
A95: Guardrails de implementación
A96: • No crear una regla por cada combinación cartesiana de detection_status, data_origin, confidence y evidence. • Normalizar primero el indicador y aplicar después una única regla de suficiencia. • La criticidad debe ser configuración funcional, no ramas independientes de código. • reason explica el resultado para UX/analytics/QA y no gobierna por sí mismo. • No extrapolar combinaciones no respaldadas por regla o fixture; si una combinación nueva requiere un tratamiento distinto, debe formalizarse antes de codificarla.
A98: Impacto esperado en documentación Kabeli
A99: Elemento | B99: Ajuste requerido
A100: M1-V50 · D | B100: Reemplazar “dato pendiente puede cambiar diagnóstico central” por una condición basada en indicator_status normalizado + criticidad y output de M01-RGL-012.
A101: M1-V50 · E | B101: Responder a partial permitido vs partial bloqueado; cuando partial_diagnostic_allowed=false no debe existir CTA de Diagnóstico.
A102: RN / fixtures | B102: Alinear M1-RN-ONB-006/007/010 y casos de prueba con un único gate y reasons reproducibles, sin reglas específicas por fixture.
A104: ID Anexo | B104: Título | C104: DP relacionado | D104: PD relacionado | E104: Variantes | F104: Estado
A105: AX-M1-004 | B105: Estado Financiero del Mes y contrato intermodular | C105: M1-DP-006 | D105: PD-M1-12 | E105: M1-V53 / M1-V54 / M1-V55 | F105: Aceptado Producto · pendiente incorporación Kabeli
A107: Gobernanza y regla canónica
A108: Existe un único Estado Financiero del Mes por snapshot evaluado. M01-RGL-012 decide primero si el Diagnóstico está habilitado. Cuando lo está, la regla canónica produce En control, Atención o Riesgo. M01 presenta y explica el resultado; M05/M06 pueden consumirlo, pero no deben mantener semáforos paralelos. M01-RGL-015 opera después para seleccionar presión dominante, prioridad, señales y CTA. El Foco del Mes no es input del color y su desarrollo detallado permanece en AX-M1-002.
A110: Ratio, umbrales y override MVP
A111: Control | B111: Definición | C111: Resultado / umbral | D111: Naturaleza | E111: Guardrail | F111: Versionamiento
A112: ratio_mes | B112: egreso_mensual_proyectado / ingreso_mensual_reconocido | C112: <0,90 → En control; >=0,90 y <1,00 → Atención; >=1,00 → Riesgo | D112: Regla canónica | E112: Mide flujo/liquidez mensual, no patrimonio | F112: Parámetros configurables/versionados
A113: mora_confirmada | B113: obligación vencida + saldo pendiente + evidencia suficiente | C113: Riesgo independientemente del ratio | D113: Único override determinista MVP | E113: No usar “presión grave” cualitativa como override | F113: Código/criterio versionado
A115: Contrato intermodular mínimo
A116: Input canónico | B116: Dueño principal | C116: Uso en cálculo | D116: Regla de conciliación | E116: No incluir / guardrail | F116: Consumidor
A117: monthly_income_recognized | B117: M05 / fuente normalizada de ingresos | C117: Denominador | D117: Usar ingreso mensual reconocido con evidencia suficiente | E117: No compensar con ahorros/patrimonio | F117: Estado Financiero canónico
A118: executed_economic_outflow_mtd | B118: M05 | C118: Egreso ya realizado | D118: Un evento económico se cuenta una sola vez | E118: Excluir transferencias propias, duplicados, reversos/sin efecto real | F118: Estado Financiero canónico
A119: pending_commitments_month | B119: M06 | C119: Compromisos del mes no ejecutados | D119: Al materializarse como movimiento, pasa de pendiente a ejecutado sin doble conteo | E119: No duplicar con movimiento conciliado | F119: Estado Financiero canónico
A120: projected_remaining_outflow | B120: M05 / proyección normalizada | C120: Gasto restante proyectado | D120: Debe excluir lo ya ejecutado o comprometido para evitar doble conteo | E120: M01 no replica algoritmo de forecasting | F120: Estado Financiero canónico
A121: risk_override_codes | B121: M06 / motor transversal | C121: Override determinista | D121: MVP: solo mora_confirmada | E121: No crear overrides cualitativos | F121: Estado Financiero canónico
A122: pressure_signal_codes | B122: M05/M06 y otras fuentes | C122: No cambia el color directamente | D122: Se consume después del estado | E122: Alimenta M01-RGL-015 | F122: Presión/CTA
...
