Workbook

Sheet Resumen Ejecutivo
B2: Informe de Certificación QA
B3: Módulo: Tratamiento de Deuda y Ruta Despeje (Entrada contextual, Home, Perfil Financiero, Onboarding de Deudas OD-01/OD-02/OD-03, Detalle de Deuda DD-01, Ruta Despeje RD-01/RD-02/RD-03, Cierre, Reingreso, Etiquetas funcionales) — Walvy App
B6: Producto: | C6: Walvy App — MVP
B7: Módulo: | C7: Módulo 4
B8: Fecha de ejecución: | C8: —
B9: Ejecutado por: | C9: —
B10: Ambiente: | C10: Certificación
B11: Versión de build: | C11: —
B14: Dashboard de Ejecución
B16: =COUNTA('Casos de Prueba'!$A$2:$A$1000) -> 93 | C16: =SUMPRODUCT(('Casos de Prueba'!$B$2:$B$1000<>"")/COUNTIF('Casos de Prueba'!$B$2:$B$1000,'Casos de Prueba'!$B$2:$B$1000&"")) -> 20 | D16: =COUNTIF('Casos de Prueba'!$H$2:$H$1000,"Automatizable") -> 90 | E16: =COUNTIF('Casos de Prueba'!$H$2:$H$1000,"Manual") -> 3 | F16: =COUNTIF('Casos de Prueba'!$I$2:$I$1000,"Aprobado") -> 0 | G16: =COUNTIF('Casos de Prueba'!$I$2:$I$1000,"Pendiente") -> 93 | H16: =COUNTIF('Casos de Prueba'!$I$2:$I$1000,"No Aplica") -> 0 | I16: =COUNTIF('Casos de Prueba'!$I$2:$I$1000,"Fallido") -> 0 | J16: =COUNTA('Registro de Defectos'!$A$2:$A$1000) -> 0 | K16: =COUNTIF('Casos de Prueba'!$I$2:$I$1000,"Bloqueado") -> 0 | L16: =IF(B16=0,0,(B16-G16)/B16) -> 0 | M16: =IF(B16=0,0,F16/B16) -> 0
B17: Total Casos | C17: Secciones | D17: Automatizables | E17: Manuales | F17: Aprobados | G17: Pendiente | H17: No Aplica | I17: Fallidos | J17: Defectos | K17: Bloqueados | L17: % Ejecutado | M17: % Aprobado
B20: Desglose por Sección
B22: Sección | C22: Casos | D22: Aprobados | E22: Pendiente | F22: No Aplica | G22: Fallido | H22: Bloqueado | I22: Estado Sección
B23: Entrada contextual · Home/Perfil | C23: =COUNTIF('Casos de Prueba'!$B$2:$B$1000,$B23) -> 4 | D23: =COUNTIFS('Casos de Prueba'!$B$2:$B$1000,$B23,'Casos de Prueba'!$I$2:$I$1000,"Aprobado") -> 0 | E23: =COUNTIFS('Casos de Prueba'!$B$2:$B$1000,$B23,'Casos de Prueba'!$I$2:$I$1000,"Pendiente") -> 4 | F23: =COUNTIFS('Casos de Prueba'!$B$2:$B$1000,$B23,'Casos de Prueba'!$I$2:$I$1000,"No Aplica") -> 0 | G23: =COUNTIFS('Casos de Prueba'!$B$2:$B$1000,$B23,'Casos de Prueba'!$I$2:$I$1000,"Fallido") -> 0 | H23: =COUNTIFS('Casos de Prueba'!$B$2:$B$1000,$B23,'Casos de Prueba'!$I$2:$I$1000,"Bloqueado") -> 0 | I23: =IF(C23=0,"—",IF(G23>0,"Con fallos",IF(H23>0,"Bloqueada",IF(E23=C23,"Pendiente",IF(D23+F23=C23,"Certificada","En ejecución"))))) -> Pendiente
B24: OD-01 · Carga documental | C24: =COUNTIF('Casos de Prueba'!$B$2:$B$1000,$B24) -> 3 | D24: =COUNTIFS('Casos de Prueba'!$B$2:$B$1000,$B24,'Casos de Prueba'!$I$2:$I$1000,"Aprobado") -> 0 | E24: =COUNTIFS('Casos de Prueba'!$B$2:$B$1000,$B24,'Casos de Prueba'!$I$2:$I$1000,"Pendiente") -> 3 | F24: =COUNTIFS('Casos de Prueba'!$B$2:$B$1000,$B24,'Casos de Prueba'!$I$2:$I$1000,"No Aplica") -> 0 | G24: =COUNTIFS('Casos de Prueba'!$B$2:$B$1000,$B24,'Casos de Prueba'!$I$2:$I$1000,"Fallido") -> 0 | H24: =COUNTIFS('Casos de Prueba'!$B$2:$B$1000,$B24,'Casos de Prueba'!$I$2:$I$1000,"Bloqueado") -> 0 | I24: =IF(C24=0,"—",IF(G24>0,"Con fallos",IF(H24>0,"Bloqueada",IF(E24=C24,"Pendiente",IF(D24+F24=C24,"Certificada","En ejecución"))))) -> Pendiente
B25: OD-01 · Registro manual | C25: =COUNTIF('Casos de Prueba'!$B$2:$B$1000,$B25) -> 3 | D25: =COUNTIFS('Casos de Prueba'!$B$2:$B$1000,$B25,'Casos de Prueba'!$I$2:$I$1000,"Aprobado") -> 0 | E25: =COUNTIFS('Casos de Prueba'!$B$2:$B$1000,$B25,'Casos de Prueba'!$I$2:$I$1000,"Pendiente") -> 3 | F25: =COUNTIFS('Casos de Prueba'!$B$2:$B$1000,$B25,'Casos de Prueba'!$I$2:$I$1000,"No Aplica") -> 0 | G25: =COUNTIFS('Casos de Prueba'!$B$2:$B$1000,$B25,'Casos de Prueba'!$I$2:$I$1000,"Fallido") -> 0 | H25: =COUNTIFS('Casos de Prueba'!$B$2:$B$1000,$B25,'Casos de Prueba'!$I$2:$I$1000,"Bloqueado") -> 0 | I25: =IF(C25=0,"—",IF(G25>0,"Con fallos",IF(H25>0,"Bloqueada",IF(E25=C25,"Pendiente",IF(D25+F25=C25,"Certificada","En ejecución"))))) -> Pendiente
B26: OD-01 · Documento protegido | C26: =COUNTIF('Casos de Prueba'!$B$2:$B$1000,$B26) -> 4 | D26: =COUNTIFS('Casos de Prueba'!$B$2:$B$1000,$B26,'Casos de Prueba'!$I$2:$I$1000,"Aprobado") -> 0 | E26: =COUNTIFS('Casos de Prueba'!$B$2:$B$1000,$B26,'Casos de Prueba'!$I$2:$I$1000,"Pendiente") -> 4 | F26: =COUNTIFS('Casos de Prueba'!$B$2:$B$1000,$B26,'Casos de Prueba'!$I$2:$I$1000,"No Aplica") -> 0 | G26: =COUNTIFS('Casos de Prueba'!$B$2:$B$1000,$B26,'Casos de Prueba'!$I$2:$I$1000,"Fallido") -> 0 | H26: =COUNTIFS('Casos de Prueba'!$B$2:$B$1000,$B26,'Casos de Prueba'!$I$2:$I$1000,"Bloqueado") -> 0 | I26: =IF(C26=0,"—",IF(G26>0,"Con fallos",IF(H26>0,"Bloqueada",IF(E26=C26,"Pendiente",IF(D26+F26=C26,"Certificada","En ejecución"))))) -> Pendiente
B27: OD-01 · Documento no procesable | C27: =COUNTIF('Casos de Prueba'!$B$2:$B$1000,$B27) -> 1 | D27: =COUNTIFS('Casos de Prueba'!$B$2:$B$1000,$B27,'Casos de Prueba'!$I$2:$I$1000,"Aprobado") -> 0 | E27: =COUNTIFS('Casos de Prueba'!$B$2:$B$1000,$B27,'Casos de Prueba'!$I$2:$I$1000,"Pendiente") -> 1 | F27: =COUNTIFS('Casos de Prueba'!$B$2:$B$1000,$B27,'Casos de Prueba'!$I$2:$I$1000,"No Aplica") -> 0 | G27: =COUNTIFS('Casos de Prueba'!$B$2:$B$1000,$B27,'Casos de Prueba'!$I$2:$I$1000,"Fallido") -> 0 | H27: =COUNTIFS('Casos de Prueba'!$B$2:$B$1000,$B27,'Casos de Prueba'!$I$2:$I$1000,"Bloqueado") -> 0 | I27: =IF(C27=0,"—",IF(G27>0,"Con fallos",IF(H27>0,"Bloqueada",IF(E27=C27,"Pendiente",IF(D27+F27=C27,"Certificada","En ejecución"))))) -> Pendiente
B28: OD-02 · Revisión y validación | C28: =COUNTIF('Casos de Prueba'!$B$2:$B$1000,$B28) -> 11 | D28: =COUNTIFS('Casos de Prueba'!$B$2:$B$1000,$B28,'Casos de Prueba'!$I$2:$I$1000,"Aprobado") -> 0 | E28: =COUNTIFS('Casos de Prueba'!$B$2:$B$1000,$B28,'Casos de Prueba'!$I$2:$I$1000,"Pendiente") -> 11 | F28: =COUNTIFS('Casos de Prueba'!$B$2:$B$1000,$B28,'Casos de Prueba'!$I$2:$I$1000,"No Aplica") -> 0 | G28: =COUNTIFS('Casos de Prueba'!$B$2:$B$1000,$B28,'Casos de Prueba'!$I$2:$I$1000,"Fallido") -> 0 | H28: =COUNTIFS('Casos de Prueba'!$B$2:$B$1000,$B28,'Casos de Prueba'!$I$2:$I$1000,"Bloqueado") -> 0 | I28: =IF(C28=0,"—",IF(G28>0,"Con fallos",IF(H28>0,"Bloqueada",IF(E28=C28,"Pendiente",IF(D28+F28=C28,"Certificada","En ejecución"))))) -> Pendiente
B29: OD-02→OD-03 · Evaluación | C29: =COUNTIF('Casos de Prueba'!$B$2:$B$1000,$B29) -> 3 | D29: =COUNTIFS('Casos de Prueba'!$B$2:$B$1000,$B29,'Casos de Prueba'!$I$2:$I$1000,"Aprobado") -> 0 | E29: =COUNTIFS('Casos de Prueba'!$B$2:$B$1000,$B29,'Casos de Prueba'!$I$2:$I$1000,"Pendiente") -> 3 | F29: =COUNTIFS('Casos de Prueba'!$B$2:$B$1000,$B29,'Casos de Prueba'!$I$2:$I$1000,"No Aplica") -> 0 | G29: =COUNTIFS('Casos de Prueba'!$B$2:$B$1000,$B29,'Casos de Prueba'!$I$2:$I$1000,"Fallido") -> 0 | H29: =COUNTIFS('Casos de Prueba'!$B$2:$B$1000,$B29,'Casos de Prueba'!$I$2:$I$1000,"Bloqueado") -> 0 | I29: =IF(C29=0,"—",IF(G29>0,"Con fallos",IF(H29>0,"Bloqueada",IF(E29=C29,"Pendiente",IF(D29+F29=C29,"Certificada","En ejecución"))))) -> Pendiente
B30: OD-03 · Resultado En Control | C30: =COUNTIF('Casos de Prueba'!$B$2:$B$1000,$B30) -> 4 | D30: =COUNTIFS('Casos de Prueba'!$B$2:$B$1000,$B30,'Casos de Prueba'!$I$2:$I$1000,"Aprobado") -> 0 | E30: =COUNTIFS('Casos de Prueba'!$B$2:$B$1000,$B30,'Casos de Prueba'!$I$2:$I$1000,"Pendiente") -> 4 | F30: =COUNTIFS('Casos de Prueba'!$B$2:$B$1000,$B30,'Casos de Prueba'!$I$2:$I$1000,"No Aplica") -> 0 | G30: =COUNTIFS('Casos de Prueba'!$B$2:$B$1000,$B30,'Casos de Prueba'!$I$2:$I$1000,"Fallido") -> 0 | H30: =COUNTIFS('Casos de Prueba'!$B$2:$B$1000,$B30,'Casos de Prueba'!$I$2:$I$1000,"Bloqueado") -> 0 | I30: =IF(C30=0,"—",IF(G30>0,"Con fallos",IF(H30>0,"Bloqueada",IF(E30=C30,"Pendiente",IF(D30+F30=C30,"Certificada","En ejecución"))))) -> Pendiente
B31: OD-03 · Resultado Atención / contexto | C31: =COUNTIF('Casos de Prueba'!$B$2:$B$1000,$B31) -> 7 | D31: =COUNTIFS('Casos de Prueba'!$B$2:$B$1000,$B31,'Casos de Prueba'!$I$2:$I$1000,"Aprobado") -> 0 | E31: =COUNTIFS('Casos de Prueba'!$B$2:$B$1000,$B31,'Casos de Prueba'!$I$2:$I$1000,"Pendiente") -> 7 | F31: =COUNTIFS('Casos de Prueba'!$B$2:$B$1000,$B31,'Casos de Prueba'!$I$2:$I$1000,"No Aplica") -> 0 | G31: =COUNTIFS('Casos de Prueba'!$B$2:$B$1000,$B31,'Casos de Prueba'!$I$2:$I$1000,"Fallido") -> 0 | H31: =COUNTIFS('Casos de Prueba'!$B$2:$B$1000,$B31,'Casos de Prueba'!$I$2:$I$1000,"Bloqueado") -> 0 | I31: =IF(C31=0,"—",IF(G31>0,"Con fallos",IF(H31>0,"Bloqueada",IF(E31=C31,"Pendiente",IF(D31+F31=C31,"Certificada","En ejecución"))))) -> Pendiente
B32: OD-03 · Resultado Riesgo / Ruta | C32: =COUNTIF('Casos de Prueba'!$B$2:$B$1000,$B32) -> 9 | D32: =COUNTIFS('Casos de Prueba'!$B$2:$B$1000,$B32,'Casos de Prueba'!$I$2:$I$1000,"Aprobado") -> 0 | E32: =COUNTIFS('Casos de Prueba'!$B$2:$B$1000,$B32,'Casos de Prueba'!$I$2:$I$1000,"Pendiente") -> 9 | F32: =COUNTIFS('Casos de Prueba'!$B$2:$B$1000,$B32,'Casos de Prueba'!$I$2:$I$1000,"No Aplica") -> 0 | G32: =COUNTIFS('Casos de Prueba'!$B$2:$B$1000,$B32,'Casos de Prueba'!$I$2:$I$1000,"Fallido") -> 0 | H32: =COUNTIFS('Casos de Prueba'!$B$2:$B$1000,$B32,'Casos de Prueba'!$I$2:$I$1000,"Bloqueado") -> 0 | I32: =IF(C32=0,"—",IF(G32>0,"Con fallos",IF(H32>0,"Bloqueada",IF(E32=C32,"Pendiente",IF(D32+F32=C32,"Certificada","En ejecución"))))) -> Pendiente
B33: RD-01 · Resumen Ruta Despeje | C33: =COUNTIF('Casos de Prueba'!$B$2:$B$1000,$B33) -> 3 | D33: =COUNTIFS('Casos de Prueba'!$B$2:$B$1000,$B33,'Casos de Prueba'!$I$2:$I$1000,"Aprobado") -> 0 | E33: =COUNTIFS('Casos de Prueba'!$B$2:$B$1000,$B33,'Casos de Prueba'!$I$2:$I$1000,"Pendiente") -> 3 | F33: =COUNTIFS('Casos de Prueba'!$B$2:$B$1000,$B33,'Casos de Prueba'!$I$2:$I$1000,"No Aplica") -> 0 | G33: =COUNTIFS('Casos de Prueba'!$B$2:$B$1000,$B33,'Casos de Prueba'!$I$2:$I$1000,"Fallido") -> 0 | H33: =COUNTIFS('Casos de Prueba'!$B$2:$B$1000,$B33,'Casos de Prueba'!$I$2:$I$1000,"Bloqueado") -> 0 | I33: =IF(C33=0,"—",IF(G33>0,"Con fallos",IF(H33>0,"Bloqueada",IF(E33=C33,"Pendiente",IF(D33+F33=C33,"Certificada","En ejecución"))))) -> Pendiente
B34: DD-01 · Detalle de deuda | C34: =COUNTIF('Casos de Prueba'!$B$2:$B$1000,$B34) -> 4 | D34: =COUNTIFS('Casos de Prueba'!$B$2:$B$1000,$B34,'Casos de Prueba'!$I$2:$I$1000,"Aprobado") -> 0 | E34: =COUNTIFS('Casos de Prueba'!$B$2:$B$1000,$B34,'Casos de Prueba'!$I$2:$I$1000,"Pendiente") -> 4 | F34: =COUNTIFS('Casos de Prueba'!$B$2:$B$1000,$B34,'Casos de Prueba'!$I$2:$I$1000,"No Aplica") -> 0 | G34: =COUNTIFS('Casos de Prueba'!$B$2:$B$1000,$B34,'Casos de Prueba'!$I$2:$I$1000,"Fallido") -> 0 | H34: =COUNTIFS('Casos de Prueba'!$B$2:$B$1000,$B34,'Casos de Prueba'!$I$2:$I$1000,"Bloqueado") -> 0 | I34: =IF(C34=0,"—",IF(G34>0,"Con fallos",IF(H34>0,"Bloqueada",IF(E34=C34,"Pendiente",IF(D34+F34=C34,"Certificada","En ejecución"))))) -> Pendiente
... B42: Etiquetas funcionales MVP | C42: =COUNTIF('Casos de Prueba'!$B$2:$B$1000,$B42) -> 5 | D42: =COUNTIFS('Casos de Prueba'!$B$2:$B$1000,$B42,'Casos de Prueba'!$I$2:$I$1000,"Aprobado") -> 0 | E42: =COUNTIFS('Casos de Prueba'!$B$2:$B$1000,$B42,'Casos de Prueba'!$I$2:$I$1000,"Pendiente") -> 5 | F42: =COUNTIFS('Casos de Prueba'!$B$2:$B$1000,$B42,'Casos de Prueba'!$I$2:$I$1000,"No Aplica") -> 0 | G42: =COUNTIFS('Casos de Prueba'!$B$2:$B$1000,$B42,'Casos de Prueba'!$I$2:$I$1000,"Fallido") -> 0 | H42: =COUNTIFS('Casos de Prueba'!$B$2:$B$1000,$B42,'Casos de Prueba'!$I$2:$I$1000,"Bloqueado") -> 0 | I42: =IF(C42=0,"—",IF(G42>0,"Con fallos",IF(H42>0,"Bloqueada",IF(E42=C42,"Pendiente",IF(D42+F42=C42,"Certificada","En ejecución"))))) -> Pendiente
B43: Total | C43: =SUM(C23:C42) -> 93 | D43: =SUM(D23:D42) -> 0 | E43: =SUM(E23:E42) -> 93 | F43: =SUM(F23:F42) -> 0 | G43: =SUM(G23:G42) -> 0 | H43: =SUM(H23:H42) -> 0 | I43: =IF(G43>0,"Con fallos",IF(H43>0,"Bloqueada",IF(E43=C43,"Pendiente",IF(D43+F43=C43,"Certificada","En ejecución")))) -> Pendiente
B46: Nota: Plataforma Android. Todos los indicadores de este resumen son fórmulas sobre las hojas «Casos de Prueba» (columnas Sección, Tipo de Prueba y Estado de Ejecución) y «Registro de Defectos»; se actualizan automáticamente al cambiar el Estado de Ejecución desde su menú desplegable (Pendiente, Aprobado, Fallido, Bloqueado, No Aplica). Casos generados desde walvy_m4_casos_funcionales_kabeli.feature: M4-V01…M4-V93 = TR-M04-044…TR-M04-136 de la Matriz de Trazabilidad Cliente v1.0.

Sheet Casos de Prueba
A1: ID | B1: Sección / Funcionalidad | C1: Nombre del Scenario | D1: Tipo | E1: Pasos de Ejecución | F1: Resultado Esperado | G1: Prioridad | H1: Tipo de Prueba | I1: Estado de Ejecución | J1: Resultado | K1: Defectos | L1: Observaciones | M1: Naturaleza de la Prueba
A2: M4-V01 | B2: Entrada contextual · Home/Perfil | C2: Entrada contextual · Home/Perfil - Existe candidato/proyección M04 accionable ya resuelto por el módulo dueño; Home solo consume el contrato. | D2: Scenario Outline | E2: # Precondiciones Given inicio sesion en la App And se cumple la variante de la matriz "Existe candidato/proyección M04 accionable ya resuelto por el módulo dueño; Home solo consume el contrato." And el estado inicial / origen es "Home" And tengo una deuda registrada en M04 And M04 entregó el candidato accionable "<familia>" para esa deuda # Pasos y validaciones When visualizo la pantalla "Home" de la vista Home Then valido que Home muestra una única acción de deuda con el CTA "<cta>" And valido que Home no muestra múltiples acciones de deuda compitiendo entre sí When presiono el boton "<cta>" en la vista Home Then valido que me encuentro en la vista "<destino>" And valido que el estado, el motivo y la situación de Ruta de la deuda son los mismos entregados por M04 # Criterio de aceptación (matriz) Then valido la obligación "Home representa el candidato M04 y deriva a su destino sin recalcular estado, reason ni Ruta; la selección del ganador global queda fuera de M04." And valido el resultado "OD-01 / OD-02 / RD según estado" And valido el negativo/borde "No mostrar múltiples acciones de deuda compitiendo." And valido la decisión/guardrail "BC-M04-002 cerrada para producción/proyección M04; orquestación global fuera." Examples: | familia | cta | destino | | F2 · Confirmar deuda | Confirmar deuda | OD-02 Revisión de deudas | | F1 · Completar información | Completar información | OD-02 Revisión de deudas | | F5 · Riesgo accionable | Ver plan | RD-01 Resumen Ruta Despeje | | F2: Obligación: Home representa el candidato M04 y deriva a su destino sin recalcular estado, reason ni Ruta; la selección del ganador global queda fuera de M04. Resultado: OD-01 / OD-02 / RD según estado Negativo/borde: No mostrar múltiples acciones de deuda compitiendo. | G2: Alta | H2: Automatizable | I2: Pendiente | L2: TR-M04-044 · FLOW-M04-001 · Entrada contextual · M04-RGL-002; M04-RGL-039 · Figma: consumidor visual/Figma · Validación: TC-M04-057 | M2: Funcional
A3: M4-V02 | B3: Entrada contextual · Home/Perfil | C3: Entrada contextual · Home/Perfil - Señal corresponde a pago próximo/al día/vencimiento simple con capacidad | D3: Scenario | E3: # Precondiciones Given inicio sesion en la App And se cumple la variante de la matriz "Señal corresponde a pago próximo/al día/vencimiento simple con capacidad" And el estado inicial / origen es "Home" And tengo una deuda confirmada con pagos al día And la Presión final M04 de la deuda es "En Control" And M06 informa un vencimiento próximo de la deuda en 3 días # Pasos y validaciones When visualizo la pantalla "Home" de la vista Home Then valido que se muestra la acción "Revisar pago" When presiono el boton "Revisar pago" en la vista Home Then valido que me encuentro en la vista "Pagos / Alertas" de M06 And valido que no se deriva a Ruta Despeje And valido que la Presión de la deuda no cambia a "Atención" ni "Riesgo" por el vencimiento # Criterio de aceptación (matriz) Then valido la obligación "Home deriva a M06/Pagos-Alertas; no a Ruta." And valido el resultado "M06 / Pagos-Alertas" And valido el negativo/borde "No elevar por mero vencimiento con capacidad." And valido el dato/estado "debt_signal · arrears_relevant_signal / mora_risk_signal" And valido la decisión/guardrail "BC-M04-002 cerrada para producción/proyección M04; orquestación global fuera." | F3: Obligación: Home deriva a M06/Pagos-Alertas; no a Ruta. Resultado: M06 / Pagos-Alertas Negativo/borde: No elevar por mero vencimiento con capacidad. | G3: Alta | H3: Automatizable | I3: Pendiente | L3: TR-M04-045 · FLOW-M04-001 · Entrada contextual · M04-RGL-016; M04-RGL-002, M04-RGL-039 · Figma: consumidor visual/Figma · Validación: TC-M04-057 | M3: Funcional
A4: M4-V03 | B4: Entrada contextual · Home/Perfil | C4: Entrada contextual · Home/Perfil - Existe deuda confirmada con faltante material accionable; si aún no está confirmada, precede F2. | D4: Scenario | E4: # Precondiciones Given inicio sesion en la App And se cumple la variante de la matriz "Existe deuda confirmada con faltante material accionable; si aún no está confirmada, precede F2." And el estado inicial / origen es "Home" And tengo una deuda "Crédito de consumo Banco Ejemplo" con estado de validación "Confirmada" And a la deuda le faltan los datos críticos "Pago mínimo / cuota mensual" y "Origen del dato" # Pasos y validaciones When visualizo la pantalla "Home" de la vista Home Then valido que se muestra la acción "Completar información" para la deuda And valido que los faltantes de la deuda se muestran consolidados en un único pendiente de calidad And valido que no se muestra acceso a Ruta Despeje completa ni plan activo When presiono el boton "Completar información" en la vista Home Then valido que me encuentro en la vista "OD-02 Revisión de deudas" con la edición de la deuda "Crédito de consumo Banco Ejemplo" And valido que se solicitan los datos "Pago mínimo / cuota mensual" y "Origen del dato" # Criterio de aceptación (matriz) Then valido la obligación "Proyectar F1/completitud hacia revisión; no plan activo." And valido la obligación "Consolidar pendings de calidad por deuda y preservar reasons secundarios." And valido el resultado "OD-02 / edición contextual" And valido el negativo/borde "No mostrar Ruta completa con dato crítico faltante." And valido el dato/estado "debt · data_completeness_status / minimum_data_ready" And valido la decisión/guardrail "BC-M04-002 cerrada para producción/proyección M04; orquestación global fuera." | F4: Obligación: Proyectar F1/completitud hacia revisión; no plan activo. Consolidar pendings de calidad por deuda y preservar reasons secundarios. Resultado: OD-02 / edición contextual Negativo/borde: No mostrar Ruta completa con dato crítico faltante. | G4: Alta | H4: Automatizable | I4: Pendiente | L4: TR-M04-046 · FLOW-M04-001 · Entrada contextual · M04-RGL-012; M04-RGL-002, M04-RGL-039 · Figma: consumidor visual/Figma · Validación: TC-M04-057 | M4: Funcional
A5: M4-V04 | B5: Entrada contextual · Home/Perfil | C5: Entrada contextual · Home/Perfil - Existe estado/proyección M04 consumible por Perfil (Salud, Ruta, calidad u orientación permitida). | D5: Scenario | E5: # Precondiciones Given inicio sesion en la App And se cumple la variante de la matriz "Existe estado/proyección M04 consumible por Perfil (Salud, Ruta, calidad u orientación permitida)." And el estado inicial / origen es "Perfil Financiero" And tengo una deuda confirmada con datos mínimos completos And M04 calculó para la deuda la Presión final "Atención" y la Salud de Deuda "Requiere atención" And visualizo la pantalla "Home" de la vista Home # Pasos y validaciones When presiono el boton "Mi Perfil" en la vista Home And selecciono la opcion "Mi Perfil" And presiono el boton "Mi Perfil Financiero" en la vista Mi Perfil Then valido que me encuentro en la vista de Perfil Financiero And valido que Perfil muestra la Salud de Deuda "Requiere atención" And valido que Perfil muestra un CTA compacto "Revisar situación" And valido que Perfil no muestra plan, cronograma ni avance completo de Ruta Despeje When presiono el boton "Revisar situación" en la vista Perfil Financiero Then valido que me encuentro en la vista "DD-01 Detalle de deuda" And valido que la Presión y la Salud mostradas coinciden con las mostradas en Perfil Financiero # Criterio de aceptación (matriz) Then valido la obligación "Perfil representa estado/CTA compacto heredado del owner M04; no recalcula ni crea state machine o señal paralela." And valido el resultado "Perfil / punto M04 según CTA" And valido el negativo/borde "No convertir Perfil en dashboard de deuda/Ruta." And valido el dato/estado "debt · functional_debt_state / pressure_evaluation_status / data_completeness_status" And valido la decisión/guardrail "BC-M04-002 cerrada para producción/proyección M04; orquestación global fuera." | F5: Obligación: Perfil representa estado/CTA compacto heredado del owner M04; no recalcula ni crea state machine o señal paralela. Resultado: Perfil / punto M04 según CTA Negativo/borde: No convertir Perfil en dashboard de deuda/Ruta. | G5: Media | H5: Automatizable | I5: Pendiente | L5: TR-M04-047 · FLOW-M04-001 · Entrada contextual · M04-RGL-002; M04-RGL-037, M04-RGL-039 · Figma: consumidor visual/Figma · Validación: TC-M04-057 | M5: Funcional
A6: M4-V05 | B6: OD-01 · Carga documental | C6: OD-01 · Carga documental - Usuario selecciona documento de deuda permitido | D6: Scenario | E6: # Precondiciones Given inicio sesion en la App And se cumple la variante de la matriz "Usuario selecciona documento de deuda permitido" And el estado inicial / origen es "OD-01 Agrega tus deudas" And me encuentro en la vista "OD-01 Agrega tus deudas" del Onboarding de Deudas # Pasos y validaciones When presiono el boton "Cargar documentos" en la vista OD-01 And selecciono el documento de deuda permitido "estado_cuenta_tarjeta.pdf" Then valido que se muestra el estado de procesamiento "Analizando" And valido que no se muestra ninguna deuda como confirmada durante el procesamiento When finaliza el procesamiento del documento Then valido que me encuentro en la vista "OD-02 Revisión de deudas" And valido que la deuda detectada se muestra con estado de validación "Pendiente de confirmación" And valido que no se ejecutó ningún pago, transferencia ni movimiento de dinero # Criterio de aceptación (matriz) Then valido la obligación "El archivo entra a procesamiento documental manual y queda pendiente hasta lectura/revisión." And valido el resultado "Analizando / OD-02" And valido el negativo/borde "No confirmar deuda antes de revisión." And valido el dato/estado "debt / document processing · document_processing_status / data_origin / confirmation_status" | F6: Obligación: El archivo entra a procesamiento documental manual y queda pendiente hasta lectura/revisión. Resultado: Analizando / OD-02 Negativo/borde: No confirmar deuda antes de revisión. | G6: Alta | H6: Automatizable | I6: Pendiente | L6: TR-M04-048 · FLOW-M04-002 · Onboarding 1 · Carga · M04-RGL-003; M04-RGL-036, M04-RGL-040 · Figma: Onboarding Deudas - 1. Carga de documentos.png · Validación: TC-M04-003, TC-M04-060 | M6: Funcional
A7: M4-V06 | B7: OD-01 · Carga documental | C7: OD-01 · Carga documental - Archivo es Informe de Deudas CMF cargado manualmente | D7: Scenario | E7: # Precondiciones Given inicio sesion en la App And se cumple la variante de la matriz "Archivo es Informe de Deudas CMF cargado manualmente" And el estado inicial / origen es "OD-01 Agrega tus deudas" And me encuentro en la vista "OD-01 Agrega tus deudas" del Onboarding de Deudas # Pasos y validaciones When presiono el boton "Cargar documentos" en la vista OD-01 And selecciono el documento "Informe_Deudas_CMF.pdf" Then valido que se muestra el estado de procesamiento "Analizando" And valido que no se solicita conectar, autorizar ni sincronizar una cuenta CMF, SFA u Open Finance And valido que no se muestra CMF/SFA como integración activa When finaliza el procesamiento del documento Then valido que me encuentro en la vista "OD-02 Revisión de deudas" And valido que el origen de las deudas detectadas se muestra como documento cargado por el usuario # Criterio de aceptación (matriz) Then valido la obligación "Se trata como documento manual bajo las mismas reglas de ingesta; no inicia conexión/consulta/sincronización CMF/SFA." And valido el resultado "Analizando / OD-02" And valido el negativo/borde "No mostrar CMF/SFA como integración activa." And valido el dato/estado "debt / document processing · data_origin / document_processing_status" | F7: Obligación: Se trata como documento manual bajo las mismas reglas de ingesta; no inicia conexión/consulta/sincronización CMF/SFA. Resultado: Analizando / OD-02 Negativo/borde: No mostrar CMF/SFA como integración activa. | G7: Alta | H7: Automatizable | I7: Pendiente | L7: TR-M04-049 · FLOW-M04-002 · Onboarding 1 · Carga · M04-RGL-004; M04-RGL-036 · Figma: Onboarding Deudas - 1. Carga de documentos.png · Validación: TC-M04-001, TC-M04-002; TC-M04-003 | M7: Funcional
A8: M4-V07 | B8: OD-01 · Carga documental | C8: OD-01 · Carga documental - Procesamiento aún no termina | D8: Scenario | E8: # Precondiciones Given inicio sesion en la App And se cumple la variante de la matriz "Procesamiento aún no termina" And el estado inicial / origen es "Procesamiento documental" And cargué el documento de deuda "estado_cuenta_tarjeta.pdf" desde la vista OD-01 And el procesamiento del documento sigue en curso # Pasos y validaciones When visualizo la pantalla de procesamiento del documento Then valido que se muestra el estado "Analizando" And valido que no se muestran datos de deuda leídos del documento And valido que no existe deuda confirmada ni acceso a Ruta Despeje When finaliza el procesamiento del documento Then valido que me encuentro en la vista "OD-02 Revisión de deudas" # Criterio de aceptación (matriz) Then valido la obligación "Mantener processing pending; no producir deuda confirmada ni Ruta completa." And valido el resultado "Pendiente / OD-02 al completar" And valido el negativo/borde "No fabricar lectura durante procesamiento." And valido el dato/estado "document processing / debt · document_processing_status=procesamiento_pendiente / confirmation_status" | F8: Obligación: Mantener processing pending; no producir deuda confirmada ni Ruta completa. Resultado: Pendiente / OD-02 al completar Negativo/borde: No fabricar lectura durante procesamiento. | G8: Media | H8: Automatizable | I8: Pendiente | L8: TR-M04-050 · FLOW-M04-002 · Onboarding 1 · Carga · M04-RGL-012; M04-RGL-040 · Figma: Figma Analizando · Validación: TC-M04-060 | M8: Funcional
A9: M4-V08 | B9: OD-01 · Registro manual | C9: OD-01 · Registro manual - Registro manual formal con campos de registro básico | D9: Scenario | E9: # Precondiciones Given inicio sesion en la App And se cumple la variante de la matriz "Registro manual formal con campos de registro básico" And el estado inicial / origen es "OD-01 / sheet deuda manual" And me encuentro en la vista "OD-01 Agrega tus deudas" del Onboarding de Deudas # Pasos y validaciones When presiono el boton "Ingresar deuda manualmente" en la vista OD-01 And ingreso los siguientes datos de la deuda: | campo | valor | | Tipo de deuda | Crédito de consumo | | Institución | Banco Ejemplo | | Saldo actual | 1.200.000 | And presiono el boton "Guardar" en la vista Deuda manual Then valido que la deuda "Crédito de consumo Banco Ejemplo" se muestra en el listado con origen "Manual" And valido que se muestra la opción "Agregar otra" And valido que se indica como pendiente el dato "Pago mínimo / cuota mensual" And valido que no se muestra lectura de Presión ni acceso a Ruta Despeje para la deuda # Criterio de aceptación (matriz) Then valido la obligación "Guardar deuda formal y reevaluar completitud; registro no implica presión ni Ruta." And valido el resultado "OD-01/OD-02" And valido el negativo/borde "No usar registro básico para conclusiones fuertes." And valido el dato/estado "debt · debt_category / debt_type / current_balance_amount / data_origin / confirmation_status" | F9: Obligación: Guardar deuda formal y reevaluar completitud; registro no implica presión ni Ruta. Resultado: OD-01/OD-02 Negativo/borde: No usar registro básico para conclusiones fuertes. | G9: Alta | H9: Automatizable | I9: Pendiente | L9: TR-M04-051 · FLOW-M04-003 · Onboarding 1 · Carga · M04-RGL-005; M04-RGL-012 · Figma: Sheet_Deuda Manual_Ingresar datos*.png · Validación: TC-M04-004, TC-M04-005 | M9: Funcional
A10: M4-V09 | B10: OD-01 · Registro manual | C10: OD-01 · Registro manual - Registro es préstamo personal o compromiso informal con monto/frecuencia | D10: Scenario | E10: # Precondiciones Given inicio sesion en la App And se cumple la variante de la matriz "Registro es préstamo personal o compromiso informal con monto/frecuencia" And el estado inicial / origen es "OD-01 / sheet deuda manual" And me encuentro en la vista "OD-01 Agrega tus deudas" del Onboarding de Deudas # Pasos y validaciones When presiono el boton "Ingresar deuda manualmente" en la vista OD-01 And ingreso los siguientes datos de la deuda: | campo | valor | | Tipo de deuda | Préstamo personal / informal | | Acreedor | Familiar | | Monto adeudado | 300.000 | | Compromiso de pago | 50.000 | | Frecuencia | Mensual | And no ingreso fecha de vencimiento formal And presiono el boton "Guardar" en la vista Deuda manual Then valido que la deuda se guarda como deuda manual informal And valido que no se exigió fecha de vencimiento formal para guardar And valido que los textos de la pantalla usan lenguaje neutral y no estigmatizante And valido que la deuda queda disponible para evaluación de Presión con las mismas reglas que una deuda formal # Criterio de aceptación (matriz) Then valido la obligación "Guardar como deuda manual/informal sin tratamiento estigmatizante; evaluar luego según mismas reglas de presión." And valido el resultado "OD-01/OD-02" And valido el negativo/borde "No exigir vencimiento formal; sí compromiso/frecuencia para presión." And valido el dato/estado "debt · debt_category=manual_debt / debt_subtype=informal_loan / is_informal / monthly_equivalent_amount" | F10: Obligación: Guardar como deuda manual/informal sin tratamiento estigmatizante; evaluar luego según mismas reglas de presión. Resultado: OD-01/OD-02 Negativo/borde: No exigir vencimiento formal; sí compromiso/frecuencia para presión. | G10: Media | H10: Automatizable | I10: Pendiente | L10: TR-M04-052 · FLOW-M04-003 · Onboarding 1 · Carga · M04-RGL-005; M04-RGL-012 · Figma: Sheet_Deuda Manual_Ingresar datos*.png · Validación: TC-M04-004, TC-M04-005 | M10: Funcional
A11: M4-V10 | B11: OD-01 · Registro manual | C11: OD-01 · Registro manual - Faltan datos para presión/Ruta | D11: Scenario | E11: # Precondiciones Given inicio sesion en la App And se cumple la variante de la matriz "Faltan datos para presión/Ruta" And el estado inicial / origen es "OD-01 / sheet deuda manual" And me encuentro en la vista "OD-01 Agrega tus deudas" del Onboarding de Deudas # Pasos y validaciones When presiono el boton "Ingresar deuda manualmente" en la vista OD-01 And ingreso el tipo de deuda "Tarjeta de crédito" y el saldo actual "450.000" And no ingreso el pago mínimo / cuota mensual And presiono el boton "Guardar pendiente" en la vista Deuda manual Then valido que me encuentro en la vista "OD-02 Revisión de deudas" And valido que la deuda se muestra con estado "Pendiente / Incompleta" And valido que se ofrece la acción "Completar" And valido que no se muestra evaluación de Presión, priorización ni cronograma para la deuda And valido que no se muestra acceso a Ruta Despeje # Criterio de aceptación (matriz) Then valido la obligación "Guardar como pendiente/incompleta; no evaluar presión fuerte, priorización ni cronograma." And valido el resultado "OD-02 / pendiente" And valido el negativo/borde "No activar Ruta ni cronograma." And valido el dato/estado "debt · data_completeness_status / minimum_data_ready=false / pressure_evaluation_status=no_evaluada" | F11: Obligación: Guardar como pendiente/incompleta; no evaluar presión fuerte, priorización ni cronograma. Resultado: OD-02 / pendiente Negativo/borde: No activar Ruta ni cronograma. | G11: Alta | H11: Automatizable | I11: Pendiente | L11: TR-M04-053 · FLOW-M04-003 · Onboarding 1 · Carga · M04-RGL-005; M04-RGL-012 · Figma: Sheet_Deuda Manual_Ingresar datos*.png · Validación: TC-M04-004, TC-M04-005 | M11: Funcional
A12: M4-V11 | B12: OD-01 · Documento protegido | C12: OD-01 · Documento protegido - Documento está protegido con contraseña | D12: Scenario | E12: # Precondiciones Given inicio sesion en la App And se cumple la variante de la matriz "Documento está protegido con contraseña" And el estado inicial / origen es "Carga documental" And me encuentro en la vista "OD-01 Agrega tus deudas" del Onboarding de Deudas Then valido que la vista OD-01 no muestra un campo de contraseña por defecto # Pasos y validaciones When presiono el boton "Cargar documentos" en la vista OD-01 And selecciono el documento protegido con contraseña "cartola_protegida.pdf" Then valido que se muestra el estado recuperable "Documento protegido" And valido que se muestra el campo para ingresar la contraseña del documento And valido que se muestra el boton "Continuar revisión" # Criterio de aceptación (matriz) Then valido la obligación "Mostrar estado recuperable y solicitar clave solo cuando sea necesaria." And valido el resultado "Estado requiere clave" And valido el negativo/borde "No mostrar campo clave por defecto." And valido el dato/estado "document processing · document_processing_status=requiere_clave" | F12: Obligación: Mostrar estado recuperable y solicitar clave solo cuando sea necesaria. Resultado: Estado requiere clave Negativo/borde: No mostrar campo clave por defecto. | G12: Alta | H12: Automatizable | I12: Pendiente | L12: TR-M04-054 · FLOW-M04-004 · Onboarding 1 · Documento protegido · M04-RGL-009 · Figma: Export 4.3-4.4 / documentado · Validación: TC-M04-006, TC-M04-007, TC-M04-008 | M12: Funcional
A13: M4-V12 | B13: OD-01 · Documento protegido | C13: OD-01 · Documento protegido - Clave correcta | D13: Scenario | E13: # Precondiciones Given inicio sesion en la App And se cumple la variante de la matriz "Clave correcta" And el estado inicial / origen es "Estado requiere clave" And cargué el documento protegido "cartola_protegida.pdf" y se muestra el estado "Documento protegido" # Pasos y validaciones When ingreso la contraseña correcta del documento And presiono el boton "Continuar revisión" Then valido que se muestra el estado de procesamiento "Analizando" When finaliza el procesamiento del documento Then valido que me encuentro en la vista "OD-02 Revisión de deudas" And valido que la contraseña no se muestra como dato de ninguna deuda detectada When cargo nuevamente el documento "cartola_protegida.pdf" desde la vista OD-01 Then valido que se vuelve a solicitar la contraseña del documento # Criterio de aceptación (matriz) Then valido la obligación "Procesar documento y continuar a revisión; clave no se persiste como atributo de deuda." And valido el resultado "Analizando / OD-02" And valido el negativo/borde "No persistir secreto." And valido el dato/estado "document processing · document_processing_status=documento_legible" | F13: Obligación: Procesar documento y continuar a revisión; clave no se persiste como atributo de deuda. Resultado: Analizando / OD-02 Negativo/borde: No persistir secreto. | G13: Alta | H13: Automatizable | I13: Pendiente | L13: TR-M04-055 · FLOW-M04-004 · Onboarding 1 · Documento protegido · M04-RGL-009; M04-RGL-040 · Figma: Documentado · Validación: TC-M04-006, TC-M04-007, TC-M04-008 | M13: Funcional
... A94: M4-V93 | B94: Etiquetas funcionales MVP | C94: Etiquetas funcionales MVP - Existe dato/regla fuente que respalda una etiqueta MVP (Perfil/Home) | D94: Scenario Outline | E94: # Precondiciones Given inicio sesion en la App And se cumple la variante de la matriz "Existe dato/regla fuente que respalda una etiqueta MVP" And el estado inicial / origen es "Perfil/Home" And tengo una deuda con "<soporte>" para la etiqueta "Requiere revisión" # Pasos y validaciones When ingreso a la vista de Perfil Financiero Then valido que la etiqueta "Requiere revisión" se muestra "<visible>" en la vista Perfil Financiero And valido que la etiqueta no reemplaza la Presión, la validación ni el CTA principal de la vista And valido que la deuda no muestra etiquetas sin regla o dato que las respalde # Criterio de aceptación (matriz) Then valido la obligación "Etiqueta resumida solo cuando exista regla/dato y sea pertinente en superficie consumidora." And valido la obligación "La etiqueta no reemplaza severidad, validación ni CTA dominante." And valido el resultado "Misma superficie" And valido el negativo/borde "No mostrar etiqueta sin regla/dato; no sobreetiquetar." And valido el dato/estado "functional_tag / functional_tag_assignment · tag_code / source_entity_type / source_rule_id / confidence_level / display_surface / tag_status" And valido la decisión/guardrail "Ajustar materialización/copy sin reabrir regla. | familia única de Etiquetas funcionales MVP; no crear RGL por superficie. anterior TR-M04-039 se conserva solo como anchor histórico. ID: GAP-MAT-M04-TAGS" Examples: | soporte | visible | | dato y regla fuente que la respaldan | visible | | sin dato ni regla fuente | oculta | | F94: Obligación: Etiqueta resumida solo cuando exista regla/dato y sea pertinente en superficie consumidora. La etiqueta no reemplaza severidad, validación ni CTA dominante. Resultado: Misma superficie Negativo/borde: No mostrar etiqueta sin regla/dato; no sobreetiquetar. | G94: Media | H94: Automatizable | I94: Pendiente | L94: TR-M04-136 · FLOW-M04-001 · Entrada contextual · Figma: Figma cerrado · taxonomía functional_tag no observada inequívocamente · Validación: TC-M04-057 | M94: Funcional

Sheet Registro de Defectos
A1: ID Defecto | B1: Caso Asociado | C1: Sección | D1: Título del Defecto | E1: Descripción | F1: Severidad | G1: Prioridad | H1: Estado | I1: Evidencia | J1: Fecha Detección | K1: Fecha Resolución | L1: Responsable

Sheet Glosario y Convenciones
B2: Glosario y Convenciones del Informe
B4: Estados de Ejecución
B5: Pendiente | C5: El caso aún no ha sido ejecutado.
B6: Aprobado | C6: El caso fue ejecutado y el resultado coincide con lo esperado.
B7: Fallido | C7: El caso fue ejecutado y el resultado NO coincide con lo esperado.
B8: Bloqueado | C8: El caso no pudo ejecutarse por dependencia de otro caso o defecto abierto.
B9: No Aplica | C9: El caso no aplica para este ciclo de pruebas o ambiente.
B11: Severidad de Defectos
B12: Crítica | C12: Bloquea funcionalidad principal. No se puede continuar sin corrección.
B13: Alta | C13: Funcionalidad principal afectada pero existe workaround.
B14: Media | C14: Funcionalidad secundaria afectada. No bloquea certificación.
B15: Baja | C15: Defecto cosmético o de UX menor.
B17: Prioridad de Casos
B18: Alta | C18: Flujo crítico del módulo. Debe pasar para aprobar certificación.
B19: Media | C19: Funcionalidad relevante. Su fallo se documenta pero no bloquea.
B20: Baja | C20: Caso complementario o cosmético.
B22: Tipo de Prueba
B23: Automatizable | C23: El caso puede ser automatizado con herramientas de test.
B24: Manual | C24: El caso requiere ejecución manual obligatoria.
B26: Convenciones
B27: Scenario | C27: Caso de prueba con datos fijos.
B28: Scenario Outline | C28: Caso parametrizado que se ejecuta con múltiples juegos de datos.
B29: — | C29: Campo sin dato o pendiente de completar.
