Workbook

Sheet 00_RESUMEN
A1: Walvy · Plan QA por fases · respuesta PMO · v1.1
A2: Solución operativa para Miguel/Kabeli. La matriz separa PASS funcional, fixture cross-contract, superficies M02/M03, E2E real y regresión final.
A4: Hallazgo rector | B4: No tratar “produce algo para otro módulo” como dependencia de entrada. Un productor puede hacer QA funcional antes y reservar la integración real para E2E.
A6: Universo actual | B6: 186 unidades contractuales vigentes = 93 Trace M04 + 34 variantes M05 + 59 variantes M06
A7: Corrección M04 | B7: M04 vigente usa TR-M04-044…136. El HTML de Miguel usa M4-Vxx; no existe crosswalk autoritativo 1:1 para V87–V93. No se fabricó ese mapeo.
A8: Propuesta Miguel | B8: El HTML declara 152 totales, pero sus propios módulos suman 186; las fases declaradas suman 159. El plan requiere reconciliación antes de operar.
A9: Qué conserva | B9: La intención: paralelizar QA. Se reemplaza la partición rígida por gates acumulativos: F1/F2/F3 son primer PASS; F4/F5 son reejecución E2E/regresión.
A10: Revisión v1.1 | B10: 23/23 excepciones revisadas: 22 aprobadas sin cambios y 1 ajustada (M5-V20). La matriz primaria de 186 casos y sus conteos permanecen sin cambio.
A12: Módulo | B12: F1 · local | C12: F2 · fixture cross | D12: F3 · M02/M03 | E12: Total | F12: Check
A13: M04 | B13: =COUNTIFS('01_MATRIZ_OPERATIVA_186'!$A:$A,$A13,'01_MATRIZ_OPERATIVA_186'!$H:$H,"F1*") | C13: =COUNTIFS('01_MATRIZ_OPERATIVA_186'!$A:$A,$A13,'01_MATRIZ_OPERATIVA_186'!$H:$H,"F2*") | D13: =COUNTIFS('01_MATRIZ_OPERATIVA_186'!$A:$A,$A13,'01_MATRIZ_OPERATIVA_186'!$H:$H,"F3*") | E13: =SUM(B13:D13) | F13: =IF(E13=93,"PASS","FAIL")
A14: M05 | B14: =COUNTIFS('01_MATRIZ_OPERATIVA_186'!$A:$A,$A14,'01_MATRIZ_OPERATIVA_186'!$H:$H,"F1*") | C14: =COUNTIFS('01_MATRIZ_OPERATIVA_186'!$A:$A,$A14,'01_MATRIZ_OPERATIVA_186'!$H:$H,"F2*") | D14: =COUNTIFS('01_MATRIZ_OPERATIVA_186'!$A:$A,$A14,'01_MATRIZ_OPERATIVA_186'!$H:$H,"F3*") | E14: =SUM(B14:D14) | F14: =IF(E14=34,"PASS","FAIL")
A15: M06 | B15: =COUNTIFS('01_MATRIZ_OPERATIVA_186'!$A:$A,$A15,'01_MATRIZ_OPERATIVA_186'!$H:$H,"F1*") | C15: =COUNTIFS('01_MATRIZ_OPERATIVA_186'!$A:$A,$A15,'01_MATRIZ_OPERATIVA_186'!$H:$H,"F2*") | D15: =COUNTIFS('01_MATRIZ_OPERATIVA_186'!$A:$A,$A15,'01_MATRIZ_OPERATIVA_186'!$H:$H,"F3*") | E15: =SUM(B15:D15) | F15: =IF(E15=59,"PASS","FAIL")
A16: TOTAL | B16: =SUM(B13:B15) | C16: =SUM(C13:C15) | D16: =SUM(D13:D15) | E16: =SUM(E13:E15) | F16: =IF(E16=186,"PASS","FAIL")
A19: Lectura de las fases
A20: F1 | B20: QA funcional local | C20: PASS del comportamiento propio del módulo. Si además produce un payload downstream, se valida aquí el payload; la entrega real se prueba después.
A21: F2 | B21: Fixture cross-contract | C21: El resultado consume input de otro módulo. Se usa payload/fixture canónico del contrato cerrado; PASS funcional, todavía no E2E.
A22: F3 | B22: M02/M03 / superficie | C22: El criterio de aceptación completo vive en Home, Perfil, avisos/canales u otra superficie M02/M03. El productor puede tener QA parcial previo.
A23: F4 | B23: E2E real | C23: Reejecución de interfaces M04↔M05↔M06 con productor/consumidor reales. No es una nueva bolsa de IDs.
A24: F5 | B24: Regresión final | C24: Smoke contractual + journeys críticos sobre el release candidato. No crea nuevas variantes ni reabre Producto.
A27: Mensaje operativo para Miguel
A28: El enfoque de separar por dependencias se mantiene, pero proponemos distinguir PASS funcional de integración. F1 valida lo owner-local; F2 valida consumidores cross-module con fixtures canónicos; F3 valida M02/M03/superficies; F4 reejecuta E2E real y F5 hace regresión final. Esto permite adelantar productores que hoy están en F3/F4/F5 sin declarar una integración como aprobada antes de tiempo. Para M04 hay además que corregir el esquema de IDs: el contrato vigente tiene 93 Trace IDs TR-M04-044…136 y el HTML usa M4-V; no fabricamos V89–V93.

Sheet 01_MATRIZ_OPERATIVA_186
A1: Matriz operativa QA · 186 unidades vigentes
A2: F1/F2/F3 = primer PASS. F4/F5 = overlays de integración/regresión. M04 se conserva con sus Trace IDs vigentes; ver crosswalk legacy.
A4: Módulo | B4: ID vigente | C4: Flujo / Subflujo | D4: Variante / Escenario | E4: Condición / Disparador | F4: Comportamiento / Obligación | G4: Dependencia real / owner | H4: Gate primario Walvy | I4: QA funcional local | J4: Fixture cross-contract | K4: M02/M03 / superficie | L4: E2E real | M4: Regresión final | N4: Fase Miguel (HTML) | O4: Excepción vs Miguel | P4: Criterio / por qué | Q4: Fuente vigente | R4: Conteo ID
A5: M04 | B5: TR-M04-044 | C5: FLOW-M04-001 · Entrada contextual | D5: Existe candidato/proyección M04 accionable ya resuelto por el módulo dueño; Home solo consume el contrato. | E5: Home | CTA contextual | F5: Home representa el candidato M04 y deriva a su destino sin recalcular estado, reason ni Ruta; la selección del ganador global queda fuera de M04. | G5: M04 | M03/Home | H5: F3 · M02/M03 / superficie | I5: No como PASS completo | J5: Parcial · productor/oráculo sí; no sustituye PASS superficie | K5: Sí | L5: Sí · F3/F5 | M5: Sí · F5 journey crítico | N5: No comparable 1:1 · Miguel usa M4-V; vigente usa TR-M04 | O5: CROSSWALK | P5: El criterio de aceptación completo vive en Home/Perfil/avisos o en una superficie M02/M03; el productor puede probarse antes, pero no reemplaza el PASS de superficie. | Q5: Walvy_M04_Matriz_Trazabilidad_Cliente_v1.3.xlsx · 01_Matriz_Trazabilidad · TR-M04-044 | R5: =COUNTIF($B$5:$B$190,B5)
A6: M04 | B6: TR-M04-045 | C6: FLOW-M04-001 · Entrada contextual | D6: Señal corresponde a pago próximo/al día/vencimiento simple con capacidad | E6: Home | CTA contextual | F6: Home deriva a M06/Pagos-Alertas; no a Ruta. | G6: M06 | M06/Pagos | H6: F3 · M02/M03 / superficie | I6: No como PASS completo | J6: Parcial · productor/oráculo sí; no sustituye PASS superficie | K6: Sí | L6: Sí · F3/F5 | M6: Sí · F5 journey crítico | N6: No comparable 1:1 · Miguel usa M4-V; vigente usa TR-M04 | O6: CROSSWALK | P6: El criterio de aceptación completo vive en Home/Perfil/avisos o en una superficie M02/M03; el productor puede probarse antes, pero no reemplaza el PASS de superficie. | Q6: Walvy_M04_Matriz_Trazabilidad_Cliente_v1.3.xlsx · 01_Matriz_Trazabilidad · TR-M04-045 | R6: =COUNTIF($B$5:$B$190,B6)
A7: M04 | B7: TR-M04-046 | C7: FLOW-M04-001 · Entrada contextual | D7: Existe deuda confirmada con faltante material accionable; si aún no está confirmada, precede F2. | E7: Home | Completar | F7: Proyectar F1/completitud hacia revisión; no plan activo. Consolidar pendings de calidad por deuda y preservar reasons secundarios. | G7: M04 | M03/Home | H7: F3 · M02/M03 / superficie | I7: No como PASS completo | J7: Parcial · productor/oráculo sí; no sustituye PASS superficie | K7: Sí | L7: Sí · F3/F5 | M7: Sí · F5 journey crítico | N7: No comparable 1:1 · Miguel usa M4-V; vigente usa TR-M04 | O7: CROSSWALK | P7: El criterio de aceptación completo vive en Home/Perfil/avisos o en una superficie M02/M03; el productor puede probarse antes, pero no reemplaza el PASS de superficie. | Q7: Walvy_M04_Matriz_Trazabilidad_Cliente_v1.3.xlsx · 01_Matriz_Trazabilidad · TR-M04-046 | R7: =COUNTIF($B$5:$B$190,B7)
A8: M04 | B8: TR-M04-047 | C8: FLOW-M04-001 · Entrada contextual | D8: Existe estado/proyección M04 consumible por Perfil (Salud, Ruta, calidad u orientación permitida). | E8: Perfil Financiero | CTA/lectura contextual | F8: Perfil representa estado/CTA compacto heredado del owner M04; no recalcula ni crea state machine o señal paralela. | G8: M04 | H8: F3 · M02/M03 / superficie | I8: No como PASS completo | J8: Parcial · productor/oráculo sí; no sustituye PASS superficie | K8: Sí | L8: Sí · F3/F5 | M8: Sí · F5 journey crítico | N8: No comparable 1:1 · Miguel usa M4-V; vigente usa TR-M04 | O8: CROSSWALK | P8: El criterio de aceptación completo vive en Home/Perfil/avisos o en una superficie M02/M03; el productor puede probarse antes, pero no reemplaza el PASS de superficie. | Q8: Walvy_M04_Matriz_Trazabilidad_Cliente_v1.3.xlsx · 01_Matriz_Trazabilidad · TR-M04-047 | R8: =COUNTIF($B$5:$B$190,B8)
A9: M04 | B9: TR-M04-048 | C9: FLOW-M04-002 · Onboarding 1 · Carga | D9: Usuario selecciona documento de deuda permitido | E9: OD-01 Agrega tus deudas | Cargar documentos | F9: El archivo entra a procesamiento documental manual y queda pendiente hasta lectura/revisión. | G9: M04 | Procesamiento documental | H9: F1 · QA funcional local | I9: Sí | J9: No requerido para PASS primario | K9: No para PASS primario | L9: No obligatorio fuera de regresión | M9: Sí · F5 smoke contractual | N9: No comparable 1:1 · Miguel usa M4-V; vigente usa TR-M04 | O9: CROSSWALK | P9: El resultado primario se determina en M04 con sus estados/reglas; una salida downstream no se trata como dependencia de entrada. | Q9: Walvy_M04_Matriz_Trazabilidad_Cliente_v1.3.xlsx · 01_Matriz_Trazabilidad · TR-M04-048 | R9: =COUNTIF($B$5:$B$190,B9)
A10: M04 | B10: TR-M04-049 | C10: FLOW-M04-002 · Onboarding 1 · Carga | D10: Archivo es Informe de Deudas CMF cargado manualmente | E10: OD-01 Agrega tus deudas | Cargar documentos | F10: Se trata como documento manual bajo las mismas reglas de ingesta; no inicia conexión/consulta/sincronización CMF/SFA. | G10: M04 | CMF/SFA externo | H10: F1 · QA funcional local | I10: Sí | J10: No requerido para PASS primario | K10: No para PASS primario | L10: No obligatorio fuera de regresión | M10: Sí · F5 smoke contractual | N10: No comparable 1:1 · Miguel usa M4-V; vigente usa TR-M04 | O10: CROSSWALK | P10: El resultado primario se determina en M04 con sus estados/reglas; una salida downstream no se trata como dependencia de entrada. | Q10: Walvy_M04_Matriz_Trazabilidad_Cliente_v1.3.xlsx · 01_Matriz_Trazabilidad · TR-M04-049 | R10: =COUNTIF($B$5:$B$190,B10)
A11: M04 | B11: TR-M04-050 | C11: FLOW-M04-002 · Onboarding 1 · Carga | D11: Procesamiento aún no termina | E11: Procesamiento documental | Estado de procesamiento | F11: Mantener processing pending; no producir deuda confirmada ni Ruta completa. | G11: M04 | Procesamiento documental | H11: F1 · QA funcional local | I11: Sí | J11: No requerido para PASS primario | K11: No para PASS primario | L11: No obligatorio fuera de regresión | M11: Sí · F5 smoke contractual | N11: No comparable 1:1 · Miguel usa M4-V; vigente usa TR-M04 | O11: CROSSWALK | P11: El resultado primario se determina en M04 con sus estados/reglas; una salida downstream no se trata como dependencia de entrada. | Q11: Walvy_M04_Matriz_Trazabilidad_Cliente_v1.3.xlsx · 01_Matriz_Trazabilidad · TR-M04-050 | R11: =COUNTIF($B$5:$B$190,B11)
A12: M04 | B12: TR-M04-051 | C12: FLOW-M04-003 · Onboarding 1 · Carga | D12: Registro manual formal con campos de registro básico | E12: OD-01 / sheet deuda manual | Guardar deuda | F12: Guardar la deuda declarada manualmente y marcarla como confirmada respecto de su existencia/pertenencia; reevaluar la completitud de forma independiente. El registro no implica Presion ni Ruta. | G12: M04 | H12: F1 · QA funcional local | I12: Sí | J12: No requerido para PASS primario | K12: No para PASS primario | L12: No obligatorio fuera de regresión | M12: Sí · F5 smoke contractual | N12: No comparable 1:1 · Miguel usa M4-V; vigente usa TR-M04 | O12: CROSSWALK | P12: El resultado primario se determina en M04 con sus estados/reglas; una salida downstream no se trata como dependencia de entrada. | Q12: Walvy_M04_Matriz_Trazabilidad_Cliente_v1.3.xlsx · 01_Matriz_Trazabilidad · TR-M04-051 | R12: =COUNTIF($B$5:$B$190,B12)
A13: M04 | B13: TR-M04-052 | C13: FLOW-M04-003 · Onboarding 1 · Carga | D13: Registro es préstamo personal o compromiso informal con monto/frecuencia | E13: OD-01 / sheet deuda manual | Guardar deuda | F13: Guardar como deuda manual/informal sin tratamiento estigmatizante; evaluar luego según mismas reglas de presión. | G13: M04 | H13: F1 · QA funcional local | I13: Sí | J13: No requerido para PASS primario | K13: No para PASS primario | L13: No obligatorio fuera de regresión | M13: Sí · F5 smoke contractual | N13: No comparable 1:1 · Miguel usa M4-V; vigente usa TR-M04 | O13: CROSSWALK | P13: El resultado primario se determina en M04 con sus estados/reglas; una salida downstream no se trata como dependencia de entrada. | Q13: Walvy_M04_Matriz_Trazabilidad_Cliente_v1.3.xlsx · 01_Matriz_Trazabilidad · TR-M04-052 | R13: =COUNTIF($B$5:$B$190,B13)
A14: M04 | B14: TR-M04-053 | C14: FLOW-M04-003 · Onboarding 1 · Carga | D14: Faltan datos para presión/Ruta | E14: OD-01 / sheet deuda manual | Guardar deuda | F14: Conservar la deuda manual como confirmada respecto de su existencia/pertenencia, pero pendiente/incompleta para el uso afectado; no evaluar presion fuerte, priorizacion ni cronograma mientras falten datos materiales requeridos. | G14: M04 | H14: F1 · QA funcional local | I14: Sí | J14: No requerido para PASS primario | K14: No para PASS primario | L14: No obligatorio fuera de regresión | M14: Sí · F5 smoke contractual | N14: No comparable 1:1 · Miguel usa M4-V; vigente usa TR-M04 | O14: CROSSWALK | P14: El resultado primario se determina en M04 con sus estados/reglas; una salida downstream no se trata como dependencia de entrada. | Q14: Walvy_M04_Matriz_Trazabilidad_Cliente_v1.3.xlsx · 01_Matriz_Trazabilidad · TR-M04-053 | R14: =COUNTIF($B$5:$B$190,B14)
A15: M04 | B15: TR-M04-054 | C15: FLOW-M04-004 · Onboarding 1 · Documento protegido | D15: Documento está protegido con contraseña | E15: Carga documental | Detectar protección | F15: Mostrar estado recuperable y solicitar clave solo cuando sea necesaria. | G15: M04 | Documento protegido | H15: F1 · QA funcional local | I15: Sí | J15: No requerido para PASS primario | K15: No para PASS primario | L15: No obligatorio fuera de regresión | M15: Sí · F5 smoke contractual | N15: No comparable 1:1 · Miguel usa M4-V; vigente usa TR-M04 | O15: CROSSWALK | P15: El resultado primario se determina en M04 con sus estados/reglas; una salida downstream no se trata como dependencia de entrada. | Q15: Walvy_M04_Matriz_Trazabilidad_Cliente_v1.3.xlsx · 01_Matriz_Trazabilidad · TR-M04-054 | R15: =COUNTIF($B$5:$B$190,B15)
A16: M04 | B16: TR-M04-055 | C16: FLOW-M04-004 · Onboarding 1 · Documento protegido | D16: Clave correcta | E16: Estado requiere clave | Continuar revisión | F16: Procesar documento y continuar a revisión; clave no se persiste como atributo de deuda. | G16: M04 | Documento protegido | H16: F1 · QA funcional local | I16: Sí | J16: No requerido para PASS primario | K16: No para PASS primario | L16: No obligatorio fuera de regresión | M16: Sí · F5 smoke contractual | N16: No comparable 1:1 · Miguel usa M4-V; vigente usa TR-M04 | O16: CROSSWALK | P16: El resultado primario se determina en M04 con sus estados/reglas; una salida downstream no se trata como dependencia de entrada. | Q16: Walvy_M04_Matriz_Trazabilidad_Cliente_v1.3.xlsx · 01_Matriz_Trazabilidad · TR-M04-055 | R16: =COUNTIF($B$5:$B$190,B16)
... A190: M06 | B190: M6-V59 | C190: Diseño / Equivalencia | D190: Pantalla Pagos vs superficie equivalente | E190: Se debe representar M6 en UX | F190: La solución debe cubrir todas las obligaciones MVP mínimas; la pantalla propia es candidata fuerte, pero el cierre visual final requiere validación UX/QA. | G190: M06 | H190: F1 · QA funcional local | I190: Sí | J190: No requerido para PASS primario | K190: No para PASS primario | L190: No obligatorio fuera de regresión | M190: Sí · F5 smoke contractual | N190: F5 | O190: SÍ | P190: El resultado primario se determina en M06 con sus estados/reglas; una salida downstream no se trata como dependencia de entrada. | Q190: Walvy_M6_Matriz_Trazabilidad_Cliente_v1.0_RESPUESTA_WALVY.xlsx · Matriz Trazabilidad · M6-V59 | R190: =COUNTIF($B$5:$B$190,B190)

Sheet 02_EXCEPCIONES_MIGUEL
A1: Excepciones respecto de la propuesta de Miguel
A2: Solo diferencias materiales. Comparación contra plan_fases_qa_pmo.html; el Excel/CSV simple mencionado en el HTML no está adjunto.
A4: Módulo | B4: ID / rango Miguel | C4: Miguel | D4: Walvy recomendado | E4: Tipo de corrección | F4: Por qué | G4: Acción para Miguel | H4: Certeza | I4: Fuente | J4: Revisión
A5: M04 | B5: Universo / IDs | C5: 93 “variantes” M4-Vxx | D5: 93 Trace vigentes TR-M04-044…136 | E5: ID / universo | F5: El contrato final M04 ya no usa M4-V como ID rector. El lineage histórico localiza M4-V01…V86; V87/V88 aparecen solo en el HTML y V89–V93 no tienen fuente explícita localizada. | G5: Mantener plan operativo sobre TR-M04 vigente y usar el crosswalk legacy solo como referencia; no inventar V89–V93. | H5: Alta | I5: M04 final v1.3 + matriz reconciliada producto | J5: Aprobado
A6: M04 | B6: M4-V87–V88 | C6: F1 y también dentro de V50–V88/F5 | D6: Una sola disposición; semanticamente entrada directa/reingreso. | E6: Duplicidad | F6: El HTML los incluye en F1 y simultáneamente el rango F5 los vuelve a incluir. | G6: Eliminar la duplicidad; no contar dos veces. | H6: Alta | I6: plan_fases_qa_pmo.html | J6: Aprobado
A7: M04 | B7: M4-V89–V93 | C7: No aparecen | D7: SOURCE_GAP: no asignar hasta mapear contra TR vigentes | E7: Ausencia | F7: El HTML declara M04=93, pero no dispone V89–V93. No se localizó un crosswalk autoritativo que convierta TR-M04-132…136 en esos V IDs. | G7: No fabricar IDs. Si Miguel aporta su Excel simple, reconciliar esos cinco contra TR vigentes. | H7: Alta | I7: plan_fases_qa_pmo.html + M04 final v1.3 | J7: Aprobado
A8: M04 | B8: M4-V30–V49 | C8: F4 | D8: Separar: consumo upstream → F2 con fixture; output/local → F1; E2E → F4 | E8: Partición demasiado gruesa | F8: “Cross-module” no significa que todo deba esperar integración real; solo los inputs externos bloquean el PASS sin fixture. | G8: Desagregar por dependencia real, usando matriz operativa vigente. | H8: Alta | I8: M04 final v1.3 · P4 / owner inputs | J8: Aprobado
A9: M04 | B9: M4-V50–V88 | C9: F5 | D9: Ruta se prueba por capas: F1 local / F2 inputs cross / F4 E2E / F5 regresión | E9: Falso bloqueo de Ruta | F9: La política prudencial y lifecycle ya están cerrados. Ruta no debe esperar completa hasta F5. | G9: Reservar F5 para journey/regresión; adelantar reglas y simulación según dependencia. | H9: Alta | I9: M04 v1.3 + M05 v1.2 prudencial | J9: Aprobado
A10: M05 | B10: M5-V11 | C10: F3 | D10: F1 productor + F3 Home | E10: Split producer/surface | F10: M05 puede validar la señal; M03/Home valida la superficie/prioridad. | G10: Ajustar fase/overlay; no reabrir regla Producto. | H10: Alta | I10: M05 v1.2 · M5-V11 | J10: Aprobado
A11: M05 | B11: M5-V12 | C11: F3 | D11: F1 | E11: Dependencia sobredimensionada | F11: La recomendación M05 exige evidencia/lifecycle, no un canal M02 para su lógica primaria. | G11: Ajustar fase/overlay; no reabrir regla Producto. | H11: Alta | I11: M05 v1.2 · M5-V12 | J11: Aprobado
A12: M05 | B12: M5-V15 | C12: F2 | D12: F1 | E12: Precondición local | F12: La confirmación de extracción se valida con candidato local controlado. | G12: Ajustar fase/overlay; no reabrir regla Producto. | H12: Alta | I12: M05 v1.2 · M5-V15 | J12: Aprobado
A13: M05 | B13: M5-V18 | C13: F2 | D13: F1 | E13: Precondición local | F13: Plan de recuperación usa evidencia/historial M05; no requiere otro módulo como input rector. | G13: Ajustar fase/overlay; no reabrir regla Producto. | H13: Alta | I13: M05 v1.2 · M5-V18 | J13: Aprobado
A14: M05 | B14: M5-V19 | C14: F4/F5 | D14: F2 fixture + F4 E2E | E14: Cross-contract | F14: Consume deuda/mora/presión; puede validar decisión de derivación con fixture antes del E2E. | G14: Ajustar fase/overlay; no reabrir regla Producto. | H14: Alta | I14: M05 v1.2 · M5-V19 | J14: Aprobado
A15: M05 | B15: M5-V20 | C15: F2 | D15: F3 · M02/M03 / superficie; fixture solo como prevalidación | E15: Dependencia M02 · wording corregido | F15: Consume catálogo/foco aprobado M02; el criterio de aceptación completo requiere M02. El fixture permite prevalidar la lógica, pero no sustituye el PASS F3. | G15: Mantener F3 como gate primario; usar fixture solo para prevalidación funcional y reservar la actualización/consumo real M02 para su gate correspondiente. | H15: Alta | I15: M05 v1.2 · M5-V20 | J15: Ajustado: gate primario corregido a F3; fixture queda solo como prevalidación funcional.
... A27: M06 | B27: M6-V59 | C27: F5 | D27: F1 funcional; cierre visual separado | E27: Pendiente mal tipificado | F27: Hub M06 está cerrado funcionalmente; quedan 15 ajustes Figma/evidencia, no una A5 Producto abierta. | G27: No usar F5 como espera de decisión Producto; tratar visual QA por su gate propio. | H27: Alta | I27: M06 v1.0 · PD-M6-02/08 | J27: Aprobado

Sheet 03_M04_CROSSWALK_LEGACY
A1: M04 · Crosswalk de IDs legacy usados por Miguel
A2: Preserva M4-V01…V93 sin afirmar equivalencia inexistente con los 93 Trace IDs vigentes. V87/V88 solo aparecen en el HTML; V89–V93 quedan como source gap.
A4: ID legacy Miguel | B4: Fase Miguel (HTML) | C4: Lineage localizado | D4: RN / reglas relacionadas | E4: Referencia cliente / P4 | F4: Tratamiento histórico | G4: Posible referencia vigente | H4: Estado crosswalk
A5: M4-V01 | B5: F3 | C5: Sí · matriz reconciliada histórica | D5: M4-RN-001 | E5: M04-RGL-002 | F5: Cubierta por contrato cliente | G5: Reconciliar semánticamente contra TR vigente; no identidad 1:1 | H5: LINEAGE_LOCALIZADO
A6: M4-V02 | B6: F3 | C6: Sí · matriz reconciliada histórica | D6: M4-RN-003; M4-RN-006 | E6: M04-RGL-003; M04-RGL-012; P4-CNT-001; P4-CNT-018 | F6: Cubierta con precisión adicional del cliente; Cubierta por contrato cliente | G6: Reconciliar semánticamente contra TR vigente; no identidad 1:1 | H6: LINEAGE_LOCALIZADO
A7: M4-V03 | B7: F3 | C7: Sí · matriz reconciliada histórica | D7: M4-RN-005; M4-RN-014 | E7: M04-RGL-006; M04-RGL-007; P4-CNT-016; M04-RGL-007 | F7: Cubierta con precisión adicional del cliente; Cubierta por contrato cliente | G7: Reconciliar semánticamente contra TR vigente; no identidad 1:1 | H7: LINEAGE_LOCALIZADO
A8: M4-V04 | B8: F3 | C8: Sí · matriz reconciliada histórica | D8: M4-RN-004; M4-RN-006 | E8: M04-RGL-012; P4-CNT-001; P4-CNT-018; M04-RGL-014; P4-CNT-018; P4-CNT-019 | F8: Cubierta con precisión adicional del cliente; Reemplazada por definición cliente | G8: Reconciliar semánticamente contra TR vigente; no identidad 1:1 | H8: LINEAGE_LOCALIZADO
A9: M4-V05 | B9: F1 | C9: Sí · matriz reconciliada histórica | D9: M4-RN-017; M4-RN-042 | E9: 01_Matriz_Trazabilidad · materialización OD/DD/RD; 06_Ajustes_Materializacion; M04-RGL-015; M04-RGL-038; P4-CNT-007; P4-CNT-016 | F9: Cubierta con precisión adicional del cliente; Reemplazada por definición cliente | G9: Reconciliar semánticamente contra TR vigente; no identidad 1:1 | H9: LINEAGE_LOCALIZADO
A10: M4-V06 | B10: F1 | C10: Sí · matriz reconciliada histórica | D10: M4-RN-017; M4-RN-018 | E10: M04-RGL-014; M04-RGL-015; P4-CNT-001; P4-CNT-018; M04-RGL-015; M04-RGL-038; P4-CNT-007; P4-CNT-016 | F10: Reemplazada por definición cliente | G10: Reconciliar semánticamente contra TR vigente; no identidad 1:1 | H10: LINEAGE_LOCALIZADO
A11: M4-V07 | B11: F1 | C11: Sí · matriz reconciliada histórica | D11: M4-RN-001; M4-RN-004 | E11: M04-RGL-002; M04-RGL-014; P4-CNT-018; P4-CNT-019 | F11: Cubierta por contrato cliente; Reemplazada por definición cliente | G11: Reconciliar semánticamente contra TR vigente; no identidad 1:1 | H11: LINEAGE_LOCALIZADO
A12: M4-V08 | B12: F1 | C12: Sí · matriz reconciliada histórica | D12: M4-RN-002 | E12: M04-RGL-002; M04-RGL-039 | F12: Cubierta con precisión adicional del cliente | G12: Reconciliar semánticamente contra TR vigente; no identidad 1:1 | H12: LINEAGE_LOCALIZADO
A13: M4-V09 | B13: F1 | C13: Sí · matriz reconciliada histórica | D13: M4-RN-002; M4-RN-004 | E13: M04-RGL-002; M04-RGL-039; M04-RGL-014; P4-CNT-018; P4-CNT-019 | F13: Cubierta con precisión adicional del cliente; Reemplazada por definición cliente | G13: Reconciliar semánticamente contra TR vigente; no identidad 1:1 | H13: LINEAGE_LOCALIZADO
A14: M4-V10 | B14: F1 | C14: Sí · matriz reconciliada histórica | D14: M4-RN-003; M4-RN-005 | E14: M04-RGL-003; M04-RGL-006; M04-RGL-007; P4-CNT-016 | F14: Cubierta con precisión adicional del cliente; Cubierta por contrato cliente | G14: Reconciliar semánticamente contra TR vigente; no identidad 1:1 | H14: LINEAGE_LOCALIZADO
A15: M4-V11 | B15: F1 | C15: Sí · matriz reconciliada histórica | D15: M4-RN-006 | E15: M04-RGL-012; P4-CNT-001; P4-CNT-018 | F15: Cubierta con precisión adicional del cliente | G15: Reconciliar semánticamente contra TR vigente; no identidad 1:1 | H15: LINEAGE_LOCALIZADO
... A90: M4-V86 | B90: F5 | C90: Sí · matriz reconciliada histórica | D90: M4-RN-018; M4-RN-050 | E90: M04-RGL-014; M04-RGL-015; P4-CNT-001; P4-CNT-018; P4-CNT-001; P4-CNT-008; M04-RGL-039 | F90: Reemplazada por definición cliente | G90: Reconciliar semánticamente contra TR vigente; no identidad 1:1 | H90: LINEAGE_LOCALIZADO
A91: M4-V87 | B91: F1/F5 DUPLICADO | C91: Solo HTML Miguel · “Entrada directa / reingreso” | G91: TR-M04-130 / TR-M04-131 · coincidencia semántica probable, NO identidad demostrada | H91: HTML_ONLY
A92: M4-V88 | B92: F1/F5 DUPLICADO | C92: Solo HTML Miguel · “Entrada directa / reingreso” | G92: TR-M04-130 / TR-M04-131 · coincidencia semántica probable, NO identidad demostrada | H92: HTML_ONLY
A93: M4-V89 | B93: NO ASIGNADO | C93: No localizado en fuentes revisadas | G93: TR-M04-132…136 existen como obligaciones vigentes, pero NO hay mapeo explícito a V89–V93 | H93: SIN_FUENTE
A94: M4-V90 | B94: NO ASIGNADO | C94: No localizado en fuentes revisadas | G94: TR-M04-132…136 existen como obligaciones vigentes, pero NO hay mapeo explícito a V89–V93 | H94: SIN_FUENTE
A95: M4-V91 | B95: NO ASIGNADO | C95: No localizado en fuentes revisadas | G95: TR-M04-132…136 existen como obligaciones vigentes, pero NO hay mapeo explícito a V89–V93 | H95: SIN_FUENTE
A96: M4-V92 | B96: NO ASIGNADO | C96: No localizado en fuentes revisadas | G96: TR-M04-132…136 existen como obligaciones vigentes, pero NO hay mapeo explícito a V89–V93 | H96: SIN_FUENTE
A97: M4-V93 | B97: NO ASIGNADO | C97: No localizado en fuentes revisadas | G97: TR-M04-132…136 existen como obligaciones vigentes, pero NO hay mapeo explícito a V89–V93 | H97: SIN_FUENTE

Sheet 04_FASES_Y_GATES
A1: Modelo operativo de fases y gates
A2: Una variante puede pasar un gate funcional y volver a ejecutarse en un gate E2E/regresión. F4/F5 no deben volver a contarse como nuevos IDs.
A4: Gate | B4: Objetivo | C4: Prerequisito | D4: Qué puede certificar QA | E4: Qué NO certifica | F4: Resultado permitido | G4: Ejemplo | H4: Regla operativa
A5: F1 · QA funcional local | B5: Validar lógica owner-local y payloads producidos. | C5: Release contiene comportamiento del módulo + datos locales/fixtures propios. | D5: Regla, estado, CTA, lifecycle, guardrail, payload producer. | E5: Entrega/consumo real por otro módulo. | F5: PASS_FUNCIONAL_LOCAL | G5: M6-V42 produce evento M05; se valida payload sin esperar M05. | H5: Output downstream NO es dependencia de entrada.
A6: F2 · Fixture cross-contract | B6: Validar consumidor usando contrato upstream cerrado. | C6: Contrato upstream determinista + fixture/oráculo versionado. | D6: Interpretación, cálculo y bordes del consumidor. | E6: Transporte/producer runtime real. | F6: PASS_FUNCIONAL_CONTRATO | G6: M04 consume headroom M05; inyectar POSITIVE/ZERO/NOT_EVALUABLE. | H6: Fixture debe reproducir exactamente el contrato owner.
A7: F3 · M02/M03 / superficie | B7: Validar Home, Perfil, avisos/canales y prioridad/superficie. | C7: M02/M03/superficie disponible en ambiente QA; producer payload válido. | D7: Representación, CTA, canal/permisos, dedupe/surface según contrato. | E7: Integraciones M04↔M05↔M06 no relacionadas. | F7: PASS_SUPERFICIE | G7: M6-V39 candidato Home; M03 decide superficie. | H7: El productor puede tener PASS previo; la superficie no.
A8: F4 · E2E real | B8: Confirmar integración real entre owners. | C8: Producer y consumer reales, contrato/versiones alineados, ambiente. | D8: Transporte, idempotencia, dedupe, propagación y consumo real. | E8: Regresión total del producto. | F8: PASS_INTEGRACION_E2E | G8: M06 payment/cycle → M04 D/aging; M05 headroom → M04 K. | H8: Reejecuta IDs ya probados; no crea una nueva bolsa.
A9: F5 · Regresión final | B9: Proteger release candidato y journeys críticos. | C9: F1-F4 aplicables cerrados o residual explícitamente aceptado. | D9: Smoke contractual + journeys completos de mayor riesgo. | E9: No reabre Producto ni reemplaza QA de fase anterior. | F9: PASS_REGRESION_RELEASE | G9: Carga → evaluación → Ruta → pago → recálculo → Home/Perfil. | H9: Selección por riesgo; conservar trazabilidad al ID original.

Sheet 05_FUENTES
A1: Fuentes y autoridad
A2: Las fuentes finales gobiernan la semántica actual. Historial y conciliación explican lineage/supersession; el HTML de Miguel es una propuesta a evaluar.
A4: Fuente | B4: Rol | C4: Autoridad en este análisis | D4: Uso | E4: URL / ruta | F4: Nota
A5: plan_fases_qa_pmo.html | B5: Propuesta Kabeli/PMO | C5: No autoritativa | D5: Fases Miguel, conteos, exclusiones y preguntas PMO | E5: Adjunto conversación: plan_fases_qa_pmo.html | F5: El footer menciona matriz_fase01.csv, pero ese archivo separado no está adjunto.
A6: Walvy_M04_Matriz_Trazabilidad_Cliente_v1.3.xlsx | B6: Contrato vigente M04 | C6: Alta | D6: 93 Trace IDs TR-M04-044…136; owner/dependencias/criterios | E6: Dentro de Entrega_Kabeli_2.0_M04_v1.3_FINAL(2).zip | F6: ID vigente M04 = Trace ID, no M4-V.
A7: Walvy_M5_Matriz_Trazabilidad_Cliente_v1.2_RESPUESTA_WALVY.xlsx | B7: Contrato vigente M05 | C7: Alta | D7: 34 variantes M5-V01…V34 | E7: Dentro de Entrega_Kabeli_2.0_M05_v1.2_FINAL(1).zip | F7: Preservar owner M05 del outcome prudencial.
A8: Walvy_M6_Matriz_Trazabilidad_Cliente_v1.0_RESPUESTA_WALVY.xlsx | B8: Contrato vigente M06 | C8: Alta | D8: 59 variantes M6-V01…V59 | E8: Dentro de Walvy_M06_Entrega_Kabeli_v1.0(4).zip | F8: R18 lineage interno; externo M06 v1.0.
A9: M02_M03_M04_M05_M06_Matriz_Transversal_v1.1.csv | B9: Contrato transversal M02 | C9: Alta en su dominio | D9: Canales/preferencias/consumidores M02-M03 | E9: Dentro de Entrega_Kabeli_2.0_M02_v1.1_20260915(3).zip | F9: No trasladar ownership productor a M02.
A10: M06_M03_M02_Matriz_Transversal_v1.0.csv | B10: Contrato transversal M06 | C10: Alta en su dominio | D10: Producer/consumer, E2E, avisos/Home/Perfil | E10: Dentro de Walvy_M06_Entrega_Kabeli_v1.0(4).zip | F10: Clave para distinguir output vs input.
A11: Walvy_M04_M05_M06_Conciliacion_Respuesta_Walvy_v1.0.xlsx | B11: Conciliación transversal | C11: Alta para delta/provenance | D11: 57 deltas, cambio de owner, explicitación, supersession | E11: https://edificateinteligente.sharepoint.com/sites/DesarrollodeProductos-Servicios/Shared%20Documents/General/Desarrollo%20app%20Kabeli/01%20Entrega%20de%20Modulos%20-%20Kabeli/Reconciliaci%C3%B3n%20M04-M06/v1.0/Walvy_M04_M05_M06_Conciliacion_Respuesta_Walvy_v1.0.xlsx?web=1 | F11: No sustituye universos completos.
A12: Walvy_M04_Matriz_Reconciliada_Producto_v1.0_respuesta.xlsx | B12: Lineage M04 legacy | C12: Histórica / soporte | D12: Mapeo M4-V01…V86 a RN/reglas reconciliadas | E12: SharePoint Construyendo M04 / archivo histórico | F12: No usar para inventar V87–V93 ni superseder v1.3.
A13: Outlook · metodología releases 2026-09-15 | B13: Operación QA | C13: Alta operativa | D13: PR → main → release explícito → TestFlight/Play Internal → QA | E13: Outlook: RE: Entrega Módulo 2 _ 02092026 | F13: Merge main no cambia automáticamente app en prueba.

Sheet 06_QA_ZERO_TRUST
A1: QA Zero Trust del plan
A2: Controles de integridad del workbook y falsificación explícita del esquema de fases.
A4: Control | B4: Fórmula / evidencia | C4: Esperado | D4: Resultado | E4: Estado | F4: Tratamiento
A5: Universo total | B5: =COUNTA('01_MATRIZ_OPERATIVA_186'!$B$5:$B$190) | C5: 186 | D5: =B5 | E5: =IF(D5=C5,"PASS","FAIL") | F5: Debe existir exactamente una fila vigente por unidad contractual.
A6: IDs duplicados | B6: =MAX('01_MATRIZ_OPERATIVA_186'!$R$5:$R$190) | C6: 1 | D6: =B6 | E6: =IF(D6=C6,"PASS","FAIL") | F6: Cualquier valor >1 bloquea.
A7: M04 vigente | B7: =COUNTIF('01_MATRIZ_OPERATIVA_186'!$A$5:$A$190,"M04") | C7: 93 | D7: =B7 | E7: =IF(D7=C7,"PASS","FAIL") | F7: 93 Trace IDs vigentes.
A8: M05 vigente | B8: =COUNTIF('01_MATRIZ_OPERATIVA_186'!$A$5:$A$190,"M05") | C8: 34 | D8: =B8 | E8: =IF(D8=C8,"PASS","FAIL") | F8: 34 variantes.
A9: M06 vigente | B9: =COUNTIF('01_MATRIZ_OPERATIVA_186'!$A$5:$A$190,"M06") | C9: 59 | D9: =B9 | E9: =IF(D9=C9,"PASS","FAIL") | F9: 59 variantes.
A10: Partición primaria F1/F2/F3 | B10: =COUNTIF('01_MATRIZ_OPERATIVA_186'!$H$5:$H$190,"F1*")+COUNTIF('01_MATRIZ_OPERATIVA_186'!$H$5:$H$190,"F2*")+COUNTIF('01_MATRIZ_OPERATIVA_186'!$H$5:$H$190,"F3*") | C10: 186 | D10: =B10 | E10: =IF(D10=C10,"PASS","FAIL") | F10: Cada unidad tiene exactamente un primer gate de PASS.
A11: M04 legacy sin fuente | B11: =COUNTIF('03_M04_CROSSWALK_LEGACY'!$H$5:$H$97,"SIN_FUENTE") | C11: 5 | D11: =B11 | E11: =IF(D11=C11,"PASS","FAIL") | F11: V89–V93 quedan como gap; no inventar.
A12: M04 legacy HTML-only | B12: =COUNTIF('03_M04_CROSSWALK_LEGACY'!$H$5:$H$97,"HTML_ONLY") | C12: 2 | D12: =B12 | E12: =IF(D12=C12,"PASS","FAIL") | F12: V87–V88 no se promocionan a identidad contractual por inferencia.
A13: Output ≠ input dependency | B13: Revisión semántica M6-V42–V47 | C13: F1 producer + F4 E2E | D13: Ver 02_EXCEPCIONES_MIGUEL | E13: =IF(COUNTIF('02_EXCEPCIONES_MIGUEL'!$B:$B,"M6-V42–V47")=1,"PASS","FAIL") | F13: Evita congelar productor por dependencia downstream.
A14: Runtime/E2E no declarado | B14: Este workbook es plan documental/funcional | C14: NO PASS runtime | D14: No evaluado | E14: =IF(D14="No evaluado","PASS","FAIL") | F14: No transformar contrato/documento en evidencia de ejecución.
A15: Revisión excepciones v1.1 | B15: =COUNTA('02_EXCEPCIONES_MIGUEL'!$J$5:$J$27) | C15: 23 | D15: =B15 | E15: =IF(D15=C15,"PASS","FAIL") | F15: Las 23 excepciones deben quedar con revisión explícita.
A16: Ajustes realizados v1.1 | B16: =COUNTIF('02_EXCEPCIONES_MIGUEL'!$J$5:$J$27,"Ajustado*") | C16: 1 | D16: =B16 | E16: =IF(D16=C16,"PASS","FAIL") | F16: Único ajuste material del reverse-check: M5-V20; no modifica 186 ni 122/41/23.

Sheet 07_PASOS_EJECUCION_APP
A1: Plan QA · Pasos de Ejecución App · M04/M05/M06 — Walvy_Plan_QA_Fases v1.1
A2: M04: pasos extraídos de M4_Pasos_Ejecucion_App_v0.2 (mapeado por índice secuencial dentro del flujo). M05/M06: pasos derivados de la Matriz de Trazabilidad. ID rector M04 = TR-M04-NNN (no usar M4-V). Columnas M-O para completar por QA.
A3: Módulo | B3: ID vigente | C3: Gate PMO | D3: Flujo / Subflujo | E3: Variante / Escenario | F3: Condición de entrada | G3: Precondición / Estado inicial | H3: Pasos de Ejecución App | I3: Dónde verificar | J3: Resultado esperado | K3: Datos de prueba / Fixture | L3: Ejecutable hoy | M3: Resultado obtenido | N3: Estado QA | O3: Notas QA | P3: Oráculo / ID fuente | Q3: Assertion concreta
A4: M04 | B4: TR-M04-044 | C4: F3 · M02/M03 / superficie | D4: FLOW-M04-001 · Entrada contextual | E4: Existe candidato/proyección M04 accionable ya resuelto por el módulo dueño; Home solo consume el contrato. | F4: Home | CTA contextual | G4: Cuenta de prueba activa y reseteada (sin deudas ni datos previos del flujo). Condición de entrada: Home | CTA contextual | H4: Seguir flujo de FLOW-M04-001 · Entrada contextual. CIERRE · Registrar resultado en columna «Resultado obtenido» y marcar «Estado QA». · Resetear solo si el siguiente caso requiere estado inicial incompatible con el actual. Casos del mismo flujo pueden reutilizar el estado. (Ajustes → Borrar mis datos · o solicitar reset al admin de QA) | I4: Pantalla activa de Ruta Despeje. | J4: Home representa el candidato M04 y deriva a su destino sin recalcular estado, reason ni Ruta; la selección del ganador global queda fuera de M04. | K4: Ambiente con Home/Perfil (M03) disponible. Producer payload válido de M04. | L4: No · requiere env | P4: Walvy_M04_Matriz_Trazabilidad_Cliente_v1.3.xlsx · 01_Matriz_Trazabilidad · TR-M04-044 | Q4: En: Pantalla activa de Ruta Despeje. → Home representa el candidato M04 y deriva a su destino sin recalcular estado, reason ni Ruta; la selección del ganador global queda fuera de M04.
A5: M04 | B5: TR-M04-045 | C5: F3 · M02/M03 / superficie | D5: FLOW-M04-001 · Entrada contextual | E5: Señal corresponde a pago próximo/al día/vencimiento simple con capacidad | F5: Home | CTA contextual | G5: Cuenta de prueba activa y reseteada (sin deudas ni datos previos del flujo). Condición de entrada: Home | CTA contextual | H5: Seguir flujo de FLOW-M04-001 · Entrada contextual. CIERRE · Registrar resultado en columna «Resultado obtenido» y marcar «Estado QA». · Resetear solo si el siguiente caso requiere estado inicial incompatible con el actual. Casos del mismo flujo pueden reutilizar el estado. (Ajustes → Borrar mis datos · o solicitar reset al admin de QA) | I5: Pantalla activa de Ruta Despeje. | J5: Home deriva a M06/Pagos-Alertas; no a Ruta. | K5: Ambiente con Home/Perfil (M03) disponible. Producer payload válido de M04. | L5: No · requiere env | P5: Walvy_M04_Matriz_Trazabilidad_Cliente_v1.3.xlsx · 01_Matriz_Trazabilidad · TR-M04-045 | Q5: En: Pantalla activa de Ruta Despeje. → Home deriva a M06/Pagos-Alertas; no a Ruta.
A6: M04 | B6: TR-M04-046 | C6: F3 · M02/M03 / superficie | D6: FLOW-M04-001 · Entrada contextual | E6: Existe deuda confirmada con faltante material accionable; si aún no está confirmada, precede F2. | F6: Home | Completar | G6: Cuenta de prueba activa y reseteada (sin deudas ni datos previos del flujo). Condición de entrada: Home | Completar | H6: Seguir flujo de FLOW-M04-001 · Entrada contextual. CIERRE · Registrar resultado en columna «Resultado obtenido» y marcar «Estado QA». · Resetear solo si el siguiente caso requiere estado inicial incompatible con el actual. Casos del mismo flujo pueden reutilizar el estado. (Ajustes → Borrar mis datos · o solicitar reset al admin de QA) | I6: Pantalla activa de Ruta Despeje. | J6: Proyectar F1/completitud hacia revisión; no plan activo. Consolidar pendings de calidad por deuda y preservar reasons secundarios. | K6: Ambiente con Home/Perfil (M03) disponible. Producer payload válido de M04. | L6: No · requiere env | P6: Walvy_M04_Matriz_Trazabilidad_Cliente_v1.3.xlsx · 01_Matriz_Trazabilidad · TR-M04-046 | Q6: En: Pantalla activa de Ruta Despeje. → Proyectar F1/completitud hacia revisión; no plan activo. Consolidar pendings de calidad por deuda y preservar reasons secundarios.
A7: M04 | B7: TR-M04-047 | C7: F3 · M02/M03 / superficie | D7: FLOW-M04-001 · Entrada contextual | E7: Existe estado/proyección M04 consumible por Perfil (Salud, Ruta, calidad u orientación permitida). | F7: Perfil Financiero | CTA/lectura contextual | G7: Cuenta de prueba activa y reseteada (sin deudas ni datos previos del flujo). Condición de entrada: Perfil Financiero | CTA/lectura contextual | H7: Seguir flujo de FLOW-M04-001 · Entrada contextual. CIERRE · Registrar resultado en columna «Resultado obtenido» y marcar «Estado QA». · Resetear solo si el siguiente caso requiere estado inicial incompatible con el actual. Casos del mismo flujo pueden reutilizar el estado. (Ajustes → Borrar mis datos · o solicitar reset al admin de QA) | I7: Pantalla activa de Ruta Despeje. | J7: Perfil representa estado/CTA compacto heredado del owner M04; no recalcula ni crea state machine o señal paralela. | K7: Ambiente con Home/Perfil (M03) disponible. Producer payload válido de M04. | L7: No · requiere env | P7: Walvy_M04_Matriz_Trazabilidad_Cliente_v1.3.xlsx · 01_Matriz_Trazabilidad · TR-M04-047 | Q7: En: Pantalla activa de Ruta Despeje. → Perfil representa estado/CTA compacto heredado del owner M04; no recalcula ni crea state machine o señal paralela.
A8: M04 | B8: TR-M04-048 | C8: F1 · QA funcional local | D8: FLOW-M04-002 · Onboarding 1 · Carga | E8: Usuario selecciona documento de deuda permitido | F8: OD-01 Agrega tus deudas | Cargar documentos | G8: Cuenta de prueba activa y reseteada (sin deudas ni datos previos del flujo). Condición de entrada: OD-01 Agrega tus deudas | Cargar documentos | H8: 1. Iniciar sesión con la cuenta de prueba reseteada. 2. Navegar a: Módulo M04 → OD-01 «Agrega tus deudas» → pantalla de carga de documentos. 3. Tocar «Cargar documento» y seleccionar un archivo permitido (PDF, XLSX o CSV de estado de cuenta). 4. Confirmar que la app acepta el archivo y muestra pantalla de análisis / spinner de procesamiento. 5. Verificar que el estado muestra «procesando» y que NO aparece ninguna deuda confirmada todavía. → Si hay spinner de análisis y cero deudas confirmadas: ✓ PASA. CIERRE · Registrar resultado en «Resultado obtenido» y marcar «Estado QA». · Resetear cuenta solo si el siguiente caso requiere estado diferente al actual. (Perfil → Herramientas QA → «Reiniciar cuenta de prueba» (doble confirmación)) | I8: Pantalla activa de Ruta Despeje. | J8: El archivo entra a procesamiento documental manual y queda pendiente hasta lectura/revisión. | L8: Sí | P8: Walvy_M04_Matriz_Trazabilidad_Cliente_v1.3.xlsx · 01_Matriz_Trazabilidad · TR-M04-048 | Q8: En: Pantalla activa de Ruta Despeje. → El archivo entra a procesamiento documental manual y queda pendiente hasta lectura/revisión.
A9: M04 | B9: TR-M04-049 | C9: F1 · QA funcional local | D9: FLOW-M04-002 · Onboarding 1 · Carga | E9: Archivo es Informe de Deudas CMF cargado manualmente | F9: OD-01 Agrega tus deudas | Cargar documentos | G9: Cuenta de prueba activa y reseteada (sin deudas ni datos previos del flujo). Condición de entrada: OD-01 Agrega tus deudas | Cargar documentos | H9: 1. Iniciar sesión con la cuenta de prueba reseteada. 2. Navegar a: OD-01 «Agrega tus deudas» → pantalla de carga de documentos. 3. Seleccionar un archivo que sea un Informe de Deudas CMF (PDF descargado del sitio CMF o equivalente). 4. Subir el archivo y observar el flujo de procesamiento. 5. Verificar que la app lo trata igual que cualquier documento manual (misma pantalla de análisis). 6. Verificar que NO aparece ningún indicador de «sincronización CMF», «conexión CMF/SFA» ni flujo automático externo. → Si el flujo es idéntico al de un PDF normal y no hay mención de sincronización: ✓ PASA. CIERRE · Registrar resultado en «Resultado obtenido» y marcar «Estado QA». · Resetear cuenta solo si el siguiente caso requiere estado diferente al actual. (Perfil → Herramientas QA → «Reiniciar cuenta de prueba» (doble confirmación)) | I9: Pantalla activa de Ruta Despeje. | J9: Se trata como documento manual bajo las mismas reglas de ingesta; no inicia conexión/consulta/sincronización CMF/SFA. | L9: Sí | P9: Walvy_M04_Matriz_Trazabilidad_Cliente_v1.3.xlsx · 01_Matriz_Trazabilidad · TR-M04-049 | Q9: En: Pantalla activa de Ruta Despeje. → Se trata como documento manual bajo las mismas reglas de ingesta; no inicia conexión/consulta/sincronización CMF/SFA.
A10: M04 | B10: TR-M04-050 | C10: F1 · QA funcional local | D10: FLOW-M04-002 · Onboarding 1 · Carga | E10: Procesamiento aún no termina | F10: Procesamiento documental | Estado de procesamiento | G10: Cuenta de prueba activa y reseteada (sin deudas ni datos previos del flujo). Condición de entrada: Procesamiento documental | Estado de procesamiento | H10: 1. Iniciar sesión con la cuenta de prueba reseteada. 2. Subir un documento (puede reutilizar el de TR-M04-048 o TR-M04-049). 3. Mientras el procesamiento está en curso (CaptureAnalyzingScreen / spinner), salir de la pantalla (navegar atrás o enviar la app al background) y volver a ingresar. 4. Verificar que la app muestra que el procesamiento sigue en curso (no reinició desde cero). 5. Verificar que NO se generó ninguna deuda confirmada ni se activó la Ruta mientras el estado era «processing». → Si el estado vuelve a «procesando» y no hay deudas: ✓ PASA. CIERRE · Registrar resultado en «Resultado obtenido» y marcar «Estado QA». · Resetear cuenta solo si el siguiente caso requiere estado diferente al actual. (Perfil → Herramientas QA → «Reiniciar cuenta de prueba» (doble confirmación)) | I10: Pantalla activa de Ruta Despeje. | J10: Mantener processing pending; no producir deuda confirmada ni Ruta completa. | L10: Sí | P10: Walvy_M04_Matriz_Trazabilidad_Cliente_v1.3.xlsx · 01_Matriz_Trazabilidad · TR-M04-050 | Q10: En: Pantalla activa de Ruta Despeje. → Mantener processing pending; no producir deuda confirmada ni Ruta completa.
A11: M04 | B11: TR-M04-051 | C11: F1 · QA funcional local | D11: FLOW-M04-003 · Onboarding 1 · Carga | E11: Registro manual formal con campos de registro básico | F11: OD-01 / sheet deuda manual | Guardar deuda | G11: Cuenta de prueba activa y reseteada (sin deudas ni datos previos del flujo). Condición de entrada: OD-01 / sheet deuda manual | Guardar deuda | H11: 1. Iniciar sesión con la cuenta de prueba reseteada. 2. Navegar a: OD-01 «Agrega tus deudas» → opción «Ingresar manualmente». 3. Rellenar todos los campos del formulario de alta manual: - Tipo de deuda (ej: tarjeta_credito) - Acreedor / institución - Saldo actual - Cuota mensual mínima - Fecha de vencimiento próxima 4. Tocar «Guardar» (o equivalente). 5. Verificar que la deuda aparece en la lista con estado confirmado. 6. Verificar que el sistema reevalúa la completitud (no queda como «falta dato crítico»). → Si la deuda queda confirmada y completa: ✓ PASA. CIERRE · Registrar resultado en «Resultado obtenido» y marcar «Estado QA». · Resetear cuenta solo si el siguiente caso requiere estado diferente al actual. (Perfil → Herramientas QA → «Reiniciar cuenta de prueba» (doble confirmación)) | I11: Pantalla activa de Ruta Despeje. | J11: Guardar la deuda declarada manualmente y marcarla como confirmada respecto de su existencia/pertenencia; reevaluar la completitud de forma independiente. El registro no implica Presion ni Ruta. | L11: Sí | P11: Walvy_M04_Matriz_Trazabilidad_Cliente_v1.3.xlsx · 01_Matriz_Trazabilidad · TR-M04-051 | Q11: En: Pantalla activa de Ruta Despeje. → Guardar la deuda declarada manualmente y marcarla como confirmada respecto de su existencia/pertenencia; reevaluar la completitud de forma independiente. El registro no implica Presion ni Ruta.
A12: M04 | B12: TR-M04-052 | C12: F1 · QA funcional local | D12: FLOW-M04-003 · Onboarding 1 · Carga | E12: Registro es préstamo personal o compromiso informal con monto/frecuencia | F12: OD-01 / sheet deuda manual | Guardar deuda | G12: Cuenta de prueba activa y reseteada (sin deudas ni datos previos del flujo). Condición de entrada: OD-01 / sheet deuda manual | Guardar deuda | H12: 1. Iniciar sesión con la cuenta de prueba reseteada. 2. Navegar a: OD-01 «Agrega tus deudas» → opción «Ingresar manualmente». 3. Seleccionar tipo de deuda informal (ej: préstamo_informal, compromiso_personal o similar). 4. Ingresar acreedor (persona o apodo) y monto/frecuencia (ej: $80.000 quincenales). 5. Guardar la deuda. 6. Verificar que se guarda sin mensajes estigmatizantes y aparece en la lista junto a las demás deudas. 7. Verificar que la presión financiera la evalúa con las mismas reglas que cualquier otra deuda. → Si se guarda correctamente y sin trato diferenciado: ✓ PASA. CIERRE · Registrar resultado en «Resultado obtenido» y marcar «Estado QA». · Resetear cuenta solo si el siguiente caso requiere estado diferente al actual. (Perfil → Herramientas QA → «Reiniciar cuenta de prueba» (doble confirmación)) | I12: Pantalla activa de Ruta Despeje. | J12: Guardar como deuda manual/informal sin tratamiento estigmatizante; evaluar luego según mismas reglas de presión. | L12: Sí | P12: Walvy_M04_Matriz_Trazabilidad_Cliente_v1.3.xlsx · 01_Matriz_Trazabilidad · TR-M04-052 | Q12: En: Pantalla activa de Ruta Despeje. → Guardar como deuda manual/informal sin tratamiento estigmatizante; evaluar luego según mismas reglas de presión.
A13: M04 | B13: TR-M04-053 | C13: F1 · QA funcional local | D13: FLOW-M04-003 · Onboarding 1 · Carga | E13: Faltan datos para presión/Ruta | F13: OD-01 / sheet deuda manual | Guardar deuda | G13: Cuenta de prueba activa y reseteada (sin deudas ni datos previos del flujo). Condición de entrada: OD-01 / sheet deuda manual | Guardar deuda | H13: 1. Iniciar sesión con la cuenta de prueba reseteada. 2. Navegar a: OD-01 «Agrega tus deudas» → opción «Ingresar manualmente». 3. Ingresar solo los datos mínimos posibles (ej: acreedor y saldo; omitir cuota y fecha de vencimiento). 4. Guardar la deuda. 5. Verificar que la deuda se guarda con estado confirmado (en cuanto a existencia), pero marcada como incompleta para presión/Ruta (muestra indicador de dato faltante). 6. Verificar que la Ruta NO se activa ni la presión se calcula errónea por datos ausentes. → Si la deuda queda confirmada-pero-incompleta y la Ruta no se activa: ✓ PASA. CIERRE · Registrar resultado en «Resultado obtenido» y marcar «Estado QA». · Resetear cuenta solo si el siguiente caso requiere estado diferente al actual. (Perfil → Herramientas QA → «Reiniciar cuenta de prueba» (doble confirmación)) | I13: Pantalla activa de Ruta Despeje. | J13: Conservar la deuda manual como confirmada respecto de su existencia/pertenencia, pero pendiente/incompleta para el uso afectado; no evaluar presion fuerte, priorizacion ni cronograma mientras falten datos materiales requeridos. | L13: Sí | P13: Walvy_M04_Matriz_Trazabilidad_Cliente_v1.3.xlsx · 01_Matriz_Trazabilidad · TR-M04-053 | Q13: En: Pantalla activa de Ruta Despeje. → Conservar la deuda manual como confirmada respecto de su existencia/pertenencia, pero pendiente/incompleta para el uso afectado; no evaluar presion fuerte, priorizacion ni cronograma mientras falten datos materiales requeridos.
A14: M04 | B14: TR-M04-054 | C14: F1 · QA funcional local | D14: FLOW-M04-004 · Onboarding 1 · Documento protegido | E14: Documento está protegido con contraseña | F14: Carga documental | Detectar protección | G14: Cuenta de prueba activa y reseteada (sin deudas ni datos previos del flujo). Condición de entrada: Carga documental | Detectar protección | H14: 1. Iniciar sesión con la cuenta de prueba reseteada. 2. Navegar a: OD-01 «Agrega tus deudas» → cargar documentos. 3. Subir un archivo PDF protegido con contraseña (QA debe crearlo previamente o usar fixture del equipo). 4. Verificar que la app detecta la protección y muestra estado «requiere clave» (no error genérico). 5. Verificar que el mensaje informa que el documento está protegido y ofrece una acción concreta. 6. Verificar que NO se crea ninguna deuda ni se avanza en el flujo hasta resolver la clave. → Si aparece el estado recuperable con solicitud de clave: ✓ PASA. CIERRE · Registrar resultado en «Resultado obtenido» y marcar «Estado QA». · Resetear cuenta solo si el siguiente caso requiere estado diferente al actual. (Perfil → Herramientas QA → «Reiniciar cuenta de prueba» (doble confirmación)) | I14: Pantalla activa de Ruta Despeje. | J14: Mostrar estado recuperable y solicitar clave solo cuando sea necesaria. | L14: Sí | P14: Walvy_M04_Matriz_Trazabilidad_Cliente_v1.3.xlsx · 01_Matriz_Trazabilidad · TR-M04-054 | Q14: En: Pantalla activa de Ruta Despeje. → Mostrar estado recuperable y solicitar clave solo cuando sea necesaria.
A15: M04 | B15: TR-M04-055 | C15: F1 · QA funcional local | D15: FLOW-M04-004 · Onboarding 1 · Documento protegido | E15: Clave correcta | F15: Estado requiere clave | Continuar revisión | G15: Cuenta de prueba activa y reseteada (sin deudas ni datos previos del flujo). Condición de entrada: Estado requiere clave | Continuar revisión | H15: 1. Continuar desde TR-M04-054 (app mostrando estado «requiere clave»). 2. Ingresar la clave correcta del PDF protegido. 3. Confirmar que la app desbloquea el documento y continúa con el procesamiento normal. 4. Verificar que NO se persiste la clave ingresada como atributo de la deuda (no debe aparecer en ningún campo). 5. Verificar que el flujo avanza a la pantalla de análisis como si fuera un documento normal. → Si procesa y la clave no queda guardada: ✓ PASA. CIERRE · Registrar resultado en «Resultado obtenido» y marcar «Estado QA». · Resetear cuenta solo si el siguiente caso requiere estado diferente al actual. (Perfil → Herramientas QA → «Reiniciar cuenta de prueba» (doble confirmación)) | I15: Pantalla activa de Ruta Despeje. | J15: Procesar documento y continuar a revisión; clave no se persiste como atributo de deuda. | L15: Sí | P15: Walvy_M04_Matriz_Trazabilidad_Cliente_v1.3.xlsx · 01_Matriz_Trazabilidad · TR-M04-055 | Q15: En: Pantalla activa de Ruta Despeje. → Procesar documento y continuar a revisión; clave no se persiste como atributo de deuda.
A16: M04 | B16: TR-M04-056 | C16: F1 · QA funcional local | D16: FLOW-M04-004 · Onboarding 1 · Documento protegido | E16: Clave incorrecta | F16: Estado requiere clave | Reintentar | G16: Cuenta de prueba activa y reseteada (sin deudas ni datos previos del flujo). Condición de entrada: Estado requiere clave | Reintentar | H16: 1. Continuar desde TR-M04-054 (app mostrando estado «requiere clave»). 2. Ingresar una clave incorrecta. 3. Verificar que la app muestra error de clave incorrecta y permite reintentar. 4. Verificar que el documento sigue en estado «requiere clave» (no se descarta automáticamente). 5. Verificar que NO se crea ninguna deuda ni avanza el flujo con la clave errónea. → Si permite reintento sin descartar el documento: ✓ PASA. CIERRE · Registrar resultado en «Resultado obtenido» y marcar «Estado QA». · Resetear cuenta solo si el siguiente caso requiere estado diferente al actual. (Perfil → Herramientas QA → «Reiniciar cuenta de prueba» (doble confirmación)) | I16: Pantalla activa de Ruta Despeje. | J16: Mantener recuperación; permitir reintento u otro documento sin confirmar deuda. | L16: Sí | P16: Walvy_M04_Matriz_Trazabilidad_Cliente_v1.3.xlsx · 01_Matriz_Trazabilidad · TR-M04-056 | Q16: En: Pantalla activa de Ruta Despeje. → Mantener recuperación; permitir reintento u otro documento sin confirmar deuda.
A17: M04 | B17: TR-M04-057 | C17: F1 · QA funcional local | D17: FLOW-M04-004 · Onboarding 1 · Documento protegido | E17: Usuario no dispone de clave | F17: Estado requiere clave | Alternativa | G17: Cuenta de prueba activa y reseteada (sin deudas ni datos previos del flujo). Condición de entrada: Estado requiere clave | Alternativa | H17: 1. Continuar desde TR-M04-054 (app mostrando estado «requiere clave»). 2. Sin ingresar clave, desplazarse en la pantalla de Carga: verificar que siguen visibles «Cargar más documentos» y «Agregar deuda manual». 3. Verificar que el flujo M04 NO queda bloqueado; el usuario puede continuar por otra vía sin necesidad de resolver la clave del documento protegido. 4. Seleccionar «Agregar deuda manual» o «Cargar más documentos» y verificar que navega correctamente. → Si el flujo continúa sin bloqueo usando las alternativas de la pantalla: ✓ PASA. Nota: No existe CTA «No tengo la clave». El contrato define que al pedir clave se vuelve a la pantalla de Carga, donde las alternativas ya están disponibles. CIERRE · Registrar resultado en «Resultado obtenido» y marcar «Estado QA». · Resetear cuenta solo si el siguiente caso requiere estado diferente al actual. (Perfil → Herramientas QA → «Reiniciar cuenta de prueba» (doble confirmación)) | I17: Pantalla activa de Ruta Despeje. | J17: Permitir subir otro documento o registrar manualmente; flujo M04 no queda bloqueado. | L17: Sí | P17: Walvy_M04_Matriz_Trazabilidad_Cliente_v1.3.xlsx · 01_Matriz_Trazabilidad · TR-M04-057 | Q17: En: Pantalla activa de Ruta Despeje. → Permitir subir otro documento o registrar manualmente; flujo M04 no queda bloqueado.
A18: M04 | B18: TR-M04-058 | C18: F1 · QA funcional local | D18: FLOW-M04-005 · Onboarding 1 · Error documento | E18: Documento no procesable o sin datos suficientes | F18: Carga/Analizando | Error de procesamiento | G18: Cuenta de prueba activa y reseteada (sin deudas ni datos previos del flujo). Condición de entrada: Carga/Analizando | Error de procesamiento | H18: 1. Iniciar sesión con la cuenta de prueba reseteada. 2. Navegar a: OD-01 «Agrega tus deudas» → cargar documentos. 3. Subir un archivo que no sea procesable: imagen sin texto, PDF en blanco, o archivo dañado. 4. Verificar que la app muestra un error de procesamiento (no un spinner infinito). 5. Verificar que la app ofrece alternativas: subir otro documento o registrar manualmente. 6. Verificar que NO se crea ninguna deuda confirmada ni se produce una lectura fuerte del archivo. → Si el error es explícito y ofrece alternativa sin crear deudas: ✓ PASA. CIERRE · Registrar resultado en «Resultado obtenido» y marcar «Estado QA». · Resetear cuenta solo si el siguiente caso requiere estado diferente al actual. (Perfil → Herramientas QA → «Reiniciar cuenta de prueba» (doble confirmación)) | I18: Pantalla activa de Ruta Despeje. | J18: Ofrecer otro documento o carga manual; no producir deuda confirmada ni lectura fuerte. | L18: Sí | P18: Walvy_M04_Matriz_Trazabilidad_Cliente_v1.3.xlsx · 01_Matriz_Trazabilidad · TR-M04-058 | Q18: En: Pantalla activa de Ruta Despeje. → Ofrecer otro documento o carga manual; no producir deuda confirmada ni lectura fuerte.
A19: M04 | B19: TR-M04-059 | C19: F1 · QA funcional local | D19: FLOW-M04-006 · Onboarding 2 · Revisión | E19: Deuda detectada con datos suficientes y sin confirmación | F19: OD-02 | Confirmar deuda | G19: Cuenta de prueba activa y reseteada (sin deudas ni datos previos del flujo). Condición de entrada: OD-02 | Confirmar deuda | H19: 1. Iniciar sesión con la cuenta de prueba reseteada. 2. Subir un documento válido con al menos una deuda identificable (o usar cuenta seed con deuda detectada). 3. Navegar a: OD-02 «Revisar deudas detectadas». 4. Localizar la deuda detectada (con datos suficientes: tipo, saldo, acreedor, cuota). 5. Tocar «Confirmar» en la deuda. 6. Verificar que el estado de la deuda cambia a confirmada (confirmationStatus=confirmed). 7. Verificar que confirmar la deuda NO activa automáticamente la Ruta (permanece en revisión). → Si la deuda queda confirmada y la Ruta no se activa sola: ✓ PASA. CIERRE · Registrar resultado en «Resultado obtenido» y marcar «Estado QA». · Resetear cuenta solo si el siguiente caso requiere estado diferente al actual. (Perfil → Herramientas QA → «Reiniciar cuenta de prueba» (doble confirmación)) | I19: Pantalla activa de Ruta Despeje. | J19: Cambiar confirmation_status a confirmed; mantener separación entre confirmar y activar Ruta. | L19: Sí | P19: Walvy_M04_Matriz_Trazabilidad_Cliente_v1.3.xlsx · 01_Matriz_Trazabilidad · TR-M04-059 | Q19: En: Pantalla activa de Ruta Despeje. → Cambiar confirmation_status a confirmed; mantener separación entre confirmar y activar Ruta.
A20: M04 | B20: TR-M04-060 | C20: F1 · QA funcional local | D20: FLOW-M04-007 · Onboarding 2 · Revisión | E20: Falta dato crítico identificable | F20: OD-02 | Completar información | G20: Cuenta de prueba activa y reseteada (sin deudas ni datos previos del flujo). Condición de entrada: OD-02 | Completar información | H20: 1. Iniciar sesión con la cuenta de prueba reseteada. 2. Subir documento o usar cuenta seed con deuda detectada que tenga un dato crítico faltante (ej: sin cuota mínima o sin fecha de vencimiento). 3. Navegar a: OD-02 → card de la deuda con dato faltante. 4. Verificar que la app muestra exactamente QUÉ dato falta (nombre del campo, no mensaje genérico). 5. Verificar que la app ofrece una acción concreta para completarlo (campo editable o CTA «Completar»). 6. Verificar que la validación del campo editable es coherente con el tipo de dato que falta. → Si el campo faltante está identificado con acción concreta: ✓ PASA. CIERRE · Registrar resultado en «Resultado obtenido» y marcar «Estado QA». · Resetear cuenta solo si el siguiente caso requiere estado diferente al actual. (Perfil → Herramientas QA → «Reiniciar cuenta de prueba» (doble confirmación)) | I20: Pantalla activa de Ruta Despeje. | J20: Mostrar exactamente que dato falta y una accion concreta de completitud; separar tipo/origen/validacion y conservar cualquier dato parcial valido ya declarado. Un derivado no calculable no autoriza a descartar el dato fuente. | L20: Sí | P20: Walvy_M04_Matriz_Trazabilidad_Cliente_v1.3.xlsx · 01_Matriz_Trazabilidad · TR-M04-060 | Q20: En: Pantalla activa de Ruta Despeje. → Mostrar exactamente que dato falta y una accion concreta de completitud; separar tipo/origen/validacion y conservar cualquier dato parcial valido ya declarado. Un derivado no calculable no autoriza a descartar el dato fuente.
A21: M04 | B21: TR-M04-061 | C21: F2 · Fixture cross-contract | D21: FLOW-M04-007 · Onboarding 2 · Revisión | E21: Usuario completa dato crítico | F21: Sheet completar | Guardar | G21: Cuenta de prueba activa y reseteada (sin deudas ni datos previos del flujo). Condición de entrada: Sheet completar | Guardar | H21: Seguir flujo de FLOW-M04-007 · Onboarding 2 · Revisión. CIERRE · Registrar resultado en columna «Resultado obtenido» y marcar «Estado QA». · Resetear solo si el siguiente caso requiere estado inicial incompatible con el actual. Casos del mismo flujo pueden reutilizar el estado. (Perfil → Herramientas QA → «Reiniciar cuenta de prueba» (doble confirmación)) | I21: Pantalla activa de Ruta Despeje. | J21: Persistir dato y reevaluar frescura, completitud y el contrato P4; si el gate queda completo, dejar Ruta elegible sin activarla. | K21: Fixture sintético (no requiere documento real). Formato: CSV o XLSX con los valores del contrato P4 upstream cerrado. Inyectar al menos: POSITIVE · ZERO · NOT_EVALUABLE. | L21: Sí · con insumo dev | P21: Walvy_M04_Matriz_Trazabilidad_Cliente_v1.3.xlsx · 01_Matriz_Trazabilidad · TR-M04-061 | Q21: En: Pantalla activa de Ruta Despeje. → Persistir dato y reevaluar frescura, completitud y el contrato P4; si el gate queda completo, dejar Ruta elegible sin activarla.
A22: M04 | B22: TR-M04-062 | C22: F1 · QA funcional local | D22: FLOW-M04-007 · Onboarding 2 · Revisión | E22: Usuario no conoce dato crítico | F22: OD-02 | Guardar pendiente | G22: Cuenta de prueba activa y reseteada (sin deudas ni datos previos del flujo). Condición de entrada: OD-02 | Guardar pendiente | H22: 1. Iniciar sesión con la cuenta de prueba reseteada. 2. Subir documento o usar cuenta seed con deuda detectada con dato crítico faltante. 3. Navegar a: OD-02 → card de la deuda → tocar «Completar» en el dato faltante. 4. En el campo de completitud, no ingresar el dato (o seleccionar «No lo sé»). 5. Guardar / avanzar sin el dato crítico. 6. Verificar que la deuda se conserva con los datos parciales conocidos (no se descarta). 7. Verificar que queda en estado pendiente/incompleta para el uso afectado (presión/Ruta). 8. Verificar que los derivados que dependen del dato ausente NO se calculan (no aparecen como 0). → Si la deuda persiste incompleta sin forzar un valor: ✓ PASA. CIERRE · Registrar resultado en «Resultado obtenido» y marcar «Estado QA». · Resetear cuenta solo si el siguiente caso requiere estado diferente al actual. (Perfil → Herramientas QA → «Reiniciar cuenta de prueba» (doble confirmación)) | I22: Pantalla activa de Ruta Despeje. | J22: Conservar la deuda y los datos parciales conocidos como pendiente/incompleta para el uso afectado; dejar derivados no calculables cuando falte un insumo y excluir solo la conclusion que dependa de ese faltante. | L22: Sí | P22: Walvy_M04_Matriz_Trazabilidad_Cliente_v1.3.xlsx · 01_Matriz_Trazabilidad · TR-M04-062 | Q22: En: Pantalla activa de Ruta Despeje. → Conservar la deuda y los datos parciales conocidos como pendiente/incompleta para el uso afectado; dejar derivados no calculables cuando falte un insumo y excluir solo la conclusion que dependa de ese faltante.
A23: M04 | B23: TR-M04-063 | C23: F1 · QA funcional local | D23: FLOW-M04-007 · Onboarding 2 · Revisión | E23: Documento identifica deuda/pago pero datos son parciales | F23: OD-02 | Revisar/Completar | G23: Cuenta de prueba activa y reseteada (sin deudas ni datos previos del flujo). Condición de entrada: OD-02 | Revisar/Completar | H23: 1. Iniciar sesión con la cuenta de prueba reseteada. 2. Subir un documento que identifique una deuda pero con datos parciales (ej: estado de cuenta con nombre de acreedor pero sin saldo exacto). 3. Navegar a: OD-02 → card de la deuda parcial. 4. Verificar que la deuda se crea con los datos disponibles y marcada como parcial/pendiente. 5. Verificar que el quality gate impide una evaluación confiable de presión/Ruta cuando los datos son insuficientes. 6. Intentar confirmar la deuda con datos parciales y verificar que el estado queda «pendiente» si no alcanza el umbral. → Si la deuda existe pero el resultado es cualitativo/parcial: ✓ PASA. CIERRE · Registrar resultado en «Resultado obtenido» y marcar «Estado QA». · Resetear cuenta solo si el siguiente caso requiere estado diferente al actual. (Perfil → Herramientas QA → «Reiniciar cuenta de prueba» (doble confirmación)) | I23: Pantalla activa de Ruta Despeje. | J23: Crear deuda pendiente con origen parcial; si el quality gate no permite una evaluación confiable, mantener resultado parcial/no calculable y orientar a completar/revisar; si está confirmada pero imprecisa, conservar lectura condicionada. | L23: Sí | P23: Walvy_M04_Matriz_Trazabilidad_Cliente_v1.3.xlsx · 01_Matriz_Trazabilidad · TR-M04-063 | Q23: En: Pantalla activa de Ruta Despeje. → Crear deuda pendiente con origen parcial; si el quality gate no permite una evaluación confiable, mantener resultado parcial/no calculable y orientar a completar/revisar; si está confirmada pero imprecisa, conservar lectura condicionada.
A24: M04 | B24: TR-M04-064 | C24: F1 · QA funcional local | D24: FLOW-M04-008 · Onboarding 2 · Revisión | E24: Deuda ya confirmada | F24: OD-02 | Continuar/Revisar | G24: Cuenta de prueba activa y reseteada (sin deudas ni datos previos del flujo). Condición de entrada: OD-02 | Continuar/Revisar | H24: 1. Iniciar sesión con cuenta que tenga al menos 1 deuda ya confirmada y 1 pendiente. 2. Navegar a: OD-02 «Revisar deudas detectadas». 3. Localizar la deuda ya confirmada. 4. Verificar que su estado muestra «confirmada» y no solicita confirmación de nuevo. 5. Verificar que las demás deudas pendientes siguen disponibles para revisión individual. 6. Avanzar / continuar con la revisión del resto sin que la deuda confirmada cambie de estado. → Si la deuda confirmada mantiene estado y no bloquea la revisión del resto: ✓ PASA. CIERRE · Registrar resultado en «Resultado obtenido» y marcar «Estado QA». · Resetear cuenta solo si el siguiente caso requiere estado diferente al actual. (Perfil → Herramientas QA → «Reiniciar cuenta de prueba» (doble confirmación)) | I24: Pantalla activa de Ruta Despeje. | J24: Mantener estado confirmado y continuar resolución del resto de instancias. | L24: Sí | P24: Walvy_M04_Matriz_Trazabilidad_Cliente_v1.3.xlsx · 01_Matriz_Trazabilidad · TR-M04-064 | Q24: En: Pantalla activa de Ruta Despeje. → Mantener estado confirmado y continuar resolución del resto de instancias.
A25: M04 | B25: TR-M04-065 | C25: F1 · QA funcional local | D25: FLOW-M04-008 · Onboarding 2 · Revisión | E25: Todas las instancias relevantes están resueltas | F25: OD-02 | Finalizar revisión | G25: Cuenta de prueba activa y reseteada (sin deudas ni datos previos del flujo). Condición de entrada: OD-02 | Finalizar revisión | H25: 1. Iniciar sesión con cuenta que tenga todas las deudas confirmadas (sin ninguna pendiente ni con «Faltan datos»). 2. Navegar a: OD-02 «Revisa tus deudas». 3. Verificar que todas las deudas muestran chip «Confirmada» y aparece el banner inferior con texto «Tus deudas están confirmadas y listas para resultado.» 4. Verificar que el botón «Ver resultado» en el footer está habilitado (solo se habilita cuando todas están confirmadas). 5. Tocar «Ver resultado». 6. Verificar que la app navega a OD-03 «Resultado» y NO vuelve a OD-01 ni repite la carga. → Si navega a Resultado con todas confirmadas: ✓ PASA. CIERRE · Registrar resultado en «Resultado obtenido» y marcar «Estado QA». · Resetear cuenta solo si el siguiente caso requiere estado diferente al actual. (Perfil → Herramientas QA → «Reiniciar cuenta de prueba» (doble confirmación)) | I25: Pantalla activa de Ruta Despeje. | J25: Cerrar revisión por lote y derivar a evaluación/resultado. | L25: Sí | P25: Walvy_M04_Matriz_Trazabilidad_Cliente_v1.3.xlsx · 01_Matriz_Trazabilidad · TR-M04-065 | Q25: En: Pantalla activa de Ruta Despeje. → Cerrar revisión por lote y derivar a evaluación/resultado.
A26: M04 | B26: TR-M04-066 | C26: F1 · QA funcional local | D26: FLOW-M04-009 · Onboarding 2 · Revisión | E26: Usuario no reconoce deuda | F26: OD-02 deuda detectada | No corresponde | G26: Cuenta de prueba activa y reseteada (sin deudas ni datos previos del flujo). Condición de entrada: OD-02 deuda detectada | No corresponde | H26: 1. Iniciar sesión con cuenta que tenga al menos una deuda detectada por documento en OD-02. 2. Navegar a OD-02 → expandir la card de la deuda → tocar «Descartar deuda». 3. Verificar que aparece modal «¿Quieres descartar la deuda?» → tocar «Descartar» para confirmar. 4. Verificar que la deuda desaparece de la lista en OD-02 (no queda en gris, se va). Si era la última deuda, la app navega a RD-01 — ese es el comportamiento correcto. 5. Avanzar a OD-03 y verificar que la deuda descartada no figura en presión ni en Ruta Despeje. → Si modal aparece, deuda se elimina y queda excluida de presión/Ruta: ✓ PASA. CIERRE · Registrar resultado en «Resultado obtenido» y marcar «Estado QA». · Resetear cuenta solo si el siguiente caso requiere estado diferente al actual. (Perfil → Herramientas QA → «Reiniciar cuenta de prueba» (doble confirmación)) | I26: Pantalla activa de Ruta Despeje. | J26: Excluir de Salud/Ruta; conservar provenance mínima de origen/decisión. | L26: Sí | P26: Walvy_M04_Matriz_Trazabilidad_Cliente_v1.3.xlsx · 01_Matriz_Trazabilidad · TR-M04-066 | Q26: En: Pantalla activa de Ruta Despeje. → Excluir de Salud/Ruta; conservar provenance mínima de origen/decisión.
A27: M04 | B27: TR-M04-067 | C27: F1 · QA funcional local | D27: FLOW-M04-010 · Onboarding 2 · Revisión | E27: Existe duplicado probable | F27: OD-02 deuda detectada/registrada | Revisar coincidencia | G27: Cuenta de prueba reseteada (sin deudas previas). Fixture con exactamente 2 deudas del MISMO acreedor cuyo saldo difiere ≤2%: Ej: «Banco X» $100.000 y «Banco X» $101.500 (diferencia = 1,5%). | H27: 📋 FIXTURE: 2 deudas del mismo acreedor, mismo tipo, saldo con diferencia ≤10%. Ej: «Santander» $620.381 y «Santander» $600.000 (diferencia = 3,3%). Un CMF real sirve. 1. Cargar el fixture (o CMF con dos deudas Santander) y navegar a OD-02. 2. Verificar que las dos filas muestran chip «Posible duplicado» (reemplaza a «Faltan datos»). 3. Verificar que aparecen como dos cards separadas, no fusionadas. 4. Verificar el pie de pantalla: · aviso «Tienes posibles duplicados» visible; · «Ver resultado» deshabilitado; · «Ver resultado con datos parciales» deshabilitado (si aparece). 5. Expandir una de las dos filas → tocar «Resolver duplicado». Verificar que se abre el sheet «¿Son la misma deuda?» con 4 opciones y «Decidir después». 6. Tocar «Decidir después»: verificar que el bloqueo se mantiene. 7. Volver a abrir «Resolver duplicado», elegir una opción y verificar que el chip desaparece de las dos filas. → Si aviso visible, cards separadas y bloqueo hasta resolver: ✓ PASA. CIERRE · Registrar resultado en «Resultado obtenido» y marcar «Estado QA». · Resetear cuenta solo si el siguiente caso requiere estado diferente al actual. (Perfil → Herramientas QA → «Reiniciar cuenta de prueba» (doble confirmación)) | I27: Pantalla Revisión de deudas detectadas (OD-02) → banner de aviso de duplicado. | J27: Solicitar revisión; no fusionar automáticamente ni doble contabilizar. | K27: Fixture sintético CSV o XLSX con 2 deudas: Fila 1: nombre «Banco X», saldo $100.000, tipo tarjeta_credito, fecha_venc cualquiera. Fila 2: nombre «Banco X», saldo $101.500, tipo tarjeta_credito, fecha_venc cualquiera. Diferencia de saldo = 1,5% (< tolerancia 2%). Requisito: creditorLabel o name idénticos (misma cadena, ignorando mayúsculas). | L27: Sí | O27: Backend: debt-review.rule.ts → detectProbableDuplicates(). Criterio: mismoAcreedor() && saldoCercano() (tolerancia TOLERANCIA_SALDO=0.02). Reason code devuelto: debt_probable_duplicate_needs_review. | P27: Walvy_M04_Matriz_Trazabilidad_Cliente_v1.3.xlsx · 01_Matriz_Trazabilidad · TR-M04-067 | Q27: En: Pantalla Revisión de deudas detectadas (OD-02) → banner de aviso de duplicado. → Solicitar revisión; no fusionar automáticamente ni doble contabilizar.
A28: M04 | B28: TR-M04-068 | C28: F1 · QA funcional local | D28: FLOW-M04-011 · Onboarding 2 · Revisión | E28: Documento contiene múltiples posibles deudas | F28: OD-02 lote | Revisar pendientes | G28: Cuenta de prueba activa y reseteada (sin deudas ni datos previos del flujo). Condición de entrada: OD-02 lote | Revisar pendientes | H28: 1. Iniciar sesión con cuenta de prueba reseteada. 2. Subir un documento que contenga múltiples deudas detectables (ej: estado de cuenta con 3+ líneas de crédito). 3. Navegar a: OD-02 «Revisar deudas detectadas». 4. Verificar que cada deuda detectada aparece como una card independiente (no consolidadas en una sola). 5. Verificar que se puede revisar/confirmar/descartar cada deuda individualmente. 6. Confirmar 1 deuda y verificar que las demás siguen pendientes de revisión. → Si cada deuda tiene su card individual: ✓ PASA. CIERRE · Registrar resultado en «Resultado obtenido» y marcar «Estado QA». · Resetear cuenta solo si el siguiente caso requiere estado diferente al actual. (Perfil → Herramientas QA → «Reiniciar cuenta de prueba» (doble confirmación)) | I28: Pantalla activa de Ruta Despeje. | J28: Separar instancias y revisar individualmente; no consolidar lote por defecto. | L28: Sí | P28: Walvy_M04_Matriz_Trazabilidad_Cliente_v1.3.xlsx · 01_Matriz_Trazabilidad · TR-M04-068 | Q28: En: Pantalla activa de Ruta Despeje. → Separar instancias y revisar individualmente; no consolidar lote por defecto.
A29: M04 | B29: TR-M04-069 | C29: F1 · QA funcional local | D29: FLOW-M04-011 · Onboarding 2 · Revisión | E29: Solo parte del lote está resuelta | F29: OD-02 lote | Continuar revisión | G29: Cuenta de prueba activa y reseteada (sin deudas ni datos previos del flujo). Condición de entrada: OD-02 lote | Continuar revisión | H29: 1. Iniciar sesión con cuenta seed que tenga un lote de deudas con solo algunas resueltas. 2. Navegar a: OD-02 «Revisar deudas detectadas». 3. Verificar que las deudas pendientes (sin resolver) siguen visibles en la lista. 4. Verificar que las deudas pendientes están FUERA de cualquier lectura concluyente de presión/Ruta. 5. Intentar avanzar a OD-03/resultado con el lote incompleto. 6. Verificar que la app no permite avanzar con conclusión hasta resolver el lote, o bien marca el resultado como provisional. → Si los pendientes siguen visibles y bloquean/marcan la conclusión: ✓ PASA. CIERRE · Registrar resultado en «Resultado obtenido» y marcar «Estado QA». · Resetear cuenta solo si el siguiente caso requiere estado diferente al actual. (Perfil → Herramientas QA → «Reiniciar cuenta de prueba» (doble confirmación)) | I29: Pantalla activa de Ruta Despeje. | J29: Mantener pendientes visibles y fuera de lectura concluyente hasta resolverlas. | L29: Sí | P29: Walvy_M04_Matriz_Trazabilidad_Cliente_v1.3.xlsx · 01_Matriz_Trazabilidad · TR-M04-069 | Q29: En: Pantalla activa de Ruta Despeje. → Mantener pendientes visibles y fuera de lectura concluyente hasta resolverlas.
A30: M04 | B30: TR-M04-070 | C30: F2 · Fixture cross-contract | D30: FLOW-M04-012 · Onboarding 2→3 | E30: Base completa para evaluación | F30: OD-02→OD-03 | Siguiente/Validar | G30: Cuenta de prueba activa y reseteada (sin deudas ni datos previos del flujo). Condición de entrada: OD-02→OD-03 | Siguiente/Validar | H30: Seguir flujo de FLOW-M04-012 · Onboarding 2→3. CIERRE · Registrar resultado en columna «Resultado obtenido» y marcar «Estado QA». · Resetear solo si el siguiente caso requiere estado inicial incompatible con el actual. Casos del mismo flujo pueden reutilizar el estado. (Ajustes → Borrar mis datos · o solicitar reset al admin de QA) | I30: Pantalla activa de Ruta Despeje. | J30: Evaluar confirmación, suficiencia, frescura y Presión P4 antes de producir resultado. | K30: Fixture sintético (no requiere documento real). Formato: CSV o XLSX con los valores del contrato P4 upstream cerrado. Inyectar al menos: POSITIVE · ZERO · NOT_EVALUABLE. | L30: Sí · con insumo dev | P30: Walvy_M04_Matriz_Trazabilidad_Cliente_v1.3.xlsx · 01_Matriz_Trazabilidad · TR-M04-070 | Q30: En: Pantalla activa de Ruta Despeje. → Evaluar confirmación, suficiencia, frescura y Presión P4 antes de producir resultado.
A31: M04 | B31: TR-M04-071 | C31: F2 · Fixture cross-contract | D31: FLOW-M04-012 · Onboarding 2→3 | E31: Base permite lectura cualitativa pero precisión es limitada | F31: OD-02→OD-03 | Siguiente/Validar | G31: Cuenta de prueba activa y reseteada (sin deudas ni datos previos del flujo). Condición de entrada: OD-02→OD-03 | Siguiente/Validar | H31: Seguir flujo de FLOW-M04-012 · Onboarding 2→3. CIERRE · Registrar resultado en columna «Resultado obtenido» y marcar «Estado QA». · Resetear solo si el siguiente caso requiere estado inicial incompatible con el actual. Casos del mismo flujo pueden reutilizar el estado. (Ajustes → Borrar mis datos · o solicitar reset al admin de QA) | I31: Pantalla activa de Ruta Despeje. | J31: Degradar la lectura cuando la calidad es insuficiente; un faltante material bloquea En Control, sin borrar evidencia adversa independientemente suficiente. | K31: Fixture sintético (no requiere documento real). Formato: CSV o XLSX con los valores del contrato P4 upstream cerrado. Inyectar al menos: POSITIVE · ZERO · NOT_EVALUABLE. | L31: Sí · con insumo dev | P31: Walvy_M04_Matriz_Trazabilidad_Cliente_v1.3.xlsx · 01_Matriz_Trazabilidad · TR-M04-071 | Q31: En: Pantalla activa de Ruta Despeje. → Degradar la lectura cuando la calidad es insuficiente; un faltante material bloquea En Control, sin borrar evidencia adversa independientemente suficiente.
A32: M04 | B32: TR-M04-072 | C32: F2 · Fixture cross-contract | D32: FLOW-M04-012 · Onboarding 2→3 | E32: Falta dato crítico o confirmación | F32: OD-02→OD-03 | Siguiente/Validar | G32: Cuenta de prueba activa y reseteada (sin deudas ni datos previos del flujo). Condición de entrada: OD-02→OD-03 | Siguiente/Validar | H32: Seguir flujo de FLOW-M04-012 · Onboarding 2→3. CIERRE · Registrar resultado en columna «Resultado obtenido» y marcar «Estado QA». · Resetear solo si el siguiente caso requiere estado inicial incompatible con el actual. Casos del mismo flujo pueden reutilizar el estado. (Ajustes → Borrar mis datos · o solicitar reset al admin de QA) | I32: Pantalla activa de Ruta Despeje. | J32: Bloquear conclusión fuerte favorable y devolver a completitud/confirmación cuando falte dato material o confirmación. | K32: Fixture sintético (no requiere documento real). Formato: CSV o XLSX con los valores del contrato P4 upstream cerrado. Inyectar al menos: POSITIVE · ZERO · NOT_EVALUABLE. | L32: Sí · con insumo dev | P32: Walvy_M04_Matriz_Trazabilidad_Cliente_v1.3.xlsx · 01_Matriz_Trazabilidad · TR-M04-072 | Q32: En: Pantalla activa de Ruta Despeje. → Bloquear conclusión fuerte favorable y devolver a completitud/confirmación cuando falte dato material o confirmación.
A33: M04 | B33: TR-M04-073 | C33: F2 · Fixture cross-contract | D33: FLOW-M04-013 · Onboarding 3 · Resultado | E33: Deuda confirmada con Presión final En Control y datos suficientes | F33: OD-03 Resultado | Ver detalle/Revisar pagos | G33: Cuenta de prueba activa y reseteada (sin deudas ni datos previos del flujo). Condición de entrada: OD-03 Resultado | Ver detalle/Revisar pagos | H33: Seguir flujo de FLOW-M04-013 · Onboarding 3 · Resultado. CIERRE · Registrar resultado en columna «Resultado obtenido» y marcar «Estado QA». · Resetear solo si el siguiente caso requiere estado inicial incompatible con el actual. Casos del mismo flujo pueden reutilizar el estado. (Ajustes → Borrar mis datos · o solicitar reset al admin de QA) | I33: Pantalla activa de Ruta Despeje. | J33: Mostrar En Control/seguimiento y mantener Ruta inactiva; el CTA operativo puede derivar a M06 sin cambiar ownership. | K33: Fixture sintético (no requiere documento real). Formato: CSV o XLSX con los valores del contrato P4 upstream cerrado. Inyectar al menos: POSITIVE · ZERO · NOT_EVALUABLE. | L33: Sí · con insumo dev | P33: Walvy_M04_Matriz_Trazabilidad_Cliente_v1.3.xlsx · 01_Matriz_Trazabilidad · TR-M04-073 | Q33: En: Pantalla activa de Ruta Despeje. → Mostrar En Control/seguimiento y mantener Ruta inactiva; el CTA operativo puede derivar a M06 sin cambiar ownership.
A34: M04 | B34: TR-M04-074 | C34: F1 · QA funcional local | D34: FLOW-M04-013 · Onboarding 3 · Resultado | E34: Estado En Control M04 con acción operativa de pagos perteneciente a M06. | F34: OD-03 Resultado | Revisar mis pagos | G34: Cuenta de prueba activa y reseteada (sin deudas ni datos previos del flujo). Condición de entrada: OD-03 Resultado | Revisar mis pagos | H34: 📋 FIXTURE REQUERIDO: cuenta seed «od03-sana». Email: qa-m04-od03-sana-*@walvy.local · Password: Walvy2024! 1. Iniciar sesión con la cuenta seed od03-sana (estado: En Control M04). 2. Navegar a: OD-03 Resultado → pantalla de estado del onboarding. 3. Verificar que el estado muestra «En Control» (Salud M04 no crítica). 4. Localizar el CTA de pagos (ej: «Revisar mis pagos» o equivalente operativo de M06). 5. Tocar el CTA y verificar que navega hacia la sección de Pagos (M06), no a Ruta Despeje. 6. Verificar que M04 no crea un calendario de pagos propio; la responsabilidad queda en M06. → Si el CTA deriva a M06/Pagos sin crear historial M04: ✓ PASA. CIERRE · Registrar resultado en «Resultado obtenido» y marcar «Estado QA». · Resetear cuenta solo si el siguiente caso requiere estado diferente al actual. (Perfil → Herramientas QA → «Reiniciar cuenta de prueba» (doble confirmación)) | I34: Pantalla activa de Ruta Despeje. | J34: CTA observado deriva a M06/Pagos manteniendo owner M06. | K34: ── CUENTA SEED (origin/qa) ── Email : qa-m04-od03-sana-*@walvy.local Password: Walvy2024! Grupo : A1 Estado : OD-03 · presión en_control · 1 deuda confirmada (tarjeta_credito $300k cuota $150k) · debt_cycle total · ruta NO activada (El email exacto queda en la salida del script seed-qa-m04.mjs) | L34: Sí · con insumo dev | P34: Walvy_M04_Matriz_Trazabilidad_Cliente_v1.3.xlsx · 01_Matriz_Trazabilidad · TR-M04-074 | Q34: En: Pantalla activa de Ruta Despeje. → CTA observado deriva a M06/Pagos manteniendo owner M06.
A35: M04 | B35: TR-M04-075 | C35: F2 · Fixture cross-contract | D35: FLOW-M04-013 · Onboarding 3 · Resultado | E35: Tarjeta con total facturado pagado dentro del ciclo | F35: OD-03 Resultado | Lectura de ciclo | G35: Cuenta de prueba activa y reseteada (sin deudas ni datos previos del flujo). Condición de entrada: OD-03 Resultado | Lectura de ciclo | H35: Seguir flujo de FLOW-M04-013 · Onboarding 3 · Resultado. CIERRE · Registrar resultado en columna «Resultado obtenido» y marcar «Estado QA». · Resetear solo si el siguiente caso requiere estado inicial incompatible con el actual. Casos del mismo flujo pueden reutilizar el estado. (Ajustes → Borrar mis datos · o solicitar reset al admin de QA) | I35: Pantalla activa de Ruta Despeje. | J35: Ciclo con total facturado cubierto: D0 por este comportamiento. La Presión final se determina por el contrato P4 completo; no escalar por el ciclo pagado. | K35: Fixture sintético (no requiere documento real). Formato: CSV o XLSX con los valores del contrato P4 upstream cerrado. Inyectar al menos: POSITIVE · ZERO · NOT_EVALUABLE. | L35: Sí · con insumo dev | P35: Walvy_M04_Matriz_Trazabilidad_Cliente_v1.3.xlsx · 01_Matriz_Trazabilidad · TR-M04-075 | Q35: En: Pantalla activa de Ruta Despeje. → Ciclo con total facturado cubierto: D0 por este comportamiento. La Presión final se determina por el contrato P4 completo; no escalar por el ciclo pagado.
A36: M04 | B36: TR-M04-076 | C36: F2 · Fixture cross-contract | D36: FLOW-M04-013 · Onboarding 3 · Resultado | E36: Compras en cuotas al día | F36: OD-03 Resultado | Lectura de cuotas | G36: Cuenta de prueba activa y reseteada (sin deudas ni datos previos del flujo). Condición de entrada: OD-03 Resultado | Lectura de cuotas | H36: Seguir flujo de FLOW-M04-013 · Onboarding 3 · Resultado. CIERRE · Registrar resultado en columna «Resultado obtenido» y marcar «Estado QA». · Resetear solo si el siguiente caso requiere estado inicial incompatible con el actual. Casos del mismo flujo pueden reutilizar el estado. (Ajustes → Borrar mis datos · o solicitar reset al admin de QA) | I36: Pantalla activa de Ruta Despeje. | J36: Compras en cuotas al día: D0 por ese comportamiento; la cuota sí integra C cuando corresponda y no activa Ruta por existir. | K36: Fixture sintético (no requiere documento real). Formato: CSV o XLSX con los valores del contrato P4 upstream cerrado. Inyectar al menos: POSITIVE · ZERO · NOT_EVALUABLE. | L36: Sí · con insumo dev | P36: Walvy_M04_Matriz_Trazabilidad_Cliente_v1.3.xlsx · 01_Matriz_Trazabilidad · TR-M04-076 | Q36: En: Pantalla activa de Ruta Despeje. → Compras en cuotas al día: D0 por ese comportamiento; la cuota sí integra C cuando corresponda y no activa Ruta por existir.
A37: M04 | B37: TR-M04-077 | C37: F2 · Fixture cross-contract | D37: FLOW-M04-014 · Onboarding 3 · Resultado | E37: Capacidad ajustada/baja según K canónico | F37: OD-03 Resultado | Revisar | G37: Cuenta de prueba activa y reseteada (sin deudas ni datos previos del flujo). Condición de entrada: OD-03 Resultado | Revisar | H37: Seguir flujo de FLOW-M04-014 · Onboarding 3 · Resultado. CIERRE · Registrar resultado en columna «Resultado obtenido» y marcar «Estado QA». · Resetear solo si el siguiente caso requiere estado inicial incompatible con el actual. Casos del mismo flujo pueden reutilizar el estado. (Ajustes → Borrar mis datos · o solicitar reset al admin de QA) | I37: Pantalla activa de Ruta Despeje. | J37: No aplicar un floor independiente de 5%. Consumir K canónico y dejar que C×K×D determine Presión. | K37: Fixture sintético (no requiere documento real). Formato: CSV o XLSX con los valores del contrato P4 upstream cerrado. Inyectar al menos: POSITIVE · ZERO · NOT_EVALUABLE. | L37: Sí · con insumo dev | P37: Walvy_M04_Matriz_Trazabilidad_Cliente_v1.3.xlsx · 01_Matriz_Trazabilidad · TR-M04-077 | Q37: En: Pantalla activa de Ruta Despeje. → No aplicar un floor independiente de 5%. Consumir K canónico y dejar que C×K×D determine Presión.
A38: M04 | B38: TR-M04-078 | C38: F1 · QA funcional local | D38: FLOW-M04-014 · Onboarding 3 · Resultado | E38: 4+ cuotas y ratio agregado >=8% del ingreso | F38: OD-03 Resultado | Revisar deudas | G38: Cuenta de prueba activa y reseteada (sin deudas ni datos previos del flujo). Condición de entrada: OD-03 Resultado | Revisar deudas | H38: 📋 FIXTURE REQUERIDO: cuenta seed «od03-fragmentado». Email: qa-m04-od03-fragmentado-*@walvy.local · Password: Walvy2024! 1. Iniciar sesión con la cuenta seed od03-fragmentado (≥4 cuotas activas, ratio ≥8% ingreso). 2. Navegar a: OD-03 Resultado. 3. Verificar que aparece el detector contextual de fragmentación (aviso o indicador informativo). 4. Verificar que el aviso de fragmentación NO cambia por sí solo la banda de Presión (semáforo). 5. Verificar que el aviso de fragmentación NO cambia la elegibilidad de Ruta (si era elegible, sigue siendo elegible). → Si el detector aparece sin alterar Presión ni elegibilidad: ✓ PASA. CIERRE · Registrar resultado en «Resultado obtenido» y marcar «Estado QA». · Resetear cuenta solo si el siguiente caso requiere estado diferente al actual. (Perfil → Herramientas QA → «Reiniciar cuenta de prueba» (doble confirmación)) | I38: Pantalla activa de Ruta Despeje. | J38: Registrar detector contextual de fragmentación. No altera por sí solo la banda de Presión ni la elegibilidad de Ruta. | K38: ── CUENTA SEED (origin/qa) ── Email : qa-m04-od03-fragmentado-*@walvy.local Password: Walvy2024! Grupo : A2 Estado : OD-03 · 4 deudas cuota_activa confirmadas ($25k c/u) · ratio fragmentación 10% · RGL-022 activo · ruta NO activada (El email exacto queda en la salida del script seed-qa-m04.mjs) | L38: Sí · con insumo dev | P38: Walvy_M04_Matriz_Trazabilidad_Cliente_v1.3.xlsx · 01_Matriz_Trazabilidad · TR-M04-078 | Q38: En: Pantalla activa de Ruta Despeje. → Registrar detector contextual de fragmentación. No altera por sí solo la banda de Presión ni la elegibilidad de Ruta.
A39: M04 | B39: TR-M04-079 | C39: F2 · Fixture cross-contract | D39: FLOW-M04-014 · Onboarding 3 · Resultado | E39: Liquidez financiada puntual para flujo ordinario, justificable como descalce y no recurrente | F39: OD-03 Resultado | Revisar deudas | G39: Cuenta de prueba activa y reseteada (sin deudas ni datos previos del flujo). Condición de entrada: OD-03 Resultado | Revisar deudas | H39: Seguir flujo de FLOW-M04-014 · Onboarding 3 · Resultado. CIERRE · Registrar resultado en columna «Resultado obtenido» y marcar «Estado QA». · Resetear solo si el siguiente caso requiere estado inicial incompatible con el actual. Casos del mismo flujo pueden reutilizar el estado. (Ajustes → Borrar mis datos · o solicitar reset al admin de QA) | I39: Pantalla activa de Ruta Despeje. | J39: Mantener contexto sin floor en el primer ciclo; si reaparece en ciclos consecutivos comparables, reevaluar bajo recurrencia RGL-021. | K39: Fixture sintético (no requiere documento real). Formato: CSV o XLSX con los valores del contrato P4 upstream cerrado. Inyectar al menos: POSITIVE · ZERO · NOT_EVALUABLE. | L39: Sí · con insumo dev | P39: Walvy_M04_Matriz_Trazabilidad_Cliente_v1.3.xlsx · 01_Matriz_Trazabilidad · TR-M04-079 | Q39: En: Pantalla activa de Ruta Despeje. → Mantener contexto sin floor en el primer ciclo; si reaparece en ciclos consecutivos comparables, reevaluar bajo recurrencia RGL-021.
A40: M04 | B40: TR-M04-080 | C40: F2 · Fixture cross-contract | D40: FLOW-M04-014 · Onboarding 3 · Resultado | E40: Cuotas con intereses/CAE/comisiones sin presión fuerte | F40: OD-03 Resultado | Revisar | G40: Cuenta de prueba activa y reseteada (sin deudas ni datos previos del flujo). Condición de entrada: OD-03 Resultado | Revisar | H40: Seguir flujo de FLOW-M04-014 · Onboarding 3 · Resultado. CIERRE · Registrar resultado en columna «Resultado obtenido» y marcar «Estado QA». · Resetear solo si el siguiente caso requiere estado inicial incompatible con el actual. Casos del mismo flujo pueden reutilizar el estado. (Ajustes → Borrar mis datos · o solicitar reset al admin de QA) | I40: Pantalla activa de Ruta Despeje. | J40: Interés, CAE o comisión financiera ordinaria no genera D por sí sola. Si está incorporada en la cuota/servicio, impacta C sin doble conteo. | K40: Fixture sintético (no requiere documento real). Formato: CSV o XLSX con los valores del contrato P4 upstream cerrado. Inyectar al menos: POSITIVE · ZERO · NOT_EVALUABLE. | L40: Sí · con insumo dev | P40: Walvy_M04_Matriz_Trazabilidad_Cliente_v1.3.xlsx · 01_Matriz_Trazabilidad · TR-M04-080 | Q40: En: Pantalla activa de Ruta Despeje. → Interés, CAE o comisión financiera ordinaria no genera D por sí sola. Si está incorporada en la cuota/servicio, impacta C sin doble conteo.
A41: M04 | B41: TR-M04-081 | C41: F2 · Fixture cross-contract | D41: FLOW-M04-014 · Onboarding 3 · Resultado | E41: Dato crítico no vigente o confianza insuficiente | F41: OD-03 Resultado | Corregir | G41: Cuenta de prueba activa y reseteada (sin deudas ni datos previos del flujo). Condición de entrada: OD-03 Resultado | Corregir | H41: Seguir flujo de FLOW-M04-014 · Onboarding 3 · Resultado. CIERRE · Registrar resultado en columna «Resultado obtenido» y marcar «Estado QA». · Resetear solo si el siguiente caso requiere estado inicial incompatible con el actual. Casos del mismo flujo pueden reutilizar el estado. (Ajustes → Borrar mis datos · o solicitar reset al admin de QA) | I41: Pantalla activa de Ruta Despeje. | J41: Degradar lectura y pedir corrección cuando un dato material no sea vigente/confiable; faltantes materiales bloquean En Control. | K41: Fixture sintético (no requiere documento real). Formato: CSV o XLSX con los valores del contrato P4 upstream cerrado. Inyectar al menos: POSITIVE · ZERO · NOT_EVALUABLE. | L41: Sí · con insumo dev | P41: Walvy_M04_Matriz_Trazabilidad_Cliente_v1.3.xlsx · 01_Matriz_Trazabilidad · TR-M04-081 | Q41: En: Pantalla activa de Ruta Despeje. → Degradar lectura y pedir corrección cuando un dato material no sea vigente/confiable; faltantes materiales bloquean En Control.
... A67: M04 | B67: TR-M04-107 | C67: F1 · QA funcional local | D67: FLOW-M04-019 · Ruta 2 · Plan | E67: Faltan datos/supuestos/confianza para proyectar fecha | F67: RD-02 Plan | Mostrar estado cualitativo | G67: Cuenta de prueba activa y reseteada (sin deudas ni datos previos del flujo). Condición de entrada: RD-02 Plan | Mostrar estado cualitativo | H67: 📋 FIXTURE REQUERIDO: cuenta seed «rd02-sin-fecha». Email: qa-m04-rd02-sin-fecha-*@walvy.local · Password: Walvy2024! 1. Iniciar sesión con la cuenta seed rd02-sin-fecha (faltan datos/confianza para proyectar fecha). 2. Navegar a: Ruta Despeje → RD-02 Plan → sección de cronograma. 3. Verificar que la app NO muestra una fecha concreta de finalización. 4. Verificar que en su lugar muestra un estado cualitativo (ej: «Completa datos para ver la duración») o pide el dato faltante. 5. Verificar que el plan de orden de deudas sí se muestra aunque no haya fecha. → Si no hay fecha y el estado es cualitativo: ✓ PASA. CIERRE · Registrar resultado en «Resultado obtenido» y marcar «Estado QA». · Resetear cuenta solo si el siguiente caso requiere estado diferente al actual. (Perfil → Herramientas QA → «Reiniciar cuenta de prueba» (doble confirmación)) | I67: Pantalla activa de Ruta Despeje. | J67: No mostrar fecha concluyente; pedir datos o mantener estado cualitativo. | K67: ── CUENTA SEED (origin/qa) ── Email : qa-m04-rd02-sin-fecha-*@walvy.local Password: Walvy2024! Grupo : D2 Estado : RD-02 · 1 deuda principal sin cuota (current_balance=NULL, minimum_payment=NULL → preliminaryOrderIds) · plan cualitativo sin fecha · REASON.orderPreliminary (El email exacto queda en la salida del script seed-qa-m04.mjs) | L67: Sí · con insumo dev | P67: Walvy_M04_Matriz_Trazabilidad_Cliente_v1.3.xlsx · 01_Matriz_Trazabilidad · TR-M04-107 | Q67: En: Pantalla activa de Ruta Despeje. → No mostrar fecha concluyente; pedir datos o mantener estado cualitativo.
A68: M04 | B68: TR-M04-108 | C68: F1 · QA funcional local | D68: FLOW-M04-019 · Ruta 2 · Plan | E68: Vista agrupada opcional autorizada por fuente | F68: RD-02 Plan | Ver deudas agrupadas | G68: Cuenta de prueba reseteada con ≥2 deudas confirmadas de distintas fuentes (ej: 1 manual + 1 detectada por documento). Ruta activa con plan RD-02 generado. | H68: NOTA: Esta variante es una capacidad opcional condicionada por PMO (vista agrupada por fuente). Si el botón/toggle de agrupamiento NO está visible en la pantalla: → Marcar «NO APLICA HOY» en Estado QA. El caso está condicionado/no materializado. Si el toggle SÍ está visible: 1. Iniciar sesión con cuenta que tenga ≥2 deudas de distinta fuente (manual + detectada). 2. Navegar a: Ruta Despeje → RD-02 Plan. 3. Activar la vista agrupada por fuente. 4. Verificar que las deudas se agrupan por origen sin que el saldo total del plan cambie. 5. Verificar que NO aparece ningún botón de «consolidar» ni «refinanciar». CIERRE · Registrar resultado en «Resultado obtenido» y marcar «Estado QA». · Resetear cuenta solo si el siguiente caso requiere estado diferente al actual. (Perfil → Herramientas QA → «Reiniciar cuenta de prueba» (doble confirmación)) | I68: Pantalla Plan de deudas / RD-02 (RoutePlanScreen) → lista de deudas del plan. | J68: Si se materializa, agrupa deudas para ordenar sin implicar refinanciamiento/consolidación. | K68: Fixture sintético con ≥2 deudas confirmadas: 1 deuda manual (origin='manual'). 1 deuda detectada por documento (origin='document', confirmationStatus='confirmed'). Ambas deben estar en el plan activo (eligibleForRoute=true). | L68: No aplica · condicionado PMO | N68: NO APLICA | O68: PMO ruling 2026-09-22 (KabeliDev/front-walvy#210): vista agrupada es capacidad opcional/condicionada — no se implementa en M04 vigente. Si el toggle no está visible: NO APLICA HOY. Si en el futuro se materializa, se cierra primero con Diseño el criterio de agrupación y el punto de acceso UX; el orden bola de nieve siempre se preserva. --- Backend: route.service.ts → buildDebtTags(); no hay groupBy endpoint. Comportamiento contractual: «Si se materializa, agrupa sin implicar refinanciamiento/consolidación». Si no hay UI de agrupamiento: marcar NO APLICA HOY. | P68: Walvy_M04_Matriz_Trazabilidad_Cliente_v1.3.xlsx · 01_Matriz_Trazabilidad · TR-M04-108 | Q68: En: Pantalla Plan de deudas / RD-02 (RoutePlanScreen) → lista de deudas del plan. → Si se materializa, agrupa deudas para ordenar sin implicar refinanciamiento/consolidación.
A69: M04 | B69: TR-M04-109 | C69: F1 · QA funcional local | D69: FLOW-M04-019 · Ruta 2 · Plan | E69: Figma usa “capacidad de ahorro comprometida/que podrías liberar” | F69: RD-02 Plan | Copy capacidad | G69: Cuenta de prueba activa y reseteada (sin deudas ni datos previos del flujo). Condición de entrada: RD-02 Plan | Copy capacidad | H69: 1. Iniciar sesión con cualquier cuenta que tenga Ruta elegible/activa con plan RD-02. 2. Navegar a: Ruta Despeje → RD-02 Plan. 3. Localizar el texto que menciona la capacidad de pago liberada al cerrar la deuda prioritaria. 4. Verificar que el copy usa la semántica de «capacidad recuperable/liberable por deuda» y NO usa el término «capacidad de ahorro general» (que es competencia de M05). 5. Verificar que el texto es informativo y no implica movimiento de dinero ni ahorro automático. → Si el copy dice «liberar» o «recuperar» capacidad (no ahorro general M05): ✓ PASA. CIERRE · Registrar resultado en «Resultado obtenido» y marcar «Estado QA». · Resetear cuenta solo si el siguiente caso requiere estado diferente al actual. (Perfil → Herramientas QA → «Reiniciar cuenta de prueba» (doble confirmación)) | I69: Pantalla activa de Ruta Despeje. | J69: La obligación documental exige semántica de capacidad recuperable/liberable por deuda, separada de ahorro general M05. | L69: Sí | P69: Walvy_M04_Matriz_Trazabilidad_Cliente_v1.3.xlsx · 01_Matriz_Trazabilidad · TR-M04-109 | Q69: En: Pantalla activa de Ruta Despeje. → La obligación documental exige semántica de capacidad recuperable/liberable por deuda, separada de ahorro general M05.
A70: M04 | B70: TR-M04-110 | C70: F2 · Fixture cross-contract | D70: FLOW-M04-020 · Ruta 2 · Simulación | E70: Ingreso disponible para colchón | F70: RD-02 Simulación | Calcular | G70: Cuenta de prueba activa y reseteada (sin deudas ni datos previos del flujo). Condición de entrada: RD-02 Simulación | Calcular | H70: Seguir flujo de FLOW-M04-020 · Ruta 2 · Simulación. CIERRE · Registrar resultado en columna «Resultado obtenido» y marcar «Estado QA». · Resetear solo si el siguiente caso requiere estado inicial incompatible con el actual. Casos del mismo flujo pueden reutilizar el estado. (Ajustes → Borrar mis datos · o solicitar reset al admin de QA) | I70: Pantalla activa de Ruta Despeje. | J70: No usar max(piso, ingreso×5%) como política vigente. Preservar únicamente el principio de protección prudencial antes de afirmar sostenibilidad. | K70: Fixture sintético (no requiere documento real). Formato: CSV o XLSX con los valores del contrato P4 upstream cerrado. Inyectar al menos: POSITIVE · ZERO · NOT_EVALUABLE. | L70: Sí · con insumo dev | P70: Walvy_M04_Matriz_Trazabilidad_Cliente_v1.3.xlsx · 01_Matriz_Trazabilidad · TR-M04-110 | Q70: En: Pantalla activa de Ruta Despeje. → No usar max(piso, ingreso×5%) como política vigente. Preservar únicamente el principio de protección prudencial antes de afirmar sostenibilidad.
A71: M04 | B71: TR-M04-111 | C71: F2 · Fixture cross-contract | D71: FLOW-M04-020 · Ruta 2 · Simulación | E71: Ingreso/gastos/pagos obligatorios disponibles | F71: RD-02 Simulación | Calcular | G71: Cuenta de prueba activa y reseteada (sin deudas ni datos previos del flujo). Condición de entrada: RD-02 Simulación | Calcular | H71: Seguir flujo de FLOW-M04-020 · Ruta 2 · Simulación. CIERRE · Registrar resultado en columna «Resultado obtenido» y marcar «Estado QA». · Resetear solo si el siguiente caso requiere estado inicial incompatible con el actual. Casos del mismo flujo pueden reutilizar el estado. (Ajustes → Borrar mis datos · o solicitar reset al admin de QA) | I71: Pantalla activa de Ruta Despeje. | J71: Consumir headroom/capacidad residual canónica producida upstream; M04 no recalcula un presupuesto paralelo. | K71: Fixture sintético (no requiere documento real). Formato: CSV o XLSX con los valores del contrato P4 upstream cerrado. Inyectar al menos: POSITIVE · ZERO · NOT_EVALUABLE. | L71: Sí · con insumo dev | P71: Walvy_M04_Matriz_Trazabilidad_Cliente_v1.3.xlsx · 01_Matriz_Trazabilidad · TR-M04-111 | Q71: En: Pantalla activa de Ruta Despeje. → Consumir headroom/capacidad residual canónica producida upstream; M04 no recalcula un presupuesto paralelo.
A72: M04 | B72: TR-M04-112 | C72: F2 · Fixture cross-contract | D72: FLOW-M04-020 · Ruta 2 · Simulación | E72: Headroom válido y protección prudencial suficientemente evaluable | F72: RD-02 Simulación | Calcular | G72: Cuenta de prueba activa y reseteada (sin deudas ni datos previos del flujo). Condición de entrada: RD-02 Simulación | Calcular | H72: Seguir flujo de FLOW-M04-020 · Ruta 2 · Simulación. CIERRE · Registrar resultado en columna «Resultado obtenido» y marcar «Estado QA». · Resetear solo si el siguiente caso requiere estado inicial incompatible con el actual. Casos del mismo flujo pueden reutilizar el estado. (Ajustes → Borrar mis datos · o solicitar reset al admin de QA) | I72: Pantalla activa de Ruta Despeje. | J72: Calcular o afirmar capacidad adicional sostenible solo bajo una política prudencial aprobada y con inputs suficientes; no usar la resta anterior espacio-colchón. | K72: Fixture sintético (no requiere documento real). Formato: CSV o XLSX con los valores del contrato P4 upstream cerrado. Inyectar al menos: POSITIVE · ZERO · NOT_EVALUABLE. | L72: Sí · con insumo dev | P72: Walvy_M04_Matriz_Trazabilidad_Cliente_v1.3.xlsx · 01_Matriz_Trazabilidad · TR-M04-112 | Q72: En: Pantalla activa de Ruta Despeje. → Calcular o afirmar capacidad adicional sostenible solo bajo una política prudencial aprobada y con inputs suficientes; no usar la resta anterior espacio-colchón.
A73: M04 | B73: TR-M04-113 | C73: F1 · QA funcional local | D73: FLOW-M04-020 · Ruta 2 · Simulación | E73: Usuario ingresa aporte manual hipotético | F73: RD-02 Simulación | Ingresar monto | G73: Cuenta de prueba activa y reseteada (sin deudas ni datos previos del flujo). Condición de entrada: RD-02 Simulación | Ingresar monto | H73: 1. Iniciar sesión con cualquier cuenta que tenga Ruta elegible/activa y plan RD-02 activo. 2. Navegar a: Ruta Despeje → RD-02 Plan → sección de simulación de aporte. 3. Ingresar un monto de aporte manual hipotético (ej: $50.000 adicionales al mes). 4. Verificar que la app recalcula el cronograma / duración del plan con el aporte hipotético. 5. Verificar que la simulación es solo un escenario (sin pago real, sin confirmación). 6. Verificar que la Ruta NO se activa ni el estado cambia por simular un aporte. → Si el cronograma cambia hipotéticamente sin mover dinero ni activar Ruta: ✓ PASA. CIERRE · Registrar resultado en «Resultado obtenido» y marcar «Estado QA». · Resetear cuenta solo si el siguiente caso requiere estado diferente al actual. (Perfil → Herramientas QA → «Reiniciar cuenta de prueba» (doble confirmación)) | I73: Pantalla activa de Ruta Despeje. | J73: Permitir simulación de aporte manual como escenario hipotético aunque la sostenibilidad prudencial no esté demostrada. | L73: Sí | P73: Walvy_M04_Matriz_Trazabilidad_Cliente_v1.3.xlsx · 01_Matriz_Trazabilidad · TR-M04-113 | Q73: En: Pantalla activa de Ruta Despeje. → Permitir simulación de aporte manual como escenario hipotético aunque la sostenibilidad prudencial no esté demostrada.
A74: M04 | B74: TR-M04-114 | C74: F2 · Fixture cross-contract | D74: FLOW-M04-020 · Ruta 2 · Simulación | E74: Protección prudencial no evaluable o capacidad sostenible no demostrable | F74: RD-02 Simulación | Ver simulación | G74: Cuenta de prueba activa y reseteada (sin deudas ni datos previos del flujo). Condición de entrada: RD-02 Simulación | Ver simulación | H74: Seguir flujo de FLOW-M04-020 · Ruta 2 · Simulación. CIERRE · Registrar resultado en columna «Resultado obtenido» y marcar «Estado QA». · Resetear solo si el siguiente caso requiere estado inicial incompatible con el actual. Casos del mismo flujo pueden reutilizar el estado. (Ajustes → Borrar mis datos · o solicitar reset al admin de QA) | I74: Pantalla activa de Ruta Despeje. | J74: Mostrar simulación referencial o abstenerse de recomendar un máximo sostenible; no convertir desconocido en 0. | K74: Fixture sintético (no requiere documento real). Formato: CSV o XLSX con los valores del contrato P4 upstream cerrado. Inyectar al menos: POSITIVE · ZERO · NOT_EVALUABLE. | L74: Sí · con insumo dev | P74: Walvy_M04_Matriz_Trazabilidad_Cliente_v1.3.xlsx · 01_Matriz_Trazabilidad · TR-M04-114 | Q74: En: Pantalla activa de Ruta Despeje. → Mostrar simulación referencial o abstenerse de recomendar un máximo sostenible; no convertir desconocido en 0.
A75: M04 | B75: TR-M04-115 | C75: F2 · Fixture cross-contract | D75: FLOW-M04-020 · Ruta 2 · Simulación | E75: Cambian saldos, mínimos, compromisos, headroom, cierre, ingreso, gasto relevante o versión de regla | F75: RD-02 Simulación | Recalcular | G75: Cuenta de prueba activa y reseteada (sin deudas ni datos previos del flujo). Condición de entrada: RD-02 Simulación | Recalcular | H75: Seguir flujo de FLOW-M04-020 · Ruta 2 · Simulación. CIERRE · Registrar resultado en columna «Resultado obtenido» y marcar «Estado QA». · Resetear solo si el siguiente caso requiere estado inicial incompatible con el actual. Casos del mismo flujo pueden reutilizar el estado. (Ajustes → Borrar mis datos · o solicitar reset al admin de QA) | I75: Pantalla activa de Ruta Despeje. | J75: Invalidar/recalcular la proyección con snapshot, versión y supuestos; no reutilizar cálculo obsoleto. | K75: Fixture sintético (no requiere documento real). Formato: CSV o XLSX con los valores del contrato P4 upstream cerrado. Inyectar al menos: POSITIVE · ZERO · NOT_EVALUABLE. | L75: Sí · con insumo dev | P75: Walvy_M04_Matriz_Trazabilidad_Cliente_v1.3.xlsx · 01_Matriz_Trazabilidad · TR-M04-115 | Q75: En: Pantalla activa de Ruta Despeje. → Invalidar/recalcular la proyección con snapshot, versión y supuestos; no reutilizar cálculo obsoleto.
A76: M04 | B76: TR-M04-116 | C76: F1 · QA funcional local | D76: FLOW-M04-021 · Ruta 2 · Simulación aceptada | E76: Usuario acepta escenario | F76: Simulación | Aceptar simulación | G76: Cuenta de prueba activa y reseteada (sin deudas ni datos previos del flujo). Condición de entrada: Simulación | Aceptar simulación | H76: 📋 FIXTURE REQUERIDO: cuenta seed «rd02-plan-fecha». Email: qa-m04-rd02-plan-fecha-*@walvy.local · Password: Walvy2024! 1. Iniciar sesión con la cuenta seed rd02-plan-fecha. 2. Navegar a: Ruta Despeje → RD-02 Plan → simulación de aporte. 3. Ingresar un aporte hipotético y observar el cronograma recalculado. 4. Tocar «Aceptar escenario» o equivalente. 5. Verificar que el plan muestra el escenario aceptado (duración/orden actualizados). 6. Verificar que NO se ejecutó ningún pago ni transferencia. 7. Verificar que aceptar el escenario NO activa la Ruta. → Si el escenario queda como estimación sin activar Ruta ni ejecutar pago: ✓ PASA. CIERRE · Registrar resultado en «Resultado obtenido» y marcar «Estado QA». · Resetear cuenta solo si el siguiente caso requiere estado diferente al actual. (Perfil → Herramientas QA → «Reiniciar cuenta de prueba» (doble confirmación)) | I76: Pantalla activa de Ruta Despeje. | J76: Actualizar estimación/escenario seleccionado del plan; no ejecutar pago. | K76: ── CUENTA SEED (origin/qa) ── Email : qa-m04-rd02-plan-fecha-*@walvy.local Password: Walvy2024! Grupo : D1 Estado : (misma cuenta que TR-M04-104) RD-02 · simular: POST /route/simulate con extraMonthlyPayment · aceptar escenario (revisionId) (El email exacto queda en la salida del script seed-qa-m04.mjs) | L76: Sí · con insumo dev | P76: Walvy_M04_Matriz_Trazabilidad_Cliente_v1.3.xlsx · 01_Matriz_Trazabilidad · TR-M04-116 | Q76: En: Pantalla activa de Ruta Despeje. → Actualizar estimación/escenario seleccionado del plan; no ejecutar pago.
A77: M04 | B77: TR-M04-117 | C77: F1 · QA funcional local | D77: FLOW-M04-021 · Ruta 2 · Simulación aceptada | E77: Escenario aceptado | F77: Simulación | Aceptar simulación | G77: Cuenta de prueba activa y reseteada (sin deudas ni datos previos del flujo). Condición de entrada: Simulación | Aceptar simulación | H77: 📋 FIXTURE REQUERIDO: cuenta seed «rd02-plan-fecha». Email: qa-m04-rd02-plan-fecha-*@walvy.local · Password: Walvy2024! 1. Continuar desde TR-M04-116 (escenario ya aceptado). 2. Verificar que el plan mantiene la naturaleza estimada (no promete una fecha exacta). 3. Verificar que el orden de deudas y la duración recalculados son coherentes con el aporte aceptado. 4. Navegar atrás y volver a RD-02; verificar que el escenario aceptado persiste. 5. Verificar que el estado de la Ruta sigue siendo «elegible» (no «activa») si no se tocó «Seguir plan». → Si el escenario persiste como estimación sin activar Ruta: ✓ PASA. CIERRE · Registrar resultado en «Resultado obtenido» y marcar «Estado QA». · Resetear cuenta solo si el siguiente caso requiere estado diferente al actual. (Perfil → Herramientas QA → «Reiniciar cuenta de prueba» (doble confirmación)) | I77: Pantalla activa de Ruta Despeje. | J77: Mantener naturaleza estimada; visualizar orden/duración recalculados. Aceptar la simulación no activa la Ruta. | K77: ── CUENTA SEED (origin/qa) ── Email : qa-m04-rd02-plan-fecha-*@walvy.local Password: Walvy2024! Grupo : D1 Estado : (misma cuenta que TR-M04-104) RD-02 · escenario aceptado activo · selected-plan persiste (El email exacto queda en la salida del script seed-qa-m04.mjs) | L77: Sí · con insumo dev | P77: Walvy_M04_Matriz_Trazabilidad_Cliente_v1.3.xlsx · 01_Matriz_Trazabilidad · TR-M04-117 | Q77: En: Pantalla activa de Ruta Despeje. → Mantener naturaleza estimada; visualizar orden/duración recalculados. Aceptar la simulación no activa la Ruta.
A78: M04 | B78: TR-M04-118 | C78: F1 · QA funcional local | D78: FLOW-M04-022 · Ruta 2→3 | E78: Ruta elegible/disponible y usuario ejecuta el primer “Seguir plan” válido desde RD-02 | F78: RD-02 Plan | Seguir plan | G78: Cuenta de prueba activa y reseteada (sin deudas ni datos previos del flujo). Condición de entrada: RD-02 Plan | Seguir plan | H78: 📋 FIXTURE REQUERIDO: cuenta seed «rd02-plan-fecha». Email: qa-m04-rd02-plan-fecha-*@walvy.local · Password: Walvy2024! 1. Iniciar sesión con la cuenta seed rd02-plan-fecha (Ruta elegible, primer «Seguir plan» no ejecutado). 2. Navegar a: Ruta Despeje → RD-02 Plan. 3. Tocar «Seguir plan» (primer tap válido desde RD-02). 4. Verificar que route_eligibility_status cambia de «elegible» → «activa». 5. Verificar que el functional_debt_state cambia a «ruta_activa» para las deudas del plan. 6. Verificar que se persiste el momento de activación (timestamp). 7. Volver a RD-02 y verificar que el estado es ahora «activa» (no puede volver a «elegible»). → Si la activación persiste y el estado es «activa»: ✓ PASA. CIERRE · Registrar resultado en «Resultado obtenido» y marcar «Estado QA». · Resetear cuenta solo si el siguiente caso requiere estado diferente al actual. (Perfil → Herramientas QA → «Reiniciar cuenta de prueba» (doble confirmación)) | I78: Pantalla activa de Ruta Despeje. | J78: Persistir la transición route_eligibility_status=elegible→activa y functional_debt_state=ruta_activa, junto con el momento de inicio. El evento es idempotente: usos posteriores de “Seguir plan” representan continuidad, no nuevas activaciones. | K78: ── CUENTA SEED (origin/qa) ── Email : qa-m04-rd02-plan-fecha-*@walvy.local Password: Walvy2024! Grupo : D1 Estado : (misma cuenta que TR-M04-104) RD-02 · QA hace clic "Seguir plan" → POST /route/apply → ACTIVATION_EVENT → routeState=activa · IMPORTANTE: ejecutar al final de la secuencia D1 (El email exacto queda en la salida del script seed-qa-m04.mjs) | L78: Sí · con insumo dev | P78: Walvy_M04_Matriz_Trazabilidad_Cliente_v1.3.xlsx · 01_Matriz_Trazabilidad · TR-M04-118 | Q78: En: Pantalla activa de Ruta Despeje. → Persistir la transición route_eligibility_status=elegible→activa y functional_debt_state=ruta_activa, junto con el momento de inicio. El evento es idempotente: usos posteriores de “Seguir plan” representan continuidad, no nuevas activaciones.
A79: M04 | B79: TR-M04-119 | C79: F2 · Fixture cross-contract | D79: FLOW-M04-022 · Ruta 2→3 | E79: Existe Ruta activa según estado canónico | F79: RD-03 Avance | Mostrar avance | G79: Cuenta de prueba activa y reseteada (sin deudas ni datos previos del flujo). Condición de entrada: RD-03 Avance | Mostrar avance | H79: Seguir flujo de FLOW-M04-022 · Ruta 2→3. CIERRE · Registrar resultado en columna «Resultado obtenido» y marcar «Estado QA». · Resetear solo si el siguiente caso requiere estado inicial incompatible con el actual. Casos del mismo flujo pueden reutilizar el estado. (Ajustes → Borrar mis datos · o solicitar reset al admin de QA) | I79: Pantalla activa de Ruta Despeje. | J79: Mostrar avance con saldo, compromiso/pagos consumidos, progreso estimado y próxima acción; conservar el estado activo y el momento inicial en continuidad/retoma sin emitir una nueva activación. | K79: Fixture sintético (no requiere documento real). Formato: CSV o XLSX con los valores del contrato P4 upstream cerrado. Inyectar al menos: POSITIVE · ZERO · NOT_EVALUABLE. | L79: Sí · con insumo dev | P79: Walvy_M04_Matriz_Trazabilidad_Cliente_v1.3.xlsx · 01_Matriz_Trazabilidad · TR-M04-119 | Q79: En: Pantalla activa de Ruta Despeje. → Mostrar avance con saldo, compromiso/pagos consumidos, progreso estimado y próxima acción; conservar el estado activo y el momento inicial en continuidad/retoma sin emitir una nueva activación.
A80: M04 | B80: TR-M04-120 | C80: F1 · QA funcional local | D80: FLOW-M04-022 · Ruta 2→3 | E80: Usuario consulta pagos recientes/historial | F80: RD-03 Avance | Ver historial | G80: Cuenta de prueba activa y reseteada (sin deudas ni datos previos del flujo). Condición de entrada: RD-03 Avance | Ver historial | H80: 📋 FIXTURE REQUERIDO: cuenta seed «rd03-avance». Email: qa-m04-rd03-avance-*@walvy.local · Password: Walvy2024! 1. Iniciar sesión con la cuenta seed rd03-avance (Ruta activa, en avance/seguimiento). 2. Navegar a: Ruta Despeje → RD-03 Avance. 3. Localizar el CTA de historial de pagos / pagos recientes. 4. Tocar el CTA y verificar que deriva a M06/Pagos (no muestra un historial propio de M04). 5. Verificar que M04 NO crea un registro operativo de pagos paralelo al de M06. → Si el CTA va a M06 y M04 no tiene historial propio: ✓ PASA. CIERRE · Registrar resultado en «Resultado obtenido» y marcar «Estado QA». · Resetear cuenta solo si el siguiente caso requiere estado diferente al actual. (Perfil → Herramientas QA → «Reiniciar cuenta de prueba» (doble confirmación)) | I80: Pantalla activa de Ruta Despeje. | J80: Derivar a M06/Pagos; M04 no crea historial operativo paralelo. | K80: ── CUENTA SEED (origin/qa) ── Email : qa-m04-rd03-avance-*@walvy.local Password: Walvy2024! Grupo : E1 Estado : RD-03 avance · ruta ACTIVA · 2 deudas: d1=$250k(próx-a-cerrar) d2=$1.8M · historial pagos → verificar CTA M06 (El email exacto queda en la salida del script seed-qa-m04.mjs) | L80: Sí · con insumo dev | P80: Walvy_M04_Matriz_Trazabilidad_Cliente_v1.3.xlsx · 01_Matriz_Trazabilidad · TR-M04-120 | Q80: En: Pantalla activa de Ruta Despeje. → Derivar a M06/Pagos; M04 no crea historial operativo paralelo.
A81: M04 | B81: TR-M04-121 | C81: F1 · QA funcional local | D81: FLOW-M04-022 · Ruta 2→3 | E81: Usuario continúa a lectura estructural | F81: RD-03 Avance | Ir a Perfil Financiero | G81: Cuenta de prueba activa y reseteada (sin deudas ni datos previos del flujo). Condición de entrada: RD-03 Avance | Ir a Perfil Financiero | H81: 📋 FIXTURE REQUERIDO: cuenta seed «rd03-avance». Email: qa-m04-rd03-avance-*@walvy.local · Password: Walvy2024! 1. Iniciar sesión con la cuenta seed rd03-avance (Ruta activa). 2. Navegar a: Ruta Despeje → RD-03 Avance. 3. Tocar «Ir a Perfil Financiero» o equivalente (lectura estructural). 4. Verificar que navega a Perfil Financiero conservando el estado canónico de la Ruta. 5. Verificar que Perfil Financiero muestra la Ruta como información de contexto pero NO embebe la pantalla completa de Ruta. → Si Perfil muestra contexto de Ruta sin embeberla y el estado se conserva: ✓ PASA. CIERRE · Registrar resultado en «Resultado obtenido» y marcar «Estado QA». · Resetear cuenta solo si el siguiente caso requiere estado diferente al actual. (Perfil → Herramientas QA → «Reiniciar cuenta de prueba» (doble confirmación)) | I81: Pantalla activa de Ruta Despeje. | J81: Navegar a Perfil conservando estado canónico; Perfil no embebe Ruta completa. | K81: ── CUENTA SEED (origin/qa) ── Email : qa-m04-rd03-avance-*@walvy.local Password: Walvy2024! Grupo : E1 Estado : (misma cuenta que TR-M04-120) RD-03 avance · ruta activa · navegación a perfil financiero (El email exacto queda en la salida del script seed-qa-m04.mjs) | L81: Sí · con insumo dev | P81: Walvy_M04_Matriz_Trazabilidad_Cliente_v1.3.xlsx · 01_Matriz_Trazabilidad · TR-M04-121 | Q81: En: Pantalla activa de Ruta Despeje. → Navegar a Perfil conservando estado canónico; Perfil no embebe Ruta completa.
A82: M04 | B82: TR-M04-122 | C82: F1 · QA funcional local | D82: FLOW-M04-022 · Ruta 2→3 | E82: Cierre/avance recalculado produce una next_suggested_debt nueva y vigente. | F82: RD-03 Avance | Mostrar siguiente deuda | G82: Cuenta de prueba activa y reseteada (sin deudas ni datos previos del flujo). Condición de entrada: RD-03 Avance | Mostrar siguiente deuda | H82: 📋 FIXTURE REQUERIDO: cuenta seed «rd03-avance». Email: qa-m04-rd03-avance-*@walvy.local · Password: Walvy2024! 1. Iniciar sesión con la cuenta seed rd03-avance (Ruta activa con avance que genera nueva deuda sugerida). 2. Navegar a: Ruta Despeje → RD-03 Avance. 3. Verificar que la app muestra la «siguiente deuda sugerida» (next_suggested_debt) correctamente. 4. Verificar que la sugerencia es coherente con el plan snowball (menor saldo pendiente). 5. Verificar que la capacidad liberada (si aplica) enriquece el payload sin cambiar el Foco del Mes (M02). 6. Verificar que el Foco del Mes (M02) NO cambió automáticamente por el avance en Ruta. → Si la siguiente deuda aparece correcta y el Foco M02 no cambió: ✓ PASA. CIERRE · Registrar resultado en «Resultado obtenido» y marcar «Estado QA». · Resetear cuenta solo si el siguiente caso requiere estado diferente al actual. (Perfil → Herramientas QA → «Reiniciar cuenta de prueba» (doble confirmación)) | I82: Pantalla activa de Ruta Despeje. | J82: F7 recomienda revisar la siguiente deuda; capacidad liberada puede enriquecer el payload si es válida; no cambiar Foco del Mes. | K82: ── CUENTA SEED (origin/qa) ── Email : qa-m04-rd03-avance-*@walvy.local Password: Walvy2024! Grupo : E1 Estado : (misma cuenta que TR-M04-120) RD-03 avance · cerrar d1 → evaluateAndPublish → next_suggested_debt pasa a d2 · recálculo snowball (El email exacto queda en la salida del script seed-qa-m04.mjs) | L82: Sí · con insumo dev | P82: Walvy_M04_Matriz_Trazabilidad_Cliente_v1.3.xlsx · 01_Matriz_Trazabilidad · TR-M04-122 | Q82: En: Pantalla activa de Ruta Despeje. → F7 recomienda revisar la siguiente deuda; capacidad liberada puede enriquecer el payload si es válida; no cambiar Foco del Mes.
A83: M04 | B83: TR-M04-123 | C83: F1 · QA funcional local | D83: FLOW-M04-022 · Ruta 2→3 | E83: Figma muestra “Capacidad de ahorro a recuperar (estimado)” | F83: RD-03 Avance | Copy capacidad | G83: Cuenta de prueba activa y reseteada (sin deudas ni datos previos del flujo). Condición de entrada: RD-03 Avance | Copy capacidad | H83: 1. Iniciar sesión con cualquier cuenta con Ruta activa en RD-03 Avance. 2. Navegar a: Ruta Despeje → RD-03 Avance. 3. Localizar el texto que menciona la capacidad relacionada con deudas. 4. Verificar que el copy usa la semántica «Capacidad de ahorro a recuperar (estimado)» o equivalente de capacidad liberable. 5. Verificar que NO dice «capacidad de ahorro disponible» (que es competencia de M05). 6. Verificar que está marcado como estimado (no como una cifra exacta garantizada). → Si el copy es «recuperar/liberar» (estimado) y no es ahorro general M05: ✓ PASA. CIERRE · Registrar resultado en «Resultado obtenido» y marcar «Estado QA». · Resetear cuenta solo si el siguiente caso requiere estado diferente al actual. (Perfil → Herramientas QA → «Reiniciar cuenta de prueba» (doble confirmación)) | I83: Pantalla activa de Ruta Despeje. | J83: La obligación documental exige capacidad recuperable/liberable por deuda, no capacidad de ahorro general M05. | L83: Sí | P83: Walvy_M04_Matriz_Trazabilidad_Cliente_v1.3.xlsx · 01_Matriz_Trazabilidad · TR-M04-123 | Q83: En: Pantalla activa de Ruta Despeje. → La obligación documental exige capacidad recuperable/liberable por deuda, no capacidad de ahorro general M05.
A84: M04 | B84: TR-M04-124 | C84: F1 · QA funcional local | D84: FLOW-M04-022 · Ruta 2→3 | E84: Figma muestra “Siguiente foco sugerido” | F84: RD-03 Avance | Copy siguiente foco | G84: Cuenta de prueba activa y reseteada (sin deudas ni datos previos del flujo). Condición de entrada: RD-03 Avance | Copy siguiente foco | H84: 1. Iniciar sesión con cualquier cuenta con Ruta activa en RD-03 Avance y múltiples deudas. 2. Navegar a: Ruta Despeje → RD-03 Avance. 3. Localizar el bloque que muestra la «Siguiente deuda sugerida» o «Siguiente foco». 4. Verificar que el texto usa «siguiente deuda» o «próximo paso» (no «Foco del Mes» que es M02). 5. Verificar que la deuda mostrada corresponde a la siguiente en el plan snowball. 6. Verificar que este bloque NO sobrescribe ni reemplaza el Foco del Mes de M02. → Si muestra «siguiente deuda» correcta sin interferir con Foco M02: ✓ PASA. CIERRE · Registrar resultado en «Resultado obtenido» y marcar «Estado QA». · Resetear cuenta solo si el siguiente caso requiere estado diferente al actual. (Perfil → Herramientas QA → «Reiniciar cuenta de prueba» (doble confirmación)) | I84: Pantalla activa de Ruta Despeje. | J84: La obligación funcional debe mantenerse como próxima deuda/próximo paso salvo regla formal de Foco. | L84: Sí | P84: Walvy_M04_Matriz_Trazabilidad_Cliente_v1.3.xlsx · 01_Matriz_Trazabilidad · TR-M04-124 | Q84: En: Pantalla activa de Ruta Despeje. → La obligación funcional debe mantenerse como próxima deuda/próximo paso salvo regla formal de Foco.
A85: M04 | B85: TR-M04-125 | C85: F2 · Fixture cross-contract | D85: FLOW-M04-023 · Ruta 3 · Cierre | E85: possible_closure cambia false→true con closed=false. | F85: RD-03 Avance | Detectar posible cierre | G85: Cuenta de prueba activa y reseteada (sin deudas ni datos previos del flujo). Condición de entrada: RD-03 Avance | Detectar posible cierre | H85: Seguir flujo de FLOW-M04-023 · Ruta 3 · Cierre. CIERRE · Registrar resultado en columna «Resultado obtenido» y marcar «Estado QA». · Resetear solo si el siguiente caso requiere estado inicial incompatible con el actual. Casos del mismo flujo pueden reutilizar el estado. (Ajustes → Borrar mis datos · o solicitar reset al admin de QA) | I85: Pantalla activa de Ruta Despeje. | J85: Hacer nacer F6 una sola vez por instancia; solicitar confirmación funcional. Persistencia true→true actualiza la misma situación, no crea otra. | K85: Fixture sintético (no requiere documento real). Formato: CSV o XLSX con los valores del contrato P4 upstream cerrado. Inyectar al menos: POSITIVE · ZERO · NOT_EVALUABLE. | L85: Sí · con insumo dev | P85: Walvy_M04_Matriz_Trazabilidad_Cliente_v1.3.xlsx · 01_Matriz_Trazabilidad · TR-M04-125 | Q85: En: Pantalla activa de Ruta Despeje. → Hacer nacer F6 una sola vez por instancia; solicitar confirmación funcional. Persistencia true→true actualiza la misma situación, no crea otra.
A86: M04 | B86: TR-M04-126 | C86: F1 · QA funcional local | D86: FLOW-M04-023 · Ruta 3 · Cierre | E86: Usuario confirma cierre con evidencia funcional suficiente | F86: RD-03 / modal cierre | Confirmar cierre | G86: Cuenta de prueba activa y reseteada (sin deudas ni datos previos del flujo). Condición de entrada: RD-03 / modal cierre | Confirmar cierre | H86: 📋 FIXTURE REQUERIDO: cuenta seed «rd03-cierre». Email: qa-m04-rd03-cierre-*@walvy.local · Password: Walvy2024! 1. Iniciar sesión con la cuenta seed rd03-cierre (Ruta activa, deuda en condición de cierre). 2. Navegar a: Ruta Despeje → RD-03 Avance → deuda que puede cerrarse. 3. Tocar «Confirmar cierre» o equivalente (modal de cierre con evidencia funcional). 4. Completar los datos requeridos por el modal (confirmación de pago total / evidencia). 5. Verificar que la deuda cambia a estado «cerrada» en el estado canónico. 6. Verificar que la deuda cerrada se excluye de la lista de deudas activas del plan. → Si la deuda queda cerrada y excluida del plan activo: ✓ PASA. CIERRE · Registrar resultado en «Resultado obtenido» y marcar «Estado QA». · Resetear cuenta solo si el siguiente caso requiere estado diferente al actual. (Perfil → Herramientas QA → «Reiniciar cuenta de prueba» (doble confirmación)) | I86: Pantalla activa de Ruta Despeje. | J86: Cambiar deuda a cerrada en estado canónico y excluirla de deuda activa. | K86: ── CUENTA SEED (origin/qa) ── Email : qa-m04-rd03-cierre-*@walvy.local Password: Walvy2024! Grupo : F1 Estado : RD-03 cierre · ruta ACTIVA · dCierre con possible_closure=true (current_balance=0) · dResto=$1.5M para recálculo · modal F6 listo (El email exacto queda en la salida del script seed-qa-m04.mjs) | L86: Sí · con insumo dev | P86: Walvy_M04_Matriz_Trazabilidad_Cliente_v1.3.xlsx · 01_Matriz_Trazabilidad · TR-M04-126 | Q86: En: Pantalla activa de Ruta Despeje. → Cambiar deuda a cerrada en estado canónico y excluirla de deuda activa.
A87: M04 | B87: TR-M04-127 | C87: F1 · QA funcional local | D87: FLOW-M04-023 · Ruta 3 · Cierre | E87: Deuda cerrada confirmada | F87: RD-03 | Recalcular | G87: Cuenta de prueba activa y reseteada (sin deudas ni datos previos del flujo). Condición de entrada: RD-03 | Recalcular | H87: 📋 FIXTURE REQUERIDO: cuenta seed «rd03-cierre». Email: qa-m04-rd03-cierre-*@walvy.local · Password: Walvy2024! 1. Continuar desde TR-M04-126 (deuda recién cerrada confirmada). 2. Verificar que la app recalcula la capacidad liberada (cuota mensual que queda disponible). 3. Verificar que el orden de las deudas restantes en el plan se actualiza (siguiente deuda prioritaria). 4. Verificar que el cronograma estimado de la Ruta se actualiza con el cierre. 5. Verificar que NO se generó ningún movimiento de dinero automático ni transferencia. → Si el plan se recalcula sin ejecutar pago automático: ✓ PASA. CIERRE · Registrar resultado en «Resultado obtenido» y marcar «Estado QA». · Resetear cuenta solo si el siguiente caso requiere estado diferente al actual. (Perfil → Herramientas QA → «Reiniciar cuenta de prueba» (doble confirmación)) | I87: Pantalla activa de Ruta Despeje. | J87: Recalcular capacidad liberada, orden, cronograma y siguiente deuda; no mover dinero automáticamente. | K87: ── CUENTA SEED (origin/qa) ── Email : qa-m04-rd03-cierre-*@walvy.local Password: Walvy2024! Grupo : F1 Estado : (misma cuenta que TR-M04-126) RD-03 cierre · deuda cerrada → plan recalcula sin ella · requiresRecalculation=true (El email exacto queda en la salida del script seed-qa-m04.mjs) | L87: Sí · con insumo dev | P87: Walvy_M04_Matriz_Trazabilidad_Cliente_v1.3.xlsx · 01_Matriz_Trazabilidad · TR-M04-127 | Q87: En: Pantalla activa de Ruta Despeje. → Recalcular capacidad liberada, orden, cronograma y siguiente deuda; no mover dinero automáticamente.
A88: M04 | B88: TR-M04-128 | C88: F2 · Fixture cross-contract | D88: FLOW-M04-023 · Ruta 3 · Cierre | E88: Cierre confirmado cambia el snapshot financiero | F88: RD-03 | Reevaluar Presión/Salud | G88: Cuenta de prueba activa y reseteada (sin deudas ni datos previos del flujo). Condición de entrada: RD-03 | Reevaluar Presión/Salud | H88: Seguir flujo de FLOW-M04-023 · Ruta 3 · Cierre. CIERRE · Registrar resultado en columna «Resultado obtenido» y marcar «Estado QA». · Resetear solo si el siguiente caso requiere estado inicial incompatible con el actual. Casos del mismo flujo pueden reutilizar el estado. (Ajustes → Borrar mis datos · o solicitar reset al admin de QA) | I88: Pantalla activa de Ruta Despeje. | J88: Recalcular Presión y Salud con el nuevo snapshot; el resultado puede mejorar o empeorar según reglas vigentes. No conservar estado obsoleto. | K88: Fixture sintético (no requiere documento real). Formato: CSV o XLSX con los valores del contrato P4 upstream cerrado. Inyectar al menos: POSITIVE · ZERO · NOT_EVALUABLE. | L88: Sí · con insumo dev | P88: Walvy_M04_Matriz_Trazabilidad_Cliente_v1.3.xlsx · 01_Matriz_Trazabilidad · TR-M04-128 | Q88: En: Pantalla activa de Ruta Despeje. → Recalcular Presión y Salud con el nuevo snapshot; el resultado puede mejorar o empeorar según reglas vigentes. No conservar estado obsoleto.
A89: M04 | B89: TR-M04-129 | C89: F1 · QA funcional local | D89: FLOW-M04-023 · Ruta 3 · Cierre | E89: Cierre ya confirmado | F89: RD-03 | Post-confirmación | G89: Cuenta de prueba activa y reseteada (sin deudas ni datos previos del flujo). Condición de entrada: RD-03 | Post-confirmación | H89: 📋 FIXTURE REQUERIDO: cuenta seed «rd03-cierre». Email: qa-m04-rd03-cierre-*@walvy.local · Password: Walvy2024! 1. Continuar desde TR-M04-126/127 (cierre ya confirmado, plan recalculado). 2. Verificar que la app muestra el modal «¡Felicitaciones!» (o equivalente de celebración de cierre). 3. Tocar «Continuar con el plan». 4. Verificar que navega de vuelta a RD-03 Avance (con el plan actualizado). 5. Verificar que la deuda cerrada ya no aparece en la lista activa del plan. 6. Verificar que el estado general de la Ruta se mantiene como «activa». → Si aparece el modal, vuelve a RD-03 y el plan está actualizado: ✓ PASA. CIERRE · Registrar resultado en «Resultado obtenido» y marcar «Estado QA». · Resetear cuenta solo si el siguiente caso requiere estado diferente al actual. (Perfil → Herramientas QA → «Reiniciar cuenta de prueba» (doble confirmación)) | I89: Pantalla activa de Ruta Despeje. | J89: Tras confirmar cierre, mostrar modal ¡Felicitaciones!; al seleccionar Continuar con el plan, retornar a RD-03 · Avance actualizado. | K89: ── CUENTA SEED (origin/qa) ── Email : qa-m04-rd03-cierre-*@walvy.local Password: Walvy2024! Grupo : F1 Estado : (misma cuenta que TR-M04-126) RD-03 cierre · modal felicitaciones + RD-03 actualizado tras cierre (El email exacto queda en la salida del script seed-qa-m04.mjs) | L89: Sí · con insumo dev | P89: Walvy_M04_Matriz_Trazabilidad_Cliente_v1.3.xlsx · 01_Matriz_Trazabilidad · TR-M04-129 | Q89: En: Pantalla activa de Ruta Despeje. → Tras confirmar cierre, mostrar modal ¡Felicitaciones!; al seleccionar Continuar con el plan, retornar a RD-03 · Avance actualizado.
A90: M04 | B90: TR-M04-130 | C90: F1 · QA funcional local | D90: FLOW-M04-024 · Entrada directa / reingreso | E90: Existe deuda confirmada + datos mínimos + Presión final Riesgo; o existe Ruta activa previa | F90: Home/Perfil/reingreso | Evaluar estado previo | G90: Cuenta de prueba activa y reseteada (sin deudas ni datos previos del flujo). Condición de entrada: Home/Perfil/reingreso | Evaluar estado previo | H90: 📋 FIXTURE REQUERIDO: cuenta seed «reingreso-gate» (sub-escenario A). Email: qa-m04-reingreso-gate-*@walvy.local · Password: Walvy2024! 1. Iniciar sesión con la cuenta seed reingreso-gate (deuda confirmada + datos mínimos + Presión=Riesgo). 2. Navegar a: Home o Perfil Financiero → buscar el CTA de Ruta Despeje / acceso directo. 3. Tocar el CTA de entrada directa. 4. Verificar que la app evalúa el gate y permite acceso directo a RD-01 como elegible/disponible. 5. Verificar que NO reinicia OD-01/OD-02 (no vuelve a pedir captura de deudas). Sub-escenario B (si hay Ruta activa previa): usar cuenta seed «reingreso-activa-y-faltante». Email: qa-m04-reingreso-activa-y-faltante-*@walvy.local 6. Verificar que con Ruta ya activa, el acceso directo retoma el estado activo (RD-03 Avance) sin reiniciar. → Si la entrada directa lleva a RD-01 elegible o retoma el estado activo: ✓ PASA. CIERRE · Registrar resultado en «Resultado obtenido» y marcar «Estado QA». · Resetear cuenta solo si el siguiente caso requiere estado diferente al actual. (Perfil → Herramientas QA → «Reiniciar cuenta de prueba» (doble confirmación)) | I90: Pantalla activa de Ruta Despeje. | J90: Con gate completo y sin Ruta activa, permitir entrada directa a RD-01 como elegible/disponible. Si ya está activa, conservar estado y momento inicial; no reactivar. | K90: ── CUENTA SEED (origin/qa) ── Email : qa-m04-reingreso-gate / reingreso-activa-y-faltante-*@walvy.local Password: Walvy2024! Grupo : G1+G2 Estado : G1(slug=reingreso-gate): ruta elegible sin activar → Home→RD-01 directo. G2(slug=reingreso-activa-y-faltante): ruta activa → reingreso conserva estado (130B) (El email exacto queda en la salida del script seed-qa-m04.mjs) | L90: Sí · con insumo dev | P90: Walvy_M04_Matriz_Trazabilidad_Cliente_v1.3.xlsx · 01_Matriz_Trazabilidad · TR-M04-130 | Q90: En: Pantalla activa de Ruta Despeje. → Con gate completo y sin Ruta activa, permitir entrada directa a RD-01 como elegible/disponible. Si ya está activa, conservar estado y momento inicial; no reactivar.
A91: M04 | B91: TR-M04-131 | C91: F1 · QA funcional local | D91: FLOW-M04-024 · Entrada directa / reingreso | E91: Falta dato crítico/confirmación | F91: Home/Perfil/reingreso | Evaluar estado previo | G91: Cuenta de prueba activa y reseteada (sin deudas ni datos previos del flujo). Condición de entrada: Home/Perfil/reingreso | Evaluar estado previo | H91: 📋 FIXTURE REQUERIDO: cuenta seed «reingreso-activa-y-faltante». Email: qa-m04-reingreso-activa-y-faltante-*@walvy.local · Password: Walvy2024! 1. Iniciar sesión con la cuenta seed reingreso-activa-y-faltante (falta dato crítico o confirmación). 2. Navegar a: Home o Perfil Financiero → CTA de Ruta Despeje / acceso directo. 3. Tocar el CTA de entrada directa. 4. Verificar que la app deriva a OD-02 para completar el dato faltante o confirmar la deuda pendiente. 5. Verificar que NO reinicia OD-01 (no vuelve a pedir carga de documento). 6. Verificar que las deudas ya existentes NO se duplican. → Si deriva a OD-02 sin reiniciar captura ni duplicar deudas: ✓ PASA. CIERRE · Registrar resultado en «Resultado obtenido» y marcar «Estado QA». · Resetear cuenta solo si el siguiente caso requiere estado diferente al actual. (Perfil → Herramientas QA → «Reiniciar cuenta de prueba» (doble confirmación)) | I91: Pantalla activa de Ruta Despeje. | J91: Derivar a OD-02 completitud/revisión sin reiniciar captura ni duplicar deuda. | K91: ── CUENTA SEED (origin/qa) ── Email : qa-m04-reingreso-activa-y-faltante-*@walvy.local Password: Walvy2024! Grupo : G2 Estado : (misma cuenta G2 que TR-M04-130B) dFaltante=unconfirmed+sin-cuota → resolveDebtEntryPoint→surface=revision → deriva OD-02 (El email exacto queda en la salida del script seed-qa-m04.mjs) | L91: Sí · con insumo dev | P91: Walvy_M04_Matriz_Trazabilidad_Cliente_v1.3.xlsx · 01_Matriz_Trazabilidad · TR-M04-131 | Q91: En: Pantalla activa de Ruta Despeje. → Derivar a OD-02 completitud/revisión sin reiniciar captura ni duplicar deuda.
A92: M04 | B92: TR-M04-132 | C92: F1 · QA funcional local | D92: FLOW-M04-007 · Onboarding 2 · Revisión | E92: Existe dato/regla fuente que respalda una etiqueta MVP | F92: OD-02 | Mostrar etiqueta funcional | G92: Cuenta de prueba reseteada. Fixture con al menos 1 deuda detectada por importación de documento (origin='document') que aún NO fue confirmada manualmente (confirmationStatus='unconfirmed'). | H92: 📋 FIXTURE REQUERIDO: deuda importada de documento, sin confirmar (origin=document, status=unconfirmed). 1. Iniciar sesión con cuenta de prueba reseteada. 2. Subir fixture CSV/XLSX con una deuda de origen documental (la app la marca como origin=document). 3. Navegar a: OD-02 Revisión de deudas (RouteConsideredScreen) sin confirmar la deuda. 4. En la card de la deuda aún no confirmada, verificar que aparece el chip amarillo «No planificado». → Si el chip está visible: ✓ PASA. 5. Confirmar la deuda manualmente y verificar que el chip «No planificado» DESAPARECE. → Si desaparece al confirmar: ✓ PASA. 6. Verificar que el chip NO reemplaza ni oculta el CTA dominante de la pantalla. CIERRE · Registrar resultado en «Resultado obtenido» y marcar «Estado QA». · Resetear cuenta solo si el siguiente caso requiere estado diferente al actual. (Perfil → Herramientas QA → «Reiniciar cuenta de prueba» (doble confirmación)) | I92: Pantalla Revisión de deudas (OD-02) / RouteConsideredScreen → chip «No planificado» (amarillo). | J92: Etiqueta sobre deuda detectada/recurrente/no planificada o que requiere revisión. La etiqueta no reemplaza severidad, validación ni CTA dominante. | K92: Fixture sintético CSV o XLSX con 1 deuda: nombre: «Tarjeta Ripley» (o cualquier acreedor) saldo: $200.000 origen: importada desde documento (la app la marca como origin='document' automáticamente cuando proviene de kread/CSV de estado de cuenta). No confirmar manualmente: la deuda debe quedar en estado 'unconfirmed'. | L92: Sí | O92: Backend: functional-tags.rule.ts → computeBasicTags(). Condición: origin==='document' && confirmationStatus==='unconfirmed' → ['no_planificado']. Frontend: FunctionalTagChip.tsx, testID=functional-tag-no_planificado. Chip NO persiste en DB: se calcula on-the-fly en cada respuesta. | P92: Walvy_M04_Matriz_Trazabilidad_Cliente_v1.3.xlsx · 01_Matriz_Trazabilidad · TR-M04-132 | Q92: En: Pantalla Revisión de deudas (OD-02) / RouteConsideredScreen → chip «No planificado» (amarillo). → Etiqueta sobre deuda detectada/recurrente/no planificada o que requiere revisión. La etiqueta no reemplaza severidad, validación ni CTA dominante.
A93: M04 | B93: TR-M04-133 | C93: F1 · QA funcional local | D93: FLOW-M04-016 · Ruta 1 · Resumen | E93: Existe dato/regla fuente que respalda una etiqueta MVP | F93: RD-01 | Mostrar etiqueta funcional | G93: Cuenta de prueba reseteada. Deuda confirmada (confirmationStatus='confirmed') con nextDueDate = HOY + 3 días (o cualquier fecha dentro de los próximos 7 días). Ruta activa con vista RD-01 Resumen. | H93: 📋 FIXTURE REQUERIDO: deuda confirmada con nextDueDate = HOY + 3 días (o cualquier fecha ≤7 días). 1. Iniciar sesión con cuenta seed rd01-elegible o cualquier cuenta con deuda confirmada con vencimiento próximo. 2. Navegar a: Ruta Despeje → RD-01 Resumen (RouteConsideredScreen). 3. En la card de la deuda con vencimiento próximo (≤7 días), verificar que aparece el chip rojo «Urgente». → Si el chip está visible: ✓ PASA. 4. Verificar que el chip NO reemplaza ni oculta la severidad principal de la pantalla ni el CTA dominante. 5. Editar la fecha de vencimiento a más de 7 días y volver a RD-01; verificar que el chip «Urgente» desaparece. → Si desaparece al cambiar la fecha: ✓ PASA (tag calculado on-the-fly). CIERRE · Registrar resultado en «Resultado obtenido» y marcar «Estado QA». · Resetear cuenta solo si el siguiente caso requiere estado diferente al actual. (Perfil → Herramientas QA → «Reiniciar cuenta de prueba» (doble confirmación)) | I93: Pantalla Resumen de Ruta (RD-01) / RouteConsideredScreen → chip «Urgente» (rojo). | J93: Etiqueta que explica señal principal o motivo de atención. La etiqueta no reemplaza severidad, validación ni CTA dominante. | K93: Deuda de prueba ya confirmada con campo nextDueDate = fecha de hoy + 3 días. Formato de fecha en fixture: YYYY-MM-DD. Umbral exacto: URGENTE_DAYS = 7 (días ≥0 y ≤7 desde hoy). | L93: Sí | O93: Backend: functional-tags.rule.ts → computeBasicTags(). Condición: confirmationStatus==='confirmed' && nextDueDate dentro de [0, 7] días. Constante: URGENTE_DAYS = 7. Frontend: FunctionalTagChip.tsx, testID=functional-tag-urgente. | P93: Walvy_M04_Matriz_Trazabilidad_Cliente_v1.3.xlsx · 01_Matriz_Trazabilidad · TR-M04-133 | Q93: En: Pantalla Resumen de Ruta (RD-01) / RouteConsideredScreen → chip «Urgente» (rojo). → Etiqueta que explica señal principal o motivo de atención. La etiqueta no reemplaza severidad, validación ni CTA dominante.
A94: M04 | B94: TR-M04-134 | C94: F1 · QA funcional local | D94: FLOW-M04-019 · Ruta 2 · Plan | E94: Existe dato/regla fuente que respalda una etiqueta MVP | F94: RD-02 | Mostrar etiqueta funcional | G94: Cuenta de prueba reseteada. Al menos 1 deuda confirmada cuya cancelación libera capacidad de pago (el plan la identifica en recoverableCapacity.components). Ruta activa con plan RD-02 generado. | H94: 📋 FIXTURE REQUERIDO: cuenta seed «rd02-plan-fecha» con al menos 1 deuda que el plan identifica como liberadora de capacidad. Email: qa-m04-rd02-plan-fecha-*@walvy.local · Password: Walvy2024! 1. Iniciar sesión con la cuenta seed rd02-plan-fecha. 2. Navegar a: Ruta Despeje → RD-02 Plan (RoutePlanScreen) → lista de deudas (PlanOrderList). 3. Buscar la deuda que el plan identifica como prioritaria / liberadora de capacidad. 4. Verificar que esa card muestra el chip verde «Recuperable». → Si el chip aparece: ✓ PASA. 5. Verificar que el chip NO aparece en deudas que no están en recoverableCapacity. 6. Verificar que el chip NO reemplaza ni oculta la severidad ni el CTA del plan. CIERRE · Registrar resultado en «Resultado obtenido» y marcar «Estado QA». · Resetear cuenta solo si el siguiente caso requiere estado diferente al actual. (Perfil → Herramientas QA → «Reiniciar cuenta de prueba» (doble confirmación)) | I94: Pantalla Plan de deudas (RD-02) / RoutePlanScreen → PlanOrderList → chip «Recuperable» (verde). | J94: Etiqueta sobre deuda prioritaria, siguiente deuda o capacidad recuperable. La etiqueta no reemplaza severidad, validación ni CTA dominante. | K94: ── CUENTA SEED (origin/qa) ── Email : qa-m04-rd02-plan-fecha-*@walvy.local Password: Walvy2024! Grupo : D1 Estado : (misma cuenta que TR-M04-104) RD-02 · tag recuperable en d1 (menor saldo, con cuota) · buildDebtTags→enrichWithPlanTags → verificar render en PlanOrderList (El email exacto queda en la salida del script seed-qa-m04.mjs) Deuda de prueba confirmada con saldo/cuota que el plan puede liberar. El backend marca la deuda en route.service.ts → buildDebtTags() → enrichWithPlanTags(). No hay campo fixture especial: depende del resultado del cálculo del plan. | L94: Sí · con insumo dev | O94: Backend: functional-tags.rule.ts → enrichWithPlanTags(debtId, basicTags, recoverableDebtIds). Origen: route.service.ts → buildDebtTags() → recoverableCapacity.components. Frontend: PlanOrderList.tsx, FunctionalTagRow, testID=functional-tag-recuperable. | P94: Walvy_M04_Matriz_Trazabilidad_Cliente_v1.3.xlsx · 01_Matriz_Trazabilidad · TR-M04-134 | Q94: En: Pantalla Plan de deudas (RD-02) / RoutePlanScreen → PlanOrderList → chip «Recuperable» (verde). → Etiqueta sobre deuda prioritaria, siguiente deuda o capacidad recuperable. La etiqueta no reemplaza severidad, validación ni CTA dominante.
A95: M04 | B95: TR-M04-135 | C95: F1 · QA funcional local | D95: FLOW-M04-017 · Detalle deuda | E95: Existe dato/regla fuente que respalda una etiqueta MVP | F95: DD-01 | Mostrar etiqueta funcional | G95: Cuenta de prueba reseteada. Deuda confirmada con nextDueDate = HOY + 3 días (o cualquier fecha ≤7 días). Plan RD-02 activo con esa deuda incluida. | H95: 📋 FIXTURE REQUERIDO: deuda confirmada con nextDueDate = HOY + 3 días (dentro del plan RD-02 activo). 1. Iniciar sesión con cuenta seed dd01-activa o cuenta con Ruta activa y deuda con vencimiento próximo. 2. Navegar a: Ruta Despeje → RD-02 Plan → tocar la deuda urgente → DD-01 Detalle (RoutePlanDetailScreen). 3. En la pantalla de detalle, verificar que aparece el chip rojo «Urgente» bajo los datos de la deuda. → Si el chip aparece: ✓ PASA. 4. Verificar que el chip NO reemplaza ni oculta la información de severidad ni el CTA dominante. 5. Verificar que una deuda cuyo nextDueDate es >7 días NO muestra el chip «Urgente» en esta misma pantalla. CIERRE · Registrar resultado en «Resultado obtenido» y marcar «Estado QA». · Resetear cuenta solo si el siguiente caso requiere estado diferente al actual. (Perfil → Herramientas QA → «Reiniciar cuenta de prueba» (doble confirmación)) | I95: Pantalla Detalle de deuda (DD-01) / RoutePlanDetailScreen → chip «Urgente» (rojo) bajo datos de deuda. | J95: Etiqueta de patrón, urgencia o recurrencia de deuda específica. La etiqueta no reemplaza severidad, validación ni CTA dominante. | K95: Deuda de prueba confirmada con campo nextDueDate = fecha HOY + 3 días. Misma condición que TR-M04-133 (urgente) pero verificada en pantalla de detalle. Umbral: URGENTE_DAYS = 7 (functional-tags.rule.ts). | L95: Sí | O95: Backend: functional-tags.rule.ts → computeBasicTags(). Misma regla que TR-M04-133: confirmed + nextDueDate en [0,7] días. Frontend: RoutePlanDetailScreen.tsx → FunctionalTagRow, testID=functional-tag-urgente. | P95: Walvy_M04_Matriz_Trazabilidad_Cliente_v1.3.xlsx · 01_Matriz_Trazabilidad · TR-M04-135 | Q95: En: Pantalla Detalle de deuda (DD-01) / RoutePlanDetailScreen → chip «Urgente» (rojo) bajo datos de deuda. → Etiqueta de patrón, urgencia o recurrencia de deuda específica. La etiqueta no reemplaza severidad, validación ni CTA dominante.
A96: M04 | B96: TR-M04-136 | C96: F3 · M02/M03 / superficie | D96: FLOW-M04-001 · Entrada contextual | E96: Existe dato/regla fuente que respalda una etiqueta MVP | F96: Perfil/Home | Mostrar etiqueta funcional | G96: Cuenta de prueba activa y reseteada (sin deudas ni datos previos del flujo). Condición de entrada: Perfil/Home | Mostrar etiqueta funcional | H96: Seguir flujo de FLOW-M04-001 · Entrada contextual. CIERRE · Registrar resultado en columna «Resultado obtenido» y marcar «Estado QA». · Resetear solo si el siguiente caso requiere estado inicial incompatible con el actual. Casos del mismo flujo pueden reutilizar el estado. (Ajustes → Borrar mis datos · o solicitar reset al admin de QA) | I96: Pantalla activa de Ruta Despeje. | J96: Etiqueta resumida solo cuando exista regla/dato y sea pertinente en superficie consumidora. La etiqueta no reemplaza severidad, validación ni CTA dominante. | K96: Ambiente con Home/Perfil (M03) disponible. Producer payload válido de M04. | L96: No · requiere env | P96: Walvy_M04_Matriz_Trazabilidad_Cliente_v1.3.xlsx · 01_Matriz_Trazabilidad · TR-M04-136 | Q96: En: Pantalla activa de Ruta Despeje. → Etiqueta resumida solo cuando exista regla/dato y sea pertinente en superficie consumidora. La etiqueta no reemplaza severidad, validación ni CTA dominante.
A97: M05 | B97: M5-V01 | C97: F1 · QA funcional local | D97: Resumen Presupuesto Vivo | E97: PV-001 · Datos suficientes | F97: Movimientos categorizados, objetivos, gasto real | G97: Cuenta de prueba activa y reseteada (sin deudas ni datos previos del flujo). Condición de entrada: Movimientos categorizados, objetivos, gasto real | I97: Pestaña Presupuesto → pantalla principal / resumen PV | J97: Calcular estado general. Usuario: Consultar presupuesto. CTA dominante: Revisar presupuesto. Copy/guardrail: Tu Presupuesto Vivo — No planilla vacía. | L97: Sí
A98: M05 | B98: M5-V02 | C98: F1 · QA funcional local | D98: Resumen Presupuesto Vivo | E98: PV-002 · Sin datos suficientes | F98: Carga de movimientos/documentos | G98: Cuenta de prueba activa y reseteada (sin deudas ni datos previos del flujo). Condición de entrada: Carga de movimientos/documentos | I98: Pestaña Presupuesto → pantalla principal / resumen PV | J98: Detectar falta de datos. Usuario: Cargar movimientos. CTA dominante: Cargar movimientos. Copy/guardrail: Necesitamos tus movimientos — No presupuesto manual en frío. | L98: Sí
A99: M05 | B99: M5-V03 | C99: F1 · QA funcional local | D99: Resumen Presupuesto Vivo | E99: PV-003 · Datos parciales | F99: Movimientos parciales, confianza | G99: Cuenta de prueba activa y reseteada (sin deudas ni datos previos del flujo). Condición de entrada: Movimientos parciales, confianza | I99: Pestaña Presupuesto → pantalla principal / resumen PV | J99: Mostrar lectura parcial. Usuario: Revisar pendientes. CTA dominante: Completar datos. Copy/guardrail: Lectura parcial — No conclusión fuerte. | L99: Sí
A100: M05 | B100: M5-V04 | C100: F1 · QA funcional local | D100: Presupuesto por categoría | E100: PV-004 · Objetivo definido | F100: Categoría, objetivo, gasto real | G100: Cuenta de prueba activa y reseteada (sin deudas ni datos previos del flujo). Condición de entrada: Categoría, objetivo, gasto real | I100: Presupuesto → sección por categoría (card de cada categoría) | J100: Comparar gasto vs objetivo. Usuario: Ajustar objetivo. CTA dominante: Ajustar objetivo. Copy/guardrail: Presupuesto por categoría — Sin copy final emocional. | L100: Sí
A101: M05 | B101: M5-V05 | C101: F1 · QA funcional local | D101: Presupuesto por categoría | E101: PV-005 · Meta operacional activa | F101: Consumo detectado, objetivo menor | G101: Cuenta de prueba activa y reseteada (sin deudas ni datos previos del flujo). Condición de entrada: Consumo detectado, objetivo menor | I101: Presupuesto → sección por categoría (card de cada categoría) | J101: Activar seguimiento. Usuario: Confirmar objetivo. CTA dominante: Confirmar objetivo. Copy/guardrail: Meta activa — Usuario decide. | L101: Sí
A102: M05 | B102: M5-V06 | C102: F1 · QA funcional local | D102: Detalle de categoría | E102: PV-006 · Sobreconsumo | F102: Gasto real, umbral, movimientos | G102: Cuenta de prueba activa y reseteada (sin deudas ni datos previos del flujo). Condición de entrada: Gasto real, umbral, movimientos | I102: Presupuesto → card categoría → Ver detalle | J102: Detectar desviación. Usuario: Revisar movimientos. CTA dominante: Revisar movimientos. Copy/guardrail: Categoría sobre el objetivo — No reasignación automática. | L102: Sí
A103: M05 | B103: M5-V07 | C103: F1 · QA funcional local | D103: Detalle de categoría | E103: PV-007 · Subejecución | F103: Objetivo, gasto real, otras categorías, ahorro | G103: Cuenta de prueba activa y reseteada (sin deudas ni datos previos del flujo). Condición de entrada: Objetivo, gasto real, otras categorías, ahorro | I103: Presupuesto → card categoría → Ver detalle | J103: Estimar destino del margen. Usuario: Ver recomendación. CTA dominante: Ver recomendación. Copy/guardrail: Menor uso del esperado — No causalidad absoluta. | L103: Sí
A104: M05 | B104: M5-V08 | C104: F1 · QA funcional local | D104: Movimientos sin categorizar | E104: PV-008 · Sin categorizar | F104: Movimiento, glosa, fecha, monto | G104: Cuenta de prueba activa y reseteada (sin deudas ni datos previos del flujo). Condición de entrada: Movimiento, glosa, fecha, monto | I104: Presupuesto → sección Movimientos sin categorizar | J104: Agrupar pendientes. Usuario: Categorizar movimiento. CTA dominante: Categorizar movimiento. Copy/guardrail: Movimientos por clasificar — No clasificar sin confianza. | L104: Sí
A105: M05 | B105: M5-V09 | C105: F1 · QA funcional local | D105: Validación de categoría | E105: PV-009 · Requiere validación | F105: Categoría sugerida, confianza | G105: Cuenta de prueba activa y reseteada (sin deudas ni datos previos del flujo). Condición de entrada: Categoría sugerida, confianza | I105: Presupuesto → modal validación / edición de categoría | J105: Solicitar confirmación. Usuario: Confirmar/corregir. CTA dominante: Confirmar categoría. Copy/guardrail: Confirma esta categoría — No IA opaca. | L105: Sí
A106: M05 | B106: M5-V10 | C106: F1 · QA funcional local | D106: Histórico y progreso | E106: PV-010 · Histórico real disponible | F106: Periodos cerrados, gasto, objetivos, calidad del dato | G106: Cuenta de prueba activa y reseteada (sin deudas ni datos previos del flujo). Condición de entrada: Periodos cerrados, gasto, objetivos, calidad del dato | I106: Presupuesto → sección Histórico / progreso mensual | J106: Comparar sin forecast. Usuario: Cambiar periodo cerrado. CTA dominante: Ver periodo. Copy/guardrail: Tu progreso en el tiempo — No forecast. | L106: Sí
A107: M05 | B107: M5-V11 | C107: F3 · M02/M03 / superficie | D107: Home | E107: PV-011 · Alerta presupuestaria | F107: Estado presupuesto, umbral | G107: Cuenta de prueba activa y reseteada (sin deudas ni datos previos del flujo). ⚠ F3: M02/M03 debe estar disponible en el ambiente QA. Condición de entrada: Estado presupuesto, umbral | I107: Pestaña Inicio → bloque / card Presupuesto | J107: Exponer señal principal. Usuario: Entrar a presupuesto. CTA dominante: Ver presupuesto. Copy/guardrail: Presupuesto por revisar — Home consume señal. | K107: Ambiente con M02/M03 operativo. Producer payload válido de M05. | L107: No · requiere env
A108: M05 | B108: M5-V12 | C108: F1 · QA funcional local | D108: Recomendaciones | E108: PV-012 · Recomendación activa | F108: Regla, evidencia, vigencia | G108: Cuenta de prueba activa y reseteada (sin deudas ni datos previos del flujo). Condición de entrada: Regla, evidencia, vigencia | I108: Presupuesto → sección Recomendaciones (canal M02) | J108: Mostrar recomendación. Usuario: Revisar recomendación. CTA dominante: Ver recomendación. Copy/guardrail: Recomendación basada en tus datos — Usuario decide. | L108: Sí
A109: M05 | B109: M5-V13 | C109: F1 · QA funcional local | D109: Ingesta asistida estructurada | E109: PV-013 · Input válido | F109: Texto, voz corta, imagen o archivo con estructura mínima | G109: Cuenta de prueba activa y reseteada (sin deudas ni datos previos del flujo). Condición de entrada: Texto, voz corta, imagen o archivo con estructura mínima | I109: Presupuesto → flujo Ingresar movimiento / asistente de voz | J109: Extraer candidato estructurado y calcular confianza. Usuario: Revisar datos extraídos. CTA dominante: Confirmar datos | L109: Sí
A110: M05 | B110: M5-V14 | C110: F1 · QA funcional local | D110: Formato no válido | E110: PV-014 · Input inválido | F110: Input sin monto, concepto, estructura financiera o contexto mínimo | G110: Cuenta de prueba activa y reseteada (sin deudas ni datos previos del flujo). Condición de entrada: Input sin monto, concepto, estructura financiera o contexto mínimo | I110: Presupuesto → carga de archivo → error de formato | J110: Rechazar interpretación libre y guiar formato. Usuario: Reingresar información. CTA dominante: Reingresar con formato válido. Copy/guardrail: Necesitamos un formato más claro — No interpretar libremente. | L110: Sí
A111: M05 | B111: M5-V15 | C111: F1 · QA funcional local | D111: Extracción pendiente de confirmación | E111: PV-015 · Datos extraídos con impacto financiero | F111: Monto, fecha, categoría, glosa o tipo de movimiento extraído | G111: Cuenta de prueba activa y reseteada (sin deudas ni datos previos del flujo). Condición de entrada: Monto, fecha, categoría, glosa o tipo de movimiento extraído | I111: Presupuesto → movimiento pendiente de confirmación | J111: Bloquear consolidación hasta confirmación o confianza suficiente. Usuario: Confirmar o corregir extracción. CTA dominante: Confirmar extracción. Copy/guardrail: Confirma estos datos — Usuario decide. | L111: Sí
A112: M05 | B112: M5-V16 | C112: F1 · QA funcional local | D112: Voz demasiado larga o relato libre | E112: PV-016 · Audio fuera de estándar | F112: Audio extenso, narrativo o con múltiples ideas no estructuradas | G112: Cuenta de prueba activa y reseteada (sin deudas ni datos previos del flujo). Condición de entrada: Audio extenso, narrativo o con múltiples ideas no estructuradas | I112: Presupuesto → asistente de voz → error de formato | J112: Pedir reingreso breve y estructurado. Usuario: Reingresar audio o texto corto. CTA dominante: Reingresar con formato válido. Copy/guardrail: Hazlo más breve — Voz MVP 10 a 15 segundos. | L112: Sí
A113: M05 | B113: M5-V17 | C113: F1 · QA funcional local | D113: Archivo sin estructura financiera | E113: PV-017 · Archivo ambiguo o no financiero | F113: Archivo sin tabla, montos, movimientos, ingresos, gastos o compromisos reconocibles | G113: Cuenta de prueba activa y reseteada (sin deudas ni datos previos del flujo). Condición de entrada: Archivo sin tabla, montos, movimientos, ingresos, gastos o compromisos reconocibles | I113: Presupuesto → carga de archivo → error de contenido | J113: Rechazar interpretación libre. Usuario: Subir archivo válido. CTA dominante: Subir archivo válido. Copy/guardrail: No encontramos datos claros — No usar LLM libre. | L113: Sí
A114: M05 | B114: M5-V18 | C114: F1 · QA funcional local | D114: Plan de recuperación | E114: PV-018 · Brecha, sobreconsumo, compra puntual o fuga con impacto | F114: Brecha, objetivo, gasto real, evidencia y confianza | G114: Cuenta de prueba activa y reseteada (sin deudas ni datos previos del flujo). Condición de entrada: Brecha, objetivo, gasto real, evidencia y confianza | I114: Presupuesto → sección Plan de recuperación / historial negativo | J114: Seleccionar estrategia predefinida de recuperación. Usuario: Revisar o aceptar ruta sugerida. CTA dominante: Crear plan de recuperación. Copy/guardrail: Recuperar equilibrio — No asesoría financiera. | L114: Sí
A115: M05 | B115: M5-V19 | C115: F2 · Fixture cross-contract | D115: Derivación Ruta Despeje | E115: PV-019 · Riesgo deuda, mora, liquidez crítica o capacidad de pago | F115: Brecha, compromisos, deuda/mora o presión de pago | G115: Cuenta de prueba activa y reseteada (sin deudas ni datos previos del flujo). ⚠ F2: preparar fixture sintético del contrato upstream antes de iniciar (ver Datos de prueba). Condición de entrada: Brecha, compromisos, deuda/mora o presión de pago | I115: Presupuesto → CTA Ruta Despeje / derivación M04 | J115: Prellenar Ruta Despeje sin aplicar automáticamente. Usuario: Aprobar o descartar derivación. CTA dominante: Ir a Ruta Despeje. Copy/guardrail: Revisar con Ruta Despeje — Prellenado + aprobación. | K115: Fixture sintético (no requiere documento real). Formato: CSV o XLSX con los valores del contrato upstream cerrado. Inyectar al menos: valor positivo · valor cero · NOT_EVALUABLE. | L115: Sí · con insumo dev
A116: M05 | B116: M5-V20 | C116: F3 · M02/M03 / superficie | D116: Sugerencia foco del mes | E116: PV-020 · Plan activo con estrategia dominante | F116: Plan de recuperación activo y foco equivalente aprobado en M2 | G116: Cuenta de prueba activa y reseteada (sin deudas ni datos previos del flujo). ⚠ F3: M02/M03 debe estar disponible en el ambiente QA. Condición de entrada: Plan de recuperación activo y foco equivalente aprobado en M2 | I116: Presupuesto → sección Sugerencia / Foco del mes (M02) | J116: Buscar foco aprobado equivalente en M2. Usuario: Aprobar actualización o mantener foco. CTA dominante: Actualizar foco del mes. Copy/guardrail: Alinear con tu foco — Solo catálogo M2. | K116: Ambiente con M02/M03 operativo. Producer payload válido de M05. | L116: No · requiere env
A117: M05 | B117: M5-V21 | C117: F1 · QA funcional local | D117: Umbrales | E117: Seguimiento informativo 50%-79% | F117: Avance entre 50% y 79% del objetivo | G117: Cuenta de prueba activa y reseteada (sin deudas ni datos previos del flujo). Condición de entrada: Avance entre 50% y 79% del objetivo | I117: Presupuesto → indicadores de umbral por categoría (semáforo %) | J117: Mostrar seguimiento informativo sin dramatizar; no competir con señales de mayor severidad. | L117: Sí
A118: M05 | B118: M5-V22 | C118: F1 · QA funcional local | D118: Umbrales | E118: Umbral preventivo 80%-89% | F118: Avance entre 80% y 89% del objetivo | G118: Cuenta de prueba activa y reseteada (sin deudas ni datos previos del flujo). Condición de entrada: Avance entre 80% y 89% del objetivo | I118: Presupuesto → indicadores de umbral por categoría (semáforo %) | J118: Mostrar señal preventiva y CTA Revisar categoría. | L118: Sí
A119: M05 | B119: M5-V23 | C119: F1 · QA funcional local | D119: Umbrales | E119: Umbral advertencia 90%-99% | F119: Avance entre 90% y 99% del objetivo | G119: Cuenta de prueba activa y reseteada (sin deudas ni datos previos del flujo). Condición de entrada: Avance entre 90% y 99% del objetivo | I119: Presupuesto → indicadores de umbral por categoría (semáforo %) | J119: Mostrar advertencia y CTA Revisar presupuesto; no duplicar recomendación si no aporta. | L119: Sí
A120: M05 | B120: M5-V24 | C120: F1 · QA funcional local | D120: Umbrales | E120: Límite alcanzado 100% | F120: Gasto real igual al objetivo | G120: Cuenta de prueba activa y reseteada (sin deudas ni datos previos del flujo). Condición de entrada: Gasto real igual al objetivo | I120: Presupuesto → indicadores de umbral por categoría (semáforo %) | J120: Mostrar límite alcanzado; CTA Revisar categoría / Ajustar objetivo; no reasignar automáticamente. | L120: Sí
A121: M05 | B121: M5-V25 | C121: F1 · QA funcional local | D121: Umbrales | E121: Sobreconsumo >100% | F121: Gasto real supera el objetivo | G121: Cuenta de prueba activa y reseteada (sin deudas ni datos previos del flujo). Condición de entrada: Gasto real supera el objetivo | I121: Presupuesto → indicadores de umbral por categoría (semáforo %) | J121: Mostrar sobreconsumo con evidencia y CTA Revisar movimientos. | L121: Sí
A122: M05 | B122: M5-V26 | C122: F1 · QA funcional local | D122: Umbrales | E122: Sobreconsumo alto >=110% | F122: Gasto real alcanza o supera 110% del objetivo | G122: Cuenta de prueba activa y reseteada (sin deudas ni datos previos del flujo). Condición de entrada: Gasto real alcanza o supera 110% del objetivo | I122: Presupuesto → indicadores de umbral por categoría (semáforo %) | J122: Elevar prioridad conforme regla producto; mantener baja confianza dominante y acción revisable. | L122: Sí
A123: M05 | B123: M5-V27 | C123: F1 · QA funcional local | D123: Patrones de gasto | E123: Gasto hormiga / fuga | F123: Patrón recurrente o drenante con exclusiones aplicadas | G123: Cuenta de prueba activa y reseteada (sin deudas ni datos previos del flujo). Condición de entrada: Patrón recurrente o drenante con exclusiones aplicadas | I123: Presupuesto → sección Patrones de gasto | J123: Mostrar card/insight con evidencia; no definir fuga solo por monto bajo. | L123: Sí
A124: M05 | B124: M5-V28 | C124: F1 · QA funcional local | D124: Margen estimado | E124: Margen estimado como ahorro | F124: Subejecución coincide con mejora de capacidad de ahorro | G124: Cuenta de prueba activa y reseteada (sin deudas ni datos previos del flujo). Condición de entrada: Subejecución coincide con mejora de capacidad de ahorro | I124: Presupuesto → bloque Disponible / Margen estimado | J124: Mostrar hipótesis prudente de contribución a ahorro; no afirmar causalidad absoluta. | L124: Sí
A125: M05 | B125: M5-V29 | C125: F1 · QA funcional local | D125: Margen estimado | E125: Margen absorbido por otra categoría | F125: Otra categoría aumenta de forma comparable a la subejecución | G125: Cuenta de prueba activa y reseteada (sin deudas ni datos previos del flujo). Condición de entrada: Otra categoría aumenta de forma comparable a la subejecución | I125: Presupuesto → bloque Disponible / Margen estimado | J125: Mostrar como hipótesis de desplazamiento y permitir revisar categoría crítica. | L125: Sí
...
